Workbook

Sheet Cover
B2: Kelen: business plan model
B3: B2B neobank for SMEs in Senegal, then Côte d'Ivoire. Five years, monthly, every figure driven by formulas.
B5: How to use
B6: 1. Pick a scenario | C6: Assumptions › cell D4: 1 = Prudent, 2 = Base, 3 = Ambitious. Rows with three values switch with it.
B7: 2. Change any input | C7: Inputs are blue on a cream background (Assumptions, Hiring plan, Market). Everything else is a formula: do not type over it.
B8: 3. Change the team | C8: Hiring plan: the fixed roles (founder, CTO, financial expert, sales lead, marketing, country manager, compliance officer). Support, developers, field sales reps and credit analysts grow with clients and the loan book: ratios on Assumptions, section 8.
B9: 4. Check the cash | C9: Dashboard › checks. If cash goes negative, raise more or earlier (Assumptions, section 11).
B11: Tabs
B12: Dashboard | C12: Headline numbers, year-by-year summary and checks.
B13: Plans | C13: The three plans with their prices, limits and features; add-ons, commissions, what is always free, partner income, credit rates and the A/B/C pricing options.
B14: Assumptions | C14: Every hypothesis with its source: timing, acquisition, pricing, usage per client, cost to serve, credit, team and tools, Maak, fixed costs by year, funding.
B15: Unit costs | C15: What one of each thing costs or earns: one employee by role, one client by plan, one loan, and the price of every fixed item.
B16: Hiring plan | C16: Fixed roles, start months and salaries (employer cost = gross + 30% charges); 'Agency hire' adds the €800 agency fee.
B17: Staff | C17: Headcount and employer cost by month: fixed roles plus the team that grows with volume.
B18: Sales & marketing | C18: New clients by channel (field sales, partners, digital) and country; marketing budget; cost to acquire a client.
B19: Clients & revenue | C19: Active clients by plan, usage (cards, balances, payroll, payouts) and every non-credit revenue line.
B20: Credit | C20: Loan book by product, interest, cost of funds, losses and the share kept by Kelen; cash tied up by credit.
B21: Costs | C21: Variable costs, fixed costs by category and the contingency, month by month.
B22: P&L monthly | C22: Revenue, cost of revenue, gross margin, operating expenses, EBITDA, tax, net income (no depreciation: equipment is expensed).
B23: P&L annual | C23: Years 1–5, cash and funding, operating figures and a euro view.
... B29: Regulatory path | C29: What each stage requires from regulators, and where its cost sits in the model.
B31: Colour code
B32: Blue on cream | C32: Input: change freely.
B33: Black | C33: Formula on the same sheet.
B34: Green | C34: Link to another sheet.
B36: Main caveats
B37: Estimates to replace | C37: Every cost line was checked against published prices and proxies in the cost research (Oct 2026, research/costs). Partner bank fees, card processing, Visa/Mastercard fees, PI-SPI business pricing (transfers to wallets) and FX costs have no public price: prudent uses public prices, base the researched value, ambitious negotiated targets. Replace them with term sheets.
B38: Partner income | C38: Interchange and a share of bank income on balances go to the partner bank. No partner has agreed to share them, so the plan counts zero; Pricing levers shows what they would add.
B39: Taxes | C39: Amounts exclude VAT and the 17% tax on financial activities (TAF), which apply to fees. Corporate tax is simplified (30%, losses carried forward without limit).
B40: Côte d'Ivoire | C40: Same 30% employer charges as Senegal; the number of formal employers is an estimate.
B41: Credit | C41: No loans before month 18. A partner microfinance institution (SFD) lends at 23% a year, under the 24% SFD usury cap. Kelen buys an SFD around month 24 and lends from it in Senegal; Côte d'Ivoire loans stay with a partner. The loan book is funded by debt lines, not equity.
B42: Licences | C42: Kelen holds no licence of its own until the SFD acquisition: partners hold the accounts, cards and loans. See Regulatory path.
B43: Sources | C43: Business model v2, Cost breakdown in euros, Senegal launch plan, the market and competitor analysis (Oct 2026, research/market) and the research notes in this project, plus IPRES/ANSD 2024, CNPS and CEPICI 2025 for the market.

Sheet Dashboard
A1: Kelen business plan: dashboard
A2: Key results for the scenario selected on Assumptions. FCFA in columns B–H, euros in column D (headline) and J–N (year by year).
A4: Scenario | B4: =Assumptions!E4 -> Base
A6: Headline numbers
A7: First month with positive EBITDA | B7: =IF(MIN('P&L monthly'!E52:BL52)=999,"not reached",MIN('P&L monthly'!E52:BL52)) -> 22 | C7: month #
A8: which is | B8: =IF(ISNUMBER(B7),DATE(YEAR(Start_Date),MONTH(Start_Date)+B7-1,1),"-") -> 47027
A9: Peak funding need (lowest cumulative cash flow before funding) | B9: =-MIN(0,MIN('Cash flow'!E16:BL16)) -> 1.3189569e+09 | C9: FCFA
A10: in euros | B10: =B9/FX_EUR -> 2010736.8 | C10: €
A11: Equity raised in the plan | B11: =SUM('Cash flow'!E19:BL19) -> 3300000000 | C11: FCFA
A12: in euros | B12: =B11/FX_EUR -> 5030817.6 | C12: €
A13: Lowest closing cash | B13: =MIN('Cash flow'!E24:BL24) -> 4.2398929e+08 | C13: FCFA | D13: =B13/FX_EUR -> 646367.51 | E13: =IF(B13<0,"Cash goes negative: raise more or earlier (Assumptions, section 11)","OK: cash stays positive") -> OK: cash stays positive
A14: in month | B14: =MATCH(B13,'Cash flow'!E24:BL24,0) -> 14 | C14: month #
A15: Cash at the end of year 5 | B15: ='Cash flow'!BL24 -> 6.0199078e+09 | C15: FCFA | D15: =B15/FX_EUR -> 9177290.2
A16: Technology from Maak | B16: =IF(Maak_Option=1,"Lease (option 1)","Equity stake (option 2)") -> Lease (option 1)
A17: Maak's stake in Kelen | B17: =IF(Maak_Option=2,Maak_Equity_Pct,0) -> 0
A18: Year by year
A19: Year | D19: ='P&L annual'!D5 -> 2027 | E19: ='P&L annual'!E5 -> 2028 | F19: ='P&L annual'!F5 -> 2029 | G19: ='P&L annual'!G5 -> 2030 | H19: ='P&L annual'!H5 -> 2031 | J19: ="Y"&1&" (€)" -> Y1 (€) | K19: ="Y"&2&" (€)" -> Y2 (€) | L19: ="Y"&3&" (€)" -> Y3 (€) | M19: ="Y"&4&" (€)" -> Y4 (€) | N19: ="Y"&5&" (€)" -> Y5 (€)
A20: Active clients (end of year) | B20: clients | D20: ='P&L annual'!D56 -> 388.38296 | E20: ='P&L annual'!E56 -> 1419.3994 | F20: ='P&L annual'!F56 -> 3304.4665 | G20: ='P&L annual'!G56 -> 5992.067 | H20: ='P&L annual'!H56 -> 9412.6103
A21: New clients in the year | B21: clients | D21: ='P&L annual'!D59 -> 410.91308 | E21: ='P&L annual'!E59 -> 1187.3569 | F21: ='P&L annual'!F59 -> 2326.8155 | G21: ='P&L annual'!G59 -> 3562.2927 | H21: ='P&L annual'!H59 -> 4883.0227
A22: Headcount (end of year) | B22: people | D22: ='P&L annual'!D60 -> 11 | E22: ='P&L annual'!E60 -> 19 | F22: ='P&L annual'!F60 -> 33 | G22: ='P&L annual'!G60 -> 51 | H22: ='P&L annual'!H60 -> 75
A23: Total revenue | B23: FCFA | D23: ='P&L annual'!D23 -> 1.5558179e+08 | E23: ='P&L annual'!E23 -> 1.1374381e+09 | F23: ='P&L annual'!F23 -> 3.5775977e+09 | G23: ='P&L annual'!G23 -> 7.1694097e+09 | H23: ='P&L annual'!H23 -> 1.2058507e+10 | J23: =D23/FX_EUR -> 237182.9 | K23: =E23/FX_EUR -> 1734013.2 | L23: =F23/FX_EUR -> 5454012.6 | M23: =G23/FX_EUR -> 10929695 | N23: =H23/FX_EUR -> 18383075
A24: Gross margin | B24: FCFA | D24: ='P&L annual'!D32 -> 64078008 | E24: ='P&L annual'!E32 -> 5.2191296e+08 | F24: ='P&L annual'!F32 -> 1.6743827e+09 | G24: ='P&L annual'!G32 -> 3.4049709e+09 | H24: ='P&L annual'!H32 -> 5.746762e+09 | J24: =D24/FX_EUR -> 97686.294 | K24: =E24/FX_EUR -> 795651.18 | L24: =F24/FX_EUR -> 2552580 | M24: =G24/FX_EUR -> 5190844.7 | N24: =H24/FX_EUR -> 8760882.1
A25: Gross margin % | B25: % | D25: ='P&L annual'!D33 -> 0.4118606 | E25: ='P&L annual'!E33 -> 0.45884955 | F25: ='P&L annual'!F33 -> 0.46801873 | G25: ='P&L annual'!G33 -> 0.47493044 | H25: ='P&L annual'!H33 -> 0.47657326
A26: Total operating expenses | B26: FCFA | D26: ='P&L annual'!D44 -> 4.5089034e+08 | E26: ='P&L annual'!E44 -> 7.0054083e+08 | F26: ='P&L annual'!F44 -> 1.0045216e+09 | G26: ='P&L annual'!G44 -> 1.2616374e+09 | H26: ='P&L annual'!H44 -> 1.6332518e+09 | J26: =D26/FX_EUR -> 687377.89 | K26: =E26/FX_EUR -> 1067967.6 | L26: =F26/FX_EUR -> 1531383.3 | M26: =G26/FX_EUR -> 1923353.9 | N26: =H26/FX_EUR -> 2489876.4
A27: EBITDA | B27: FCFA | D27: ='P&L annual'!D45 -> -3.8681233e+08 | E27: ='P&L annual'!E45 -> -1.7862787e+08 | F27: ='P&L annual'!F45 -> 6.6986112e+08 | G27: ='P&L annual'!G45 -> 2.1433335e+09 | H27: ='P&L annual'!H45 -> 4.1135101e+09 | J27: =D27/FX_EUR -> -589691.59 | K27: =E27/FX_EUR -> -272316.43 | L27: =F27/FX_EUR -> 1021196.7 | M27: =G27/FX_EUR -> 3267490.8 | N27: =H27/FX_EUR -> 6271005.8
A28: EBITDA margin | B28: % | D28: ='P&L annual'!D46 -> -2.4862314 | E28: ='P&L annual'!E46 -> -0.15704403 | F28: ='P&L annual'!F46 -> 0.18723769 | G28: ='P&L annual'!G46 -> 0.29895536 | H28: ='P&L annual'!H46 -> 0.34112931
A29: Net income | B29: FCFA | D29: ='P&L annual'!D48 -> -3.8681233e+08 | E29: ='P&L annual'!E48 -> -1.7862787e+08 | F29: ='P&L annual'!F48 -> 6.3853484e+08 | G29: ='P&L annual'!G48 -> 1.5003334e+09 | H29: ='P&L annual'!H48 -> 2.8794571e+09 | J29: =D29/FX_EUR -> -589691.59 | K29: =E29/FX_EUR -> -272316.43 | L29: =F29/FX_EUR -> 973440.09 | M29: =G29/FX_EUR -> 2287243.6 | N29: =H29/FX_EUR -> 4389704
A30: Closing cash | B30: FCFA | D30: ='P&L annual'!D53 -> 4.8318767e+08 | E30: ='P&L annual'!E53 -> 2.008311e+09 | F30: ='P&L annual'!F53 -> 2.3351678e+09 | G30: ='P&L annual'!G53 -> 3.5155775e+09 | H30: ='P&L annual'!H53 -> 6.0199078e+09 | J30: =D30/FX_EUR -> 736614.86 | K30: =E30/FX_EUR -> 3061650.4 | L30: =F30/FX_EUR -> 3559940.4 | M30: =G30/FX_EUR -> 5359463.4 | N30: =H30/FX_EUR -> 9177290.2
A31: Loan book (end of year) | B31: FCFA | D31: ='P&L annual'!D61 -> 0 | E31: ='P&L annual'!E61 -> 4.6248764e+08 | F31: ='P&L annual'!F61 -> 2.6124191e+09 | G31: ='P&L annual'!G61 -> 4.998759e+09 | H31: ='P&L annual'!H61 -> 7.85595e+09 | J31: =D31/FX_EUR -> 0 | K31: =E31/FX_EUR -> 705057.86 | L31: =F31/FX_EUR -> 3982607.3 | M31: =G31/FX_EUR -> 7620558.9 | N31: =H31/FX_EUR -> 11976319
A32: Revenue per active client a month (ARPA) | B32: FCFA / month | D32: ='Unit economics'!D13 -> 88541.5 | E32: ='Unit economics'!E13 -> 107584.33 | F32: ='Unit economics'!F13 -> 123594.36 | G32: ='Unit economics'!G13 -> 126941.22 | H32: ='Unit economics'!H13 -> 128715.15 | J32: =D32/FX_EUR -> 134.98065 | K32: =E32/FX_EUR -> 164.01125 | L32: =F32/FX_EUR -> 188.41839 | M32: =G32/FX_EUR -> 193.52064 | N32: =H32/FX_EUR -> 196.22498
A33: Blended CAC | B33: FCFA / client | D33: ='Unit economics'!D20 -> 203740.15 | E33: ='Unit economics'!E20 -> 118062.58 | F33: ='Unit economics'!F20 -> 98005.214 | G33: ='Unit economics'!G20 -> 88115.755 | H33: ='Unit economics'!H20 -> 86075.16 | J33: =D33/FX_EUR -> 310.59986 | K33: =E33/FX_EUR -> 179.98525 | L33: =F33/FX_EUR -> 149.40798 | M33: =G33/FX_EUR -> 134.3316 | N33: =H33/FX_EUR -> 131.22074
A34: CAC payback (months) | B34: months | D34: ='Unit economics'!D21 -> 5.5870107 | E34: ='Unit economics'!E21 -> 2.3916243 | F34: ='Unit economics'!F21 -> 1.6942882 | G34: ='Unit economics'!G21 -> 1.4615743 | H34: ='Unit economics'!H21 -> 1.4031965
A36: Checks
A37: New-client mix adds up to 100% | B37: =IF(ABS(Mix_Petite+Mix_Moyenne+Mix_Grande-1)<0.0001,"OK","ERROR") -> OK
A38: Cost of revenue in the P&L equals variable costs | B38: =IF(ABS(SUM('P&L monthly'!E30:BL30)-SUM(Costs!E23:BL23))<1,"OK","ERROR") -> OK
A39: Opex in the P&L equals fixed costs | B39: =IF(ABS(SUM('P&L monthly'!E43:BL43)-SUM(Costs!E95:BL95))<1,"OK","ERROR") -> OK
A40: Annual revenue equals monthly revenue | B40: =IF(ABS('P&L annual'!I23-SUM('P&L monthly'!E23:BL23))<1,"OK","ERROR") -> OK
A41: Closing cash never negative | B41: =IF(MIN('Cash flow'!E24:BL24)>=0,"OK","RAISE MORE") -> OK

Sheet Plans
A1: Plans, add-ons and commissions
A2: The offer as clients see it, for the pricing option selected on Assumptions. Every price, limit and fee links to Assumptions; feature rows are the product definition.
A5: The three plans
A6: Clients choose by what they need, not by staff count. Two simple limits: a number of transfers to bank accounts (salaries never count) and an amount sent to mobile money (salaries included).
A7: What is included | B7: Essentiel | C7: Pro | D7: Business | E7: Notes
A8: Price
A9: Monthly price | B9: =Price_Petite -> 9900 | C9: =Price_Moyenne -> 19500 | D9: =Price_Grande -> 69500 | E9: FCFA a month, excluding VAT. Option A / B / C on Assumptions.
A10: in € | B10: =IF(ISNUMBER(B9),B9/FX_EUR,"") -> 15.092453 | C10: =IF(ISNUMBER(C9),C9/FX_EUR,"") -> 29.727558 | D10: =IF(ISNUMBER(D9),D9/FX_EUR,"") -> 105.95207
A11: Yearly billing (price for 12 months) | B11: =Price_Petite*(12-Annual_Free) -> 99000 | C11: =Price_Moyenne*(12-Annual_Free) -> 195000 | D11: =Price_Grande*(12-Annual_Free) -> 695000 | E11: ="Pay yearly and get "&Annual_Free&" months free." -> Pay yearly and get 2 months free.
A12: in € | B12: =IF(ISNUMBER(B11),B11/FX_EUR,"") -> 150.92453 | C12: =IF(ISNUMBER(C11),C11/FX_EUR,"") -> 297.27558 | D12: =IF(ISNUMBER(D11),D11/FX_EUR,"") -> 1059.5207
A13: Free trial | B13: =Free_Months&" month free" -> 1 month free | C13: =Free_Months&" month free" -> 1 month free | D13: =Free_Months&" month free" -> 1 month free | E13: Every new client, every plan.
A14: Limits
A15: Users included | B15: =Users_Incl_Petite -> 2 | C15: =Users_Incl_Moyenne -> 3 | D15: =Users_Incl_Grande -> 10 | E15: Essentiel: 1 main user + 1 invited free. More users: add-on below.
A16: Bank transfers a month | B16: =Transfers_Incl_Petite -> 30 | C16: =Transfers_Incl_Moyenne -> 100 | D16: =Transfers_Incl_Grande -> 400 | E16: Payments to suppliers and others by bank transfer. Salaries and transfers to wallets never count. Above it: fee per extra transfer. Incoming transfers are free and unlimited.
A17: Mobile money free up to | B17: =MM_Free_Petite -> 200000 | C17: =MM_Free_Moyenne -> 1000000 | D17: =MM_Free_Grande -> 5000000 | E17: FCFA a month sent to wallets (Wave, Orange Money, Mixx…), salaries included. Above it: the mobile money fee below. Fair use: no splitting into many tiny transfers.
A18: in € | B18: =IF(ISNUMBER(B17),B17/FX_EUR,"") -> 304.89803 | C18: =IF(ISNUMBER(C17),C17/FX_EUR,"") -> 1524.4902 | D18: =IF(ISNUMBER(D17),D17/FX_EUR,"") -> 7622.4509
A19: Salaries to bank accounts free up to | B19: =Payroll_Free_Petite -> 3000000 | C19: =Payroll_Free_Moyenne -> 15000000 | D19: =Payroll_Free_Grande -> 60000000 | E19: FCFA of salaries a month. Above it: fee per extra transfer for each salary.
A20: in € | B20: =IF(ISNUMBER(B19),B19/FX_EUR,"") -> 4573.4705 | C20: =IF(ISNUMBER(C19),C19/FX_EUR,"") -> 22867.353 | D20: =IF(ISNUMBER(D19),D19/FX_EUR,"") -> 91469.41
A21: Physical cards included | B21: =Cards_Phys_Incl_Petite -> 1 | C21: =Cards_Phys_Incl_Moyenne -> 1 | D21: =Cards_Phys_Incl_Grande -> 1 | E21: Visa cards for staff, co-branded with the partner bank. More cards: one-off fee below.
A22: Virtual cards | B22: 2 | C22: 10 | D22: Unlimited | E22: For online payments: ads, software, subscriptions.
A23: Sub-accounts | B23: 1 | C23: 5 | D23: Unlimited | E23: Separate balances by project, site or budget.
A24: Features
A25: Business account with its own IBAN | B25: ✓ | C25: ✓ | D25: ✓ | E25: Held at the partner bank.
A26: Salary payments to any bank or wallet | B26: ✓ | C26: ✓ | D26: ✓ | E26: Bulk runs, scheduled paydays, status per employee.
A27: Import a payroll file (KayFay, Sage, Excel…) | B27: ✓ | C27: ✓ | D27: ✓
A28: Invoices and payment links (Wave, Orange Money, card) | B28: ✓ | C28: ✓ | D28: ✓ | E28: Commission on mobile-money collections: see commissions.
A29: Approvals (double signature) | B29: — | C29: ✓ | D29: ✓ multi-level, custom rules | E29: Locked on Essentiel: tapping it shows an "Unlock with Pro" button.
A30: Accounting module (accountant access, receipts, SYSCOHADA export) | B30: — | C30: ✓ | D30: ✓ | E30: Locked on Essentiel.
A31: Spend control (limits and budgets per card or person) | B31: — | C31: Basic | D31: Full
A32: API and several companies under one login | B32: — | C32: — | D32: ✓
A33: Support | B33: Chat | C33: Priority | D33: Dedicated adviser
A34: Payroll module (payslips and declarations) | B34: Paid option | C34: Paid option | D34: Paid option | E34: Per payslip: see add-ons.
A35: International supplier payments | B35: ✓ | C35: ✓ | D35: ✓ | E35: Fee per payment: see commissions.
A37: Add-ons
A38: Paid only when a client goes beyond its plan or chooses an option. Upgrade prompts appear at 80% and 100% of each limit.
A39: Add-on | B39: Price | C39: Unit | E39: When it applies
A40: Extra user | B40: =Extra_User_Fee -> 2500 | C40: FCFA / month | E40: Each user beyond the plan.
A41: in € | B41: =IF(ISNUMBER(B40),B40/FX_EUR,"") -> 3.8112254
A42: Extra physical card | B42: =Card_Fee -> 6500 | C42: FCFA, one-off | E42: The first physical card is free; each other card is paid once, for printing and delivery. No monthly fee.
A43: in € | B43: =IF(ISNUMBER(B42),B42/FX_EUR,"") -> 9.9091861
A44: Bank transfer above the plan allowance | B44: =Overage_Fee -> 450 | C44: FCFA / transfer | E44: Each bank transfer beyond the monthly number, and each salary to a bank account above the free amount. Not charged on transfers to wallets. Banks charge 3,000–5,000.
A45: in € | B45: =IF(ISNUMBER(B44),B44/FX_EUR,"") -> 0.68602058
A46: Mobile money above the free amount | B46: =MM_Fee -> 0.0125 | C46: % of amount | E46: Only the part sent to wallets above the plan's free amount. Kelen pays the operators 1% (capped at 5,000 FCFA) until a deal is signed. Wave charges 1%.
A47: Mobile money fee: cap per transfer | B47: =MM_Fee_Cap -> 8500 | C47: FCFA / transfer | E47: The fee above never exceeds this on a single transfer (reached at 680,000 FCFA).
A48: in € | B48: =IF(ISNUMBER(B47),B47/FX_EUR,"") -> 12.958166
A49: Card payment in other currencies | B49: =FX_Fixed_Fee -> 200 | C49: FCFA / payment | E49: On top of the % below, for each card payment in dollars or euros.
A50: in € | B50: =IF(ISNUMBER(B49),B49/FX_EUR,"") -> 0.30489803
A51: International payment | B51: =Intl_Fixed_Fee -> 1500 | C51: FCFA / payment | E51: On top of the % below, for each payment abroad.
A52: in € | B52: =IF(ISNUMBER(B51),B51/FX_EUR,"") -> 2.2867353
A53: Payroll module | B53: =Payslip_Fee -> 900 | C53: FCFA / payslip | E53: Payslip plus the monthly IPRES, CSS and income-tax declarations. Optional, every plan.
A54: in € | B54: =IF(ISNUMBER(B53),B53/FX_EUR,"") -> 1.3720412
A56: Commissions
A57: Charged as a share of the amount, on top of the plan.
A58: Commission | B58: Rate | C58: Unit | E58: What it is for
A59: Payment links and QR collections (mobile money) | B59: =PL_Fee -> 0.012 | C59: % of amount | E59: When a client's customer pays an invoice by Wave or Orange Money. Card and transfer payments are free.
A60: Card spending in other currencies | B60: =FX_Fee -> 0.03 | C60: % of amount | E60: Ads, software and travel paid in dollars or euros, plus a fixed fee per payment (below). Card spending in FCFA is free.
A61: International supplier payments | B61: =Intl_Fee -> 0.038 | C61: % of amount | E61: Paying suppliers abroad (China, Turkey, Dubai, France). About the rate the bank or provider charges Kelen (3.5% assumed), plus a fixed fee (below). The 0.6% tax on transfers out of the zone is added at cost.
A63: Always free
A64: What clients never pay for.
A65: Item | B65: Note
A66: Opening the account | B66: Online, no branch visit.
A67: Salaries to bank accounts up to the plan's free amount | B67: Any number of employees.
A68: Mobile money up to the plan's free amount | B68: Salaries and other payments to wallets.
A69: Incoming transfers | B69: From any bank or wallet in the WAEMU.
A70: Card spending in FCFA
A71: Virtual cards up to the plan limit
A73: Possible income from partners (not in the plan)
A74: This income goes to the partner bank, which owns the accounts and cards. Nothing obliges it to share; the plan counts zero. Items to ask for in the negotiation; what they would add is on Pricing levers.
A75: Item | B75: Possible rate | C75: Unit | E75: What it is
A76: Interchange share on card spending in FCFA | B76: about 0.3% | C76: % of spending | E76: Part of the fee shops pay on every card payment. The BCEAO gives it to the bank that issues the card.
A77: Share of bank income on client balances | B77: about 1.25% | C77: % a year | E77: Part of what the partner bank earns on the money clients keep in their accounts.
A78: Interchange on card spending abroad | B78: about 0.8% | C78: % of spending | E78: Paid by Visa / Mastercard to the bank that issues the card, on foreign payments.
A80: Credit (from month 18)
A81: Loans made by a partner microfinance institution, then by Kelen's own in Senegal. Rates are all-in, under the 24% cap.
A82: Product | B82: Rate | C82: Unit | E82: What it is
A83: Invoice financing | B83: =Yield_Factoring -> 0.23 | C83: % a year | E83: Cash now against an invoice a client will pay in 30–90 days.
A84: Payroll bridge | B84: =Yield_Bridge -> 0.23 | C84: % a year | E84: Short loan to pay salaries on time when a client pays late.
A85: Credit line | B85: =Yield_Line -> 0.23 | C85: % a year | E85: Cash reserve to draw and repay, sized on the account's flows.
A86: Equipment loan | B86: =Yield_Term -> 0.22 | C86: % a year | E86: Vehicles, machines, computers; 6–24 months.
A87: Salary advance (employees) | B87: =Yield_Advance -> 0.23 | C87: % a year | E87: Part of earned salary before payday, repaid from the next salary.
A89: Pricing options
A90: Switch on Assumptions (Pricing option). B is the base.
A91: Plan | B91: A: acquisition first | C91: B: balanced | D91: C: revenue first | E91: Note
A92: Essentiel | B92: =OFFSET(Price_Petite,0,1) -> 7500 | C92: =OFFSET(Price_Petite,0,2) -> 9900 | D92: =OFFSET(Price_Petite,0,3) -> 9900 | E92: FCFA a month
A93: in € | B93: =IF(ISNUMBER(B92),B92/FX_EUR,"") -> 11.433676 | C93: =IF(ISNUMBER(C92),C92/FX_EUR,"") -> 15.092453 | D93: =IF(ISNUMBER(D92),D92/FX_EUR,"") -> 15.092453
A94: Pro | B94: =OFFSET(Price_Moyenne,0,1) -> 17500 | C94: =OFFSET(Price_Moyenne,0,2) -> 19500 | D94: =OFFSET(Price_Moyenne,0,3) -> 29900 | E94: FCFA a month
A95: in € | B95: =IF(ISNUMBER(B94),B94/FX_EUR,"") -> 26.678578 | C95: =IF(ISNUMBER(C94),C94/FX_EUR,"") -> 29.727558 | D95: =IF(ISNUMBER(D94),D94/FX_EUR,"") -> 45.582256
A96: Business | B96: =OFFSET(Price_Grande,0,1) -> 59500 | C96: =OFFSET(Price_Grande,0,2) -> 69500 | D96: =OFFSET(Price_Grande,0,3) -> 89900 | E96: FCFA a month
A97: in € | B97: =IF(ISNUMBER(B96),B96/FX_EUR,"") -> 90.707165 | C97: =IF(ISNUMBER(C96),C96/FX_EUR,"") -> 105.95207 | D97: =IF(ISNUMBER(D96),D96/FX_EUR,"") -> 137.05167

Sheet How it works
A1: How Kelen works
A2: Who does what, how the money moves, and when Kelen needs its own cash. Kelen never holds client money: it sits at the partner bank, and later also at Kelen's own SFD.
A5: The partners
A6: Kelen is the app, the onboarding, the support and the controls. The licences, the accounts and the cards belong to partners until Kelen owns an SFD.
A7: Partner | B7: What it does | C7: What Kelen pays it | D7: When
A8: Partner bank | B8: Holds every client account (in the client's name, at the bank), signs off the identity checks, executes transfers (same bank, interbank, PI-SPI, SWIFT), issues the Visa cards under its name and keeps the client money. | C8: A fee per account, a fee per transfer, card programme set-up, and a cash guarantee (collateral) for the cards. | D8: From launch, both countries.
A9: Wave and Orange Money (directly or through an aggregator: HUB2, PayDunya, CinetPay, InTouch) | B9: Deliver transfers to wallets and collect payment-link payments. | C9: 1% per transfer to a wallet today (Wave capped at 5,000 FCFA), about 1% on collections. Aggregators: 1.5–2% public, less with volume. | D9: From launch.
A10: Card processor (HPS, Paymentology, GIM-UEMOA…) | B10: Approves every card payment in real time against the client's balance and handles card files. | C10: A monthly fee per active card. | D10: From the card launch.
A11: Visa / Mastercard | B11: The card network. Paid through the partner bank. | C11: Cross-border fees on payments in other currencies. | D11: From the card launch.
A12: Partner SFD (microfinance institution) | B12: Lends under its licence and with its funding; Kelen finds, scores and services the loans. | C12: Kelen keeps a share of the net margin and puts up a first-loss reserve. | D12: Month 18 to month 24 in Senegal; all along in Côte d'Ivoire.
A13: International payment provider (partner bank, Capi Money or others) | B13: Converts FCFA and pays suppliers abroad in euros, dollars or yuan. | C13: Its rate (about 3.5% assumed); Kelen charges 3.8% plus 1,500 FCFA per payment. The 0.6% tax is passed on to the client. | D13: From month 13.
A14: Maak (group company) | B14: The banking platform: accounts ledger, payments, cards and app back-end. | C14: A lease for 3 years, then upgrades and maintenance. | D14: From month 1.
A16: Service by service
A17: What each side does and how the money moves. 'Cash Kelen must put up' is Kelen's own money, not client money.
A18: Service | B18: Partner bank or SFD does | C18: Kelen does | D18: How the money moves | E18: Cash Kelen must put up
A19: Business account | B19: Opens the account in the client's name and holds the money. | C19: App and web access, onboarding file, identity checks, support. | D19: The client's money stays in the client's account at the bank. | E19: None.
A20: Bank transfers and salaries to bank accounts | B20: Executes the transfer from the client's account: free inside the same bank, through the interbank system or PI-SPI otherwise. | C20: Payment screens, bulk payroll runs, approvals, status per payment. | D20: Client account → recipient's bank account, directly. | E20: None.
A21: Transfers to wallets (salaries and others) | B21: Route 1: sends from the client's account straight to Wave or Orange Money through PI-SPI, if the bank offers business transfers to wallets. | C21: Bulk runs and approvals. Route 2 or 3: Kelen runs the payout through Wave, Orange Money or an aggregator. | D21: Route 1: client account → wallet. Routes 2 and 3: client account → a prefunded business wallet or aggregator balance → employee's wallet. | E21: Route 1: none. Routes 2 and 3: a float covering 1–3 days of payouts, larger on paydays. Not in the plan yet: see the routes below.
A22: Payment links (collections) | B22: Receives the settlement and credits the client's account. | C22: The link, the invoice, matching payments to invoices. | D22: The customer pays by Wave or Orange Money → operator or aggregator merchant account → settled to the bank (same day to 5 days; Orange D+5) → client's account. | E22: None if the client is credited at settlement. A float if Kelen credits instantly.
A23: Cards (co-branded with the partner bank) | B23: Issues the cards under its name and Visa licence, pays Visa every day and debits the client's account. | C23: Card design and ordering, spending limits and controls in the app, first-line disputes. | D23: The client pays → the processor checks the balance and blocks the amount → next day Visa debits the bank → the bank debits the client's account. | E23: Collateral at the bank (60M FCFA in the plan, from month 4). If the bank runs the cards as prepaid, also a float of a few days of card spending.
A24: International payments | B24: Converts and sends the payment (SWIFT), checks the foreign-exchange paperwork. | C24: Collects invoices and import documents, compliance checks, sends the instruction. | D24: Client account debited (amount + fee + 0.6% tax) → provider → supplier abroad. | E24: None if the provider debits on execution; a balance if it needs prefunding.
A25: Payroll module and accounting | B25: Nothing. | C25: Software only: payslips, declarations, accountant access, exports. | D25: No money moves. | E25: None.
A26: Credit, partner SFD (Senegal months 18–24; Côte d'Ivoire) | B26: Signs the loan, lends its money (or debt lines), carries the risk above the first-loss reserve. | C26: Scoring from account data, the loan offer in the app, repayments collected from the account. | D26: SFD → client's account; repayments taken from the account. | E26: First-loss reserve (share of the loan book).
A27: Credit, Kelen's own SFD (Senegal from month 24) | B27: — | C27: Lends itself and keeps the whole margin, under the 24% rate cap. | D27: Kelen's SFD → client's account; repayments back to the SFD. | E27: Equity in the loans (capital ratio) plus debt lines for the rest.
A29: Transfers to mobile money: the three routes
A30: Not every bank can send to wallets today. The route decides the cost and whether Kelen must prefund a float. The plan assumes no deal: 1% capped at 5,000 FCFA.
A31: Route | B31: How it works | C31: Cost today | D31: Cash Kelen must put up | E31: Status
A32: 1. Partner bank through PI-SPI | B32: The bank sends from the client's account straight to the wallet. From 2 November 2026 every interoperable transfer goes through PI-SPI, Wave included. | C32: Set freely by the bank for businesses: to negotiate (capped or flat). | D32: None. | E32: The bank needs PI-SPI business access (bulk payments). Certified in Senegal so far: 9 participants, including Ecobank, which is certified in all 8 countries. Make it a condition when choosing the bank.
A33: 2. Direct contract with Wave Business and Orange Money | B33: A business wallet with each operator, paid out through their API. | C33: Wave 1% (reportedly capped at 5,000 FCFA); Orange 1%, 1.5% to other wallets. | D33: The business wallets must be topped up before payouts (1–3 days of volume, more on paydays). | E33: Possible now. The float is client money in transit: it must sit under a licensed partner's name.
A34: 3. Aggregator (HUB2, PayDunya, CinetPay, InTouch) | B34: One API to every operator. | C34: 1.5–2% public; HUB2 and InTouch on quote, lower with volume. | D34: A prefunded balance at the aggregator. | E34: Possible now; the most expensive public route.
A35: 4. Kelen's own SFD on PI-SPI (after month 24) | B35: SFDs can join PI-SPI (UM ACEP, an SFD, is certified for business payments). | C35: PI-SPI fees only. | D35: The SFD's own settlement account. | E35: Later; depends on the SFD bought.
A37: The card programme
A38: Co-branded, not fully white-label: like Djamo's cards with Ecobank, or Wave's virtual Visa with Ecobank.
A39: Question | B39: Answer
A40: Whose name is on the card? | B40: The partner bank is the issuer (its Visa licence and card number range) and its name is on the card next to Kelen's brand.
A41: Does Kelen need cash for card payments? | B41: Not for the payments themselves: the bank pays Visa and debits the client's account. Kelen puts up collateral (60M FCFA in the plan) so the bank is covered for disputes, fraud or a failed debit. If the bank runs the cards as prepaid, a float of a few days of spending must also be prefunded.
A42: Who earns the interchange? | B42: The bank, as the issuer. Kelen only if the bank agrees to share it: not in the plan.
A43: What does Kelen pay? | B43: The processor per active card, the printing of physical cards, Visa's cross-border fees on foreign payments, and any set-up fee the bank asks.
A44: Can Kelen's own SFD issue cards later? | B44: Not on its own at first: Visa membership needs a bank sponsor or large collateral. The plan keeps the partner bank for cards.
A46: What changes when Kelen owns an SFD (Senegal, from month 24)
A47: Item | B47: With partners only | C47: With Kelen's own SFD
A48: Credit | B48: The partner SFD lends; Kelen keeps a share of the margin and covers first losses. | C48: Kelen's SFD lends and keeps the whole margin; it needs capital and debt lines to fund the loans.
A49: Client money | B49: At the partner bank; the bank keeps the income on balances. | C49: SFDs can take deposits: money held at Kelen's SFD would earn Kelen the income. The bank account stays for cards and transfers.
A50: Transfers to wallets | B50: Through the partner bank, the operators or an aggregator. | C50: Possibly direct through PI-SPI, if the SFD connects.
A51: Cards | B51: Partner bank. | C51: Still the partner bank.
A52: Côte d'Ivoire | B52: Partner bank and partner SFD. | C52: No change: Kelen's SFD is licensed in Senegal only.
A53: Rules | B53: The partners' licences; Kelen is their outsourced provider. | C53: BCEAO supervision of the SFD, the 24% rate cap, capital and reporting rules.

Sheet Assumptions
A1: Assumptions and hypotheses
A2: Every blue cell on a cream background is an input. Change it and the whole model updates. Amounts in FCFA unless stated. Column D is the value the model uses.
B4: Scenario (1 = Prudent, 2 = Base, 3 = Ambitious) | D4: 2 | E4: =CHOOSE(Scenario,"Prudent","Base","Ambitious") -> Base | I4: Rows with Prudent / Base / Ambitious values switch with this cell.
B7: 1. General | C7: Unit | D7: Value used | E7: Prudent | F7: Base | G7: Ambitious | H7: € / FCFA equivalent | I7: Source / note
B8: Model start (month 1) | C8: date | D8: 46388 | I8: First month of the plan. Company set-up, licence file and product build start here.
B9: FCFA per euro | C9: FCFA | D9: 655.957 | I9: Fixed parity CFA franc / euro (BCEAO).
B10: FCFA per US dollar | C10: FCFA | D10: 580 | I10: Planning rate, used for vendor prices quoted in USD.
B11: Corporate income tax rate | C11: % | D11: 0.3 | I11: Senegal CIT 30%. Simplification: losses carried forward without limit (Senegal allows 3 years). Minimum tax and the 17% TAF on financial services are not modelled.
B12: Annual pay rise (from year 2) | C12: % / year | D12: 0.05 | I12: Applied to every salary each new year.
B13: Contingency on fixed costs | C13: % | D13: 0.05 | I13: Same 5% as the cost breakdown.
B15: 2. Timing (month numbers, 1 = first month of the model) | C15: Unit | D15: Value used | E15: Prudent | F15: Base | G15: Ambitious | H15: € / FCFA equivalent | I15: Source / note
B16: Commercial launch, Senegal | C16: month # | D16: 5 | I16: After partner bank integration and card programme set-up (business account with IBAN via the partner bank).
B17: Commercial launch, Côte d'Ivoire | C17: month # | D17: 19 | I17: One month after the Abidjan office opens. Partners hold the licences in Côte d'Ivoire too.
B18: Dakar office (Regus) from | C18: month # | D18: 1 | I18: Regus from day one: no lease, deposit or fit-out (decision).
B19: Abidjan office (Regus) and first Côte d'Ivoire hires | C19: month # | D19: 18 | I19: Not before month 18 (decision).
B20: Payment links go live | C20: month # | D20: 18 | I20: 'Bientôt' feature in the app.
B21: B2C launch: employee salary accounts and personal accounts | C21: month # | D21: 29 | I21: Not before 2 years of commercial activity: Senegal launch + 24 months (decision).
B22: Acquisition of a microfinance company (SFD) closes | C22: month # | D22: 24 | I22: Around year 2 (decision). Due diligence and the change-of-control approval run during year 2.
B23: Own SFD lends from | C23: month # | D23: 25 | I23: Before this month the partner SFD lends and Kelen keeps a share of the margin. Côte d'Ivoire loans stay with a partner: SFD licences are national.
B24: Card programme collateral at partner bank | C24: month # | D24: 4
B25: Partner bank set-up fee paid, Senegal | C25: month # | D25: 2
B26: Partner bank set-up fee paid, Côte d'Ivoire | C26: month # | D26: 16
B27: Card processor set-up fee paid | C27: month # | D27: 3
B28: Card processor monthly minimum starts | C28: month # | D28: 5
B29: Cloud hosting starts | C29: month # | D29: 2
B30: Partner SFD integration fee paid | C30: month # | D30: 15 | I30: Partner SFD signed early; integration paid before the first loans.
B31: Côte d'Ivoire subsidiary created | C31: month # | D31: 16 | I31: Before the first Abidjan hires.
B32: First tech audit (then every 12 months) | C32: month # | D32: 4 | I32: Before launch, for the partner bank; repeated yearly.
B34: 3. Client acquisition (sales and marketing) | C34: Unit | D34: Value used | E34: Prudent | F34: Base | G34: Ambitious | H34: € / FCFA equivalent | I34: Source / note
B35: New clients signed per field sales rep per month | C35: clients | D35: =CHOOSE(Scenario,E35,F35,G35) -> 8 | E35: 7 | F35: 8 | G35: 13 | I35: Rep counts come from the hiring plan. A rep sells from the month after joining. Base lowered from 10 to 8 after the market analysis (Oct 2026): Julaya had about 2,800 active users in Senegal after six years. Validate in the pilot.
B36: Côte d'Ivoire rep productivity vs Senegal | C36: x | D36: 0.9 | I36: Slightly lower at first: new market, brand unknown.
B37: Partner channel, Senegal: clients a month at launch | C37: clients | D37: =CHOOSE(Scenario,E37,F37,G37) -> 8 | E37: 6 | F37: 8 | G37: 14 | I37: Accountants, payroll software (KayFay, Sage, Odoo), chambers of commerce. Base lowered from 10 to 8 after the market analysis (Oct 2026).
B38: Partner channel, Côte d'Ivoire: clients a month at launch | C38: clients | D38: =CHOOSE(Scenario,E38,F38,G38) -> 6 | E38: 4 | F38: 6 | G38: 9
B39: Partner channel monthly growth | C39: % / month | D39: 0.06
B40: Partner channel cap, Senegal | C40: clients / month | D40: 80
B41: Partner channel cap, Côte d'Ivoire | C41: clients / month | D41: 60
B42: Digital ads cost per signed client | C42: FCFA | D42: =CHOOSE(Scenario,E42,F42,G42) -> 75000 | E42: 100000 | F42: 75000 | G42: 55000 | H42: =D42/FX_EUR -> 114.33676 | I42: Media spend only. Meta leads 600–2,800 FCFA; lead-to-client conversion assumed 2–4%.
B43: Share of new clients on Essentiel (mostly small firms) | C43: % | D43: 0.6 | I43: Plans are chosen by limits and features, not staff count. Small firms (about 5 staff) take Essentiel. The three shares must add up to 100% (see check on the Dashboard).
B44: Share of new clients on Pro (mostly mid-size firms) | C44: % | D44: 0.3 | I44: Firms that need approvals (double signature) or the accounting module, typically 10–50 staff.
B45: Share of new clients on Business (mostly large firms) | C45: % | D45: 0.1
B46: Monthly churn, Essentiel | C46: % / month | D46: =CHOOSE(Scenario,E46,F46,G46) -> 0.02 | E46: 0.03 | F46: 0.02 | G46: 0.015 | I46: Small companies leave or close more often.
B47: Monthly churn, Pro | C47: % / month | D47: =CHOOSE(Scenario,E47,F47,G47) -> 0.0125 | E47: 0.02 | F47: 0.0125 | G47: 0.01
B48: Monthly churn, Business | C48: % / month | D48: =CHOOSE(Scenario,E48,F48,G48) -> 0.0075 | E48: 0.015 | F48: 0.0075 | G48: 0.005
B49: Referral fee per partner-channel client | C49: FCFA | D49: 25000 | H49: =D49/FX_EUR -> 38.112254 | I49: Paid to accountants and payroll software partners (cost breakdown).
B50: Field sales transport allowance per rep | C50: FCFA / month | D50: 75000 | H50: =D50/FX_EUR -> 114.33676 | I50: 50–100k FCFA (cost breakdown).
B52: 4. Plans and pricing | C52: Unit | D52: Value used | E52: Prudent | F52: Base | G52: Ambitious | H52: € / FCFA equivalent | I52: Source / note
B53: Pricing option (1 = A acquisition first, 2 = B balanced, 3 = C revenue first) | C53: option | D53: 2 | I53: Decision (Oct 2026): plans by limits and features, not staff count. B is the base. Switch to compare; prices below change with it. See the Pricing levers tab.
B55: 4a. Plan prices (columns E–G are options A, B, C) | C55: Unit | D55: Value used | E55: Option A | F55: Option B | G55: Option C | H55: € / FCFA equivalent | I55: Source / note
B56: Essentiel plan | C56: FCFA / month | D56: =CHOOSE(Pricing_Option,E56,F56,G56) -> 9900 | E56: 7500 | F56: 9900 | G56: 9900 | H56: =D56/FX_EUR -> 15.092453 | I56: Decision (Oct 2026): package P3. 1 user + 1 invited free, 30 transfers, 1 physical and 2 virtual cards, salaries free up to 3M FCFA a month. Below a bank's micro-business account fee (10,000).
B57: Pro plan | C57: FCFA / month | D57: =CHOOSE(Pricing_Option,E57,F57,G57) -> 19500 | E57: 17500 | F57: 19500 | G57: 29900 | H57: =D57/FX_EUR -> 29.727558 | I57: Decision (Oct 2026): 19,500 (was 29,900; option C keeps the old price for comparison). 3 users, 150 transfers, 3 physical and 10 virtual cards, approvals, accounting module, salaries free up to 15M FCFA a month.
B58: Business plan | C58: FCFA / month | D58: =CHOOSE(Pricing_Option,E58,F58,G58) -> 69500 | E58: 59500 | F58: 69500 | G58: 89900 | H58: =D58/FX_EUR -> 105.95207 | I58: Decision (Oct 2026): 69,500 (was 89,900). 10 users, 500 transfers, 10 physical and unlimited virtual cards, multi-level approvals, API, several companies, adviser, salaries free up to 60M FCFA a month.
B60: 4b. Plan limits, add-ons and fees | C60: Unit | D60: Value used | E60: Prudent | F60: Base | G60: Ambitious | H60: € / FCFA equivalent | I60: Source / note
B61: Annual price increase | C61: % / year | D61: 0
B62: Free months for every new client | C62: months | D62: 1 | I62: Decision (Oct 2026): first month free on every plan (was 3).
B63: Share of clients paying yearly | C63: % | D63: 0.3
B64: Months free on yearly billing | C64: months | D64: 2 | I64: Yearly price = 10 months.
B65: Users included, Essentiel | C65: users | D65: 2 | I65: 1 main user + 1 invited free.
B66: Users included, Pro | C66: users | D66: 3
B67: Users included, Business | C67: users | D67: 10
B68: Transfers included a month, Essentiel | C68: transfers | D68: 30 | I68: Decision (Oct 2026): transfers to bank accounts only. Salaries never count; transfers to wallets fall under the mobile money allowance.
B69: Transfers included a month, Pro | C69: transfers | D69: 100 | I69: Decision (Oct 2026): 100.
B70: Transfers included a month, Business | C70: transfers | D70: 400 | I70: Decision (Oct 2026): 400.
B71: Physical cards included, Essentiel | C71: cards | D71: 1 | I71: Decision (Oct 2026): the first physical card is free on every plan; the others are paid (one-off fee below). Virtual cards: 2 / 10 / unlimited.
B72: Physical cards included, Pro | C72: cards | D72: 1
B73: Physical cards included, Business | C73: cards | D73: 1
B74: Salaries to bank accounts free up to, Essentiel | C74: FCFA / month | D74: 3000000 | H74: =D74/FX_EUR -> 4573.4705 | I74: Decision (Oct 2026). Above it, each salary to a bank account costs the fee per transfer above the allowance. Average clients stay far below. Salaries to wallets count in the mobile money allowance.
B75: Salaries to bank accounts free up to, Pro | C75: FCFA / month | D75: 15000000 | H75: =D75/FX_EUR -> 22867.353
B76: Salaries to bank accounts free up to, Business | C76: FCFA / month | D76: 60000000 | H76: =D76/FX_EUR -> 91469.41
B77: Extra user beyond the plan | C77: FCFA / month | D77: 2500 | H77: =D77/FX_EUR -> 3.8112254
B78: Extra physical card beyond the plan | C78: FCFA / month | D78: 0 | H78: =D78/FX_EUR -> 0 | I78: Decision (Oct 2026): no monthly fee; only the one-off card fee below.
B79: Mobile money free up to, Essentiel | C79: FCFA / month | D79: 200000 | H79: =D79/FX_EUR -> 304.89803 | I79: Decision (Oct 2026): every transfer to a wallet (Wave, Orange Money…), salaries included. Fair use: the allowance cannot be split into many tiny transfers.
B80: Mobile money free up to, Pro | C80: FCFA / month | D80: 1000000 | H80: =D80/FX_EUR -> 1524.4902
B81: Mobile money free up to, Business | C81: FCFA / month | D81: 5000000 | H81: =D81/FX_EUR -> 7622.4509
B82: Fee on mobile money above the free amount | C82: % of amount | D82: 0.0125 | I82: Decision (Oct 2026): 1.25%, capped per transfer (below). No deal with the operators yet: Kelen pays 1% capped at 5,000 FCFA. Wave charges 1%.
B83: Mobile money fee: cap per transfer | C83: FCFA / transfer | D83: 8500 | H83: =D83/FX_EUR -> 12.958166 | I83: Decision (Oct 2026). Reached at 680,000 FCFA per transfer; average transfers (75,000–200,000) stay below it, so it does not change the totals.
B84: Physical card fee beyond the plan (one-off) | C84: FCFA | D84: 6500 | H84: =D84/FX_EUR -> 9.9091861 | I84: Decision (Oct 2026): 6,500 for printing and delivery of each card beyond the first.
B85: Fee per card payment in foreign currencies | C85: FCFA / payment | D85: 200 | H85: =D85/FX_EUR -> 0.30489803 | I85: Decision (Oct 2026): 200, like Djamo.
B86: Average card payment in foreign currencies | C86: FCFA | D86: 25000 | H86: =D86/FX_EUR -> 38.112254 | I86: Assumption: ads and software subscriptions, about $40. Used to count payments.
B87: Fee on card spending in foreign currencies | C87: % | D87: 0.03 | I87: Decision (Oct 2026): 3% plus a fixed fee per payment (below), like Djamo (3–4% + 200 F). Cost research (Oct 2026): networks charge the issuer about 1.2%; banks charge clients 2–3% (NSIA 2.5%, UBA 2.5–3%, Coris 2% + 500 F), Djamo 3–4% + 200 F. Card spending in FCFA is free.
B88: Interchange earned on card spending in foreign currencies | C88: % of foreign spending | D88: 0 | I88: Not in the plan: no partner has agreed to share it. Possible upside if negotiated: see Pricing levers. Card networks pay the issuer (the partner bank) about 0.4–1.2%.
B89: Card spending in foreign currencies allowed by the FX rules | C89: x | D89: =CHOOSE(Scenario,E89,F89,G89) -> 1 | E89: 0.6 | F89: 1 | G89: 1 | I89: Règlement 06/2024/CM/UEMOA, Art. 47, limits residents' card use abroad to usual travel and personal expenses. Prudent assumes 40% of SME foreign card spending (ads, software) is blocked.
B90: Interchange share received on FCFA card spending | C90: % | D90: 0 | I90: Not in the plan: no partner has agreed to share it. Possible upside if negotiated: see Pricing levers. The BCEAO gives the issuer (the partner bank) 20% of the merchant fee, about 0.4–0.7%.
B91: Share of bank income on client balances | C91: % / year | D91: 0 | I91: Not in the plan: no partner has agreed to share it. Possible upside if negotiated: see Pricing levers. The partner bank earns about 3–5% a year on client balances.
B92: Fee per transfer above the plan allowance | C92: FCFA | D92: 450 | H92: =D92/FX_EUR -> 0.68602058 | I92: Decision (Oct 2026). Allowance: 30 / 150 / 500 transfers to bank accounts a month; salaries and transfers to wallets never count. Also charged on each salary to a bank account above the free amount. Banks charge 3,000–5,000 per interbank transfer.
B93: Payment links: fee on mobile money collections | C93: % | D93: 0.012 | I93: Decision (Oct 2026): 1.2%. Cost research (Oct 2026): gateways charge 1.5–3% (PayTech 1.5–2%, PayDunya 2.25%, Flutterwave 2%); Wave and Orange merchant 1%. Card and transfer payments are free.
B94: Payment links: operator and aggregator cost | C94: % | D94: =CHOOSE(Scenario,E94,F94,G94) -> 0.01 | E94: 0.012 | F94: 0.01 | G94: 0.005 | I94: Cost research (Oct 2026): Wave and Orange merchant pricing 1%; gateways 1.5–3%; receiving through PI-SPI is free. Ambitious = direct operator deal or PI-SPI routing.
B95: Payment links: share collected by mobile money | C95: % | D95: 0.7 | I95: The rest by card or transfer, free.
B96: Payment links: share of clients using them (at maturity) | C96: % | D96: 0.25
B97: Payment links: months to reach maturity | C97: months | D97: 12
B99: 4c. Paid modules | C99: Unit | D99: Value used | E99: Prudent | F99: Base | G99: Ambitious | H99: € / FCFA equivalent | I99: Source / note
B100: Payroll module goes live | C100: month # | D100: 11 | I100: Payslips plus the monthly IPRES, CSS and income-tax declarations, built from the salaries Kelen pays. Senegal first, Côte d'Ivoire rules at its launch.
B101: Payroll module: price per payslip | C101: FCFA / payslip | D101: 900 | H101: =D101/FX_EUR -> 1.3720412 | I101: Decision (Oct 2026): 900. Still about 2× cheaper than payroll software (KayFay 1,500–2,500 per payslip, minimum 15,000 a month).
B102: Payroll module: share of client employees covered (at maturity) | C102: % | D102: 0.4 | I102: Assumption: 40% of clients use it.
B103: Payroll module: months to reach maturity | C103: months | D103: 12
B104: Payroll module: cost per payslip | C104: FCFA / payslip | D104: 15 | H104: =D104/FX_EUR -> 0.022867353 | I104: Cost research (Oct 2026): WhatsApp utility message about 2.3 FCFA (Meta, Rest of Africa); Orange SMS 4–10 FCFA; plus computing.
B105: International supplier payments go live | C105: month # | D105: 13 | I105: Through the partner bank's foreign-exchange set-up, under the 2024 WAEMU foreign-exchange rules.
B106: International payments: fee charged (% of amount) | C106: % of amount | D106: 0.038 | I106: Decision (Oct 2026): 3.8%, 0.3 point above the assumed cost, plus the fixed fee below. Banks charge SMEs about 3–4% all-in; Capi Money about 3% (to check). The 0.6% tax on transfers out of the zone is passed on at cost.
B107: International payments: cost to Kelen (% of amount) | C107: % of amount | D107: 0.027 | I107: Provider not chosen yet (partner bank, Capi Money or others). Assumed all-in 3.5%.
B108: International payments: fixed fee per payment | C108: FCFA / payment | D108: 1500 | H108: =D108/FX_EUR -> 2.2867353 | I108: Decision (Oct 2026): 1,500, far below the banks' 25,000–60,000 FCFA of fixed fees per payment.
B109: International payments: average payment | C109: FCFA | D109: 1000000 | H109: =D109/FX_EUR -> 1524.4902 | I109: Assumption, used to count payments for the fixed fee.
...

Sheet Unit costs
A1: Unit costs and prices
A2: What one of each thing costs or earns, in FCFA with the euro amount on the 'in €' line underneath. Every cell links to the inputs on Assumptions and Hiring plan: change them there.
A5: Each service: what the client pays, what it costs Kelen, what Kelen keeps
A6: One example of each service, in FCFA, at the current scenario's costs. 'Status' says how solid the cost is: quoted, researched (public prices) or estimate. Kelen never pays the 0.6% tax on transfers out of the zone or the transfer tax: they are passed on at cost.
A7: Service (example) | B7: Who Kelen pays | C7: Client pays | D7: Cost to Kelen | E7: Kelen keeps | F7: Margin | G7: Status of the cost
A8: Account and plan
A9: Pro plan, one month (bank fee and messaging only) | B9: Partner bank (fee per account), WhatsApp / SMS | C9: =Price_Moyenne -> 19500 | D9: =Bank_Fee+Notif_Cost -> 1850 | E9: =C9-D9 -> 17650 | F9: =IF(C9>0,E9/C9,"") -> 0.90512821 | G9: Bank fee: estimate, no term sheet yet
A10: in € | C10: =IF(ISNUMBER(C9),C9/FX_EUR,"") -> 29.727558 | D10: =IF(ISNUMBER(D9),D9/FX_EUR,"") -> 2.8203068 | E10: =IF(ISNUMBER(E9),E9/FX_EUR,"") -> 26.907252
A11: Opening a new client (identity checks) | B11: Identity-check vendor | C11: =0 -> 0 | D11: =KYB_Cost+KYC_Cost*KYC_Persons -> 3300 | E11: =C11-D11 -> -3300 | F11: =IF(C11>0,E11/C11,"") | G11: Researched (vendor prices)
A12: in € | C12: =IF(ISNUMBER(C11),C11/FX_EUR,"") -> 0 | D12: =IF(ISNUMBER(D11),D11/FX_EUR,"") -> 5.0308176 | E12: =IF(ISNUMBER(E11),E11/FX_EUR,"") -> -5.0308176
A13: Extra user, one month | B13: Nobody | C13: =Extra_User_Fee -> 2500 | D13: =0 -> 0 | E13: =C13-D13 -> 2500 | F13: =IF(C13>0,E13/C13,"") -> 1
A14: in € | C14: =IF(ISNUMBER(C13),C13/FX_EUR,"") -> 3.8112254 | D14: =IF(ISNUMBER(D13),D13/FX_EUR,"") -> 0 | E14: =IF(ISNUMBER(E13),E13/FX_EUR,"") -> 3.8112254
A15: Transfers
A16: Bank transfer to a supplier, inside the allowance | B16: Partner bank | C16: =0 -> 0 | D16: =Supplier_Payout_Cost -> 150 | E16: =C16-D16 -> -150 | F16: =IF(C16>0,E16/C16,"") | G16: Researched: 150–2,000 FCFA in bank tariffs; same-bank transfers free
A17: in € | C17: =IF(ISNUMBER(C16),C16/FX_EUR,"") -> 0 | D17: =IF(ISNUMBER(D16),D16/FX_EUR,"") -> 0.22867353 | E17: =IF(ISNUMBER(E16),E16/FX_EUR,"") -> -0.22867353
A18: Bank transfer above the allowance | B18: Partner bank | C18: =Overage_Fee -> 450 | D18: =Supplier_Payout_Cost -> 150 | E18: =C18-D18 -> 300 | F18: =IF(C18>0,E18/C18,"") -> 0.66666667 | G18: Researched, as above
A19: in € | C19: =IF(ISNUMBER(C18),C18/FX_EUR,"") -> 0.68602058 | D19: =IF(ISNUMBER(D18),D18/FX_EUR,"") -> 0.22867353 | E19: =IF(ISNUMBER(E18),E18/FX_EUR,"") -> 0.45734705
A20: Salary to a bank account | B20: Partner bank | C20: =0 -> 0 | D20: =Bank_Payout_Cost -> 100 | E20: =C20-D20 -> -100 | F20: =IF(C20>0,E20/C20,"") | G20: Researched, as above
A21: in € | C21: =IF(ISNUMBER(C20),C20/FX_EUR,"") -> 0 | D21: =IF(ISNUMBER(D20),D20/FX_EUR,"") -> 0.15244902 | E21: =IF(ISNUMBER(E20),E20/FX_EUR,"") -> -0.15244902
A22: 75,000 FCFA to a wallet, inside the free amount | B22: Wave / Orange Money (or an aggregator) | C22: =0 -> 0 | D22: =(IF(MM_Cost_Cap>0,MIN(MM_Cost_Pct*75000,MM_Cost_Cap),MM_Cost_Pct*75000)+MM_Cost_Flat) -> 375 | E22: =C22-D22 -> -375 | F22: =IF(C22>0,E22/C22,"") | G22: Public price: 1% (no deal yet)
A23: in € | C23: =IF(ISNUMBER(C22),C22/FX_EUR,"") -> 0 | D23: =IF(ISNUMBER(D22),D22/FX_EUR,"") -> 0.57168381 | E23: =IF(ISNUMBER(E22),E22/FX_EUR,"") -> -0.57168381
A24: 200,000 FCFA salary to a wallet, above the free amount | B24: Wave / Orange Money (or an aggregator) | C24: =MIN(MM_Fee*200000,MM_Fee_Cap) -> 2500 | D24: =(IF(MM_Cost_Cap>0,MIN(MM_Cost_Pct*200000,MM_Cost_Cap),MM_Cost_Pct*200000)+MM_Cost_Flat) -> 1000 | E24: =C24-D24 -> 1500 | F24: =IF(C24>0,E24/C24,"") -> 0.6 | G24: Public price: 1% (no deal yet)
A25: in € | C25: =IF(ISNUMBER(C24),C24/FX_EUR,"") -> 3.8112254 | D25: =IF(ISNUMBER(D24),D24/FX_EUR,"") -> 1.5244902 | E25: =IF(ISNUMBER(E24),E24/FX_EUR,"") -> 2.2867353
A26: 1,000,000 FCFA to a wallet, above the free amount (both caps apply) | B26: Wave / Orange Money (or an aggregator) | C26: =MIN(MM_Fee*1000000,MM_Fee_Cap) -> 8500 | D26: =(IF(MM_Cost_Cap>0,MIN(MM_Cost_Pct*1000000,MM_Cost_Cap),MM_Cost_Pct*1000000)+MM_Cost_Flat) -> 2500 | E26: =C26-D26 -> 6000 | F26: =IF(C26>0,E26/C26,"") -> 0.70588235 | G26: 5,000 FCFA cap: secondary source, to verify
A27: in € | C27: =IF(ISNUMBER(C26),C26/FX_EUR,"") -> 12.958166 | D27: =IF(ISNUMBER(D26),D26/FX_EUR,"") -> 3.8112254 | E27: =IF(ISNUMBER(E26),E26/FX_EUR,"") -> 9.146941
A28: 100,000 FCFA collected by Wave through a payment link | B28: Wave / Orange Money (or an aggregator) | C28: =PL_Fee*100000 -> 1200 | D28: =PL_Cost*100000 -> 1000 | E28: =C28-D28 -> 200 | F28: =IF(C28>0,E28/C28,"") -> 0.16666667 | G28: Public price: about 1%
A29: in € | C29: =IF(ISNUMBER(C28),C28/FX_EUR,"") -> 1.8293882 | D29: =IF(ISNUMBER(D28),D28/FX_EUR,"") -> 1.5244902 | E29: =IF(ISNUMBER(E28),E28/FX_EUR,"") -> 0.30489803
A30: Cards
A31: Active card, one month | B31: Card processor | C31: =0 -> 0 | D31: =Card_Proc_Fee -> 600 | E31: =C31-D31 -> -600 | F31: =IF(C31>0,E31/C31,"") | G31: Estimate: processors quote privately
A32: in € | C32: =IF(ISNUMBER(C31),C31/FX_EUR,"") -> 0 | D32: =IF(ISNUMBER(D31),D31/FX_EUR,"") -> 0.9146941 | E32: =IF(ISNUMBER(E31),E31/FX_EUR,"") -> -0.9146941
A33: Extra physical card (one-off) | B33: Card printer | C33: =Card_Fee -> 6500 | D33: =Card_Prod_Cost -> 4500 | E33: =C33-D33 -> 2000 | F33: =IF(C33>0,E33/C33,"") -> 0.30769231 | G33: Researched: 3,000–6,000 FCFA
A34: in € | C34: =IF(ISNUMBER(C33),C33/FX_EUR,"") -> 9.9091861 | D34: =IF(ISNUMBER(D33),D33/FX_EUR,"") -> 6.8602058 | E34: =IF(ISNUMBER(E33),E33/FX_EUR,"") -> 3.0489803
A35: 50,000 FCFA card payment in FCFA | B35: Fraud and disputes (interchange stays with the bank) | C35: =0 -> 0 | D35: =50000*Fraud_Rate -> 75 | E35: =C35-D35 -> -75 | F35: =IF(C35>0,E35/C35,"") | G35: Estimate
A36: in € | C36: =IF(ISNUMBER(C35),C35/FX_EUR,"") -> 0 | D36: =IF(ISNUMBER(D35),D35/FX_EUR,"") -> 0.11433676 | E36: =IF(ISNUMBER(E35),E35/FX_EUR,"") -> -0.11433676
A37: 25,000 FCFA card payment in dollars (ads, software) | B37: Visa / Mastercard and the partner bank (FX margin) | C37: =25000*FX_Fee+FX_Fixed_Fee -> 950 | D37: =25000*(Scheme_Rate+Fraud_Rate)+Scheme_Fixed -> 587.5 | E37: =C37-D37 -> 362.5 | F37: =IF(C37>0,E37/C37,"") -> 0.38157895 | G37: Researched: network fees about 0.9% + $0.43; bank FX margin to quote
A38: in € | C38: =IF(ISNUMBER(C37),C37/FX_EUR,"") -> 1.4482657 | D38: =IF(ISNUMBER(D37),D37/FX_EUR,"") -> 0.89563798 | E38: =IF(ISNUMBER(E37),E37/FX_EUR,"") -> 0.55262769
A39: International payments and payroll
A40: 1,000,000 FCFA paid to a supplier abroad | B40: Partner bank or provider (Capi Money…) | C40: =1000000*Intl_Fee+Intl_Fixed_Fee -> 39500 | D40: =1000000*Intl_Cost -> 27000 | E40: =C40-D40 -> 12500 | F40: =IF(C40>0,E40/C40,"") -> 0.3164557 | G40: Assumed: provider not chosen yet
A41: in € | C41: =IF(ISNUMBER(C40),C40/FX_EUR,"") -> 60.217362 | D41: =IF(ISNUMBER(D40),D40/FX_EUR,"") -> 41.161235 | E41: =IF(ISNUMBER(E40),E40/FX_EUR,"") -> 19.056127
A42: One payslip with the monthly declarations | B42: WhatsApp / SMS, computing | C42: =Payslip_Fee -> 900 | D42: =Payslip_Cost -> 15 | E42: =C42-D42 -> 885 | F42: =IF(C42>0,E42/C42,"") -> 0.98333333 | G42: Researched
A43: in € | C43: =IF(ISNUMBER(C42),C42/FX_EUR,"") -> 1.3720412 | D43: =IF(ISNUMBER(D42),D42/FX_EUR,"") -> 0.022867353 | E43: =IF(ISNUMBER(E42),E42/FX_EUR,"") -> 1.3491738
A44: Credit
A45: 1,000,000 FCFA credit line for a year, Kelen's own SFD | B45: Lenders (cost of funds), credit losses, servicing | C45: =1000000*Yield_Line -> 230000 | D45: =1000000*(CoF+CoR_Line*CoR_Mult+Servicing) -> 145000 | E45: =C45-D45 -> 85000 | F45: =IF(C45>0,E45/C45,"") -> 0.36956522 | G45: With the partner SFD, Kelen keeps its share of this (Assumptions, section 7)
A46: in € | C46: =IF(ISNUMBER(C45),C45/FX_EUR,"") -> 350.63274 | D46: =IF(ISNUMBER(D45),D45/FX_EUR,"") -> 221.05107 | E46: =IF(ISNUMBER(E45),E45/FX_EUR,"") -> 129.58166
A48: One employee, per month
A49: Employer cost plus what each person adds: Regus desk, phone, Gmail and ClickUp, a Claude seat for the CTO and developers. One-off at hiring: a laptop (a MacBook for the CTO and developers), plus the agency fee for senior roles.
A50: Role | B50: Country | C50: Agency hire | D50: Gross salary | E50: Employer charges | F50: Employer cost | G50: Office (Regus) | H50: Phone and data | I50: Gmail and ClickUp | J50: Claude seat | K50: All-in per month | L50: One-off at hiring
A51: ='Hiring plan'!C5 -> CEO (full salary from year 2) | B51: ='Hiring plan'!D5 -> SN | C51: ='Hiring plan'!J5 -> Y | D51: ='Hiring plan'!I5 -> 2500000 | E51: =D51*Employer_Charges -> 750000 | F51: =D51+E51 -> 3250000 | G51: =Regus_EUR*FX_EUR -> 196787.1 | H51: =Phone_Cost -> 5000 | I51: =(Gmail_USD+ClickUp_USD)*FX_USD -> 10440 | J51: =IF('Hiring plan'!B5="Engineering & product",Claude_USD*FX_USD,0) -> 0 | K51: =SUM(F51:J51) -> 3462227.1 | L51: =IF('Hiring plan'!B5="Engineering & product",Laptop_Dev_USD*FX_USD,Laptop_EUR*FX_EUR)+IF(C51="Y",Agency_Fee_EUR*FX_EUR,0) -> 852744.1
A52: in € | D52: =IF(ISNUMBER(D51),D51/FX_EUR,"") -> 3811.2254 | E52: =IF(ISNUMBER(E51),E51/FX_EUR,"") -> 1143.3676 | F52: =IF(ISNUMBER(F51),F51/FX_EUR,"") -> 4954.5931 | G52: =IF(ISNUMBER(G51),G51/FX_EUR,"") -> 300 | H52: =IF(ISNUMBER(H51),H51/FX_EUR,"") -> 7.6224509 | I52: =IF(ISNUMBER(I51),I51/FX_EUR,"") -> 15.915677 | J52: =IF(ISNUMBER(J51),J51/FX_EUR,"") -> 0 | K52: =IF(ISNUMBER(K51),K51/FX_EUR,"") -> 5278.1312 | L52: =IF(ISNUMBER(L51),L51/FX_EUR,"") -> 1300
A53: ='Hiring plan'!C6 -> CTO (also codes) | B53: ='Hiring plan'!D6 -> SN | C53: ='Hiring plan'!J6 -> Y | D53: ='Hiring plan'!I6 -> 2500000 | E53: =D53*Employer_Charges -> 750000 | F53: =D53+E53 -> 3250000 | G53: =Regus_EUR*FX_EUR -> 196787.1 | H53: =Phone_Cost -> 5000 | I53: =(Gmail_USD+ClickUp_USD)*FX_USD -> 10440 | J53: =IF('Hiring plan'!B6="Engineering & product",Claude_USD*FX_USD,0) -> 14500 | K53: =SUM(F53:J53) -> 3476727.1 | L53: =IF('Hiring plan'!B6="Engineering & product",Laptop_Dev_USD*FX_USD,Laptop_EUR*FX_EUR)+IF(C53="Y",Agency_Fee_EUR*FX_EUR,0) -> 1684765.6
A54: in € | D54: =IF(ISNUMBER(D53),D53/FX_EUR,"") -> 3811.2254 | E54: =IF(ISNUMBER(E53),E53/FX_EUR,"") -> 1143.3676 | F54: =IF(ISNUMBER(F53),F53/FX_EUR,"") -> 4954.5931 | G54: =IF(ISNUMBER(G53),G53/FX_EUR,"") -> 300 | H54: =IF(ISNUMBER(H53),H53/FX_EUR,"") -> 7.6224509 | I54: =IF(ISNUMBER(I53),I53/FX_EUR,"") -> 15.915677 | J54: =IF(ISNUMBER(J53),J53/FX_EUR,"") -> 22.105107 | K54: =IF(ISNUMBER(K53),K53/FX_EUR,"") -> 5300.2363 | L54: =IF(ISNUMBER(L53),L53/FX_EUR,"") -> 2568.4086
A55: ='Hiring plan'!C7 -> Financial expert (finance, partners, credit lead) | B55: ='Hiring plan'!D7 -> SN | C55: ='Hiring plan'!J7 -> Y | D55: ='Hiring plan'!I7 -> 1500000 | E55: =D55*Employer_Charges -> 450000 | F55: =D55+E55 -> 1950000 | G55: =Regus_EUR*FX_EUR -> 196787.1 | H55: =Phone_Cost -> 5000 | I55: =(Gmail_USD+ClickUp_USD)*FX_USD -> 10440 | J55: =IF('Hiring plan'!B7="Engineering & product",Claude_USD*FX_USD,0) -> 0 | K55: =SUM(F55:J55) -> 2162227.1 | L55: =IF('Hiring plan'!B7="Engineering & product",Laptop_Dev_USD*FX_USD,Laptop_EUR*FX_EUR)+IF(C55="Y",Agency_Fee_EUR*FX_EUR,0) -> 852744.1
A56: in € | D56: =IF(ISNUMBER(D55),D55/FX_EUR,"") -> 2286.7353 | E56: =IF(ISNUMBER(E55),E55/FX_EUR,"") -> 686.02058 | F56: =IF(ISNUMBER(F55),F55/FX_EUR,"") -> 2972.7558 | G56: =IF(ISNUMBER(G55),G55/FX_EUR,"") -> 300 | H56: =IF(ISNUMBER(H55),H55/FX_EUR,"") -> 7.6224509 | I56: =IF(ISNUMBER(I55),I55/FX_EUR,"") -> 15.915677 | J56: =IF(ISNUMBER(J55),J55/FX_EUR,"") -> 0 | K56: =IF(ISNUMBER(K55),K55/FX_EUR,"") -> 3296.294 | L56: =IF(ISNUMBER(L55),L55/FX_EUR,"") -> 1300
A57: ='Hiring plan'!C8 -> Sales lead (also sells; incl. bonus) | B57: ='Hiring plan'!D8 -> SN | C57: ='Hiring plan'!J8 -> N | D57: ='Hiring plan'!I8 -> 1200000 | E57: =D57*Employer_Charges -> 360000 | F57: =D57+E57 -> 1560000 | G57: =Regus_EUR*FX_EUR -> 196787.1 | H57: =Phone_Cost -> 5000 | I57: =(Gmail_USD+ClickUp_USD)*FX_USD -> 10440 | J57: =IF('Hiring plan'!B8="Engineering & product",Claude_USD*FX_USD,0) -> 0 | K57: =SUM(F57:J57) -> 1772227.1 | L57: =IF('Hiring plan'!B8="Engineering & product",Laptop_Dev_USD*FX_USD,Laptop_EUR*FX_EUR)+IF(C57="Y",Agency_Fee_EUR*FX_EUR,0) -> 327978.5
A58: in € | D58: =IF(ISNUMBER(D57),D57/FX_EUR,"") -> 1829.3882 | E58: =IF(ISNUMBER(E57),E57/FX_EUR,"") -> 548.81646 | F58: =IF(ISNUMBER(F57),F57/FX_EUR,"") -> 2378.2047 | G58: =IF(ISNUMBER(G57),G57/FX_EUR,"") -> 300 | H58: =IF(ISNUMBER(H57),H57/FX_EUR,"") -> 7.6224509 | I58: =IF(ISNUMBER(I57),I57/FX_EUR,"") -> 15.915677 | J58: =IF(ISNUMBER(J57),J57/FX_EUR,"") -> 0 | K58: =IF(ISNUMBER(K57),K57/FX_EUR,"") -> 2701.7428 | L58: =IF(ISNUMBER(L57),L57/FX_EUR,"") -> 500
A59: ='Hiring plan'!C9 -> Marketing manager (senior) | B59: ='Hiring plan'!D9 -> SN | C59: ='Hiring plan'!J9 -> N | D59: ='Hiring plan'!I9 -> 900000 | E59: =D59*Employer_Charges -> 270000 | F59: =D59+E59 -> 1170000 | G59: =Regus_EUR*FX_EUR -> 196787.1 | H59: =Phone_Cost -> 5000 | I59: =(Gmail_USD+ClickUp_USD)*FX_USD -> 10440 | J59: =IF('Hiring plan'!B9="Engineering & product",Claude_USD*FX_USD,0) -> 0 | K59: =SUM(F59:J59) -> 1382227.1 | L59: =IF('Hiring plan'!B9="Engineering & product",Laptop_Dev_USD*FX_USD,Laptop_EUR*FX_EUR)+IF(C59="Y",Agency_Fee_EUR*FX_EUR,0) -> 327978.5
A60: in € | D60: =IF(ISNUMBER(D59),D59/FX_EUR,"") -> 1372.0412 | E60: =IF(ISNUMBER(E59),E59/FX_EUR,"") -> 411.61235 | F60: =IF(ISNUMBER(F59),F59/FX_EUR,"") -> 1783.6535 | G60: =IF(ISNUMBER(G59),G59/FX_EUR,"") -> 300 | H60: =IF(ISNUMBER(H59),H59/FX_EUR,"") -> 7.6224509 | I60: =IF(ISNUMBER(I59),I59/FX_EUR,"") -> 15.915677 | J60: =IF(ISNUMBER(J59),J59/FX_EUR,"") -> 0 | K60: =IF(ISNUMBER(K59),K59/FX_EUR,"") -> 2107.1916 | L60: =IF(ISNUMBER(L59),L59/FX_EUR,"") -> 500
A61: ='Hiring plan'!C10 -> Marketing officer (junior) | B61: ='Hiring plan'!D10 -> SN | C61: ='Hiring plan'!J10 -> N | D61: ='Hiring plan'!I10 -> 400000 | E61: =D61*Employer_Charges -> 120000 | F61: =D61+E61 -> 520000 | G61: =Regus_EUR*FX_EUR -> 196787.1 | H61: =Phone_Cost -> 5000 | I61: =(Gmail_USD+ClickUp_USD)*FX_USD -> 10440 | J61: =IF('Hiring plan'!B10="Engineering & product",Claude_USD*FX_USD,0) -> 0 | K61: =SUM(F61:J61) -> 732227.1 | L61: =IF('Hiring plan'!B10="Engineering & product",Laptop_Dev_USD*FX_USD,Laptop_EUR*FX_EUR)+IF(C61="Y",Agency_Fee_EUR*FX_EUR,0) -> 327978.5
A62: in € | D62: =IF(ISNUMBER(D61),D61/FX_EUR,"") -> 609.79607 | E62: =IF(ISNUMBER(E61),E61/FX_EUR,"") -> 182.93882 | F62: =IF(ISNUMBER(F61),F61/FX_EUR,"") -> 792.73489 | G62: =IF(ISNUMBER(G61),G61/FX_EUR,"") -> 300 | H62: =IF(ISNUMBER(H61),H61/FX_EUR,"") -> 7.6224509 | I62: =IF(ISNUMBER(I61),I61/FX_EUR,"") -> 15.915677 | J62: =IF(ISNUMBER(J61),J61/FX_EUR,"") -> 0 | K62: =IF(ISNUMBER(K61),K61/FX_EUR,"") -> 1116.273 | L62: =IF(ISNUMBER(L61),L61/FX_EUR,"") -> 500
A63: ='Hiring plan'!C11 -> Country manager, Abidjan | B63: ='Hiring plan'!D11 -> CI | C63: ='Hiring plan'!J11 -> Y | D63: ='Hiring plan'!I11 -> 2800000 | E63: =D63*Employer_Charges -> 840000 | F63: =D63+E63 -> 3640000 | G63: =Regus_EUR*FX_EUR -> 196787.1 | H63: =Phone_Cost -> 5000 | I63: =(Gmail_USD+ClickUp_USD)*FX_USD -> 10440 | J63: =IF('Hiring plan'!B11="Engineering & product",Claude_USD*FX_USD,0) -> 0 | K63: =SUM(F63:J63) -> 3852227.1 | L63: =IF('Hiring plan'!B11="Engineering & product",Laptop_Dev_USD*FX_USD,Laptop_EUR*FX_EUR)+IF(C63="Y",Agency_Fee_EUR*FX_EUR,0) -> 852744.1
A64: in € | D64: =IF(ISNUMBER(D63),D63/FX_EUR,"") -> 4268.5725 | E64: =IF(ISNUMBER(E63),E63/FX_EUR,"") -> 1280.5717 | F64: =IF(ISNUMBER(F63),F63/FX_EUR,"") -> 5549.1442 | G64: =IF(ISNUMBER(G63),G63/FX_EUR,"") -> 300 | H64: =IF(ISNUMBER(H63),H63/FX_EUR,"") -> 7.6224509 | I64: =IF(ISNUMBER(I63),I63/FX_EUR,"") -> 15.915677 | J64: =IF(ISNUMBER(J63),J63/FX_EUR,"") -> 0 | K64: =IF(ISNUMBER(K63),K63/FX_EUR,"") -> 5872.6824 | L64: =IF(ISNUMBER(L63),L63/FX_EUR,"") -> 1300
A65: ='Hiring plan'!C12 -> Compliance officer (AML/CFT) | B65: ='Hiring plan'!D12 -> SN | C65: ='Hiring plan'!J12 -> Y | D65: ='Hiring plan'!I12 -> 1500000 | E65: =D65*Employer_Charges -> 450000 | F65: =D65+E65 -> 1950000 | G65: =Regus_EUR*FX_EUR -> 196787.1 | H65: =Phone_Cost -> 5000 | I65: =(Gmail_USD+ClickUp_USD)*FX_USD -> 10440 | J65: =IF('Hiring plan'!B12="Engineering & product",Claude_USD*FX_USD,0) -> 0 | K65: =SUM(F65:J65) -> 2162227.1 | L65: =IF('Hiring plan'!B12="Engineering & product",Laptop_Dev_USD*FX_USD,Laptop_EUR*FX_EUR)+IF(C65="Y",Agency_Fee_EUR*FX_EUR,0) -> 852744.1
A66: in € | D66: =IF(ISNUMBER(D65),D65/FX_EUR,"") -> 2286.7353 | E66: =IF(ISNUMBER(E65),E65/FX_EUR,"") -> 686.02058 | F66: =IF(ISNUMBER(F65),F65/FX_EUR,"") -> 2972.7558 | G66: =IF(ISNUMBER(G65),G65/FX_EUR,"") -> 300 | H66: =IF(ISNUMBER(H65),H65/FX_EUR,"") -> 7.6224509 | I66: =IF(ISNUMBER(I65),I65/FX_EUR,"") -> 15.915677 | J66: =IF(ISNUMBER(J65),J65/FX_EUR,"") -> 0 | K66: =IF(ISNUMBER(K65),K65/FX_EUR,"") -> 3296.294 | L66: =IF(ISNUMBER(L65),L65/FX_EUR,"") -> 1300
A67: Customer support agent (grows with volume) | B67: SN | C67: =IF(Agency_Support=1,"Y","N") -> N | D67: =Salary_Support -> 280000 | E67: =D67*Employer_Charges -> 84000 | F67: =D67+E67 -> 364000 | G67: =Regus_EUR*FX_EUR -> 196787.1 | H67: =Phone_Cost -> 5000 | I67: =(Gmail_USD+ClickUp_USD)*FX_USD -> 10440 | J67: =0 -> 0 | K67: =SUM(F67:J67) -> 576227.1 | L67: =IF(FALSE(),Laptop_Dev_USD*FX_USD,Laptop_EUR*FX_EUR)+IF(C67="Y",Agency_Fee_EUR*FX_EUR,0) -> 327978.5
A68: in € | D68: =IF(ISNUMBER(D67),D67/FX_EUR,"") -> 426.85725 | E68: =IF(ISNUMBER(E67),E67/FX_EUR,"") -> 128.05717 | F68: =IF(ISNUMBER(F67),F67/FX_EUR,"") -> 554.91442 | G68: =IF(ISNUMBER(G67),G67/FX_EUR,"") -> 300 | H68: =IF(ISNUMBER(H67),H67/FX_EUR,"") -> 7.6224509 | I68: =IF(ISNUMBER(I67),I67/FX_EUR,"") -> 15.915677 | J68: =IF(ISNUMBER(J67),J67/FX_EUR,"") -> 0 | K68: =IF(ISNUMBER(K67),K67/FX_EUR,"") -> 878.45255 | L68: =IF(ISNUMBER(L67),L67/FX_EUR,"") -> 500
A69: Developer (grows with volume) | B69: SN | C69: =IF(Agency_Dev=1,"Y","N") -> Y | D69: =Salary_Dev -> 1200000 | E69: =D69*Employer_Charges -> 360000 | F69: =D69+E69 -> 1560000 | G69: =Regus_EUR*FX_EUR -> 196787.1 | H69: =Phone_Cost -> 5000 | I69: =(Gmail_USD+ClickUp_USD)*FX_USD -> 10440 | J69: =Claude_USD*FX_USD -> 14500 | K69: =SUM(F69:J69) -> 1786727.1 | L69: =IF(TRUE(),Laptop_Dev_USD*FX_USD,Laptop_EUR*FX_EUR)+IF(C69="Y",Agency_Fee_EUR*FX_EUR,0) -> 1684765.6
A70: in € | D70: =IF(ISNUMBER(D69),D69/FX_EUR,"") -> 1829.3882 | E70: =IF(ISNUMBER(E69),E69/FX_EUR,"") -> 548.81646 | F70: =IF(ISNUMBER(F69),F69/FX_EUR,"") -> 2378.2047 | G70: =IF(ISNUMBER(G69),G69/FX_EUR,"") -> 300 | H70: =IF(ISNUMBER(H69),H69/FX_EUR,"") -> 7.6224509 | I70: =IF(ISNUMBER(I69),I69/FX_EUR,"") -> 15.915677 | J70: =IF(ISNUMBER(J69),J69/FX_EUR,"") -> 22.105107 | K70: =IF(ISNUMBER(K69),K69/FX_EUR,"") -> 2723.8479 | L70: =IF(ISNUMBER(L69),L69/FX_EUR,"") -> 2568.4086
A71: Field sales rep, Senegal (grows with volume) | B71: SN | C71: =IF(Agency_Rep=1,"Y","N") -> N | D71: =Salary_Rep_SN -> 400000 | E71: =D71*Employer_Charges -> 120000 | F71: =D71+E71 -> 520000 | G71: =Regus_EUR*FX_EUR -> 196787.1 | H71: =Phone_Cost -> 5000 | I71: =(Gmail_USD+ClickUp_USD)*FX_USD -> 10440 | J71: =0 -> 0 | K71: =SUM(F71:J71) -> 732227.1 | L71: =IF(FALSE(),Laptop_Dev_USD*FX_USD,Laptop_EUR*FX_EUR)+IF(C71="Y",Agency_Fee_EUR*FX_EUR,0) -> 327978.5
A72: in € | D72: =IF(ISNUMBER(D71),D71/FX_EUR,"") -> 609.79607 | E72: =IF(ISNUMBER(E71),E71/FX_EUR,"") -> 182.93882 | F72: =IF(ISNUMBER(F71),F71/FX_EUR,"") -> 792.73489 | G72: =IF(ISNUMBER(G71),G71/FX_EUR,"") -> 300 | H72: =IF(ISNUMBER(H71),H71/FX_EUR,"") -> 7.6224509 | I72: =IF(ISNUMBER(I71),I71/FX_EUR,"") -> 15.915677 | J72: =IF(ISNUMBER(J71),J71/FX_EUR,"") -> 0 | K72: =IF(ISNUMBER(K71),K71/FX_EUR,"") -> 1116.273 | L72: =IF(ISNUMBER(L71),L71/FX_EUR,"") -> 500
A73: Field sales rep, Côte d'Ivoire (grows with volume) | B73: CI | C73: =IF(Agency_Rep=1,"Y","N") -> N | D73: =Salary_Rep_CI -> 450000 | E73: =D73*Employer_Charges -> 135000 | F73: =D73+E73 -> 585000 | G73: =Regus_EUR*FX_EUR -> 196787.1 | H73: =Phone_Cost -> 5000 | I73: =(Gmail_USD+ClickUp_USD)*FX_USD -> 10440 | J73: =0 -> 0 | K73: =SUM(F73:J73) -> 797227.1 | L73: =IF(FALSE(),Laptop_Dev_USD*FX_USD,Laptop_EUR*FX_EUR)+IF(C73="Y",Agency_Fee_EUR*FX_EUR,0) -> 327978.5
A74: in € | D74: =IF(ISNUMBER(D73),D73/FX_EUR,"") -> 686.02058 | E74: =IF(ISNUMBER(E73),E73/FX_EUR,"") -> 205.80617 | F74: =IF(ISNUMBER(F73),F73/FX_EUR,"") -> 891.82675 | G74: =IF(ISNUMBER(G73),G73/FX_EUR,"") -> 300 | H74: =IF(ISNUMBER(H73),H73/FX_EUR,"") -> 7.6224509 | I74: =IF(ISNUMBER(I73),I73/FX_EUR,"") -> 15.915677 | J74: =IF(ISNUMBER(J73),J73/FX_EUR,"") -> 0 | K74: =IF(ISNUMBER(K73),K73/FX_EUR,"") -> 1215.3649 | L74: =IF(ISNUMBER(L73),L73/FX_EUR,"") -> 500
A75: Credit analyst (grows with volume) | B75: SN | C75: =IF(Agency_Credit=1,"Y","N") -> Y | D75: =Salary_Credit -> 600000 | E75: =D75*Employer_Charges -> 180000 | F75: =D75+E75 -> 780000 | G75: =Regus_EUR*FX_EUR -> 196787.1 | H75: =Phone_Cost -> 5000 | I75: =(Gmail_USD+ClickUp_USD)*FX_USD -> 10440 | J75: =0 -> 0 | K75: =SUM(F75:J75) -> 992227.1 | L75: =IF(FALSE(),Laptop_Dev_USD*FX_USD,Laptop_EUR*FX_EUR)+IF(C75="Y",Agency_Fee_EUR*FX_EUR,0) -> 852744.1
A76: in € | D76: =IF(ISNUMBER(D75),D75/FX_EUR,"") -> 914.6941 | E76: =IF(ISNUMBER(E75),E75/FX_EUR,"") -> 274.40823 | F76: =IF(ISNUMBER(F75),F75/FX_EUR,"") -> 1189.1023 | G76: =IF(ISNUMBER(G75),G75/FX_EUR,"") -> 300 | H76: =IF(ISNUMBER(H75),H75/FX_EUR,"") -> 7.6224509 | I76: =IF(ISNUMBER(I75),I75/FX_EUR,"") -> 15.915677 | J76: =IF(ISNUMBER(J75),J75/FX_EUR,"") -> 0 | K76: =IF(ISNUMBER(K75),K75/FX_EUR,"") -> 1512.6405 | L76: =IF(ISNUMBER(L75),L75/FX_EUR,"") -> 1300
A77: Company-wide, not per person: 2 shared Claude seats, the website and domain. Field reps also get the transport allowance (Sales & marketing). Pay rises 5% a year from year 2.
A79: One business client, per month, by plan
A80: Steady state: after the free month, payment links and paid modules at full adoption, no credit. Pricing option and scenario inputs at their current value.
A81: Line | B81: How it is calculated | D81: Essentiel (small firm) | E81: Pro (mid-size firm) | F81: Business (large firm)
A82: Revenue
A83: Subscription (after the yearly-billing discount) | B83: Plan price × (1 − share paying yearly × free months on yearly billing ÷ 12) | D83: =Price_Petite*(1-Annual_Share*Annual_Free/12) -> 9405 | E83: =Price_Moyenne*(1-Annual_Share*Annual_Free/12) -> 18525 | F83: =Price_Grande*(1-Annual_Share*Annual_Free/12) -> 66025
A84: in € | D84: =IF(ISNUMBER(D83),D83/FX_EUR,"") -> 14.33783 | E84: =IF(ISNUMBER(E83),E83/FX_EUR,"") -> 28.24118 | F84: =IF(ISNUMBER(F83),F83/FX_EUR,"") -> 100.65446
A85: Fees on foreign-currency card spending | B85: Foreign-currency card spending × (FX fee + fixed fee ÷ average payment) | D85: =Spend_For_Petite*Foreign_Spend_Factor*(FX_Fee+FX_Fixed_Fee/FX_Avg_Txn) -> 11400 | E85: =Spend_For_Moyenne*Foreign_Spend_Factor*(FX_Fee+FX_Fixed_Fee/FX_Avg_Txn) -> 45600 | F85: =Spend_For_Grande*Foreign_Spend_Factor*(FX_Fee+FX_Fixed_Fee/FX_Avg_Txn) -> 133000
A86: in € | D86: =IF(ISNUMBER(D85),D85/FX_EUR,"") -> 17.379188 | E86: =IF(ISNUMBER(E85),E85/FX_EUR,"") -> 69.516752 | F86: =IF(ISNUMBER(F85),F85/FX_EUR,"") -> 202.75719
A87: Bank transfers above the plan allowance | B87: Paid bank transfers above the allowance × fee per transfer | D87: =Overage_Petite*(1-Sup_Wallet_Share)*Overage_Fee -> 270 | E87: =Overage_Moyenne*(1-Sup_Wallet_Share)*Overage_Fee -> 810 | F87: =Overage_Grande*(1-Sup_Wallet_Share)*Overage_Fee -> 2700
A88: in € | D88: =IF(ISNUMBER(D87),D87/FX_EUR,"") -> 0.41161235 | E88: =IF(ISNUMBER(E87),E87/FX_EUR,"") -> 1.234837 | F88: =IF(ISNUMBER(F87),F87/FX_EUR,"") -> 4.1161235
A89: Payment link fees (average client) | B89: Collections × adoption × share by mobile money × fee | D89: =PL_Coll_Petite*PL_Adoption*PL_Momo_Share*PL_Fee -> 1680 | E89: =PL_Coll_Moyenne*PL_Adoption*PL_Momo_Share*PL_Fee -> 6300 | F89: =PL_Coll_Grande*PL_Adoption*PL_Momo_Share*PL_Fee -> 21000
A90: in € | D90: =IF(ISNUMBER(D89),D89/FX_EUR,"") -> 2.5611435 | E90: =IF(ISNUMBER(E89),E89/FX_EUR,"") -> 9.6042881 | F90: =IF(ISNUMBER(F89),F89/FX_EUR,"") -> 32.014294
A91: Extra users | B91: Users beyond the plan × fee per user | D91: =MAX(0,Users_Petite-Users_Incl_Petite)*Extra_User_Fee -> 0 | E91: =MAX(0,Users_Moyenne-Users_Incl_Moyenne)*Extra_User_Fee -> 2500 | F91: =MAX(0,Users_Grande-Users_Incl_Grande)*Extra_User_Fee -> 5000
A92: in € | D92: =IF(ISNUMBER(D91),D91/FX_EUR,"") -> 0 | E92: =IF(ISNUMBER(E91),E91/FX_EUR,"") -> 3.8112254 | F92: =IF(ISNUMBER(F91),F91/FX_EUR,"") -> 7.6224509
A93: Mobile money above the free amount (average client) | B93: Amount sent to wallets above the plan's free amount × fee (clients spread around the average) | D93: =(MM_Low_Share*MAX(0,0.5*(Emp_Petite*Avg_Salary*Wallet_Share+Supplier_Petite*Sup_Wallet_Share*Sup_Avg_Amount)-MM_Free_Petite)+MM_Mid_Share*MAX(0,(Emp_Petite*Avg_Salary*Wallet_Share+Supplier_Petite*Sup_Wallet_Share*Sup_Avg_Amount)-MM_Free_Petite)+(1-MM_Low_Share-MM_Mid_Share)*MAX(0,2.25*(Emp_Petite*Avg_Salary*Wallet_Share+Supplier_Petite*Sup_Wallet_Share*Sup_Avg_Amount)-MM_Free_Petite))*MM_Fee -> 9375 | E93: =(MM_Low_Share*MAX(0,0.5*(Emp_Moyenne*Avg_Salary*Wallet_Share+Supplier_Moyenne*Sup_Wallet_Share*Sup_Avg_Amount)-MM_Free_Moyenne)+MM_Mid_Share*MAX(0,(Emp_Moyenne*Avg_Salary*Wallet_Share+Supplier_Moyenne*Sup_Wallet_Share*Sup_Avg_Amount)-MM_Free_Moyenne)+(1-MM_Low_Share-MM_Mid_Share)*MAX(0,2.25*(Emp_Moyenne*Avg_Salary*Wallet_Share+Supplier_Moyenne*Sup_Wallet_Share*Sup_Avg_Amount)-MM_Free_Moyenne))*MM_Fee -> 43125 | F93: =(MM_Low_Share*MAX(0,0.5*(Emp_Grande*Avg_Salary*Wallet_Share+Supplier_Grande*Sup_Wallet_Share*Sup_Avg_Amount)-MM_Free_Grande)+MM_Mid_Share*MAX(0,(Emp_Grande*Avg_Salary*Wallet_Share+Supplier_Grande*Sup_Wallet_Share*Sup_Avg_Amount)-MM_Free_Grande)+(1-MM_Low_Share-MM_Mid_Share)*MAX(0,2.25*(Emp_Grande*Avg_Salary*Wallet_Share+Supplier_Grande*Sup_Wallet_Share*Sup_Avg_Amount)-MM_Free_Grande))*MM_Fee -> 188750
A94: in € | D94: =IF(ISNUMBER(D93),D93/FX_EUR,"") -> 14.292095 | E94: =IF(ISNUMBER(E93),E93/FX_EUR,"") -> 65.743639 | F94: =IF(ISNUMBER(F93),F93/FX_EUR,"") -> 287.74752
A95: Payroll module (average client) | B95: Employees × uptake × price per payslip | D95: =Emp_Petite*Payroll_Mod_Uptake*Payslip_Fee -> 1800 | E95: =Emp_Moyenne*Payroll_Mod_Uptake*Payslip_Fee -> 9000 | F95: =Emp_Grande*Payroll_Mod_Uptake*Payslip_Fee -> 43200
A96: in € | D96: =IF(ISNUMBER(D95),D95/FX_EUR,"") -> 2.7440823 | E96: =IF(ISNUMBER(E95),E95/FX_EUR,"") -> 13.720412 | F96: =IF(ISNUMBER(F95),F95/FX_EUR,"") -> 65.857975
A97: International payments (average client) | B97: Monthly volume × uptake × (fee + fixed fee ÷ average payment) | D97: =Intl_Vol_Petite*Intl_Uptake*(Intl_Fee+Intl_Fixed_Fee/Intl_Avg_Payment) -> 5135 | E97: =Intl_Vol_Moyenne*Intl_Uptake*(Intl_Fee+Intl_Fixed_Fee/Intl_Avg_Payment) -> 11850 | F97: =Intl_Vol_Grande*Intl_Uptake*(Intl_Fee+Intl_Fixed_Fee/Intl_Avg_Payment) -> 47400
A98: in € | D98: =IF(ISNUMBER(D97),D97/FX_EUR,"") -> 7.828257 | E98: =IF(ISNUMBER(E97),E97/FX_EUR,"") -> 18.065209 | F98: =IF(ISNUMBER(F97),F97/FX_EUR,"") -> 72.260834
A99: Revenue per client | D99: =D83+D85+D87+D89+D91+D93+D95+D97 -> 39065 | E99: =E83+E85+E87+E89+E91+E93+E95+E97 -> 137710 | F99: =F83+F85+F87+F89+F91+F93+F95+F97 -> 507075
A100: in € | D100: =IF(ISNUMBER(D99),D99/FX_EUR,"") -> 59.554209 | E100: =IF(ISNUMBER(E99),E99/FX_EUR,"") -> 209.93754 | F100: =IF(ISNUMBER(F99),F99/FX_EUR,"") -> 773.03085
A101: Cost to serve
A102: Partner bank fee per business account | B102: Flat fee per account | D102: =Bank_Fee -> 1500 | E102: =Bank_Fee -> 1500 | F102: =Bank_Fee -> 1500
A103: in € | D103: =IF(ISNUMBER(D102),D102/FX_EUR,"") -> 2.2867353 | E103: =IF(ISNUMBER(E102),E102/FX_EUR,"") -> 2.2867353 | F103: =IF(ISNUMBER(F102),F102/FX_EUR,"") -> 2.2867353
A104: Card processing | B104: Active cards × processing fee per card | D104: =Cards_Act_Petite*Card_Proc_Fee -> 1200 | E104: =Cards_Act_Moyenne*Card_Proc_Fee -> 3600 | F104: =Cards_Act_Grande*Card_Proc_Fee -> 6000
...

Sheet Hiring plan
A1: Hiring plan
A2: One line per hire or group of identical hires. Edit headcount, start month, end month (leave blank if they stay) and gross salary. Spare lines at the bottom for new roles.
A4: # | B4: Department | C4: Role | D4: Country | E4: Category | F4: Headcount | G4: Start month | H4: End month | I4: Gross salary (FCFA / month) | J4: Agency hire (Y/N) | K4: Employer cost per person (FCFA / month) | L4: Note | M4: Gross salary (€ / month) | N4: Employer cost per person (€ / month)
A5: 1 | B5: Leadership | C5: CEO (full salary from year 2) | D5: SN | F5: 1 | G5: 13 | I5: 2500000 | J5: Y | K5: =IF(I5="",0,I5*(1+Employer_Charges)) -> 3250000 | L5: Founders and shareholders run the company unpaid in year 1 (decision). | M5: =IF(N(I5)=0,0,I5/FX_EUR) -> 3811.2254 | N5: =IF(N(K5)=0,0,K5/FX_EUR) -> 4954.5931
A6: 2 | B6: Engineering & product | C6: CTO (also codes) | D6: SN | F6: 1 | G6: 1 | I6: 2500000 | J6: Y | K6: =IF(I6="",0,I6*(1+Employer_Charges)) -> 3250000 | L6: Developers are added with volume on the Staff sheet (2 at the start). | M6: =IF(N(I6)=0,0,I6/FX_EUR) -> 3811.2254 | N6: =IF(N(K6)=0,0,K6/FX_EUR) -> 4954.5931
A7: 3 | B7: Finance & admin | C7: Financial expert (finance, partners, credit lead) | D7: SN | F7: 1 | G7: 1 | I7: 1500000 | J7: Y | K7: =IF(I7="",0,I7*(1+Employer_Charges)) -> 1950000 | L7: Starting team. Credit analysts are added with the loan book. | M7: =IF(N(I7)=0,0,I7/FX_EUR) -> 2286.7353 | N7: =IF(N(K7)=0,0,K7/FX_EUR) -> 2972.7558
A8: 4 | B8: Sales & partnerships | C8: Sales lead (also sells; incl. bonus) | D8: SN | E8: Sales rep | F8: 1 | G8: 1 | I8: 1200000 | J8: N | K8: =IF(I8="",0,I8*(1+Employer_Charges)) -> 1560000 | L8: Plus 2 field reps from month 4, then reps grow with clients (Staff sheet). | M8: =IF(N(I8)=0,0,I8/FX_EUR) -> 1829.3882 | N8: =IF(N(K8)=0,0,K8/FX_EUR) -> 2378.2047
A9: 5 | B9: Marketing | C9: Marketing manager (senior) | D9: SN | F9: 1 | G9: 4 | I9: 900000 | J9: N | K9: =IF(I9="",0,I9*(1+Employer_Charges)) -> 1170000 | L9: Prepares the launch; runs digital ads and partnerships. | M9: =IF(N(I9)=0,0,I9/FX_EUR) -> 1372.0412 | N9: =IF(N(K9)=0,0,K9/FX_EUR) -> 1783.6535
A10: 6 | B10: Marketing | C10: Marketing officer (junior) | D10: SN | F10: 1 | G10: 5 | I10: 400000 | J10: N | K10: =IF(I10="",0,I10*(1+Employer_Charges)) -> 520000 | L10: Content, social media, events. | M10: =IF(N(I10)=0,0,I10/FX_EUR) -> 609.79607 | N10: =IF(N(K10)=0,0,K10/FX_EUR) -> 792.73489
A11: 7 | B11: Leadership | C11: Country manager, Abidjan | D11: CI | F11: 1 | G11: =CI_Office_Start -> 18 | I11: 2800000 | J11: Y | K11: =IF(I11="",0,I11*(1+Employer_Charges)) -> 3640000 | L11: Joins when the Abidjan office opens. | M11: =IF(N(I11)=0,0,I11/FX_EUR) -> 4268.5725 | N11: =IF(N(K11)=0,0,K11/FX_EUR) -> 5549.1442
A12: 8 | B12: Compliance & risk | C12: Compliance officer (AML/CFT) | D12: SN | F12: 1 | G12: =SFD_Acq_Month -> 24 | I12: 1500000 | J12: Y | K12: =IF(I12="",0,I12*(1+Employer_Charges)) -> 1950000 | L12: Required once Kelen holds its own licence (SFD). | M12: =IF(N(I12)=0,0,I12/FX_EUR) -> 2286.7353 | N12: =IF(N(K12)=0,0,K12/FX_EUR) -> 2972.7558
A13: 9 | K13: =IF(I13="",0,I13*(1+Employer_Charges)) -> 0 | M13: =IF(N(I13)=0,0,I13/FX_EUR) -> 0 | N13: =IF(N(K13)=0,0,K13/FX_EUR) -> 0
A14: 10 | K14: =IF(I14="",0,I14*(1+Employer_Charges)) -> 0 | M14: =IF(N(I14)=0,0,I14/FX_EUR) -> 0 | N14: =IF(N(K14)=0,0,K14/FX_EUR) -> 0
A15: 11 | K15: =IF(I15="",0,I15*(1+Employer_Charges)) -> 0 | M15: =IF(N(I15)=0,0,I15/FX_EUR) -> 0 | N15: =IF(N(K15)=0,0,K15/FX_EUR) -> 0
A16: 12 | K16: =IF(I16="",0,I16*(1+Employer_Charges)) -> 0 | M16: =IF(N(I16)=0,0,I16/FX_EUR) -> 0 | N16: =IF(N(K16)=0,0,K16/FX_EUR) -> 0
A17: 13 | K17: =IF(I17="",0,I17*(1+Employer_Charges)) -> 0 | M17: =IF(N(I17)=0,0,I17/FX_EUR) -> 0 | N17: =IF(N(K17)=0,0,K17/FX_EUR) -> 0
A18: 14 | K18: =IF(I18="",0,I18*(1+Employer_Charges)) -> 0 | M18: =IF(N(I18)=0,0,I18/FX_EUR) -> 0 | N18: =IF(N(K18)=0,0,K18/FX_EUR) -> 0
A19: 15 | K19: =IF(I19="",0,I19*(1+Employer_Charges)) -> 0 | M19: =IF(N(I19)=0,0,I19/FX_EUR) -> 0 | N19: =IF(N(K19)=0,0,K19/FX_EUR) -> 0
A20: 16 | K20: =IF(I20="",0,I20*(1+Employer_Charges)) -> 0 | M20: =IF(N(I20)=0,0,I20/FX_EUR) -> 0 | N20: =IF(N(K20)=0,0,K20/FX_EUR) -> 0
A21: 17 | K21: =IF(I21="",0,I21*(1+Employer_Charges)) -> 0 | M21: =IF(N(I21)=0,0,I21/FX_EUR) -> 0 | N21: =IF(N(K21)=0,0,K21/FX_EUR) -> 0
A22: 18 | K22: =IF(I22="",0,I22*(1+Employer_Charges)) -> 0 | M22: =IF(N(I22)=0,0,I22/FX_EUR) -> 0 | N22: =IF(N(K22)=0,0,K22/FX_EUR) -> 0
A23: 19 | K23: =IF(I23="",0,I23*(1+Employer_Charges)) -> 0 | M23: =IF(N(I23)=0,0,I23/FX_EUR) -> 0 | N23: =IF(N(K23)=0,0,K23/FX_EUR) -> 0
A24: 20 | K24: =IF(I24="",0,I24*(1+Employer_Charges)) -> 0 | M24: =IF(N(I24)=0,0,I24/FX_EUR) -> 0 | N24: =IF(N(K24)=0,0,K24/FX_EUR) -> 0
... A32: 28 | K32: =IF(I32="",0,I32*(1+Employer_Charges)) -> 0 | M32: =IF(N(I32)=0,0,I32/FX_EUR) -> 0 | N32: =IF(N(K32)=0,0,K32/FX_EUR) -> 0
B34: Employer cost = gross salary × (1 + employer charges), 30% on Assumptions section 8. Customer support, developers, field sales reps and credit analysts grow with volume: see the Staff sheet and the ratios on Assumptions section 8.

Sheet Staff
A1: Staff
A2: Headcount and employer cost by month, from the hiring plan. Pay rises each year by the rate on Assumptions.
A3: Month # | D3: Total / end | E3: 1 | F3: =E3+1 -> 2 | G3: =F3+1 -> 3 | H3: =G3+1 -> 4 | I3: =H3+1 -> 5 | J3: =I3+1 -> 6 | K3: =J3+1 -> 7 | L3: =K3+1 -> 8 | M3: =L3+1 -> 9 | ... BL3: =BK3+1 -> 60
A4: Month | E4: =DATE(YEAR(Start_Date),MONTH(Start_Date)+E3-1,1) -> 46388 | F4: =DATE(YEAR(Start_Date),MONTH(Start_Date)+F3-1,1) -> 46419 | G4: =DATE(YEAR(Start_Date),MONTH(Start_Date)+G3-1,1) -> 46447 | H4: =DATE(YEAR(Start_Date),MONTH(Start_Date)+H3-1,1) -> 46478 | I4: =DATE(YEAR(Start_Date),MONTH(Start_Date)+I3-1,1) -> 46508 | J4: =DATE(YEAR(Start_Date),MONTH(Start_Date)+J3-1,1) -> 46539 | K4: =DATE(YEAR(Start_Date),MONTH(Start_Date)+K3-1,1) -> 46569 | L4: =DATE(YEAR(Start_Date),MONTH(Start_Date)+L3-1,1) -> 46600 | ... BL4: =DATE(YEAR(Start_Date),MONTH(Start_Date)+BL3-1,1) -> 48183
A5: Year | E5: =INT((E3-1)/12)+1 -> 1 | F5: =INT((F3-1)/12)+1 -> 1 | G5: =INT((G3-1)/12)+1 -> 1 | H5: =INT((H3-1)/12)+1 -> 1 | I5: =INT((I3-1)/12)+1 -> 1 | J5: =INT((J3-1)/12)+1 -> 1 | K5: =INT((K3-1)/12)+1 -> 1 | L5: =INT((L3-1)/12)+1 -> 1 | ... BL5: =INT((BL3-1)/12)+1 -> 5
A8: Headcount by hire line
A9: =IF('Hiring plan'!$C$5="","(spare line 1)",'Hiring plan'!$C$5&" · "&'Hiring plan'!$D$5) -> CEO (full salary from year 2) · SN | B9: people | D9: =MAX(E9:BL9) -> 1 | E9: =IF(AND(N('Hiring plan'!$F$5)>0,E$3>='Hiring plan'!$G$5,E$3<=IF('Hiring plan'!$H$5="",999,'Hiring plan'!$H$5)),'Hiring plan'!$F$5,0) -> 0 | F9: =IF(AND(N('Hiring plan'!$F$5)>0,F$3>='Hiring plan'!$G$5,F$3<=IF('Hiring plan'!$H$5="",999,'Hiring plan'!$H$5)),'Hiring plan'!$F$5,0) -> 0 | G9: =IF(AND(N('Hiring plan'!$F$5)>0,G$3>='Hiring plan'!$G$5,G$3<=IF('Hiring plan'!$H$5="",999,'Hiring plan'!$H$5)),'Hiring plan'!$F$5,0) -> 0 | H9: =IF(AND(N('Hiring plan'!$F$5)>0,H$3>='Hiring plan'!$G$5,H$3<=IF('Hiring plan'!$H$5="",999,'Hiring plan'!$H$5)),'Hiring plan'!$F$5,0) -> 0 | I9: =IF(AND(N('Hiring plan'!$F$5)>0,I$3>='Hiring plan'!$G$5,I$3<=IF('Hiring plan'!$H$5="",999,'Hiring plan'!$H$5)),'Hiring plan'!$F$5,0) -> 0 | J9: =IF(AND(N('Hiring plan'!$F$5)>0,J$3>='Hiring plan'!$G$5,J$3<=IF('Hiring plan'!$H$5="",999,'Hiring plan'!$H$5)),'Hiring plan'!$F$5,0) -> 0 | K9: =IF(AND(N('Hiring plan'!$F$5)>0,K$3>='Hiring plan'!$G$5,K$3<=IF('Hiring plan'!$H$5="",999,'Hiring plan'!$H$5)),'Hiring plan'!$F$5,0) -> 0 | L9: =IF(AND(N('Hiring plan'!$F$5)>0,L$3>='Hiring plan'!$G$5,L$3<=IF('Hiring plan'!$H$5="",999,'Hiring plan'!$H$5)),'Hiring plan'!$F$5,0) -> 0 | ... BL9: =IF(AND(N('Hiring plan'!$F$5)>0,BL$3>='Hiring plan'!$G$5,BL$3<=IF('Hiring plan'!$H$5="",999,'Hiring plan'!$H$5)),'Hiring plan'!$F$5,0) -> 1
A10: =IF('Hiring plan'!$C$6="","(spare line 2)",'Hiring plan'!$C$6&" · "&'Hiring plan'!$D$6) -> CTO (also codes) · SN | B10: people | D10: =MAX(E10:BL10) -> 1 | E10: =IF(AND(N('Hiring plan'!$F$6)>0,E$3>='Hiring plan'!$G$6,E$3<=IF('Hiring plan'!$H$6="",999,'Hiring plan'!$H$6)),'Hiring plan'!$F$6,0) -> 1 | F10: =IF(AND(N('Hiring plan'!$F$6)>0,F$3>='Hiring plan'!$G$6,F$3<=IF('Hiring plan'!$H$6="",999,'Hiring plan'!$H$6)),'Hiring plan'!$F$6,0) -> 1 | G10: =IF(AND(N('Hiring plan'!$F$6)>0,G$3>='Hiring plan'!$G$6,G$3<=IF('Hiring plan'!$H$6="",999,'Hiring plan'!$H$6)),'Hiring plan'!$F$6,0) -> 1 | H10: =IF(AND(N('Hiring plan'!$F$6)>0,H$3>='Hiring plan'!$G$6,H$3<=IF('Hiring plan'!$H$6="",999,'Hiring plan'!$H$6)),'Hiring plan'!$F$6,0) -> 1 | I10: =IF(AND(N('Hiring plan'!$F$6)>0,I$3>='Hiring plan'!$G$6,I$3<=IF('Hiring plan'!$H$6="",999,'Hiring plan'!$H$6)),'Hiring plan'!$F$6,0) -> 1 | J10: =IF(AND(N('Hiring plan'!$F$6)>0,J$3>='Hiring plan'!$G$6,J$3<=IF('Hiring plan'!$H$6="",999,'Hiring plan'!$H$6)),'Hiring plan'!$F$6,0) -> 1 | K10: =IF(AND(N('Hiring plan'!$F$6)>0,K$3>='Hiring plan'!$G$6,K$3<=IF('Hiring plan'!$H$6="",999,'Hiring plan'!$H$6)),'Hiring plan'!$F$6,0) -> 1 | L10: =IF(AND(N('Hiring plan'!$F$6)>0,L$3>='Hiring plan'!$G$6,L$3<=IF('Hiring plan'!$H$6="",999,'Hiring plan'!$H$6)),'Hiring plan'!$F$6,0) -> 1 | ... BL10: =IF(AND(N('Hiring plan'!$F$6)>0,BL$3>='Hiring plan'!$G$6,BL$3<=IF('Hiring plan'!$H$6="",999,'Hiring plan'!$H$6)),'Hiring plan'!$F$6,0) -> 1
A11: =IF('Hiring plan'!$C$7="","(spare line 3)",'Hiring plan'!$C$7&" · "&'Hiring plan'!$D$7) -> Financial expert (finance, partners, credit lead) · SN | B11: people | D11: =MAX(E11:BL11) -> 1 | E11: =IF(AND(N('Hiring plan'!$F$7)>0,E$3>='Hiring plan'!$G$7,E$3<=IF('Hiring plan'!$H$7="",999,'Hiring plan'!$H$7)),'Hiring plan'!$F$7,0) -> 1 | F11: =IF(AND(N('Hiring plan'!$F$7)>0,F$3>='Hiring plan'!$G$7,F$3<=IF('Hiring plan'!$H$7="",999,'Hiring plan'!$H$7)),'Hiring plan'!$F$7,0) -> 1 | G11: =IF(AND(N('Hiring plan'!$F$7)>0,G$3>='Hiring plan'!$G$7,G$3<=IF('Hiring plan'!$H$7="",999,'Hiring plan'!$H$7)),'Hiring plan'!$F$7,0) -> 1 | H11: =IF(AND(N('Hiring plan'!$F$7)>0,H$3>='Hiring plan'!$G$7,H$3<=IF('Hiring plan'!$H$7="",999,'Hiring plan'!$H$7)),'Hiring plan'!$F$7,0) -> 1 | I11: =IF(AND(N('Hiring plan'!$F$7)>0,I$3>='Hiring plan'!$G$7,I$3<=IF('Hiring plan'!$H$7="",999,'Hiring plan'!$H$7)),'Hiring plan'!$F$7,0) -> 1 | J11: =IF(AND(N('Hiring plan'!$F$7)>0,J$3>='Hiring plan'!$G$7,J$3<=IF('Hiring plan'!$H$7="",999,'Hiring plan'!$H$7)),'Hiring plan'!$F$7,0) -> 1 | K11: =IF(AND(N('Hiring plan'!$F$7)>0,K$3>='Hiring plan'!$G$7,K$3<=IF('Hiring plan'!$H$7="",999,'Hiring plan'!$H$7)),'Hiring plan'!$F$7,0) -> 1 | L11: =IF(AND(N('Hiring plan'!$F$7)>0,L$3>='Hiring plan'!$G$7,L$3<=IF('Hiring plan'!$H$7="",999,'Hiring plan'!$H$7)),'Hiring plan'!$F$7,0) -> 1 | ... BL11: =IF(AND(N('Hiring plan'!$F$7)>0,BL$3>='Hiring plan'!$G$7,BL$3<=IF('Hiring plan'!$H$7="",999,'Hiring plan'!$H$7)),'Hiring plan'!$F$7,0) -> 1
A12: =IF('Hiring plan'!$C$8="","(spare line 4)",'Hiring plan'!$C$8&" · "&'Hiring plan'!$D$8) -> Sales lead (also sells; incl. bonus) · SN | B12: people | D12: =MAX(E12:BL12) -> 1 | E12: =IF(AND(N('Hiring plan'!$F$8)>0,E$3>='Hiring plan'!$G$8,E$3<=IF('Hiring plan'!$H$8="",999,'Hiring plan'!$H$8)),'Hiring plan'!$F$8,0) -> 1 | F12: =IF(AND(N('Hiring plan'!$F$8)>0,F$3>='Hiring plan'!$G$8,F$3<=IF('Hiring plan'!$H$8="",999,'Hiring plan'!$H$8)),'Hiring plan'!$F$8,0) -> 1 | G12: =IF(AND(N('Hiring plan'!$F$8)>0,G$3>='Hiring plan'!$G$8,G$3<=IF('Hiring plan'!$H$8="",999,'Hiring plan'!$H$8)),'Hiring plan'!$F$8,0) -> 1 | H12: =IF(AND(N('Hiring plan'!$F$8)>0,H$3>='Hiring plan'!$G$8,H$3<=IF('Hiring plan'!$H$8="",999,'Hiring plan'!$H$8)),'Hiring plan'!$F$8,0) -> 1 | I12: =IF(AND(N('Hiring plan'!$F$8)>0,I$3>='Hiring plan'!$G$8,I$3<=IF('Hiring plan'!$H$8="",999,'Hiring plan'!$H$8)),'Hiring plan'!$F$8,0) -> 1 | J12: =IF(AND(N('Hiring plan'!$F$8)>0,J$3>='Hiring plan'!$G$8,J$3<=IF('Hiring plan'!$H$8="",999,'Hiring plan'!$H$8)),'Hiring plan'!$F$8,0) -> 1 | K12: =IF(AND(N('Hiring plan'!$F$8)>0,K$3>='Hiring plan'!$G$8,K$3<=IF('Hiring plan'!$H$8="",999,'Hiring plan'!$H$8)),'Hiring plan'!$F$8,0) -> 1 | L12: =IF(AND(N('Hiring plan'!$F$8)>0,L$3>='Hiring plan'!$G$8,L$3<=IF('Hiring plan'!$H$8="",999,'Hiring plan'!$H$8)),'Hiring plan'!$F$8,0) -> 1 | ... BL12: =IF(AND(N('Hiring plan'!$F$8)>0,BL$3>='Hiring plan'!$G$8,BL$3<=IF('Hiring plan'!$H$8="",999,'Hiring plan'!$H$8)),'Hiring plan'!$F$8,0) -> 1
A13: =IF('Hiring plan'!$C$9="","(spare line 5)",'Hiring plan'!$C$9&" · "&'Hiring plan'!$D$9) -> Marketing manager (senior) · SN | B13: people | D13: =MAX(E13:BL13) -> 1 | E13: =IF(AND(N('Hiring plan'!$F$9)>0,E$3>='Hiring plan'!$G$9,E$3<=IF('Hiring plan'!$H$9="",999,'Hiring plan'!$H$9)),'Hiring plan'!$F$9,0) -> 0 | F13: =IF(AND(N('Hiring plan'!$F$9)>0,F$3>='Hiring plan'!$G$9,F$3<=IF('Hiring plan'!$H$9="",999,'Hiring plan'!$H$9)),'Hiring plan'!$F$9,0) -> 0 | G13: =IF(AND(N('Hiring plan'!$F$9)>0,G$3>='Hiring plan'!$G$9,G$3<=IF('Hiring plan'!$H$9="",999,'Hiring plan'!$H$9)),'Hiring plan'!$F$9,0) -> 0 | H13: =IF(AND(N('Hiring plan'!$F$9)>0,H$3>='Hiring plan'!$G$9,H$3<=IF('Hiring plan'!$H$9="",999,'Hiring plan'!$H$9)),'Hiring plan'!$F$9,0) -> 1 | I13: =IF(AND(N('Hiring plan'!$F$9)>0,I$3>='Hiring plan'!$G$9,I$3<=IF('Hiring plan'!$H$9="",999,'Hiring plan'!$H$9)),'Hiring plan'!$F$9,0) -> 1 | J13: =IF(AND(N('Hiring plan'!$F$9)>0,J$3>='Hiring plan'!$G$9,J$3<=IF('Hiring plan'!$H$9="",999,'Hiring plan'!$H$9)),'Hiring plan'!$F$9,0) -> 1 | K13: =IF(AND(N('Hiring plan'!$F$9)>0,K$3>='Hiring plan'!$G$9,K$3<=IF('Hiring plan'!$H$9="",999,'Hiring plan'!$H$9)),'Hiring plan'!$F$9,0) -> 1 | L13: =IF(AND(N('Hiring plan'!$F$9)>0,L$3>='Hiring plan'!$G$9,L$3<=IF('Hiring plan'!$H$9="",999,'Hiring plan'!$H$9)),'Hiring plan'!$F$9,0) -> 1 | ... BL13: =IF(AND(N('Hiring plan'!$F$9)>0,BL$3>='Hiring plan'!$G$9,BL$3<=IF('Hiring plan'!$H$9="",999,'Hiring plan'!$H$9)),'Hiring plan'!$F$9,0) -> 1
A14: =IF('Hiring plan'!$C$10="","(spare line 6)",'Hiring plan'!$C$10&" · "&'Hiring plan'!$D$10) -> Marketing officer (junior) · SN | B14: people | D14: =MAX(E14:BL14) -> 1 | E14: =IF(AND(N('Hiring plan'!$F$10)>0,E$3>='Hiring plan'!$G$10,E$3<=IF('Hiring plan'!$H$10="",999,'Hiring plan'!$H$10)),'Hiring plan'!$F$10,0) -> 0 | F14: =IF(AND(N('Hiring plan'!$F$10)>0,F$3>='Hiring plan'!$G$10,F$3<=IF('Hiring plan'!$H$10="",999,'Hiring plan'!$H$10)),'Hiring plan'!$F$10,0) -> 0 | G14: =IF(AND(N('Hiring plan'!$F$10)>0,G$3>='Hiring plan'!$G$10,G$3<=IF('Hiring plan'!$H$10="",999,'Hiring plan'!$H$10)),'Hiring plan'!$F$10,0) -> 0 | H14: =IF(AND(N('Hiring plan'!$F$10)>0,H$3>='Hiring plan'!$G$10,H$3<=IF('Hiring plan'!$H$10="",999,'Hiring plan'!$H$10)),'Hiring plan'!$F$10,0) -> 0 | I14: =IF(AND(N('Hiring plan'!$F$10)>0,I$3>='Hiring plan'!$G$10,I$3<=IF('Hiring plan'!$H$10="",999,'Hiring plan'!$H$10)),'Hiring plan'!$F$10,0) -> 1 | J14: =IF(AND(N('Hiring plan'!$F$10)>0,J$3>='Hiring plan'!$G$10,J$3<=IF('Hiring plan'!$H$10="",999,'Hiring plan'!$H$10)),'Hiring plan'!$F$10,0) -> 1 | K14: =IF(AND(N('Hiring plan'!$F$10)>0,K$3>='Hiring plan'!$G$10,K$3<=IF('Hiring plan'!$H$10="",999,'Hiring plan'!$H$10)),'Hiring plan'!$F$10,0) -> 1 | L14: =IF(AND(N('Hiring plan'!$F$10)>0,L$3>='Hiring plan'!$G$10,L$3<=IF('Hiring plan'!$H$10="",999,'Hiring plan'!$H$10)),'Hiring plan'!$F$10,0) -> 1 | ... BL14: =IF(AND(N('Hiring plan'!$F$10)>0,BL$3>='Hiring plan'!$G$10,BL$3<=IF('Hiring plan'!$H$10="",999,'Hiring plan'!$H$10)),'Hiring plan'!$F$10,0) -> 1
A15: =IF('Hiring plan'!$C$11="","(spare line 7)",'Hiring plan'!$C$11&" · "&'Hiring plan'!$D$11) -> Country manager, Abidjan · CI | B15: people | D15: =MAX(E15:BL15) -> 1 | E15: =IF(AND(N('Hiring plan'!$F$11)>0,E$3>='Hiring plan'!$G$11,E$3<=IF('Hiring plan'!$H$11="",999,'Hiring plan'!$H$11)),'Hiring plan'!$F$11,0) -> 0 | F15: =IF(AND(N('Hiring plan'!$F$11)>0,F$3>='Hiring plan'!$G$11,F$3<=IF('Hiring plan'!$H$11="",999,'Hiring plan'!$H$11)),'Hiring plan'!$F$11,0) -> 0 | G15: =IF(AND(N('Hiring plan'!$F$11)>0,G$3>='Hiring plan'!$G$11,G$3<=IF('Hiring plan'!$H$11="",999,'Hiring plan'!$H$11)),'Hiring plan'!$F$11,0) -> 0 | H15: =IF(AND(N('Hiring plan'!$F$11)>0,H$3>='Hiring plan'!$G$11,H$3<=IF('Hiring plan'!$H$11="",999,'Hiring plan'!$H$11)),'Hiring plan'!$F$11,0) -> 0 | I15: =IF(AND(N('Hiring plan'!$F$11)>0,I$3>='Hiring plan'!$G$11,I$3<=IF('Hiring plan'!$H$11="",999,'Hiring plan'!$H$11)),'Hiring plan'!$F$11,0) -> 0 | J15: =IF(AND(N('Hiring plan'!$F$11)>0,J$3>='Hiring plan'!$G$11,J$3<=IF('Hiring plan'!$H$11="",999,'Hiring plan'!$H$11)),'Hiring plan'!$F$11,0) -> 0 | K15: =IF(AND(N('Hiring plan'!$F$11)>0,K$3>='Hiring plan'!$G$11,K$3<=IF('Hiring plan'!$H$11="",999,'Hiring plan'!$H$11)),'Hiring plan'!$F$11,0) -> 0 | L15: =IF(AND(N('Hiring plan'!$F$11)>0,L$3>='Hiring plan'!$G$11,L$3<=IF('Hiring plan'!$H$11="",999,'Hiring plan'!$H$11)),'Hiring plan'!$F$11,0) -> 0 | ... BL15: =IF(AND(N('Hiring plan'!$F$11)>0,BL$3>='Hiring plan'!$G$11,BL$3<=IF('Hiring plan'!$H$11="",999,'Hiring plan'!$H$11)),'Hiring plan'!$F$11,0) -> 1
A16: =IF('Hiring plan'!$C$12="","(spare line 8)",'Hiring plan'!$C$12&" · "&'Hiring plan'!$D$12) -> Compliance officer (AML/CFT) · SN | B16: people | D16: =MAX(E16:BL16) -> 1 | E16: =IF(AND(N('Hiring plan'!$F$12)>0,E$3>='Hiring plan'!$G$12,E$3<=IF('Hiring plan'!$H$12="",999,'Hiring plan'!$H$12)),'Hiring plan'!$F$12,0) -> 0 | F16: =IF(AND(N('Hiring plan'!$F$12)>0,F$3>='Hiring plan'!$G$12,F$3<=IF('Hiring plan'!$H$12="",999,'Hiring plan'!$H$12)),'Hiring plan'!$F$12,0) -> 0 | G16: =IF(AND(N('Hiring plan'!$F$12)>0,G$3>='Hiring plan'!$G$12,G$3<=IF('Hiring plan'!$H$12="",999,'Hiring plan'!$H$12)),'Hiring plan'!$F$12,0) -> 0 | H16: =IF(AND(N('Hiring plan'!$F$12)>0,H$3>='Hiring plan'!$G$12,H$3<=IF('Hiring plan'!$H$12="",999,'Hiring plan'!$H$12)),'Hiring plan'!$F$12,0) -> 0 | I16: =IF(AND(N('Hiring plan'!$F$12)>0,I$3>='Hiring plan'!$G$12,I$3<=IF('Hiring plan'!$H$12="",999,'Hiring plan'!$H$12)),'Hiring plan'!$F$12,0) -> 0 | J16: =IF(AND(N('Hiring plan'!$F$12)>0,J$3>='Hiring plan'!$G$12,J$3<=IF('Hiring plan'!$H$12="",999,'Hiring plan'!$H$12)),'Hiring plan'!$F$12,0) -> 0 | K16: =IF(AND(N('Hiring plan'!$F$12)>0,K$3>='Hiring plan'!$G$12,K$3<=IF('Hiring plan'!$H$12="",999,'Hiring plan'!$H$12)),'Hiring plan'!$F$12,0) -> 0 | L16: =IF(AND(N('Hiring plan'!$F$12)>0,L$3>='Hiring plan'!$G$12,L$3<=IF('Hiring plan'!$H$12="",999,'Hiring plan'!$H$12)),'Hiring plan'!$F$12,0) -> 0 | ... BL16: =IF(AND(N('Hiring plan'!$F$12)>0,BL$3>='Hiring plan'!$G$12,BL$3<=IF('Hiring plan'!$H$12="",999,'Hiring plan'!$H$12)),'Hiring plan'!$F$12,0) -> 1
A17: =IF('Hiring plan'!$C$13="","(spare line 9)",'Hiring plan'!$C$13&" · "&'Hiring plan'!$D$13) -> (spare line 9) | B17: people | D17: =MAX(E17:BL17) -> 0 | E17: =IF(AND(N('Hiring plan'!$F$13)>0,E$3>='Hiring plan'!$G$13,E$3<=IF('Hiring plan'!$H$13="",999,'Hiring plan'!$H$13)),'Hiring plan'!$F$13,0) -> 0 | F17: =IF(AND(N('Hiring plan'!$F$13)>0,F$3>='Hiring plan'!$G$13,F$3<=IF('Hiring plan'!$H$13="",999,'Hiring plan'!$H$13)),'Hiring plan'!$F$13,0) -> 0 | G17: =IF(AND(N('Hiring plan'!$F$13)>0,G$3>='Hiring plan'!$G$13,G$3<=IF('Hiring plan'!$H$13="",999,'Hiring plan'!$H$13)),'Hiring plan'!$F$13,0) -> 0 | H17: =IF(AND(N('Hiring plan'!$F$13)>0,H$3>='Hiring plan'!$G$13,H$3<=IF('Hiring plan'!$H$13="",999,'Hiring plan'!$H$13)),'Hiring plan'!$F$13,0) -> 0 | I17: =IF(AND(N('Hiring plan'!$F$13)>0,I$3>='Hiring plan'!$G$13,I$3<=IF('Hiring plan'!$H$13="",999,'Hiring plan'!$H$13)),'Hiring plan'!$F$13,0) -> 0 | J17: =IF(AND(N('Hiring plan'!$F$13)>0,J$3>='Hiring plan'!$G$13,J$3<=IF('Hiring plan'!$H$13="",999,'Hiring plan'!$H$13)),'Hiring plan'!$F$13,0) -> 0 | K17: =IF(AND(N('Hiring plan'!$F$13)>0,K$3>='Hiring plan'!$G$13,K$3<=IF('Hiring plan'!$H$13="",999,'Hiring plan'!$H$13)),'Hiring plan'!$F$13,0) -> 0 | L17: =IF(AND(N('Hiring plan'!$F$13)>0,L$3>='Hiring plan'!$G$13,L$3<=IF('Hiring plan'!$H$13="",999,'Hiring plan'!$H$13)),'Hiring plan'!$F$13,0) -> 0 | ... BL17: =IF(AND(N('Hiring plan'!$F$13)>0,BL$3>='Hiring plan'!$G$13,BL$3<=IF('Hiring plan'!$H$13="",999,'Hiring plan'!$H$13)),'Hiring plan'!$F$13,0) -> 0
A18: =IF('Hiring plan'!$C$14="","(spare line 10)",'Hiring plan'!$C$14&" · "&'Hiring plan'!$D$14) -> (spare line 10) | B18: people | D18: =MAX(E18:BL18) -> 0 | E18: =IF(AND(N('Hiring plan'!$F$14)>0,E$3>='Hiring plan'!$G$14,E$3<=IF('Hiring plan'!$H$14="",999,'Hiring plan'!$H$14)),'Hiring plan'!$F$14,0) -> 0 | F18: =IF(AND(N('Hiring plan'!$F$14)>0,F$3>='Hiring plan'!$G$14,F$3<=IF('Hiring plan'!$H$14="",999,'Hiring plan'!$H$14)),'Hiring plan'!$F$14,0) -> 0 | G18: =IF(AND(N('Hiring plan'!$F$14)>0,G$3>='Hiring plan'!$G$14,G$3<=IF('Hiring plan'!$H$14="",999,'Hiring plan'!$H$14)),'Hiring plan'!$F$14,0) -> 0 | H18: =IF(AND(N('Hiring plan'!$F$14)>0,H$3>='Hiring plan'!$G$14,H$3<=IF('Hiring plan'!$H$14="",999,'Hiring plan'!$H$14)),'Hiring plan'!$F$14,0) -> 0 | I18: =IF(AND(N('Hiring plan'!$F$14)>0,I$3>='Hiring plan'!$G$14,I$3<=IF('Hiring plan'!$H$14="",999,'Hiring plan'!$H$14)),'Hiring plan'!$F$14,0) -> 0 | J18: =IF(AND(N('Hiring plan'!$F$14)>0,J$3>='Hiring plan'!$G$14,J$3<=IF('Hiring plan'!$H$14="",999,'Hiring plan'!$H$14)),'Hiring plan'!$F$14,0) -> 0 | K18: =IF(AND(N('Hiring plan'!$F$14)>0,K$3>='Hiring plan'!$G$14,K$3<=IF('Hiring plan'!$H$14="",999,'Hiring plan'!$H$14)),'Hiring plan'!$F$14,0) -> 0 | L18: =IF(AND(N('Hiring plan'!$F$14)>0,L$3>='Hiring plan'!$G$14,L$3<=IF('Hiring plan'!$H$14="",999,'Hiring plan'!$H$14)),'Hiring plan'!$F$14,0) -> 0 | ... BL18: =IF(AND(N('Hiring plan'!$F$14)>0,BL$3>='Hiring plan'!$G$14,BL$3<=IF('Hiring plan'!$H$14="",999,'Hiring plan'!$H$14)),'Hiring plan'!$F$14,0) -> 0
A19: =IF('Hiring plan'!$C$15="","(spare line 11)",'Hiring plan'!$C$15&" · "&'Hiring plan'!$D$15) -> (spare line 11) | B19: people | D19: =MAX(E19:BL19) -> 0 | E19: =IF(AND(N('Hiring plan'!$F$15)>0,E$3>='Hiring plan'!$G$15,E$3<=IF('Hiring plan'!$H$15="",999,'Hiring plan'!$H$15)),'Hiring plan'!$F$15,0) -> 0 | F19: =IF(AND(N('Hiring plan'!$F$15)>0,F$3>='Hiring plan'!$G$15,F$3<=IF('Hiring plan'!$H$15="",999,'Hiring plan'!$H$15)),'Hiring plan'!$F$15,0) -> 0 | G19: =IF(AND(N('Hiring plan'!$F$15)>0,G$3>='Hiring plan'!$G$15,G$3<=IF('Hiring plan'!$H$15="",999,'Hiring plan'!$H$15)),'Hiring plan'!$F$15,0) -> 0 | H19: =IF(AND(N('Hiring plan'!$F$15)>0,H$3>='Hiring plan'!$G$15,H$3<=IF('Hiring plan'!$H$15="",999,'Hiring plan'!$H$15)),'Hiring plan'!$F$15,0) -> 0 | I19: =IF(AND(N('Hiring plan'!$F$15)>0,I$3>='Hiring plan'!$G$15,I$3<=IF('Hiring plan'!$H$15="",999,'Hiring plan'!$H$15)),'Hiring plan'!$F$15,0) -> 0 | J19: =IF(AND(N('Hiring plan'!$F$15)>0,J$3>='Hiring plan'!$G$15,J$3<=IF('Hiring plan'!$H$15="",999,'Hiring plan'!$H$15)),'Hiring plan'!$F$15,0) -> 0 | K19: =IF(AND(N('Hiring plan'!$F$15)>0,K$3>='Hiring plan'!$G$15,K$3<=IF('Hiring plan'!$H$15="",999,'Hiring plan'!$H$15)),'Hiring plan'!$F$15,0) -> 0 | L19: =IF(AND(N('Hiring plan'!$F$15)>0,L$3>='Hiring plan'!$G$15,L$3<=IF('Hiring plan'!$H$15="",999,'Hiring plan'!$H$15)),'Hiring plan'!$F$15,0) -> 0 | ... BL19: =IF(AND(N('Hiring plan'!$F$15)>0,BL$3>='Hiring plan'!$G$15,BL$3<=IF('Hiring plan'!$H$15="",999,'Hiring plan'!$H$15)),'Hiring plan'!$F$15,0) -> 0
A20: =IF('Hiring plan'!$C$16="","(spare line 12)",'Hiring plan'!$C$16&" · "&'Hiring plan'!$D$16) -> (spare line 12) | B20: people | D20: =MAX(E20:BL20) -> 0 | E20: =IF(AND(N('Hiring plan'!$F$16)>0,E$3>='Hiring plan'!$G$16,E$3<=IF('Hiring plan'!$H$16="",999,'Hiring plan'!$H$16)),'Hiring plan'!$F$16,0) -> 0 | F20: =IF(AND(N('Hiring plan'!$F$16)>0,F$3>='Hiring plan'!$G$16,F$3<=IF('Hiring plan'!$H$16="",999,'Hiring plan'!$H$16)),'Hiring plan'!$F$16,0) -> 0 | G20: =IF(AND(N('Hiring plan'!$F$16)>0,G$3>='Hiring plan'!$G$16,G$3<=IF('Hiring plan'!$H$16="",999,'Hiring plan'!$H$16)),'Hiring plan'!$F$16,0) -> 0 | H20: =IF(AND(N('Hiring plan'!$F$16)>0,H$3>='Hiring plan'!$G$16,H$3<=IF('Hiring plan'!$H$16="",999,'Hiring plan'!$H$16)),'Hiring plan'!$F$16,0) -> 0 | I20: =IF(AND(N('Hiring plan'!$F$16)>0,I$3>='Hiring plan'!$G$16,I$3<=IF('Hiring plan'!$H$16="",999,'Hiring plan'!$H$16)),'Hiring plan'!$F$16,0) -> 0 | J20: =IF(AND(N('Hiring plan'!$F$16)>0,J$3>='Hiring plan'!$G$16,J$3<=IF('Hiring plan'!$H$16="",999,'Hiring plan'!$H$16)),'Hiring plan'!$F$16,0) -> 0 | K20: =IF(AND(N('Hiring plan'!$F$16)>0,K$3>='Hiring plan'!$G$16,K$3<=IF('Hiring plan'!$H$16="",999,'Hiring plan'!$H$16)),'Hiring plan'!$F$16,0) -> 0 | L20: =IF(AND(N('Hiring plan'!$F$16)>0,L$3>='Hiring plan'!$G$16,L$3<=IF('Hiring plan'!$H$16="",999,'Hiring plan'!$H$16)),'Hiring plan'!$F$16,0) -> 0 | ... BL20: =IF(AND(N('Hiring plan'!$F$16)>0,BL$3>='Hiring plan'!$G$16,BL$3<=IF('Hiring plan'!$H$16="",999,'Hiring plan'!$H$16)),'Hiring plan'!$F$16,0) -> 0
A21: =IF('Hiring plan'!$C$17="","(spare line 13)",'Hiring plan'!$C$17&" · "&'Hiring plan'!$D$17) -> (spare line 13) | B21: people | D21: =MAX(E21:BL21) -> 0 | E21: =IF(AND(N('Hiring plan'!$F$17)>0,E$3>='Hiring plan'!$G$17,E$3<=IF('Hiring plan'!$H$17="",999,'Hiring plan'!$H$17)),'Hiring plan'!$F$17,0) -> 0 | F21: =IF(AND(N('Hiring plan'!$F$17)>0,F$3>='Hiring plan'!$G$17,F$3<=IF('Hiring plan'!$H$17="",999,'Hiring plan'!$H$17)),'Hiring plan'!$F$17,0) -> 0 | G21: =IF(AND(N('Hiring plan'!$F$17)>0,G$3>='Hiring plan'!$G$17,G$3<=IF('Hiring plan'!$H$17="",999,'Hiring plan'!$H$17)),'Hiring plan'!$F$17,0) -> 0 | H21: =IF(AND(N('Hiring plan'!$F$17)>0,H$3>='Hiring plan'!$G$17,H$3<=IF('Hiring plan'!$H$17="",999,'Hiring plan'!$H$17)),'Hiring plan'!$F$17,0) -> 0 | I21: =IF(AND(N('Hiring plan'!$F$17)>0,I$3>='Hiring plan'!$G$17,I$3<=IF('Hiring plan'!$H$17="",999,'Hiring plan'!$H$17)),'Hiring plan'!$F$17,0) -> 0 | J21: =IF(AND(N('Hiring plan'!$F$17)>0,J$3>='Hiring plan'!$G$17,J$3<=IF('Hiring plan'!$H$17="",999,'Hiring plan'!$H$17)),'Hiring plan'!$F$17,0) -> 0 | K21: =IF(AND(N('Hiring plan'!$F$17)>0,K$3>='Hiring plan'!$G$17,K$3<=IF('Hiring plan'!$H$17="",999,'Hiring plan'!$H$17)),'Hiring plan'!$F$17,0) -> 0 | L21: =IF(AND(N('Hiring plan'!$F$17)>0,L$3>='Hiring plan'!$G$17,L$3<=IF('Hiring plan'!$H$17="",999,'Hiring plan'!$H$17)),'Hiring plan'!$F$17,0) -> 0 | ... BL21: =IF(AND(N('Hiring plan'!$F$17)>0,BL$3>='Hiring plan'!$G$17,BL$3<=IF('Hiring plan'!$H$17="",999,'Hiring plan'!$H$17)),'Hiring plan'!$F$17,0) -> 0
A22: =IF('Hiring plan'!$C$18="","(spare line 14)",'Hiring plan'!$C$18&" · "&'Hiring plan'!$D$18) -> (spare line 14) | B22: people | D22: =MAX(E22:BL22) -> 0 | E22: =IF(AND(N('Hiring plan'!$F$18)>0,E$3>='Hiring plan'!$G$18,E$3<=IF('Hiring plan'!$H$18="",999,'Hiring plan'!$H$18)),'Hiring plan'!$F$18,0) -> 0 | F22: =IF(AND(N('Hiring plan'!$F$18)>0,F$3>='Hiring plan'!$G$18,F$3<=IF('Hiring plan'!$H$18="",999,'Hiring plan'!$H$18)),'Hiring plan'!$F$18,0) -> 0 | G22: =IF(AND(N('Hiring plan'!$F$18)>0,G$3>='Hiring plan'!$G$18,G$3<=IF('Hiring plan'!$H$18="",999,'Hiring plan'!$H$18)),'Hiring plan'!$F$18,0) -> 0 | H22: =IF(AND(N('Hiring plan'!$F$18)>0,H$3>='Hiring plan'!$G$18,H$3<=IF('Hiring plan'!$H$18="",999,'Hiring plan'!$H$18)),'Hiring plan'!$F$18,0) -> 0 | I22: =IF(AND(N('Hiring plan'!$F$18)>0,I$3>='Hiring plan'!$G$18,I$3<=IF('Hiring plan'!$H$18="",999,'Hiring plan'!$H$18)),'Hiring plan'!$F$18,0) -> 0 | J22: =IF(AND(N('Hiring plan'!$F$18)>0,J$3>='Hiring plan'!$G$18,J$3<=IF('Hiring plan'!$H$18="",999,'Hiring plan'!$H$18)),'Hiring plan'!$F$18,0) -> 0 | K22: =IF(AND(N('Hiring plan'!$F$18)>0,K$3>='Hiring plan'!$G$18,K$3<=IF('Hiring plan'!$H$18="",999,'Hiring plan'!$H$18)),'Hiring plan'!$F$18,0) -> 0 | L22: =IF(AND(N('Hiring plan'!$F$18)>0,L$3>='Hiring plan'!$G$18,L$3<=IF('Hiring plan'!$H$18="",999,'Hiring plan'!$H$18)),'Hiring plan'!$F$18,0) -> 0 | ... BL22: =IF(AND(N('Hiring plan'!$F$18)>0,BL$3>='Hiring plan'!$G$18,BL$3<=IF('Hiring plan'!$H$18="",999,'Hiring plan'!$H$18)),'Hiring plan'!$F$18,0) -> 0
A23: =IF('Hiring plan'!$C$19="","(spare line 15)",'Hiring plan'!$C$19&" · "&'Hiring plan'!$D$19) -> (spare line 15) | B23: people | D23: =MAX(E23:BL23) -> 0 | E23: =IF(AND(N('Hiring plan'!$F$19)>0,E$3>='Hiring plan'!$G$19,E$3<=IF('Hiring plan'!$H$19="",999,'Hiring plan'!$H$19)),'Hiring plan'!$F$19,0) -> 0 | F23: =IF(AND(N('Hiring plan'!$F$19)>0,F$3>='Hiring plan'!$G$19,F$3<=IF('Hiring plan'!$H$19="",999,'Hiring plan'!$H$19)),'Hiring plan'!$F$19,0) -> 0 | G23: =IF(AND(N('Hiring plan'!$F$19)>0,G$3>='Hiring plan'!$G$19,G$3<=IF('Hiring plan'!$H$19="",999,'Hiring plan'!$H$19)),'Hiring plan'!$F$19,0) -> 0 | H23: =IF(AND(N('Hiring plan'!$F$19)>0,H$3>='Hiring plan'!$G$19,H$3<=IF('Hiring plan'!$H$19="",999,'Hiring plan'!$H$19)),'Hiring plan'!$F$19,0) -> 0 | I23: =IF(AND(N('Hiring plan'!$F$19)>0,I$3>='Hiring plan'!$G$19,I$3<=IF('Hiring plan'!$H$19="",999,'Hiring plan'!$H$19)),'Hiring plan'!$F$19,0) -> 0 | J23: =IF(AND(N('Hiring plan'!$F$19)>0,J$3>='Hiring plan'!$G$19,J$3<=IF('Hiring plan'!$H$19="",999,'Hiring plan'!$H$19)),'Hiring plan'!$F$19,0) -> 0 | K23: =IF(AND(N('Hiring plan'!$F$19)>0,K$3>='Hiring plan'!$G$19,K$3<=IF('Hiring plan'!$H$19="",999,'Hiring plan'!$H$19)),'Hiring plan'!$F$19,0) -> 0 | L23: =IF(AND(N('Hiring plan'!$F$19)>0,L$3>='Hiring plan'!$G$19,L$3<=IF('Hiring plan'!$H$19="",999,'Hiring plan'!$H$19)),'Hiring plan'!$F$19,0) -> 0 | ... BL23: =IF(AND(N('Hiring plan'!$F$19)>0,BL$3>='Hiring plan'!$G$19,BL$3<=IF('Hiring plan'!$H$19="",999,'Hiring plan'!$H$19)),'Hiring plan'!$F$19,0) -> 0
A24: =IF('Hiring plan'!$C$20="","(spare line 16)",'Hiring plan'!$C$20&" · "&'Hiring plan'!$D$20) -> (spare line 16) | B24: people | D24: =MAX(E24:BL24) -> 0 | E24: =IF(AND(N('Hiring plan'!$F$20)>0,E$3>='Hiring plan'!$G$20,E$3<=IF('Hiring plan'!$H$20="",999,'Hiring plan'!$H$20)),'Hiring plan'!$F$20,0) -> 0 | F24: =IF(AND(N('Hiring plan'!$F$20)>0,F$3>='Hiring plan'!$G$20,F$3<=IF('Hiring plan'!$H$20="",999,'Hiring plan'!$H$20)),'Hiring plan'!$F$20,0) -> 0 | G24: =IF(AND(N('Hiring plan'!$F$20)>0,G$3>='Hiring plan'!$G$20,G$3<=IF('Hiring plan'!$H$20="",999,'Hiring plan'!$H$20)),'Hiring plan'!$F$20,0) -> 0 | H24: =IF(AND(N('Hiring plan'!$F$20)>0,H$3>='Hiring plan'!$G$20,H$3<=IF('Hiring plan'!$H$20="",999,'Hiring plan'!$H$20)),'Hiring plan'!$F$20,0) -> 0 | I24: =IF(AND(N('Hiring plan'!$F$20)>0,I$3>='Hiring plan'!$G$20,I$3<=IF('Hiring plan'!$H$20="",999,'Hiring plan'!$H$20)),'Hiring plan'!$F$20,0) -> 0 | J24: =IF(AND(N('Hiring plan'!$F$20)>0,J$3>='Hiring plan'!$G$20,J$3<=IF('Hiring plan'!$H$20="",999,'Hiring plan'!$H$20)),'Hiring plan'!$F$20,0) -> 0 | K24: =IF(AND(N('Hiring plan'!$F$20)>0,K$3>='Hiring plan'!$G$20,K$3<=IF('Hiring plan'!$H$20="",999,'Hiring plan'!$H$20)),'Hiring plan'!$F$20,0) -> 0 | L24: =IF(AND(N('Hiring plan'!$F$20)>0,L$3>='Hiring plan'!$G$20,L$3<=IF('Hiring plan'!$H$20="",999,'Hiring plan'!$H$20)),'Hiring plan'!$F$20,0) -> 0 | ... BL24: =IF(AND(N('Hiring plan'!$F$20)>0,BL$3>='Hiring plan'!$G$20,BL$3<=IF('Hiring plan'!$H$20="",999,'Hiring plan'!$H$20)),'Hiring plan'!$F$20,0) -> 0
A25: =IF('Hiring plan'!$C$21="","(spare line 17)",'Hiring plan'!$C$21&" · "&'Hiring plan'!$D$21) -> (spare line 17) | B25: people | D25: =MAX(E25:BL25) -> 0 | E25: =IF(AND(N('Hiring plan'!$F$21)>0,E$3>='Hiring plan'!$G$21,E$3<=IF('Hiring plan'!$H$21="",999,'Hiring plan'!$H$21)),'Hiring plan'!$F$21,0) -> 0 | F25: =IF(AND(N('Hiring plan'!$F$21)>0,F$3>='Hiring plan'!$G$21,F$3<=IF('Hiring plan'!$H$21="",999,'Hiring plan'!$H$21)),'Hiring plan'!$F$21,0) -> 0 | G25: =IF(AND(N('Hiring plan'!$F$21)>0,G$3>='Hiring plan'!$G$21,G$3<=IF('Hiring plan'!$H$21="",999,'Hiring plan'!$H$21)),'Hiring plan'!$F$21,0) -> 0 | H25: =IF(AND(N('Hiring plan'!$F$21)>0,H$3>='Hiring plan'!$G$21,H$3<=IF('Hiring plan'!$H$21="",999,'Hiring plan'!$H$21)),'Hiring plan'!$F$21,0) -> 0 | I25: =IF(AND(N('Hiring plan'!$F$21)>0,I$3>='Hiring plan'!$G$21,I$3<=IF('Hiring plan'!$H$21="",999,'Hiring plan'!$H$21)),'Hiring plan'!$F$21,0) -> 0 | J25: =IF(AND(N('Hiring plan'!$F$21)>0,J$3>='Hiring plan'!$G$21,J$3<=IF('Hiring plan'!$H$21="",999,'Hiring plan'!$H$21)),'Hiring plan'!$F$21,0) -> 0 | K25: =IF(AND(N('Hiring plan'!$F$21)>0,K$3>='Hiring plan'!$G$21,K$3<=IF('Hiring plan'!$H$21="",999,'Hiring plan'!$H$21)),'Hiring plan'!$F$21,0) -> 0 | L25: =IF(AND(N('Hiring plan'!$F$21)>0,L$3>='Hiring plan'!$G$21,L$3<=IF('Hiring plan'!$H$21="",999,'Hiring plan'!$H$21)),'Hiring plan'!$F$21,0) -> 0 | ... BL25: =IF(AND(N('Hiring plan'!$F$21)>0,BL$3>='Hiring plan'!$G$21,BL$3<=IF('Hiring plan'!$H$21="",999,'Hiring plan'!$H$21)),'Hiring plan'!$F$21,0) -> 0
A26: =IF('Hiring plan'!$C$22="","(spare line 18)",'Hiring plan'!$C$22&" · "&'Hiring plan'!$D$22) -> (spare line 18) | B26: people | D26: =MAX(E26:BL26) -> 0 | E26: =IF(AND(N('Hiring plan'!$F$22)>0,E$3>='Hiring plan'!$G$22,E$3<=IF('Hiring plan'!$H$22="",999,'Hiring plan'!$H$22)),'Hiring plan'!$F$22,0) -> 0 | F26: =IF(AND(N('Hiring plan'!$F$22)>0,F$3>='Hiring plan'!$G$22,F$3<=IF('Hiring plan'!$H$22="",999,'Hiring plan'!$H$22)),'Hiring plan'!$F$22,0) -> 0 | G26: =IF(AND(N('Hiring plan'!$F$22)>0,G$3>='Hiring plan'!$G$22,G$3<=IF('Hiring plan'!$H$22="",999,'Hiring plan'!$H$22)),'Hiring plan'!$F$22,0) -> 0 | H26: =IF(AND(N('Hiring plan'!$F$22)>0,H$3>='Hiring plan'!$G$22,H$3<=IF('Hiring plan'!$H$22="",999,'Hiring plan'!$H$22)),'Hiring plan'!$F$22,0) -> 0 | I26: =IF(AND(N('Hiring plan'!$F$22)>0,I$3>='Hiring plan'!$G$22,I$3<=IF('Hiring plan'!$H$22="",999,'Hiring plan'!$H$22)),'Hiring plan'!$F$22,0) -> 0 | J26: =IF(AND(N('Hiring plan'!$F$22)>0,J$3>='Hiring plan'!$G$22,J$3<=IF('Hiring plan'!$H$22="",999,'Hiring plan'!$H$22)),'Hiring plan'!$F$22,0) -> 0 | K26: =IF(AND(N('Hiring plan'!$F$22)>0,K$3>='Hiring plan'!$G$22,K$3<=IF('Hiring plan'!$H$22="",999,'Hiring plan'!$H$22)),'Hiring plan'!$F$22,0) -> 0 | L26: =IF(AND(N('Hiring plan'!$F$22)>0,L$3>='Hiring plan'!$G$22,L$3<=IF('Hiring plan'!$H$22="",999,'Hiring plan'!$H$22)),'Hiring plan'!$F$22,0) -> 0 | ... BL26: =IF(AND(N('Hiring plan'!$F$22)>0,BL$3>='Hiring plan'!$G$22,BL$3<=IF('Hiring plan'!$H$22="",999,'Hiring plan'!$H$22)),'Hiring plan'!$F$22,0) -> 0
A27: =IF('Hiring plan'!$C$23="","(spare line 19)",'Hiring plan'!$C$23&" · "&'Hiring plan'!$D$23) -> (spare line 19) | B27: people | D27: =MAX(E27:BL27) -> 0 | E27: =IF(AND(N('Hiring plan'!$F$23)>0,E$3>='Hiring plan'!$G$23,E$3<=IF('Hiring plan'!$H$23="",999,'Hiring plan'!$H$23)),'Hiring plan'!$F$23,0) -> 0 | F27: =IF(AND(N('Hiring plan'!$F$23)>0,F$3>='Hiring plan'!$G$23,F$3<=IF('Hiring plan'!$H$23="",999,'Hiring plan'!$H$23)),'Hiring plan'!$F$23,0) -> 0 | G27: =IF(AND(N('Hiring plan'!$F$23)>0,G$3>='Hiring plan'!$G$23,G$3<=IF('Hiring plan'!$H$23="",999,'Hiring plan'!$H$23)),'Hiring plan'!$F$23,0) -> 0 | H27: =IF(AND(N('Hiring plan'!$F$23)>0,H$3>='Hiring plan'!$G$23,H$3<=IF('Hiring plan'!$H$23="",999,'Hiring plan'!$H$23)),'Hiring plan'!$F$23,0) -> 0 | I27: =IF(AND(N('Hiring plan'!$F$23)>0,I$3>='Hiring plan'!$G$23,I$3<=IF('Hiring plan'!$H$23="",999,'Hiring plan'!$H$23)),'Hiring plan'!$F$23,0) -> 0 | J27: =IF(AND(N('Hiring plan'!$F$23)>0,J$3>='Hiring plan'!$G$23,J$3<=IF('Hiring plan'!$H$23="",999,'Hiring plan'!$H$23)),'Hiring plan'!$F$23,0) -> 0 | K27: =IF(AND(N('Hiring plan'!$F$23)>0,K$3>='Hiring plan'!$G$23,K$3<=IF('Hiring plan'!$H$23="",999,'Hiring plan'!$H$23)),'Hiring plan'!$F$23,0) -> 0 | L27: =IF(AND(N('Hiring plan'!$F$23)>0,L$3>='Hiring plan'!$G$23,L$3<=IF('Hiring plan'!$H$23="",999,'Hiring plan'!$H$23)),'Hiring plan'!$F$23,0) -> 0 | ... BL27: =IF(AND(N('Hiring plan'!$F$23)>0,BL$3>='Hiring plan'!$G$23,BL$3<=IF('Hiring plan'!$H$23="",999,'Hiring plan'!$H$23)),'Hiring plan'!$F$23,0) -> 0
A28: =IF('Hiring plan'!$C$24="","(spare line 20)",'Hiring plan'!$C$24&" · "&'Hiring plan'!$D$24) -> (spare line 20) | B28: people | D28: =MAX(E28:BL28) -> 0 | E28: =IF(AND(N('Hiring plan'!$F$24)>0,E$3>='Hiring plan'!$G$24,E$3<=IF('Hiring plan'!$H$24="",999,'Hiring plan'!$H$24)),'Hiring plan'!$F$24,0) -> 0 | F28: =IF(AND(N('Hiring plan'!$F$24)>0,F$3>='Hiring plan'!$G$24,F$3<=IF('Hiring plan'!$H$24="",999,'Hiring plan'!$H$24)),'Hiring plan'!$F$24,0) -> 0 | G28: =IF(AND(N('Hiring plan'!$F$24)>0,G$3>='Hiring plan'!$G$24,G$3<=IF('Hiring plan'!$H$24="",999,'Hiring plan'!$H$24)),'Hiring plan'!$F$24,0) -> 0 | H28: =IF(AND(N('Hiring plan'!$F$24)>0,H$3>='Hiring plan'!$G$24,H$3<=IF('Hiring plan'!$H$24="",999,'Hiring plan'!$H$24)),'Hiring plan'!$F$24,0) -> 0 | I28: =IF(AND(N('Hiring plan'!$F$24)>0,I$3>='Hiring plan'!$G$24,I$3<=IF('Hiring plan'!$H$24="",999,'Hiring plan'!$H$24)),'Hiring plan'!$F$24,0) -> 0 | J28: =IF(AND(N('Hiring plan'!$F$24)>0,J$3>='Hiring plan'!$G$24,J$3<=IF('Hiring plan'!$H$24="",999,'Hiring plan'!$H$24)),'Hiring plan'!$F$24,0) -> 0 | K28: =IF(AND(N('Hiring plan'!$F$24)>0,K$3>='Hiring plan'!$G$24,K$3<=IF('Hiring plan'!$H$24="",999,'Hiring plan'!$H$24)),'Hiring plan'!$F$24,0) -> 0 | L28: =IF(AND(N('Hiring plan'!$F$24)>0,L$3>='Hiring plan'!$G$24,L$3<=IF('Hiring plan'!$H$24="",999,'Hiring plan'!$H$24)),'Hiring plan'!$F$24,0) -> 0 | ... BL28: =IF(AND(N('Hiring plan'!$F$24)>0,BL$3>='Hiring plan'!$G$24,BL$3<=IF('Hiring plan'!$H$24="",999,'Hiring plan'!$H$24)),'Hiring plan'!$F$24,0) -> 0
A29: =IF('Hiring plan'!$C$25="","(spare line 21)",'Hiring plan'!$C$25&" · "&'Hiring plan'!$D$25) -> (spare line 21) | B29: people | D29: =MAX(E29:BL29) -> 0 | E29: =IF(AND(N('Hiring plan'!$F$25)>0,E$3>='Hiring plan'!$G$25,E$3<=IF('Hiring plan'!$H$25="",999,'Hiring plan'!$H$25)),'Hiring plan'!$F$25,0) -> 0 | F29: =IF(AND(N('Hiring plan'!$F$25)>0,F$3>='Hiring plan'!$G$25,F$3<=IF('Hiring plan'!$H$25="",999,'Hiring plan'!$H$25)),'Hiring plan'!$F$25,0) -> 0 | G29: =IF(AND(N('Hiring plan'!$F$25)>0,G$3>='Hiring plan'!$G$25,G$3<=IF('Hiring plan'!$H$25="",999,'Hiring plan'!$H$25)),'Hiring plan'!$F$25,0) -> 0 | H29: =IF(AND(N('Hiring plan'!$F$25)>0,H$3>='Hiring plan'!$G$25,H$3<=IF('Hiring plan'!$H$25="",999,'Hiring plan'!$H$25)),'Hiring plan'!$F$25,0) -> 0 | I29: =IF(AND(N('Hiring plan'!$F$25)>0,I$3>='Hiring plan'!$G$25,I$3<=IF('Hiring plan'!$H$25="",999,'Hiring plan'!$H$25)),'Hiring plan'!$F$25,0) -> 0 | J29: =IF(AND(N('Hiring plan'!$F$25)>0,J$3>='Hiring plan'!$G$25,J$3<=IF('Hiring plan'!$H$25="",999,'Hiring plan'!$H$25)),'Hiring plan'!$F$25,0) -> 0 | K29: =IF(AND(N('Hiring plan'!$F$25)>0,K$3>='Hiring plan'!$G$25,K$3<=IF('Hiring plan'!$H$25="",999,'Hiring plan'!$H$25)),'Hiring plan'!$F$25,0) -> 0 | L29: =IF(AND(N('Hiring plan'!$F$25)>0,L$3>='Hiring plan'!$G$25,L$3<=IF('Hiring plan'!$H$25="",999,'Hiring plan'!$H$25)),'Hiring plan'!$F$25,0) -> 0 | ... BL29: =IF(AND(N('Hiring plan'!$F$25)>0,BL$3>='Hiring plan'!$G$25,BL$3<=IF('Hiring plan'!$H$25="",999,'Hiring plan'!$H$25)),'Hiring plan'!$F$25,0) -> 0
A30: =IF('Hiring plan'!$C$26="","(spare line 22)",'Hiring plan'!$C$26&" · "&'Hiring plan'!$D$26) -> (spare line 22) | B30: people | D30: =MAX(E30:BL30) -> 0 | E30: =IF(AND(N('Hiring plan'!$F$26)>0,E$3>='Hiring plan'!$G$26,E$3<=IF('Hiring plan'!$H$26="",999,'Hiring plan'!$H$26)),'Hiring plan'!$F$26,0) -> 0 | F30: =IF(AND(N('Hiring plan'!$F$26)>0,F$3>='Hiring plan'!$G$26,F$3<=IF('Hiring plan'!$H$26="",999,'Hiring plan'!$H$26)),'Hiring plan'!$F$26,0) -> 0 | G30: =IF(AND(N('Hiring plan'!$F$26)>0,G$3>='Hiring plan'!$G$26,G$3<=IF('Hiring plan'!$H$26="",999,'Hiring plan'!$H$26)),'Hiring plan'!$F$26,0) -> 0 | H30: =IF(AND(N('Hiring plan'!$F$26)>0,H$3>='Hiring plan'!$G$26,H$3<=IF('Hiring plan'!$H$26="",999,'Hiring plan'!$H$26)),'Hiring plan'!$F$26,0) -> 0 | I30: =IF(AND(N('Hiring plan'!$F$26)>0,I$3>='Hiring plan'!$G$26,I$3<=IF('Hiring plan'!$H$26="",999,'Hiring plan'!$H$26)),'Hiring plan'!$F$26,0) -> 0 | J30: =IF(AND(N('Hiring plan'!$F$26)>0,J$3>='Hiring plan'!$G$26,J$3<=IF('Hiring plan'!$H$26="",999,'Hiring plan'!$H$26)),'Hiring plan'!$F$26,0) -> 0 | K30: =IF(AND(N('Hiring plan'!$F$26)>0,K$3>='Hiring plan'!$G$26,K$3<=IF('Hiring plan'!$H$26="",999,'Hiring plan'!$H$26)),'Hiring plan'!$F$26,0) -> 0 | L30: =IF(AND(N('Hiring plan'!$F$26)>0,L$3>='Hiring plan'!$G$26,L$3<=IF('Hiring plan'!$H$26="",999,'Hiring plan'!$H$26)),'Hiring plan'!$F$26,0) -> 0 | ... BL30: =IF(AND(N('Hiring plan'!$F$26)>0,BL$3>='Hiring plan'!$G$26,BL$3<=IF('Hiring plan'!$H$26="",999,'Hiring plan'!$H$26)),'Hiring plan'!$F$26,0) -> 0
A31: =IF('Hiring plan'!$C$27="","(spare line 23)",'Hiring plan'!$C$27&" · "&'Hiring plan'!$D$27) -> (spare line 23) | B31: people | D31: =MAX(E31:BL31) -> 0 | E31: =IF(AND(N('Hiring plan'!$F$27)>0,E$3>='Hiring plan'!$G$27,E$3<=IF('Hiring plan'!$H$27="",999,'Hiring plan'!$H$27)),'Hiring plan'!$F$27,0) -> 0 | F31: =IF(AND(N('Hiring plan'!$F$27)>0,F$3>='Hiring plan'!$G$27,F$3<=IF('Hiring plan'!$H$27="",999,'Hiring plan'!$H$27)),'Hiring plan'!$F$27,0) -> 0 | G31: =IF(AND(N('Hiring plan'!$F$27)>0,G$3>='Hiring plan'!$G$27,G$3<=IF('Hiring plan'!$H$27="",999,'Hiring plan'!$H$27)),'Hiring plan'!$F$27,0) -> 0 | H31: =IF(AND(N('Hiring plan'!$F$27)>0,H$3>='Hiring plan'!$G$27,H$3<=IF('Hiring plan'!$H$27="",999,'Hiring plan'!$H$27)),'Hiring plan'!$F$27,0) -> 0 | I31: =IF(AND(N('Hiring plan'!$F$27)>0,I$3>='Hiring plan'!$G$27,I$3<=IF('Hiring plan'!$H$27="",999,'Hiring plan'!$H$27)),'Hiring plan'!$F$27,0) -> 0 | J31: =IF(AND(N('Hiring plan'!$F$27)>0,J$3>='Hiring plan'!$G$27,J$3<=IF('Hiring plan'!$H$27="",999,'Hiring plan'!$H$27)),'Hiring plan'!$F$27,0) -> 0 | K31: =IF(AND(N('Hiring plan'!$F$27)>0,K$3>='Hiring plan'!$G$27,K$3<=IF('Hiring plan'!$H$27="",999,'Hiring plan'!$H$27)),'Hiring plan'!$F$27,0) -> 0 | L31: =IF(AND(N('Hiring plan'!$F$27)>0,L$3>='Hiring plan'!$G$27,L$3<=IF('Hiring plan'!$H$27="",999,'Hiring plan'!$H$27)),'Hiring plan'!$F$27,0) -> 0 | ... BL31: =IF(AND(N('Hiring plan'!$F$27)>0,BL$3>='Hiring plan'!$G$27,BL$3<=IF('Hiring plan'!$H$27="",999,'Hiring plan'!$H$27)),'Hiring plan'!$F$27,0) -> 0
A32: =IF('Hiring plan'!$C$28="","(spare line 24)",'Hiring plan'!$C$28&" · "&'Hiring plan'!$D$28) -> (spare line 24) | B32: people | D32: =MAX(E32:BL32) -> 0 | E32: =IF(AND(N('Hiring plan'!$F$28)>0,E$3>='Hiring plan'!$G$28,E$3<=IF('Hiring plan'!$H$28="",999,'Hiring plan'!$H$28)),'Hiring plan'!$F$28,0) -> 0 | F32: =IF(AND(N('Hiring plan'!$F$28)>0,F$3>='Hiring plan'!$G$28,F$3<=IF('Hiring plan'!$H$28="",999,'Hiring plan'!$H$28)),'Hiring plan'!$F$28,0) -> 0 | G32: =IF(AND(N('Hiring plan'!$F$28)>0,G$3>='Hiring plan'!$G$28,G$3<=IF('Hiring plan'!$H$28="",999,'Hiring plan'!$H$28)),'Hiring plan'!$F$28,0) -> 0 | H32: =IF(AND(N('Hiring plan'!$F$28)>0,H$3>='Hiring plan'!$G$28,H$3<=IF('Hiring plan'!$H$28="",999,'Hiring plan'!$H$28)),'Hiring plan'!$F$28,0) -> 0 | I32: =IF(AND(N('Hiring plan'!$F$28)>0,I$3>='Hiring plan'!$G$28,I$3<=IF('Hiring plan'!$H$28="",999,'Hiring plan'!$H$28)),'Hiring plan'!$F$28,0) -> 0 | J32: =IF(AND(N('Hiring plan'!$F$28)>0,J$3>='Hiring plan'!$G$28,J$3<=IF('Hiring plan'!$H$28="",999,'Hiring plan'!$H$28)),'Hiring plan'!$F$28,0) -> 0 | K32: =IF(AND(N('Hiring plan'!$F$28)>0,K$3>='Hiring plan'!$G$28,K$3<=IF('Hiring plan'!$H$28="",999,'Hiring plan'!$H$28)),'Hiring plan'!$F$28,0) -> 0 | L32: =IF(AND(N('Hiring plan'!$F$28)>0,L$3>='Hiring plan'!$G$28,L$3<=IF('Hiring plan'!$H$28="",999,'Hiring plan'!$H$28)),'Hiring plan'!$F$28,0) -> 0 | ... BL32: =IF(AND(N('Hiring plan'!$F$28)>0,BL$3>='Hiring plan'!$G$28,BL$3<=IF('Hiring plan'!$H$28="",999,'Hiring plan'!$H$28)),'Hiring plan'!$F$28,0) -> 0
A33: =IF('Hiring plan'!$C$29="","(spare line 25)",'Hiring plan'!$C$29&" · "&'Hiring plan'!$D$29) -> (spare line 25) | B33: people | D33: =MAX(E33:BL33) -> 0 | E33: =IF(AND(N('Hiring plan'!$F$29)>0,E$3>='Hiring plan'!$G$29,E$3<=IF('Hiring plan'!$H$29="",999,'Hiring plan'!$H$29)),'Hiring plan'!$F$29,0) -> 0 | F33: =IF(AND(N('Hiring plan'!$F$29)>0,F$3>='Hiring plan'!$G$29,F$3<=IF('Hiring plan'!$H$29="",999,'Hiring plan'!$H$29)),'Hiring plan'!$F$29,0) -> 0 | G33: =IF(AND(N('Hiring plan'!$F$29)>0,G$3>='Hiring plan'!$G$29,G$3<=IF('Hiring plan'!$H$29="",999,'Hiring plan'!$H$29)),'Hiring plan'!$F$29,0) -> 0 | H33: =IF(AND(N('Hiring plan'!$F$29)>0,H$3>='Hiring plan'!$G$29,H$3<=IF('Hiring plan'!$H$29="",999,'Hiring plan'!$H$29)),'Hiring plan'!$F$29,0) -> 0 | I33: =IF(AND(N('Hiring plan'!$F$29)>0,I$3>='Hiring plan'!$G$29,I$3<=IF('Hiring plan'!$H$29="",999,'Hiring plan'!$H$29)),'Hiring plan'!$F$29,0) -> 0 | J33: =IF(AND(N('Hiring plan'!$F$29)>0,J$3>='Hiring plan'!$G$29,J$3<=IF('Hiring plan'!$H$29="",999,'Hiring plan'!$H$29)),'Hiring plan'!$F$29,0) -> 0 | K33: =IF(AND(N('Hiring plan'!$F$29)>0,K$3>='Hiring plan'!$G$29,K$3<=IF('Hiring plan'!$H$29="",999,'Hiring plan'!$H$29)),'Hiring plan'!$F$29,0) -> 0 | L33: =IF(AND(N('Hiring plan'!$F$29)>0,L$3>='Hiring plan'!$G$29,L$3<=IF('Hiring plan'!$H$29="",999,'Hiring plan'!$H$29)),'Hiring plan'!$F$29,0) -> 0 | ... BL33: =IF(AND(N('Hiring plan'!$F$29)>0,BL$3>='Hiring plan'!$G$29,BL$3<=IF('Hiring plan'!$H$29="",999,'Hiring plan'!$H$29)),'Hiring plan'!$F$29,0) -> 0
A34: =IF('Hiring plan'!$C$30="","(spare line 26)",'Hiring plan'!$C$30&" · "&'Hiring plan'!$D$30) -> (spare line 26) | B34: people | D34: =MAX(E34:BL34) -> 0 | E34: =IF(AND(N('Hiring plan'!$F$30)>0,E$3>='Hiring plan'!$G$30,E$3<=IF('Hiring plan'!$H$30="",999,'Hiring plan'!$H$30)),'Hiring plan'!$F$30,0) -> 0 | F34: =IF(AND(N('Hiring plan'!$F$30)>0,F$3>='Hiring plan'!$G$30,F$3<=IF('Hiring plan'!$H$30="",999,'Hiring plan'!$H$30)),'Hiring plan'!$F$30,0) -> 0 | G34: =IF(AND(N('Hiring plan'!$F$30)>0,G$3>='Hiring plan'!$G$30,G$3<=IF('Hiring plan'!$H$30="",999,'Hiring plan'!$H$30)),'Hiring plan'!$F$30,0) -> 0 | H34: =IF(AND(N('Hiring plan'!$F$30)>0,H$3>='Hiring plan'!$G$30,H$3<=IF('Hiring plan'!$H$30="",999,'Hiring plan'!$H$30)),'Hiring plan'!$F$30,0) -> 0 | I34: =IF(AND(N('Hiring plan'!$F$30)>0,I$3>='Hiring plan'!$G$30,I$3<=IF('Hiring plan'!$H$30="",999,'Hiring plan'!$H$30)),'Hiring plan'!$F$30,0) -> 0 | J34: =IF(AND(N('Hiring plan'!$F$30)>0,J$3>='Hiring plan'!$G$30,J$3<=IF('Hiring plan'!$H$30="",999,'Hiring plan'!$H$30)),'Hiring plan'!$F$30,0) -> 0 | K34: =IF(AND(N('Hiring plan'!$F$30)>0,K$3>='Hiring plan'!$G$30,K$3<=IF('Hiring plan'!$H$30="",999,'Hiring plan'!$H$30)),'Hiring plan'!$F$30,0) -> 0 | L34: =IF(AND(N('Hiring plan'!$F$30)>0,L$3>='Hiring plan'!$G$30,L$3<=IF('Hiring plan'!$H$30="",999,'Hiring plan'!$H$30)),'Hiring plan'!$F$30,0) -> 0 | ... BL34: =IF(AND(N('Hiring plan'!$F$30)>0,BL$3>='Hiring plan'!$G$30,BL$3<=IF('Hiring plan'!$H$30="",999,'Hiring plan'!$H$30)),'Hiring plan'!$F$30,0) -> 0
A35: =IF('Hiring plan'!$C$31="","(spare line 27)",'Hiring plan'!$C$31&" · "&'Hiring plan'!$D$31) -> (spare line 27) | B35: people | D35: =MAX(E35:BL35) -> 0 | E35: =IF(AND(N('Hiring plan'!$F$31)>0,E$3>='Hiring plan'!$G$31,E$3<=IF('Hiring plan'!$H$31="",999,'Hiring plan'!$H$31)),'Hiring plan'!$F$31,0) -> 0 | F35: =IF(AND(N('Hiring plan'!$F$31)>0,F$3>='Hiring plan'!$G$31,F$3<=IF('Hiring plan'!$H$31="",999,'Hiring plan'!$H$31)),'Hiring plan'!$F$31,0) -> 0 | G35: =IF(AND(N('Hiring plan'!$F$31)>0,G$3>='Hiring plan'!$G$31,G$3<=IF('Hiring plan'!$H$31="",999,'Hiring plan'!$H$31)),'Hiring plan'!$F$31,0) -> 0 | H35: =IF(AND(N('Hiring plan'!$F$31)>0,H$3>='Hiring plan'!$G$31,H$3<=IF('Hiring plan'!$H$31="",999,'Hiring plan'!$H$31)),'Hiring plan'!$F$31,0) -> 0 | I35: =IF(AND(N('Hiring plan'!$F$31)>0,I$3>='Hiring plan'!$G$31,I$3<=IF('Hiring plan'!$H$31="",999,'Hiring plan'!$H$31)),'Hiring plan'!$F$31,0) -> 0 | J35: =IF(AND(N('Hiring plan'!$F$31)>0,J$3>='Hiring plan'!$G$31,J$3<=IF('Hiring plan'!$H$31="",999,'Hiring plan'!$H$31)),'Hiring plan'!$F$31,0) -> 0 | K35: =IF(AND(N('Hiring plan'!$F$31)>0,K$3>='Hiring plan'!$G$31,K$3<=IF('Hiring plan'!$H$31="",999,'Hiring plan'!$H$31)),'Hiring plan'!$F$31,0) -> 0 | L35: =IF(AND(N('Hiring plan'!$F$31)>0,L$3>='Hiring plan'!$G$31,L$3<=IF('Hiring plan'!$H$31="",999,'Hiring plan'!$H$31)),'Hiring plan'!$F$31,0) -> 0 | ... BL35: =IF(AND(N('Hiring plan'!$F$31)>0,BL$3>='Hiring plan'!$G$31,BL$3<=IF('Hiring plan'!$H$31="",999,'Hiring plan'!$H$31)),'Hiring plan'!$F$31,0) -> 0
A36: =IF('Hiring plan'!$C$32="","(spare line 28)",'Hiring plan'!$C$32&" · "&'Hiring plan'!$D$32) -> (spare line 28) | B36: people | D36: =MAX(E36:BL36) -> 0 | E36: =IF(AND(N('Hiring plan'!$F$32)>0,E$3>='Hiring plan'!$G$32,E$3<=IF('Hiring plan'!$H$32="",999,'Hiring plan'!$H$32)),'Hiring plan'!$F$32,0) -> 0 | F36: =IF(AND(N('Hiring plan'!$F$32)>0,F$3>='Hiring plan'!$G$32,F$3<=IF('Hiring plan'!$H$32="",999,'Hiring plan'!$H$32)),'Hiring plan'!$F$32,0) -> 0 | G36: =IF(AND(N('Hiring plan'!$F$32)>0,G$3>='Hiring plan'!$G$32,G$3<=IF('Hiring plan'!$H$32="",999,'Hiring plan'!$H$32)),'Hiring plan'!$F$32,0) -> 0 | H36: =IF(AND(N('Hiring plan'!$F$32)>0,H$3>='Hiring plan'!$G$32,H$3<=IF('Hiring plan'!$H$32="",999,'Hiring plan'!$H$32)),'Hiring plan'!$F$32,0) -> 0 | I36: =IF(AND(N('Hiring plan'!$F$32)>0,I$3>='Hiring plan'!$G$32,I$3<=IF('Hiring plan'!$H$32="",999,'Hiring plan'!$H$32)),'Hiring plan'!$F$32,0) -> 0 | J36: =IF(AND(N('Hiring plan'!$F$32)>0,J$3>='Hiring plan'!$G$32,J$3<=IF('Hiring plan'!$H$32="",999,'Hiring plan'!$H$32)),'Hiring plan'!$F$32,0) -> 0 | K36: =IF(AND(N('Hiring plan'!$F$32)>0,K$3>='Hiring plan'!$G$32,K$3<=IF('Hiring plan'!$H$32="",999,'Hiring plan'!$H$32)),'Hiring plan'!$F$32,0) -> 0 | L36: =IF(AND(N('Hiring plan'!$F$32)>0,L$3>='Hiring plan'!$G$32,L$3<=IF('Hiring plan'!$H$32="",999,'Hiring plan'!$H$32)),'Hiring plan'!$F$32,0) -> 0 | ... BL36: =IF(AND(N('Hiring plan'!$F$32)>0,BL$3>='Hiring plan'!$G$32,BL$3<=IF('Hiring plan'!$H$32="",999,'Hiring plan'!$H$32)),'Hiring plan'!$F$32,0) -> 0
A38: Employer cost by hire line
A39: =A9 -> CEO (full salary from year 2) · SN | B39: FCFA | D39: =SUM(E39:BL39) -> 1.7649962e+08 | E39: =E9*'Hiring plan'!$K$5*(1+Salary_Raise)^(E$5-1) -> 0 | F39: =F9*'Hiring plan'!$K$5*(1+Salary_Raise)^(F$5-1) -> 0 | G39: =G9*'Hiring plan'!$K$5*(1+Salary_Raise)^(G$5-1) -> 0 | H39: =H9*'Hiring plan'!$K$5*(1+Salary_Raise)^(H$5-1) -> 0 | I39: =I9*'Hiring plan'!$K$5*(1+Salary_Raise)^(I$5-1) -> 0 | J39: =J9*'Hiring plan'!$K$5*(1+Salary_Raise)^(J$5-1) -> 0 | K39: =K9*'Hiring plan'!$K$5*(1+Salary_Raise)^(K$5-1) -> 0 | L39: =L9*'Hiring plan'!$K$5*(1+Salary_Raise)^(L$5-1) -> 0 | ... BL39: =BL9*'Hiring plan'!$K$5*(1+Salary_Raise)^(BL$5-1) -> 3950395.3
A40: =A10 -> CTO (also codes) · SN | B40: FCFA | D40: =SUM(E40:BL40) -> 2.1549962e+08 | E40: =E10*'Hiring plan'!$K$6*(1+Salary_Raise)^(E$5-1) -> 3250000 | F40: =F10*'Hiring plan'!$K$6*(1+Salary_Raise)^(F$5-1) -> 3250000 | G40: =G10*'Hiring plan'!$K$6*(1+Salary_Raise)^(G$5-1) -> 3250000 | H40: =H10*'Hiring plan'!$K$6*(1+Salary_Raise)^(H$5-1) -> 3250000 | I40: =I10*'Hiring plan'!$K$6*(1+Salary_Raise)^(I$5-1) -> 3250000 | J40: =J10*'Hiring plan'!$K$6*(1+Salary_Raise)^(J$5-1) -> 3250000 | K40: =K10*'Hiring plan'!$K$6*(1+Salary_Raise)^(K$5-1) -> 3250000 | L40: =L10*'Hiring plan'!$K$6*(1+Salary_Raise)^(L$5-1) -> 3250000 | ... BL40: =BL10*'Hiring plan'!$K$6*(1+Salary_Raise)^(BL$5-1) -> 3950395.3
A41: =A11 -> Financial expert (finance, partners, credit lead) · SN | B41: FCFA | D41: =SUM(E41:BL41) -> 1.2929977e+08 | E41: =E11*'Hiring plan'!$K$7*(1+Salary_Raise)^(E$5-1) -> 1950000 | F41: =F11*'Hiring plan'!$K$7*(1+Salary_Raise)^(F$5-1) -> 1950000 | G41: =G11*'Hiring plan'!$K$7*(1+Salary_Raise)^(G$5-1) -> 1950000 | H41: =H11*'Hiring plan'!$K$7*(1+Salary_Raise)^(H$5-1) -> 1950000 | I41: =I11*'Hiring plan'!$K$7*(1+Salary_Raise)^(I$5-1) -> 1950000 | J41: =J11*'Hiring plan'!$K$7*(1+Salary_Raise)^(J$5-1) -> 1950000 | K41: =K11*'Hiring plan'!$K$7*(1+Salary_Raise)^(K$5-1) -> 1950000 | L41: =L11*'Hiring plan'!$K$7*(1+Salary_Raise)^(L$5-1) -> 1950000 | ... BL41: =BL11*'Hiring plan'!$K$7*(1+Salary_Raise)^(BL$5-1) -> 2370237.2
A42: =A12 -> Sales lead (also sells; incl. bonus) · SN | B42: FCFA | D42: =SUM(E42:BL42) -> 103439817 | E42: =E12*'Hiring plan'!$K$8*(1+Salary_Raise)^(E$5-1) -> 1560000 | F42: =F12*'Hiring plan'!$K$8*(1+Salary_Raise)^(F$5-1) -> 1560000 | G42: =G12*'Hiring plan'!$K$8*(1+Salary_Raise)^(G$5-1) -> 1560000 | H42: =H12*'Hiring plan'!$K$8*(1+Salary_Raise)^(H$5-1) -> 1560000 | I42: =I12*'Hiring plan'!$K$8*(1+Salary_Raise)^(I$5-1) -> 1560000 | J42: =J12*'Hiring plan'!$K$8*(1+Salary_Raise)^(J$5-1) -> 1560000 | K42: =K12*'Hiring plan'!$K$8*(1+Salary_Raise)^(K$5-1) -> 1560000 | L42: =L12*'Hiring plan'!$K$8*(1+Salary_Raise)^(L$5-1) -> 1560000 | ... BL42: =BL12*'Hiring plan'!$K$8*(1+Salary_Raise)^(BL$5-1) -> 1896189.8
A43: =A13 -> Marketing manager (senior) · SN | B43: FCFA | D43: =SUM(E43:BL43) -> 74069863 | E43: =E13*'Hiring plan'!$K$9*(1+Salary_Raise)^(E$5-1) -> 0 | F43: =F13*'Hiring plan'!$K$9*(1+Salary_Raise)^(F$5-1) -> 0 | G43: =G13*'Hiring plan'!$K$9*(1+Salary_Raise)^(G$5-1) -> 0 | H43: =H13*'Hiring plan'!$K$9*(1+Salary_Raise)^(H$5-1) -> 1170000 | I43: =I13*'Hiring plan'!$K$9*(1+Salary_Raise)^(I$5-1) -> 1170000 | J43: =J13*'Hiring plan'!$K$9*(1+Salary_Raise)^(J$5-1) -> 1170000 | K43: =K13*'Hiring plan'!$K$9*(1+Salary_Raise)^(K$5-1) -> 1170000 | L43: =L13*'Hiring plan'!$K$9*(1+Salary_Raise)^(L$5-1) -> 1170000 | ... BL43: =BL13*'Hiring plan'!$K$9*(1+Salary_Raise)^(BL$5-1) -> 1422142.3
A44: =A14 -> Marketing officer (junior) · SN | B44: FCFA | D44: =SUM(E44:BL44) -> 32399939 | E44: =E14*'Hiring plan'!$K$10*(1+Salary_Raise)^(E$5-1) -> 0 | F44: =F14*'Hiring plan'!$K$10*(1+Salary_Raise)^(F$5-1) -> 0 | G44: =G14*'Hiring plan'!$K$10*(1+Salary_Raise)^(G$5-1) -> 0 | H44: =H14*'Hiring plan'!$K$10*(1+Salary_Raise)^(H$5-1) -> 0 | I44: =I14*'Hiring plan'!$K$10*(1+Salary_Raise)^(I$5-1) -> 520000 | J44: =J14*'Hiring plan'!$K$10*(1+Salary_Raise)^(J$5-1) -> 520000 | K44: =K14*'Hiring plan'!$K$10*(1+Salary_Raise)^(K$5-1) -> 520000 | L44: =L14*'Hiring plan'!$K$10*(1+Salary_Raise)^(L$5-1) -> 520000 | ... BL44: =BL14*'Hiring plan'!$K$10*(1+Salary_Raise)^(BL$5-1) -> 632063.25
A45: =A15 -> Country manager, Abidjan · CI | B45: FCFA | D45: =SUM(E45:BL45) -> 178569573 | E45: =E15*'Hiring plan'!$K$11*(1+Salary_Raise)^(E$5-1) -> 0 | F45: =F15*'Hiring plan'!$K$11*(1+Salary_Raise)^(F$5-1) -> 0 | G45: =G15*'Hiring plan'!$K$11*(1+Salary_Raise)^(G$5-1) -> 0 | H45: =H15*'Hiring plan'!$K$11*(1+Salary_Raise)^(H$5-1) -> 0 | I45: =I15*'Hiring plan'!$K$11*(1+Salary_Raise)^(I$5-1) -> 0 | J45: =J15*'Hiring plan'!$K$11*(1+Salary_Raise)^(J$5-1) -> 0 | K45: =K15*'Hiring plan'!$K$11*(1+Salary_Raise)^(K$5-1) -> 0 | L45: =L15*'Hiring plan'!$K$11*(1+Salary_Raise)^(L$5-1) -> 0 | ... BL45: =BL15*'Hiring plan'!$K$11*(1+Salary_Raise)^(BL$5-1) -> 4424442.8
A46: =A16 -> Compliance officer (AML/CFT) · SN | B46: FCFA | D46: =SUM(E46:BL46) -> 83377271 | E46: =E16*'Hiring plan'!$K$12*(1+Salary_Raise)^(E$5-1) -> 0 | F46: =F16*'Hiring plan'!$K$12*(1+Salary_Raise)^(F$5-1) -> 0 | G46: =G16*'Hiring plan'!$K$12*(1+Salary_Raise)^(G$5-1) -> 0 | H46: =H16*'Hiring plan'!$K$12*(1+Salary_Raise)^(H$5-1) -> 0 | I46: =I16*'Hiring plan'!$K$12*(1+Salary_Raise)^(I$5-1) -> 0 | J46: =J16*'Hiring plan'!$K$12*(1+Salary_Raise)^(J$5-1) -> 0 | K46: =K16*'Hiring plan'!$K$12*(1+Salary_Raise)^(K$5-1) -> 0 | L46: =L16*'Hiring plan'!$K$12*(1+Salary_Raise)^(L$5-1) -> 0 | ... BL46: =BL16*'Hiring plan'!$K$12*(1+Salary_Raise)^(BL$5-1) -> 2370237.2
A47: =A17 -> (spare line 9) | B47: FCFA | D47: =SUM(E47:BL47) -> 0 | E47: =E17*'Hiring plan'!$K$13*(1+Salary_Raise)^(E$5-1) -> 0 | F47: =F17*'Hiring plan'!$K$13*(1+Salary_Raise)^(F$5-1) -> 0 | G47: =G17*'Hiring plan'!$K$13*(1+Salary_Raise)^(G$5-1) -> 0 | H47: =H17*'Hiring plan'!$K$13*(1+Salary_Raise)^(H$5-1) -> 0 | I47: =I17*'Hiring plan'!$K$13*(1+Salary_Raise)^(I$5-1) -> 0 | J47: =J17*'Hiring plan'!$K$13*(1+Salary_Raise)^(J$5-1) -> 0 | K47: =K17*'Hiring plan'!$K$13*(1+Salary_Raise)^(K$5-1) -> 0 | L47: =L17*'Hiring plan'!$K$13*(1+Salary_Raise)^(L$5-1) -> 0 | ... BL47: =BL17*'Hiring plan'!$K$13*(1+Salary_Raise)^(BL$5-1) -> 0
A48: =A18 -> (spare line 10) | B48: FCFA | D48: =SUM(E48:BL48) -> 0 | E48: =E18*'Hiring plan'!$K$14*(1+Salary_Raise)^(E$5-1) -> 0 | F48: =F18*'Hiring plan'!$K$14*(1+Salary_Raise)^(F$5-1) -> 0 | G48: =G18*'Hiring plan'!$K$14*(1+Salary_Raise)^(G$5-1) -> 0 | H48: =H18*'Hiring plan'!$K$14*(1+Salary_Raise)^(H$5-1) -> 0 | I48: =I18*'Hiring plan'!$K$14*(1+Salary_Raise)^(I$5-1) -> 0 | J48: =J18*'Hiring plan'!$K$14*(1+Salary_Raise)^(J$5-1) -> 0 | K48: =K18*'Hiring plan'!$K$14*(1+Salary_Raise)^(K$5-1) -> 0 | L48: =L18*'Hiring plan'!$K$14*(1+Salary_Raise)^(L$5-1) -> 0 | ... BL48: =BL18*'Hiring plan'!$K$14*(1+Salary_Raise)^(BL$5-1) -> 0
A49: =A19 -> (spare line 11) | B49: FCFA | D49: =SUM(E49:BL49) -> 0 | E49: =E19*'Hiring plan'!$K$15*(1+Salary_Raise)^(E$5-1) -> 0 | F49: =F19*'Hiring plan'!$K$15*(1+Salary_Raise)^(F$5-1) -> 0 | G49: =G19*'Hiring plan'!$K$15*(1+Salary_Raise)^(G$5-1) -> 0 | H49: =H19*'Hiring plan'!$K$15*(1+Salary_Raise)^(H$5-1) -> 0 | I49: =I19*'Hiring plan'!$K$15*(1+Salary_Raise)^(I$5-1) -> 0 | J49: =J19*'Hiring plan'!$K$15*(1+Salary_Raise)^(J$5-1) -> 0 | K49: =K19*'Hiring plan'!$K$15*(1+Salary_Raise)^(K$5-1) -> 0 | L49: =L19*'Hiring plan'!$K$15*(1+Salary_Raise)^(L$5-1) -> 0 | ... BL49: =BL19*'Hiring plan'!$K$15*(1+Salary_Raise)^(BL$5-1) -> 0
A50: =A20 -> (spare line 12) | B50: FCFA | D50: =SUM(E50:BL50) -> 0 | E50: =E20*'Hiring plan'!$K$16*(1+Salary_Raise)^(E$5-1) -> 0 | F50: =F20*'Hiring plan'!$K$16*(1+Salary_Raise)^(F$5-1) -> 0 | G50: =G20*'Hiring plan'!$K$16*(1+Salary_Raise)^(G$5-1) -> 0 | H50: =H20*'Hiring plan'!$K$16*(1+Salary_Raise)^(H$5-1) -> 0 | I50: =I20*'Hiring plan'!$K$16*(1+Salary_Raise)^(I$5-1) -> 0 | J50: =J20*'Hiring plan'!$K$16*(1+Salary_Raise)^(J$5-1) -> 0 | K50: =K20*'Hiring plan'!$K$16*(1+Salary_Raise)^(K$5-1) -> 0 | L50: =L20*'Hiring plan'!$K$16*(1+Salary_Raise)^(L$5-1) -> 0 | ... BL50: =BL20*'Hiring plan'!$K$16*(1+Salary_Raise)^(BL$5-1) -> 0
A51: =A21 -> (spare line 13) | B51: FCFA | D51: =SUM(E51:BL51) -> 0 | E51: =E21*'Hiring plan'!$K$17*(1+Salary_Raise)^(E$5-1) -> 0 | F51: =F21*'Hiring plan'!$K$17*(1+Salary_Raise)^(F$5-1) -> 0 | G51: =G21*'Hiring plan'!$K$17*(1+Salary_Raise)^(G$5-1) -> 0 | H51: =H21*'Hiring plan'!$K$17*(1+Salary_Raise)^(H$5-1) -> 0 | I51: =I21*'Hiring plan'!$K$17*(1+Salary_Raise)^(I$5-1) -> 0 | J51: =J21*'Hiring plan'!$K$17*(1+Salary_Raise)^(J$5-1) -> 0 | K51: =K21*'Hiring plan'!$K$17*(1+Salary_Raise)^(K$5-1) -> 0 | L51: =L21*'Hiring plan'!$K$17*(1+Salary_Raise)^(L$5-1) -> 0 | ... BL51: =BL21*'Hiring plan'!$K$17*(1+Salary_Raise)^(BL$5-1) -> 0
A52: =A22 -> (spare line 14) | B52: FCFA | D52: =SUM(E52:BL52) -> 0 | E52: =E22*'Hiring plan'!$K$18*(1+Salary_Raise)^(E$5-1) -> 0 | F52: =F22*'Hiring plan'!$K$18*(1+Salary_Raise)^(F$5-1) -> 0 | G52: =G22*'Hiring plan'!$K$18*(1+Salary_Raise)^(G$5-1) -> 0 | H52: =H22*'Hiring plan'!$K$18*(1+Salary_Raise)^(H$5-1) -> 0 | I52: =I22*'Hiring plan'!$K$18*(1+Salary_Raise)^(I$5-1) -> 0 | J52: =J22*'Hiring plan'!$K$18*(1+Salary_Raise)^(J$5-1) -> 0 | K52: =K22*'Hiring plan'!$K$18*(1+Salary_Raise)^(K$5-1) -> 0 | L52: =L22*'Hiring plan'!$K$18*(1+Salary_Raise)^(L$5-1) -> 0 | ... BL52: =BL22*'Hiring plan'!$K$18*(1+Salary_Raise)^(BL$5-1) -> 0
A53: =A23 -> (spare line 15) | B53: FCFA | D53: =SUM(E53:BL53) -> 0 | E53: =E23*'Hiring plan'!$K$19*(1+Salary_Raise)^(E$5-1) -> 0 | F53: =F23*'Hiring plan'!$K$19*(1+Salary_Raise)^(F$5-1) -> 0 | G53: =G23*'Hiring plan'!$K$19*(1+Salary_Raise)^(G$5-1) -> 0 | H53: =H23*'Hiring plan'!$K$19*(1+Salary_Raise)^(H$5-1) -> 0 | I53: =I23*'Hiring plan'!$K$19*(1+Salary_Raise)^(I$5-1) -> 0 | J53: =J23*'Hiring plan'!$K$19*(1+Salary_Raise)^(J$5-1) -> 0 | K53: =K23*'Hiring plan'!$K$19*(1+Salary_Raise)^(K$5-1) -> 0 | L53: =L23*'Hiring plan'!$K$19*(1+Salary_Raise)^(L$5-1) -> 0 | ... BL53: =BL23*'Hiring plan'!$K$19*(1+Salary_Raise)^(BL$5-1) -> 0
A54: =A24 -> (spare line 16) | B54: FCFA | D54: =SUM(E54:BL54) -> 0 | E54: =E24*'Hiring plan'!$K$20*(1+Salary_Raise)^(E$5-1) -> 0 | F54: =F24*'Hiring plan'!$K$20*(1+Salary_Raise)^(F$5-1) -> 0 | G54: =G24*'Hiring plan'!$K$20*(1+Salary_Raise)^(G$5-1) -> 0 | H54: =H24*'Hiring plan'!$K$20*(1+Salary_Raise)^(H$5-1) -> 0 | I54: =I24*'Hiring plan'!$K$20*(1+Salary_Raise)^(I$5-1) -> 0 | J54: =J24*'Hiring plan'!$K$20*(1+Salary_Raise)^(J$5-1) -> 0 | K54: =K24*'Hiring plan'!$K$20*(1+Salary_Raise)^(K$5-1) -> 0 | L54: =L24*'Hiring plan'!$K$20*(1+Salary_Raise)^(L$5-1) -> 0 | ... BL54: =BL24*'Hiring plan'!$K$20*(1+Salary_Raise)^(BL$5-1) -> 0
A55: =A25 -> (spare line 17) | B55: FCFA | D55: =SUM(E55:BL55) -> 0 | E55: =E25*'Hiring plan'!$K$21*(1+Salary_Raise)^(E$5-1) -> 0 | F55: =F25*'Hiring plan'!$K$21*(1+Salary_Raise)^(F$5-1) -> 0 | G55: =G25*'Hiring plan'!$K$21*(1+Salary_Raise)^(G$5-1) -> 0 | H55: =H25*'Hiring plan'!$K$21*(1+Salary_Raise)^(H$5-1) -> 0 | I55: =I25*'Hiring plan'!$K$21*(1+Salary_Raise)^(I$5-1) -> 0 | J55: =J25*'Hiring plan'!$K$21*(1+Salary_Raise)^(J$5-1) -> 0 | K55: =K25*'Hiring plan'!$K$21*(1+Salary_Raise)^(K$5-1) -> 0 | L55: =L25*'Hiring plan'!$K$21*(1+Salary_Raise)^(L$5-1) -> 0 | ... BL55: =BL25*'Hiring plan'!$K$21*(1+Salary_Raise)^(BL$5-1) -> 0
A56: =A26 -> (spare line 18) | B56: FCFA | D56: =SUM(E56:BL56) -> 0 | E56: =E26*'Hiring plan'!$K$22*(1+Salary_Raise)^(E$5-1) -> 0 | F56: =F26*'Hiring plan'!$K$22*(1+Salary_Raise)^(F$5-1) -> 0 | G56: =G26*'Hiring plan'!$K$22*(1+Salary_Raise)^(G$5-1) -> 0 | H56: =H26*'Hiring plan'!$K$22*(1+Salary_Raise)^(H$5-1) -> 0 | I56: =I26*'Hiring plan'!$K$22*(1+Salary_Raise)^(I$5-1) -> 0 | J56: =J26*'Hiring plan'!$K$22*(1+Salary_Raise)^(J$5-1) -> 0 | K56: =K26*'Hiring plan'!$K$22*(1+Salary_Raise)^(K$5-1) -> 0 | L56: =L26*'Hiring plan'!$K$22*(1+Salary_Raise)^(L$5-1) -> 0 | ... BL56: =BL26*'Hiring plan'!$K$22*(1+Salary_Raise)^(BL$5-1) -> 0
A57: =A27 -> (spare line 19) | B57: FCFA | D57: =SUM(E57:BL57) -> 0 | E57: =E27*'Hiring plan'!$K$23*(1+Salary_Raise)^(E$5-1) -> 0 | F57: =F27*'Hiring plan'!$K$23*(1+Salary_Raise)^(F$5-1) -> 0 | G57: =G27*'Hiring plan'!$K$23*(1+Salary_Raise)^(G$5-1) -> 0 | H57: =H27*'Hiring plan'!$K$23*(1+Salary_Raise)^(H$5-1) -> 0 | I57: =I27*'Hiring plan'!$K$23*(1+Salary_Raise)^(I$5-1) -> 0 | J57: =J27*'Hiring plan'!$K$23*(1+Salary_Raise)^(J$5-1) -> 0 | K57: =K27*'Hiring plan'!$K$23*(1+Salary_Raise)^(K$5-1) -> 0 | L57: =L27*'Hiring plan'!$K$23*(1+Salary_Raise)^(L$5-1) -> 0 | ... BL57: =BL27*'Hiring plan'!$K$23*(1+Salary_Raise)^(BL$5-1) -> 0
A58: =A28 -> (spare line 20) | B58: FCFA | D58: =SUM(E58:BL58) -> 0 | E58: =E28*'Hiring plan'!$K$24*(1+Salary_Raise)^(E$5-1) -> 0 | F58: =F28*'Hiring plan'!$K$24*(1+Salary_Raise)^(F$5-1) -> 0 | G58: =G28*'Hiring plan'!$K$24*(1+Salary_Raise)^(G$5-1) -> 0 | H58: =H28*'Hiring plan'!$K$24*(1+Salary_Raise)^(H$5-1) -> 0 | I58: =I28*'Hiring plan'!$K$24*(1+Salary_Raise)^(I$5-1) -> 0 | J58: =J28*'Hiring plan'!$K$24*(1+Salary_Raise)^(J$5-1) -> 0 | K58: =K28*'Hiring plan'!$K$24*(1+Salary_Raise)^(K$5-1) -> 0 | L58: =L28*'Hiring plan'!$K$24*(1+Salary_Raise)^(L$5-1) -> 0 | ... BL58: =BL28*'Hiring plan'!$K$24*(1+Salary_Raise)^(BL$5-1) -> 0
A59: =A29 -> (spare line 21) | B59: FCFA | D59: =SUM(E59:BL59) -> 0 | E59: =E29*'Hiring plan'!$K$25*(1+Salary_Raise)^(E$5-1) -> 0 | F59: =F29*'Hiring plan'!$K$25*(1+Salary_Raise)^(F$5-1) -> 0 | G59: =G29*'Hiring plan'!$K$25*(1+Salary_Raise)^(G$5-1) -> 0 | H59: =H29*'Hiring plan'!$K$25*(1+Salary_Raise)^(H$5-1) -> 0 | I59: =I29*'Hiring plan'!$K$25*(1+Salary_Raise)^(I$5-1) -> 0 | J59: =J29*'Hiring plan'!$K$25*(1+Salary_Raise)^(J$5-1) -> 0 | K59: =K29*'Hiring plan'!$K$25*(1+Salary_Raise)^(K$5-1) -> 0 | L59: =L29*'Hiring plan'!$K$25*(1+Salary_Raise)^(L$5-1) -> 0 | ... BL59: =BL29*'Hiring plan'!$K$25*(1+Salary_Raise)^(BL$5-1) -> 0
A60: =A30 -> (spare line 22) | B60: FCFA | D60: =SUM(E60:BL60) -> 0 | E60: =E30*'Hiring plan'!$K$26*(1+Salary_Raise)^(E$5-1) -> 0 | F60: =F30*'Hiring plan'!$K$26*(1+Salary_Raise)^(F$5-1) -> 0 | G60: =G30*'Hiring plan'!$K$26*(1+Salary_Raise)^(G$5-1) -> 0 | H60: =H30*'Hiring plan'!$K$26*(1+Salary_Raise)^(H$5-1) -> 0 | I60: =I30*'Hiring plan'!$K$26*(1+Salary_Raise)^(I$5-1) -> 0 | J60: =J30*'Hiring plan'!$K$26*(1+Salary_Raise)^(J$5-1) -> 0 | K60: =K30*'Hiring plan'!$K$26*(1+Salary_Raise)^(K$5-1) -> 0 | L60: =L30*'Hiring plan'!$K$26*(1+Salary_Raise)^(L$5-1) -> 0 | ... BL60: =BL30*'Hiring plan'!$K$26*(1+Salary_Raise)^(BL$5-1) -> 0
A61: =A31 -> (spare line 23) | B61: FCFA | D61: =SUM(E61:BL61) -> 0 | E61: =E31*'Hiring plan'!$K$27*(1+Salary_Raise)^(E$5-1) -> 0 | F61: =F31*'Hiring plan'!$K$27*(1+Salary_Raise)^(F$5-1) -> 0 | G61: =G31*'Hiring plan'!$K$27*(1+Salary_Raise)^(G$5-1) -> 0 | H61: =H31*'Hiring plan'!$K$27*(1+Salary_Raise)^(H$5-1) -> 0 | I61: =I31*'Hiring plan'!$K$27*(1+Salary_Raise)^(I$5-1) -> 0 | J61: =J31*'Hiring plan'!$K$27*(1+Salary_Raise)^(J$5-1) -> 0 | K61: =K31*'Hiring plan'!$K$27*(1+Salary_Raise)^(K$5-1) -> 0 | L61: =L31*'Hiring plan'!$K$27*(1+Salary_Raise)^(L$5-1) -> 0 | ... BL61: =BL31*'Hiring plan'!$K$27*(1+Salary_Raise)^(BL$5-1) -> 0
A62: =A32 -> (spare line 24) | B62: FCFA | D62: =SUM(E62:BL62) -> 0 | E62: =E32*'Hiring plan'!$K$28*(1+Salary_Raise)^(E$5-1) -> 0 | F62: =F32*'Hiring plan'!$K$28*(1+Salary_Raise)^(F$5-1) -> 0 | G62: =G32*'Hiring plan'!$K$28*(1+Salary_Raise)^(G$5-1) -> 0 | H62: =H32*'Hiring plan'!$K$28*(1+Salary_Raise)^(H$5-1) -> 0 | I62: =I32*'Hiring plan'!$K$28*(1+Salary_Raise)^(I$5-1) -> 0 | J62: =J32*'Hiring plan'!$K$28*(1+Salary_Raise)^(J$5-1) -> 0 | K62: =K32*'Hiring plan'!$K$28*(1+Salary_Raise)^(K$5-1) -> 0 | L62: =L32*'Hiring plan'!$K$28*(1+Salary_Raise)^(L$5-1) -> 0 | ... BL62: =BL32*'Hiring plan'!$K$28*(1+Salary_Raise)^(BL$5-1) -> 0
A63: =A33 -> (spare line 25) | B63: FCFA | D63: =SUM(E63:BL63) -> 0 | E63: =E33*'Hiring plan'!$K$29*(1+Salary_Raise)^(E$5-1) -> 0 | F63: =F33*'Hiring plan'!$K$29*(1+Salary_Raise)^(F$5-1) -> 0 | G63: =G33*'Hiring plan'!$K$29*(1+Salary_Raise)^(G$5-1) -> 0 | H63: =H33*'Hiring plan'!$K$29*(1+Salary_Raise)^(H$5-1) -> 0 | I63: =I33*'Hiring plan'!$K$29*(1+Salary_Raise)^(I$5-1) -> 0 | J63: =J33*'Hiring plan'!$K$29*(1+Salary_Raise)^(J$5-1) -> 0 | K63: =K33*'Hiring plan'!$K$29*(1+Salary_Raise)^(K$5-1) -> 0 | L63: =L33*'Hiring plan'!$K$29*(1+Salary_Raise)^(L$5-1) -> 0 | ... BL63: =BL33*'Hiring plan'!$K$29*(1+Salary_Raise)^(BL$5-1) -> 0
A64: =A34 -> (spare line 26) | B64: FCFA | D64: =SUM(E64:BL64) -> 0 | E64: =E34*'Hiring plan'!$K$30*(1+Salary_Raise)^(E$5-1) -> 0 | F64: =F34*'Hiring plan'!$K$30*(1+Salary_Raise)^(F$5-1) -> 0 | G64: =G34*'Hiring plan'!$K$30*(1+Salary_Raise)^(G$5-1) -> 0 | H64: =H34*'Hiring plan'!$K$30*(1+Salary_Raise)^(H$5-1) -> 0 | I64: =I34*'Hiring plan'!$K$30*(1+Salary_Raise)^(I$5-1) -> 0 | J64: =J34*'Hiring plan'!$K$30*(1+Salary_Raise)^(J$5-1) -> 0 | K64: =K34*'Hiring plan'!$K$30*(1+Salary_Raise)^(K$5-1) -> 0 | L64: =L34*'Hiring plan'!$K$30*(1+Salary_Raise)^(L$5-1) -> 0 | ... BL64: =BL34*'Hiring plan'!$K$30*(1+Salary_Raise)^(BL$5-1) -> 0
A65: =A35 -> (spare line 27) | B65: FCFA | D65: =SUM(E65:BL65) -> 0 | E65: =E35*'Hiring plan'!$K$31*(1+Salary_Raise)^(E$5-1) -> 0 | F65: =F35*'Hiring plan'!$K$31*(1+Salary_Raise)^(F$5-1) -> 0 | G65: =G35*'Hiring plan'!$K$31*(1+Salary_Raise)^(G$5-1) -> 0 | H65: =H35*'Hiring plan'!$K$31*(1+Salary_Raise)^(H$5-1) -> 0 | I65: =I35*'Hiring plan'!$K$31*(1+Salary_Raise)^(I$5-1) -> 0 | J65: =J35*'Hiring plan'!$K$31*(1+Salary_Raise)^(J$5-1) -> 0 | K65: =K35*'Hiring plan'!$K$31*(1+Salary_Raise)^(K$5-1) -> 0 | L65: =L35*'Hiring plan'!$K$31*(1+Salary_Raise)^(L$5-1) -> 0 | ... BL65: =BL35*'Hiring plan'!$K$31*(1+Salary_Raise)^(BL$5-1) -> 0
A66: =A36 -> (spare line 28) | B66: FCFA | D66: =SUM(E66:BL66) -> 0 | E66: =E36*'Hiring plan'!$K$32*(1+Salary_Raise)^(E$5-1) -> 0 | F66: =F36*'Hiring plan'!$K$32*(1+Salary_Raise)^(F$5-1) -> 0 | G66: =G36*'Hiring plan'!$K$32*(1+Salary_Raise)^(G$5-1) -> 0 | H66: =H36*'Hiring plan'!$K$32*(1+Salary_Raise)^(H$5-1) -> 0 | I66: =I36*'Hiring plan'!$K$32*(1+Salary_Raise)^(I$5-1) -> 0 | J66: =J36*'Hiring plan'!$K$32*(1+Salary_Raise)^(J$5-1) -> 0 | K66: =K36*'Hiring plan'!$K$32*(1+Salary_Raise)^(K$5-1) -> 0 | L66: =L36*'Hiring plan'!$K$32*(1+Salary_Raise)^(L$5-1) -> 0 | ... BL66: =BL36*'Hiring plan'!$K$32*(1+Salary_Raise)^(BL$5-1) -> 0
A68: Team that grows with volume
A69: Customer support agents · SN | B69: people | D69: =MAX(E69:BL69) -> 29 | E69: =IF(E$3>=Support_Start,MAX(Support_Min,ROUNDUP('Clients & revenue'!E17/Clients_per_Support+'Clients & revenue'!E32/EmpAcc_per_Support,0)),0) -> 0 | F69: =IF(F$3>=Support_Start,MAX(Support_Min,ROUNDUP('Clients & revenue'!F17/Clients_per_Support+'Clients & revenue'!F32/EmpAcc_per_Support,0)),0) -> 0 | G69: =IF(G$3>=Support_Start,MAX(Support_Min,ROUNDUP('Clients & revenue'!G17/Clients_per_Support+'Clients & revenue'!G32/EmpAcc_per_Support,0)),0) -> 0 | H69: =IF(H$3>=Support_Start,MAX(Support_Min,ROUNDUP('Clients & revenue'!H17/Clients_per_Support+'Clients & revenue'!H32/EmpAcc_per_Support,0)),0) -> 2 | I69: =IF(I$3>=Support_Start,MAX(Support_Min,ROUNDUP('Clients & revenue'!I17/Clients_per_Support+'Clients & revenue'!I32/EmpAcc_per_Support,0)),0) -> 2 | J69: =IF(J$3>=Support_Start,MAX(Support_Min,ROUNDUP('Clients & revenue'!J17/Clients_per_Support+'Clients & revenue'!J32/EmpAcc_per_Support,0)),0) -> 2 | K69: =IF(K$3>=Support_Start,MAX(Support_Min,ROUNDUP('Clients & revenue'!K17/Clients_per_Support+'Clients & revenue'!K32/EmpAcc_per_Support,0)),0) -> 2 | L69: =IF(L$3>=Support_Start,MAX(Support_Min,ROUNDUP('Clients & revenue'!L17/Clients_per_Support+'Clients & revenue'!L32/EmpAcc_per_Support,0)),0) -> 2 | ... BL69: =IF(BL$3>=Support_Start,MAX(Support_Min,ROUNDUP('Clients & revenue'!BL17/Clients_per_Support+'Clients & revenue'!BL32/EmpAcc_per_Support,0)),0) -> 29
A70: Developers · SN | B70: people | D70: =MAX(E70:BL70) -> 6 | E70: =Devs_Min+ROUNDDOWN('Clients & revenue'!E17/Clients_per_Dev,0) -> 2 | F70: =Devs_Min+ROUNDDOWN('Clients & revenue'!F17/Clients_per_Dev,0) -> 2 | G70: =Devs_Min+ROUNDDOWN('Clients & revenue'!G17/Clients_per_Dev,0) -> 2 | H70: =Devs_Min+ROUNDDOWN('Clients & revenue'!H17/Clients_per_Dev,0) -> 2 | I70: =Devs_Min+ROUNDDOWN('Clients & revenue'!I17/Clients_per_Dev,0) -> 2 | J70: =Devs_Min+ROUNDDOWN('Clients & revenue'!J17/Clients_per_Dev,0) -> 2 | K70: =Devs_Min+ROUNDDOWN('Clients & revenue'!K17/Clients_per_Dev,0) -> 2 | L70: =Devs_Min+ROUNDDOWN('Clients & revenue'!L17/Clients_per_Dev,0) -> 2 | ... BL70: =Devs_Min+ROUNDDOWN('Clients & revenue'!BL17/Clients_per_Dev,0) -> 6
A71: Field sales reps, Senegal · SN | B71: people | D71: =MAX(E71:BL71) -> 16 | E71: =IF(E$3>=Reps_Start,MAX(Reps_Min_SN,ROUNDUP(0/Clients_per_Rep,0)),0) -> 0 | F71: =IF(F$3>=Reps_Start,MAX(Reps_Min_SN,ROUNDUP('Clients & revenue'!E19/Clients_per_Rep,0)),0) -> 0 | G71: =IF(G$3>=Reps_Start,MAX(Reps_Min_SN,ROUNDUP('Clients & revenue'!F19/Clients_per_Rep,0)),0) -> 0 | H71: =IF(H$3>=Reps_Start,MAX(Reps_Min_SN,ROUNDUP('Clients & revenue'!G19/Clients_per_Rep,0)),0) -> 2 | I71: =IF(I$3>=Reps_Start,MAX(Reps_Min_SN,ROUNDUP('Clients & revenue'!H19/Clients_per_Rep,0)),0) -> 2 | J71: =IF(J$3>=Reps_Start,MAX(Reps_Min_SN,ROUNDUP('Clients & revenue'!I19/Clients_per_Rep,0)),0) -> 2 | K71: =IF(K$3>=Reps_Start,MAX(Reps_Min_SN,ROUNDUP('Clients & revenue'!J19/Clients_per_Rep,0)),0) -> 2 | L71: =IF(L$3>=Reps_Start,MAX(Reps_Min_SN,ROUNDUP('Clients & revenue'!K19/Clients_per_Rep,0)),0) -> 2 | M71: =IF(M$3>=Reps_Start,MAX(Reps_Min_SN,ROUNDUP('Clients & revenue'!L19/Clients_per_Rep,0)),0) -> 2 | ... BL71: =IF(BL$3>=Reps_Start,MAX(Reps_Min_SN,ROUNDUP('Clients & revenue'!BK19/Clients_per_Rep,0)),0) -> 16
A72: Field sales reps, Côte d'Ivoire · CI | B72: people | D72: =MAX(E72:BL72) -> 8 | E72: =IF(E$3>=CI_Office_Start,MAX(Reps_Min_CI,ROUNDUP(0/Clients_per_Rep,0)),0) -> 0 | F72: =IF(F$3>=CI_Office_Start,MAX(Reps_Min_CI,ROUNDUP('Clients & revenue'!E20/Clients_per_Rep,0)),0) -> 0 | G72: =IF(G$3>=CI_Office_Start,MAX(Reps_Min_CI,ROUNDUP('Clients & revenue'!F20/Clients_per_Rep,0)),0) -> 0 | H72: =IF(H$3>=CI_Office_Start,MAX(Reps_Min_CI,ROUNDUP('Clients & revenue'!G20/Clients_per_Rep,0)),0) -> 0 | I72: =IF(I$3>=CI_Office_Start,MAX(Reps_Min_CI,ROUNDUP('Clients & revenue'!H20/Clients_per_Rep,0)),0) -> 0 | J72: =IF(J$3>=CI_Office_Start,MAX(Reps_Min_CI,ROUNDUP('Clients & revenue'!I20/Clients_per_Rep,0)),0) -> 0 | K72: =IF(K$3>=CI_Office_Start,MAX(Reps_Min_CI,ROUNDUP('Clients & revenue'!J20/Clients_per_Rep,0)),0) -> 0 | L72: =IF(L$3>=CI_Office_Start,MAX(Reps_Min_CI,ROUNDUP('Clients & revenue'!K20/Clients_per_Rep,0)),0) -> 0 | M72: =IF(M$3>=CI_Office_Start,MAX(Reps_Min_CI,ROUNDUP('Clients & revenue'!L20/Clients_per_Rep,0)),0) -> 0 | ... BL72: =IF(BL$3>=CI_Office_Start,MAX(Reps_Min_CI,ROUNDUP('Clients & revenue'!BK20/Clients_per_Rep,0)),0) -> 8
A73: Credit analysts and collections · SN | B73: people | D73: =MAX(E73:BL73) -> 8 | E73: =IF(E$3>=MIN(Start_Factoring,Start_Bridge,Start_Line,Start_Term)-Credit_Lead_Months,MAX(1,ROUNDUP(0/Book_per_Credit,0)),0) -> 0 | F73: =IF(F$3>=MIN(Start_Factoring,Start_Bridge,Start_Line,Start_Term)-Credit_Lead_Months,MAX(1,ROUNDUP(Credit!E25/Book_per_Credit,0)),0) -> 0 | G73: =IF(G$3>=MIN(Start_Factoring,Start_Bridge,Start_Line,Start_Term)-Credit_Lead_Months,MAX(1,ROUNDUP(Credit!F25/Book_per_Credit,0)),0) -> 0 | H73: =IF(H$3>=MIN(Start_Factoring,Start_Bridge,Start_Line,Start_Term)-Credit_Lead_Months,MAX(1,ROUNDUP(Credit!G25/Book_per_Credit,0)),0) -> 0 | I73: =IF(I$3>=MIN(Start_Factoring,Start_Bridge,Start_Line,Start_Term)-Credit_Lead_Months,MAX(1,ROUNDUP(Credit!H25/Book_per_Credit,0)),0) -> 0 | J73: =IF(J$3>=MIN(Start_Factoring,Start_Bridge,Start_Line,Start_Term)-Credit_Lead_Months,MAX(1,ROUNDUP(Credit!I25/Book_per_Credit,0)),0) -> 0 | K73: =IF(K$3>=MIN(Start_Factoring,Start_Bridge,Start_Line,Start_Term)-Credit_Lead_Months,MAX(1,ROUNDUP(Credit!J25/Book_per_Credit,0)),0) -> 0 | L73: =IF(L$3>=MIN(Start_Factoring,Start_Bridge,Start_Line,Start_Term)-Credit_Lead_Months,MAX(1,ROUNDUP(Credit!K25/Book_per_Credit,0)),0) -> 0 | M73: =IF(M$3>=MIN(Start_Factoring,Start_Bridge,Start_Line,Start_Term)-Credit_Lead_Months,MAX(1,ROUNDUP(Credit!L25/Book_per_Credit,0)),0) -> 0 | ... BL73: =IF(BL$3>=MIN(Start_Factoring,Start_Bridge,Start_Line,Start_Term)-Credit_Lead_Months,MAX(1,ROUNDUP(Credit!BK25/Book_per_Credit,0)),0) -> 8
A74: Employer cost: Customer support agents | B74: FCFA | D74: =SUM(E74:BL74) -> 2.5080197e+08 | E74: =E69*Salary_Support*(1+Employer_Charges)*(1+Salary_Raise)^(E$5-1) -> 0 | F74: =F69*Salary_Support*(1+Employer_Charges)*(1+Salary_Raise)^(F$5-1) -> 0 | G74: =G69*Salary_Support*(1+Employer_Charges)*(1+Salary_Raise)^(G$5-1) -> 0 | H74: =H69*Salary_Support*(1+Employer_Charges)*(1+Salary_Raise)^(H$5-1) -> 728000 | I74: =I69*Salary_Support*(1+Employer_Charges)*(1+Salary_Raise)^(I$5-1) -> 728000 | J74: =J69*Salary_Support*(1+Employer_Charges)*(1+Salary_Raise)^(J$5-1) -> 728000 | K74: =K69*Salary_Support*(1+Employer_Charges)*(1+Salary_Raise)^(K$5-1) -> 728000 | L74: =L69*Salary_Support*(1+Employer_Charges)*(1+Salary_Raise)^(L$5-1) -> 728000 | ... BL74: =BL69*Salary_Support*(1+Employer_Charges)*(1+Salary_Raise)^(BL$5-1) -> 12830884
A75: Employer cost: Developers | B75: FCFA | D75: =SUM(E75:BL75) -> 3.3802631e+08 | E75: =E70*Salary_Dev*(1+Employer_Charges)*(1+Salary_Raise)^(E$5-1) -> 3120000 | F75: =F70*Salary_Dev*(1+Employer_Charges)*(1+Salary_Raise)^(F$5-1) -> 3120000 | G75: =G70*Salary_Dev*(1+Employer_Charges)*(1+Salary_Raise)^(G$5-1) -> 3120000 | H75: =H70*Salary_Dev*(1+Employer_Charges)*(1+Salary_Raise)^(H$5-1) -> 3120000 | I75: =I70*Salary_Dev*(1+Employer_Charges)*(1+Salary_Raise)^(I$5-1) -> 3120000 | J75: =J70*Salary_Dev*(1+Employer_Charges)*(1+Salary_Raise)^(J$5-1) -> 3120000 | K75: =K70*Salary_Dev*(1+Employer_Charges)*(1+Salary_Raise)^(K$5-1) -> 3120000 | L75: =L70*Salary_Dev*(1+Employer_Charges)*(1+Salary_Raise)^(L$5-1) -> 3120000 | ... BL75: =BL70*Salary_Dev*(1+Employer_Charges)*(1+Salary_Raise)^(BL$5-1) -> 11377138
A76: Employer cost: Field sales reps, Senegal | B76: FCFA | D76: =SUM(E76:BL76) -> 2.2350277e+08 | E76: =E71*Salary_Rep_SN*(1+Employer_Charges)*(1+Salary_Raise)^(E$5-1) -> 0 | F76: =F71*Salary_Rep_SN*(1+Employer_Charges)*(1+Salary_Raise)^(F$5-1) -> 0 | G76: =G71*Salary_Rep_SN*(1+Employer_Charges)*(1+Salary_Raise)^(G$5-1) -> 0 | H76: =H71*Salary_Rep_SN*(1+Employer_Charges)*(1+Salary_Raise)^(H$5-1) -> 1040000 | I76: =I71*Salary_Rep_SN*(1+Employer_Charges)*(1+Salary_Raise)^(I$5-1) -> 1040000 | J76: =J71*Salary_Rep_SN*(1+Employer_Charges)*(1+Salary_Raise)^(J$5-1) -> 1040000 | K76: =K71*Salary_Rep_SN*(1+Employer_Charges)*(1+Salary_Raise)^(K$5-1) -> 1040000 | L76: =L71*Salary_Rep_SN*(1+Employer_Charges)*(1+Salary_Raise)^(L$5-1) -> 1040000 | ... BL76: =BL71*Salary_Rep_SN*(1+Employer_Charges)*(1+Salary_Raise)^(BL$5-1) -> 10113012
A77: Employer cost: Field sales reps, Côte d'Ivoire | B77: FCFA | D77: =SUM(E77:BL77) -> 1.0717396e+08 | E77: =E72*Salary_Rep_CI*(1+Employer_Charges)*(1+Salary_Raise)^(E$5-1) -> 0 | F77: =F72*Salary_Rep_CI*(1+Employer_Charges)*(1+Salary_Raise)^(F$5-1) -> 0 | G77: =G72*Salary_Rep_CI*(1+Employer_Charges)*(1+Salary_Raise)^(G$5-1) -> 0 | H77: =H72*Salary_Rep_CI*(1+Employer_Charges)*(1+Salary_Raise)^(H$5-1) -> 0 | I77: =I72*Salary_Rep_CI*(1+Employer_Charges)*(1+Salary_Raise)^(I$5-1) -> 0 | J77: =J72*Salary_Rep_CI*(1+Employer_Charges)*(1+Salary_Raise)^(J$5-1) -> 0 | K77: =K72*Salary_Rep_CI*(1+Employer_Charges)*(1+Salary_Raise)^(K$5-1) -> 0 | L77: =L72*Salary_Rep_CI*(1+Employer_Charges)*(1+Salary_Raise)^(L$5-1) -> 0 | ... BL77: =BL72*Salary_Rep_CI*(1+Employer_Charges)*(1+Salary_Raise)^(BL$5-1) -> 5688569.2
A78: Employer cost: Credit analysts and collections | B78: FCFA | D78: =SUM(E78:BL78) -> 1.4909291e+08 | E78: =E73*Salary_Credit*(1+Employer_Charges)*(1+Salary_Raise)^(E$5-1) -> 0 | F78: =F73*Salary_Credit*(1+Employer_Charges)*(1+Salary_Raise)^(F$5-1) -> 0 | G78: =G73*Salary_Credit*(1+Employer_Charges)*(1+Salary_Raise)^(G$5-1) -> 0 | H78: =H73*Salary_Credit*(1+Employer_Charges)*(1+Salary_Raise)^(H$5-1) -> 0 | I78: =I73*Salary_Credit*(1+Employer_Charges)*(1+Salary_Raise)^(I$5-1) -> 0 | J78: =J73*Salary_Credit*(1+Employer_Charges)*(1+Salary_Raise)^(J$5-1) -> 0 | K78: =K73*Salary_Credit*(1+Employer_Charges)*(1+Salary_Raise)^(K$5-1) -> 0 | L78: =L73*Salary_Credit*(1+Employer_Charges)*(1+Salary_Raise)^(L$5-1) -> 0 | ... BL78: =BL73*Salary_Credit*(1+Employer_Charges)*(1+Salary_Raise)^(BL$5-1) -> 7584759
A79: New hires in these roles | B79: people | D79: =SUM(E79:BL79) -> 67 | E79: =E69+E70+E71+E72+E73 -> 2 | F79: =MAX(0,F69-E69)+MAX(0,F70-E70)+MAX(0,F71-E71)+MAX(0,F72-E72)+MAX(0,F73-E73) -> 0 | G79: =MAX(0,G69-F69)+MAX(0,G70-F70)+MAX(0,G71-F71)+MAX(0,G72-F72)+MAX(0,G73-F73) -> 0 | H79: =MAX(0,H69-G69)+MAX(0,H70-G70)+MAX(0,H71-G71)+MAX(0,H72-G72)+MAX(0,H73-G73) -> 4 | I79: =MAX(0,I69-H69)+MAX(0,I70-H70)+MAX(0,I71-H71)+MAX(0,I72-H72)+MAX(0,I73-H73) -> 0 | J79: =MAX(0,J69-I69)+MAX(0,J70-I70)+MAX(0,J71-I71)+MAX(0,J72-I72)+MAX(0,J73-I73) -> 0 | K79: =MAX(0,K69-J69)+MAX(0,K70-J70)+MAX(0,K71-J71)+MAX(0,K72-J72)+MAX(0,K73-J73) -> 0 | L79: =MAX(0,L69-K69)+MAX(0,L70-K70)+MAX(0,L71-K71)+MAX(0,L72-K72)+MAX(0,L73-K73) -> 0 | M79: =MAX(0,M69-L69)+MAX(0,M70-L70)+MAX(0,M71-L71)+MAX(0,M72-L72)+MAX(0,M73-L73) -> 0 | ... BL79: =MAX(0,BL69-BK69)+MAX(0,BL70-BK70)+MAX(0,BL71-BK71)+MAX(0,BL72-BK72)+MAX(0,BL73-BK73) -> 2
A81: Summary
A82: Total headcount | B82: people | D82: =BL82 -> 75 | E82: =SUM(E9:E36)+E69+E70+E71+E72+E73 -> 5 | F82: =SUM(F9:F36)+F69+F70+F71+F72+F73 -> 5 | G82: =SUM(G9:G36)+G69+G70+G71+G72+G73 -> 5 | H82: =SUM(H9:H36)+H69+H70+H71+H72+H73 -> 10 | I82: =SUM(I9:I36)+I69+I70+I71+I72+I73 -> 11 | J82: =SUM(J9:J36)+J69+J70+J71+J72+J73 -> 11 | K82: =SUM(K9:K36)+K69+K70+K71+K72+K73 -> 11 | L82: =SUM(L9:L36)+L69+L70+L71+L72+L73 -> 11 | ... BL82: =SUM(BL9:BL36)+BL69+BL70+BL71+BL72+BL73 -> 75
A83: Headcount, Senegal | B83: people | D83: =BL83 -> 66 | E83: =SUMIF('Hiring plan'!$D$5:$D$32,"SN",E9:E36)+E69+E70+E71+E73 -> 5 | F83: =SUMIF('Hiring plan'!$D$5:$D$32,"SN",F9:F36)+F69+F70+F71+F73 -> 5 | G83: =SUMIF('Hiring plan'!$D$5:$D$32,"SN",G9:G36)+G69+G70+G71+G73 -> 5 | H83: =SUMIF('Hiring plan'!$D$5:$D$32,"SN",H9:H36)+H69+H70+H71+H73 -> 10 | I83: =SUMIF('Hiring plan'!$D$5:$D$32,"SN",I9:I36)+I69+I70+I71+I73 -> 11 | J83: =SUMIF('Hiring plan'!$D$5:$D$32,"SN",J9:J36)+J69+J70+J71+J73 -> 11 | K83: =SUMIF('Hiring plan'!$D$5:$D$32,"SN",K9:K36)+K69+K70+K71+K73 -> 11 | L83: =SUMIF('Hiring plan'!$D$5:$D$32,"SN",L9:L36)+L69+L70+L71+L73 -> 11 | ... BL83: =SUMIF('Hiring plan'!$D$5:$D$32,"SN",BL9:BL36)+BL69+BL70+BL71+BL73 -> 66
A84: Headcount, Côte d'Ivoire | B84: people | D84: =BL84 -> 9 | E84: =SUMIF('Hiring plan'!$D$5:$D$32,"CI",E9:E36)+E72 -> 0 | F84: =SUMIF('Hiring plan'!$D$5:$D$32,"CI",F9:F36)+F72 -> 0 | G84: =SUMIF('Hiring plan'!$D$5:$D$32,"CI",G9:G36)+G72 -> 0 | H84: =SUMIF('Hiring plan'!$D$5:$D$32,"CI",H9:H36)+H72 -> 0 | I84: =SUMIF('Hiring plan'!$D$5:$D$32,"CI",I9:I36)+I72 -> 0 | J84: =SUMIF('Hiring plan'!$D$5:$D$32,"CI",J9:J36)+J72 -> 0 | K84: =SUMIF('Hiring plan'!$D$5:$D$32,"CI",K9:K36)+K72 -> 0 | L84: =SUMIF('Hiring plan'!$D$5:$D$32,"CI",L9:L36)+L72 -> 0 | ... BL84: =SUMIF('Hiring plan'!$D$5:$D$32,"CI",BL9:BL36)+BL72 -> 9
A85: Engineering headcount (CTO and developers) | B85: people | D85: =BL85 -> 7 | E85: =SUMIF('Hiring plan'!$B$5:$B$32,"Engineering & product",E9:E36)+E70 -> 3 | F85: =SUMIF('Hiring plan'!$B$5:$B$32,"Engineering & product",F9:F36)+F70 -> 3 | G85: =SUMIF('Hiring plan'!$B$5:$B$32,"Engineering & product",G9:G36)+G70 -> 3 | H85: =SUMIF('Hiring plan'!$B$5:$B$32,"Engineering & product",H9:H36)+H70 -> 3 | I85: =SUMIF('Hiring plan'!$B$5:$B$32,"Engineering & product",I9:I36)+I70 -> 3 | J85: =SUMIF('Hiring plan'!$B$5:$B$32,"Engineering & product",J9:J36)+J70 -> 3 | K85: =SUMIF('Hiring plan'!$B$5:$B$32,"Engineering & product",K9:K36)+K70 -> 3 | L85: =SUMIF('Hiring plan'!$B$5:$B$32,"Engineering & product",L9:L36)+L70 -> 3 | ... BL85: =SUMIF('Hiring plan'!$B$5:$B$32,"Engineering & product",BL9:BL36)+BL70 -> 7
A86: Field sales reps, Senegal | B86: people | D86: =BL86 -> 17 | E86: =SUMIFS(E9:E36,'Hiring plan'!$E$5:$E$32,"Sales rep",'Hiring plan'!$D$5:$D$32,"SN")+E71 -> 1 | F86: =SUMIFS(F9:F36,'Hiring plan'!$E$5:$E$32,"Sales rep",'Hiring plan'!$D$5:$D$32,"SN")+F71 -> 1 | G86: =SUMIFS(G9:G36,'Hiring plan'!$E$5:$E$32,"Sales rep",'Hiring plan'!$D$5:$D$32,"SN")+G71 -> 1 | H86: =SUMIFS(H9:H36,'Hiring plan'!$E$5:$E$32,"Sales rep",'Hiring plan'!$D$5:$D$32,"SN")+H71 -> 3 | I86: =SUMIFS(I9:I36,'Hiring plan'!$E$5:$E$32,"Sales rep",'Hiring plan'!$D$5:$D$32,"SN")+I71 -> 3 | J86: =SUMIFS(J9:J36,'Hiring plan'!$E$5:$E$32,"Sales rep",'Hiring plan'!$D$5:$D$32,"SN")+J71 -> 3 | K86: =SUMIFS(K9:K36,'Hiring plan'!$E$5:$E$32,"Sales rep",'Hiring plan'!$D$5:$D$32,"SN")+K71 -> 3 | L86: =SUMIFS(L9:L36,'Hiring plan'!$E$5:$E$32,"Sales rep",'Hiring plan'!$D$5:$D$32,"SN")+L71 -> 3 | ... BL86: =SUMIFS(BL9:BL36,'Hiring plan'!$E$5:$E$32,"Sales rep",'Hiring plan'!$D$5:$D$32,"SN")+BL71 -> 17
A87: Field sales reps, Côte d'Ivoire | B87: people | D87: =BL87 -> 8 | E87: =SUMIFS(E9:E36,'Hiring plan'!$E$5:$E$32,"Sales rep",'Hiring plan'!$D$5:$D$32,"CI")+E72 -> 0 | F87: =SUMIFS(F9:F36,'Hiring plan'!$E$5:$E$32,"Sales rep",'Hiring plan'!$D$5:$D$32,"CI")+F72 -> 0 | G87: =SUMIFS(G9:G36,'Hiring plan'!$E$5:$E$32,"Sales rep",'Hiring plan'!$D$5:$D$32,"CI")+G72 -> 0 | H87: =SUMIFS(H9:H36,'Hiring plan'!$E$5:$E$32,"Sales rep",'Hiring plan'!$D$5:$D$32,"CI")+H72 -> 0 | I87: =SUMIFS(I9:I36,'Hiring plan'!$E$5:$E$32,"Sales rep",'Hiring plan'!$D$5:$D$32,"CI")+I72 -> 0 | J87: =SUMIFS(J9:J36,'Hiring plan'!$E$5:$E$32,"Sales rep",'Hiring plan'!$D$5:$D$32,"CI")+J72 -> 0 | K87: =SUMIFS(K9:K36,'Hiring plan'!$E$5:$E$32,"Sales rep",'Hiring plan'!$D$5:$D$32,"CI")+K72 -> 0 | L87: =SUMIFS(L9:L36,'Hiring plan'!$E$5:$E$32,"Sales rep",'Hiring plan'!$D$5:$D$32,"CI")+L72 -> 0 | ... BL87: =SUMIFS(BL9:BL36,'Hiring plan'!$E$5:$E$32,"Sales rep",'Hiring plan'!$D$5:$D$32,"CI")+BL72 -> 8
A88: New hires this month | B88: people | D88: =SUM(E88:BL88) -> 75 | E88: =SUMPRODUCT(--('Hiring plan'!$G$5:$G$32=E$3),'Hiring plan'!$F$5:$F$32)+E79 -> 5 | F88: =SUMPRODUCT(--('Hiring plan'!$G$5:$G$32=F$3),'Hiring plan'!$F$5:$F$32)+F79 -> 0 | G88: =SUMPRODUCT(--('Hiring plan'!$G$5:$G$32=G$3),'Hiring plan'!$F$5:$F$32)+G79 -> 0 | H88: =SUMPRODUCT(--('Hiring plan'!$G$5:$G$32=H$3),'Hiring plan'!$F$5:$F$32)+H79 -> 5 | I88: =SUMPRODUCT(--('Hiring plan'!$G$5:$G$32=I$3),'Hiring plan'!$F$5:$F$32)+I79 -> 1 | J88: =SUMPRODUCT(--('Hiring plan'!$G$5:$G$32=J$3),'Hiring plan'!$F$5:$F$32)+J79 -> 0 | K88: =SUMPRODUCT(--('Hiring plan'!$G$5:$G$32=K$3),'Hiring plan'!$F$5:$F$32)+K79 -> 0 | L88: =SUMPRODUCT(--('Hiring plan'!$G$5:$G$32=L$3),'Hiring plan'!$F$5:$F$32)+L79 -> 0 | ... BL88: =SUMPRODUCT(--('Hiring plan'!$G$5:$G$32=BL$3),'Hiring plan'!$F$5:$F$32)+BL79 -> 2
A89: of which CTO and developers (MacBooks) | B89: people | D89: =SUM(E89:BL89) -> 7 | E89: =SUMPRODUCT(--('Hiring plan'!$G$5:$G$32=E$3),--('Hiring plan'!$B$5:$B$32="Engineering & product"),'Hiring plan'!$F$5:$F$32)+E70 -> 3 | F89: =SUMPRODUCT(--('Hiring plan'!$G$5:$G$32=F$3),--('Hiring plan'!$B$5:$B$32="Engineering & product"),'Hiring plan'!$F$5:$F$32)+MAX(0,F70-E70) -> 0 | G89: =SUMPRODUCT(--('Hiring plan'!$G$5:$G$32=G$3),--('Hiring plan'!$B$5:$B$32="Engineering & product"),'Hiring plan'!$F$5:$F$32)+MAX(0,G70-F70) -> 0 | H89: =SUMPRODUCT(--('Hiring plan'!$G$5:$G$32=H$3),--('Hiring plan'!$B$5:$B$32="Engineering & product"),'Hiring plan'!$F$5:$F$32)+MAX(0,H70-G70) -> 0 | I89: =SUMPRODUCT(--('Hiring plan'!$G$5:$G$32=I$3),--('Hiring plan'!$B$5:$B$32="Engineering & product"),'Hiring plan'!$F$5:$F$32)+MAX(0,I70-H70) -> 0 | J89: =SUMPRODUCT(--('Hiring plan'!$G$5:$G$32=J$3),--('Hiring plan'!$B$5:$B$32="Engineering & product"),'Hiring plan'!$F$5:$F$32)+MAX(0,J70-I70) -> 0 | K89: =SUMPRODUCT(--('Hiring plan'!$G$5:$G$32=K$3),--('Hiring plan'!$B$5:$B$32="Engineering & product"),'Hiring plan'!$F$5:$F$32)+MAX(0,K70-J70) -> 0 | L89: =SUMPRODUCT(--('Hiring plan'!$G$5:$G$32=L$3),--('Hiring plan'!$B$5:$B$32="Engineering & product"),'Hiring plan'!$F$5:$F$32)+MAX(0,L70-K70) -> 0 | M89: =SUMPRODUCT(--('Hiring plan'!$G$5:$G$32=M$3),--('Hiring plan'!$B$5:$B$32="Engineering & product"),'Hiring plan'!$F$5:$F$32)+MAX(0,M70-L70) -> 0 | ... BL89: =SUMPRODUCT(--('Hiring plan'!$G$5:$G$32=BL$3),--('Hiring plan'!$B$5:$B$32="Engineering & product"),'Hiring plan'!$F$5:$F$32)+MAX(0,BL70-BK70) -> 0
A90: Headcount: Leadership | B90: people | D90: =BL90 -> 2 | E90: =SUMIF('Hiring plan'!$B$5:$B$32,"Leadership",E9:E36)+0 -> 0 | F90: =SUMIF('Hiring plan'!$B$5:$B$32,"Leadership",F9:F36)+0 -> 0 | G90: =SUMIF('Hiring plan'!$B$5:$B$32,"Leadership",G9:G36)+0 -> 0 | H90: =SUMIF('Hiring plan'!$B$5:$B$32,"Leadership",H9:H36)+0 -> 0 | I90: =SUMIF('Hiring plan'!$B$5:$B$32,"Leadership",I9:I36)+0 -> 0 | J90: =SUMIF('Hiring plan'!$B$5:$B$32,"Leadership",J9:J36)+0 -> 0 | K90: =SUMIF('Hiring plan'!$B$5:$B$32,"Leadership",K9:K36)+0 -> 0 | L90: =SUMIF('Hiring plan'!$B$5:$B$32,"Leadership",L9:L36)+0 -> 0 | ... BL90: =SUMIF('Hiring plan'!$B$5:$B$32,"Leadership",BL9:BL36)+0 -> 2
A91: Headcount: Engineering & product | B91: people | D91: =BL91 -> 7 | E91: =SUMIF('Hiring plan'!$B$5:$B$32,"Engineering & product",E9:E36)+E70 -> 3 | F91: =SUMIF('Hiring plan'!$B$5:$B$32,"Engineering & product",F9:F36)+F70 -> 3 | G91: =SUMIF('Hiring plan'!$B$5:$B$32,"Engineering & product",G9:G36)+G70 -> 3 | H91: =SUMIF('Hiring plan'!$B$5:$B$32,"Engineering & product",H9:H36)+H70 -> 3 | I91: =SUMIF('Hiring plan'!$B$5:$B$32,"Engineering & product",I9:I36)+I70 -> 3 | J91: =SUMIF('Hiring plan'!$B$5:$B$32,"Engineering & product",J9:J36)+J70 -> 3 | K91: =SUMIF('Hiring plan'!$B$5:$B$32,"Engineering & product",K9:K36)+K70 -> 3 | L91: =SUMIF('Hiring plan'!$B$5:$B$32,"Engineering & product",L9:L36)+L70 -> 3 | ... BL91: =SUMIF('Hiring plan'!$B$5:$B$32,"Engineering & product",BL9:BL36)+BL70 -> 7
A92: Headcount: Compliance & risk | B92: people | D92: =BL92 -> 1 | E92: =SUMIF('Hiring plan'!$B$5:$B$32,"Compliance & risk",E9:E36)+0 -> 0 | F92: =SUMIF('Hiring plan'!$B$5:$B$32,"Compliance & risk",F9:F36)+0 -> 0 | G92: =SUMIF('Hiring plan'!$B$5:$B$32,"Compliance & risk",G9:G36)+0 -> 0 | H92: =SUMIF('Hiring plan'!$B$5:$B$32,"Compliance & risk",H9:H36)+0 -> 0 | I92: =SUMIF('Hiring plan'!$B$5:$B$32,"Compliance & risk",I9:I36)+0 -> 0 | J92: =SUMIF('Hiring plan'!$B$5:$B$32,"Compliance & risk",J9:J36)+0 -> 0 | K92: =SUMIF('Hiring plan'!$B$5:$B$32,"Compliance & risk",K9:K36)+0 -> 0 | L92: =SUMIF('Hiring plan'!$B$5:$B$32,"Compliance & risk",L9:L36)+0 -> 0 | ... BL92: =SUMIF('Hiring plan'!$B$5:$B$32,"Compliance & risk",BL9:BL36)+0 -> 1
A93: Headcount: Credit | B93: people | D93: =BL93 -> 8 | E93: =SUMIF('Hiring plan'!$B$5:$B$32,"Credit",E9:E36)+E73 -> 0 | F93: =SUMIF('Hiring plan'!$B$5:$B$32,"Credit",F9:F36)+F73 -> 0 | G93: =SUMIF('Hiring plan'!$B$5:$B$32,"Credit",G9:G36)+G73 -> 0 | H93: =SUMIF('Hiring plan'!$B$5:$B$32,"Credit",H9:H36)+H73 -> 0 | I93: =SUMIF('Hiring plan'!$B$5:$B$32,"Credit",I9:I36)+I73 -> 0 | J93: =SUMIF('Hiring plan'!$B$5:$B$32,"Credit",J9:J36)+J73 -> 0 | K93: =SUMIF('Hiring plan'!$B$5:$B$32,"Credit",K9:K36)+K73 -> 0 | L93: =SUMIF('Hiring plan'!$B$5:$B$32,"Credit",L9:L36)+L73 -> 0 | ... BL93: =SUMIF('Hiring plan'!$B$5:$B$32,"Credit",BL9:BL36)+BL73 -> 8
A94: Headcount: Operations & support | B94: people | D94: =BL94 -> 29 | E94: =SUMIF('Hiring plan'!$B$5:$B$32,"Operations & support",E9:E36)+E69 -> 0 | F94: =SUMIF('Hiring plan'!$B$5:$B$32,"Operations & support",F9:F36)+F69 -> 0 | G94: =SUMIF('Hiring plan'!$B$5:$B$32,"Operations & support",G9:G36)+G69 -> 0 | H94: =SUMIF('Hiring plan'!$B$5:$B$32,"Operations & support",H9:H36)+H69 -> 2 | I94: =SUMIF('Hiring plan'!$B$5:$B$32,"Operations & support",I9:I36)+I69 -> 2 | J94: =SUMIF('Hiring plan'!$B$5:$B$32,"Operations & support",J9:J36)+J69 -> 2 | K94: =SUMIF('Hiring plan'!$B$5:$B$32,"Operations & support",K9:K36)+K69 -> 2 | L94: =SUMIF('Hiring plan'!$B$5:$B$32,"Operations & support",L9:L36)+L69 -> 2 | ... BL94: =SUMIF('Hiring plan'!$B$5:$B$32,"Operations & support",BL9:BL36)+BL69 -> 29
A95: Headcount: Sales & partnerships | B95: people | D95: =BL95 -> 25 | E95: =SUMIF('Hiring plan'!$B$5:$B$32,"Sales & partnerships",E9:E36)+E71+E72 -> 1 | F95: =SUMIF('Hiring plan'!$B$5:$B$32,"Sales & partnerships",F9:F36)+F71+F72 -> 1 | G95: =SUMIF('Hiring plan'!$B$5:$B$32,"Sales & partnerships",G9:G36)+G71+G72 -> 1 | H95: =SUMIF('Hiring plan'!$B$5:$B$32,"Sales & partnerships",H9:H36)+H71+H72 -> 3 | I95: =SUMIF('Hiring plan'!$B$5:$B$32,"Sales & partnerships",I9:I36)+I71+I72 -> 3 | J95: =SUMIF('Hiring plan'!$B$5:$B$32,"Sales & partnerships",J9:J36)+J71+J72 -> 3 | K95: =SUMIF('Hiring plan'!$B$5:$B$32,"Sales & partnerships",K9:K36)+K71+K72 -> 3 | L95: =SUMIF('Hiring plan'!$B$5:$B$32,"Sales & partnerships",L9:L36)+L71+L72 -> 3 | ... BL95: =SUMIF('Hiring plan'!$B$5:$B$32,"Sales & partnerships",BL9:BL36)+BL71+BL72 -> 25
A96: Headcount: Marketing | B96: people | D96: =BL96 -> 2 | E96: =SUMIF('Hiring plan'!$B$5:$B$32,"Marketing",E9:E36)+0 -> 0 | F96: =SUMIF('Hiring plan'!$B$5:$B$32,"Marketing",F9:F36)+0 -> 0 | G96: =SUMIF('Hiring plan'!$B$5:$B$32,"Marketing",G9:G36)+0 -> 0 | H96: =SUMIF('Hiring plan'!$B$5:$B$32,"Marketing",H9:H36)+0 -> 1 | I96: =SUMIF('Hiring plan'!$B$5:$B$32,"Marketing",I9:I36)+0 -> 2 | J96: =SUMIF('Hiring plan'!$B$5:$B$32,"Marketing",J9:J36)+0 -> 2 | K96: =SUMIF('Hiring plan'!$B$5:$B$32,"Marketing",K9:K36)+0 -> 2 | L96: =SUMIF('Hiring plan'!$B$5:$B$32,"Marketing",L9:L36)+0 -> 2 | ... BL96: =SUMIF('Hiring plan'!$B$5:$B$32,"Marketing",BL9:BL36)+0 -> 2
A97: Headcount: Finance & admin | B97: people | D97: =BL97 -> 1 | E97: =SUMIF('Hiring plan'!$B$5:$B$32,"Finance & admin",E9:E36)+0 -> 1 | F97: =SUMIF('Hiring plan'!$B$5:$B$32,"Finance & admin",F9:F36)+0 -> 1 | G97: =SUMIF('Hiring plan'!$B$5:$B$32,"Finance & admin",G9:G36)+0 -> 1 | H97: =SUMIF('Hiring plan'!$B$5:$B$32,"Finance & admin",H9:H36)+0 -> 1 | I97: =SUMIF('Hiring plan'!$B$5:$B$32,"Finance & admin",I9:I36)+0 -> 1 | J97: =SUMIF('Hiring plan'!$B$5:$B$32,"Finance & admin",J9:J36)+0 -> 1 | K97: =SUMIF('Hiring plan'!$B$5:$B$32,"Finance & admin",K9:K36)+0 -> 1 | L97: =SUMIF('Hiring plan'!$B$5:$B$32,"Finance & admin",L9:L36)+0 -> 1 | ... BL97: =SUMIF('Hiring plan'!$B$5:$B$32,"Finance & admin",BL9:BL36)+0 -> 1
A98: Staff cost: Leadership | B98: FCFA | D98: =SUM(E98:BL98) -> 3.5506919e+08 | E98: =SUMIF('Hiring plan'!$B$5:$B$32,"Leadership",E39:E66)+0 -> 0 | F98: =SUMIF('Hiring plan'!$B$5:$B$32,"Leadership",F39:F66)+0 -> 0 | G98: =SUMIF('Hiring plan'!$B$5:$B$32,"Leadership",G39:G66)+0 -> 0 | H98: =SUMIF('Hiring plan'!$B$5:$B$32,"Leadership",H39:H66)+0 -> 0 | I98: =SUMIF('Hiring plan'!$B$5:$B$32,"Leadership",I39:I66)+0 -> 0 | J98: =SUMIF('Hiring plan'!$B$5:$B$32,"Leadership",J39:J66)+0 -> 0 | K98: =SUMIF('Hiring plan'!$B$5:$B$32,"Leadership",K39:K66)+0 -> 0 | L98: =SUMIF('Hiring plan'!$B$5:$B$32,"Leadership",L39:L66)+0 -> 0 | ... BL98: =SUMIF('Hiring plan'!$B$5:$B$32,"Leadership",BL39:BL66)+0 -> 8374838.1
A99: Staff cost: Engineering & product | B99: FCFA | D99: =SUM(E99:BL99) -> 5.5352593e+08 | E99: =SUMIF('Hiring plan'!$B$5:$B$32,"Engineering & product",E39:E66)+E75 -> 6370000 | F99: =SUMIF('Hiring plan'!$B$5:$B$32,"Engineering & product",F39:F66)+F75 -> 6370000 | G99: =SUMIF('Hiring plan'!$B$5:$B$32,"Engineering & product",G39:G66)+G75 -> 6370000 | H99: =SUMIF('Hiring plan'!$B$5:$B$32,"Engineering & product",H39:H66)+H75 -> 6370000 | I99: =SUMIF('Hiring plan'!$B$5:$B$32,"Engineering & product",I39:I66)+I75 -> 6370000 | J99: =SUMIF('Hiring plan'!$B$5:$B$32,"Engineering & product",J39:J66)+J75 -> 6370000 | K99: =SUMIF('Hiring plan'!$B$5:$B$32,"Engineering & product",K39:K66)+K75 -> 6370000 | L99: =SUMIF('Hiring plan'!$B$5:$B$32,"Engineering & product",L39:L66)+L75 -> 6370000 | ... BL99: =SUMIF('Hiring plan'!$B$5:$B$32,"Engineering & product",BL39:BL66)+BL75 -> 15327534
A100: Staff cost: Compliance & risk | B100: FCFA | D100: =SUM(E100:BL100) -> 83377271 | E100: =SUMIF('Hiring plan'!$B$5:$B$32,"Compliance & risk",E39:E66)+0 -> 0 | F100: =SUMIF('Hiring plan'!$B$5:$B$32,"Compliance & risk",F39:F66)+0 -> 0 | G100: =SUMIF('Hiring plan'!$B$5:$B$32,"Compliance & risk",G39:G66)+0 -> 0 | H100: =SUMIF('Hiring plan'!$B$5:$B$32,"Compliance & risk",H39:H66)+0 -> 0 | I100: =SUMIF('Hiring plan'!$B$5:$B$32,"Compliance & risk",I39:I66)+0 -> 0 | J100: =SUMIF('Hiring plan'!$B$5:$B$32,"Compliance & risk",J39:J66)+0 -> 0 | K100: =SUMIF('Hiring plan'!$B$5:$B$32,"Compliance & risk",K39:K66)+0 -> 0 | L100: =SUMIF('Hiring plan'!$B$5:$B$32,"Compliance & risk",L39:L66)+0 -> 0 | ... BL100: =SUMIF('Hiring plan'!$B$5:$B$32,"Compliance & risk",BL39:BL66)+0 -> 2370237.2
A101: Staff cost: Credit | B101: FCFA | D101: =SUM(E101:BL101) -> 1.4909291e+08 | E101: =SUMIF('Hiring plan'!$B$5:$B$32,"Credit",E39:E66)+E78 -> 0 | F101: =SUMIF('Hiring plan'!$B$5:$B$32,"Credit",F39:F66)+F78 -> 0 | G101: =SUMIF('Hiring plan'!$B$5:$B$32,"Credit",G39:G66)+G78 -> 0 | H101: =SUMIF('Hiring plan'!$B$5:$B$32,"Credit",H39:H66)+H78 -> 0 | I101: =SUMIF('Hiring plan'!$B$5:$B$32,"Credit",I39:I66)+I78 -> 0 | J101: =SUMIF('Hiring plan'!$B$5:$B$32,"Credit",J39:J66)+J78 -> 0 | K101: =SUMIF('Hiring plan'!$B$5:$B$32,"Credit",K39:K66)+K78 -> 0 | L101: =SUMIF('Hiring plan'!$B$5:$B$32,"Credit",L39:L66)+L78 -> 0 | ... BL101: =SUMIF('Hiring plan'!$B$5:$B$32,"Credit",BL39:BL66)+BL78 -> 7584759
A102: Staff cost: Operations & support | B102: FCFA | D102: =SUM(E102:BL102) -> 2.5080197e+08 | E102: =SUMIF('Hiring plan'!$B$5:$B$32,"Operations & support",E39:E66)+E74 -> 0 | F102: =SUMIF('Hiring plan'!$B$5:$B$32,"Operations & support",F39:F66)+F74 -> 0 | G102: =SUMIF('Hiring plan'!$B$5:$B$32,"Operations & support",G39:G66)+G74 -> 0 | H102: =SUMIF('Hiring plan'!$B$5:$B$32,"Operations & support",H39:H66)+H74 -> 728000 | I102: =SUMIF('Hiring plan'!$B$5:$B$32,"Operations & support",I39:I66)+I74 -> 728000 | J102: =SUMIF('Hiring plan'!$B$5:$B$32,"Operations & support",J39:J66)+J74 -> 728000 | K102: =SUMIF('Hiring plan'!$B$5:$B$32,"Operations & support",K39:K66)+K74 -> 728000 | L102: =SUMIF('Hiring plan'!$B$5:$B$32,"Operations & support",L39:L66)+L74 -> 728000 | ... BL102: =SUMIF('Hiring plan'!$B$5:$B$32,"Operations & support",BL39:BL66)+BL74 -> 12830884
A103: Staff cost: Sales & partnerships | B103: FCFA | D103: =SUM(E103:BL103) -> 4.3411654e+08 | E103: =SUMIF('Hiring plan'!$B$5:$B$32,"Sales & partnerships",E39:E66)+E76+E77 -> 1560000 | F103: =SUMIF('Hiring plan'!$B$5:$B$32,"Sales & partnerships",F39:F66)+F76+F77 -> 1560000 | G103: =SUMIF('Hiring plan'!$B$5:$B$32,"Sales & partnerships",G39:G66)+G76+G77 -> 1560000 | H103: =SUMIF('Hiring plan'!$B$5:$B$32,"Sales & partnerships",H39:H66)+H76+H77 -> 2600000 | I103: =SUMIF('Hiring plan'!$B$5:$B$32,"Sales & partnerships",I39:I66)+I76+I77 -> 2600000 | J103: =SUMIF('Hiring plan'!$B$5:$B$32,"Sales & partnerships",J39:J66)+J76+J77 -> 2600000 | K103: =SUMIF('Hiring plan'!$B$5:$B$32,"Sales & partnerships",K39:K66)+K76+K77 -> 2600000 | L103: =SUMIF('Hiring plan'!$B$5:$B$32,"Sales & partnerships",L39:L66)+L76+L77 -> 2600000 | ... BL103: =SUMIF('Hiring plan'!$B$5:$B$32,"Sales & partnerships",BL39:BL66)+BL76+BL77 -> 17697771
A104: Staff cost: Marketing | B104: FCFA | D104: =SUM(E104:BL104) -> 1.064698e+08 | E104: =SUMIF('Hiring plan'!$B$5:$B$32,"Marketing",E39:E66)+0 -> 0 | F104: =SUMIF('Hiring plan'!$B$5:$B$32,"Marketing",F39:F66)+0 -> 0 | G104: =SUMIF('Hiring plan'!$B$5:$B$32,"Marketing",G39:G66)+0 -> 0 | H104: =SUMIF('Hiring plan'!$B$5:$B$32,"Marketing",H39:H66)+0 -> 1170000 | I104: =SUMIF('Hiring plan'!$B$5:$B$32,"Marketing",I39:I66)+0 -> 1690000 | J104: =SUMIF('Hiring plan'!$B$5:$B$32,"Marketing",J39:J66)+0 -> 1690000 | K104: =SUMIF('Hiring plan'!$B$5:$B$32,"Marketing",K39:K66)+0 -> 1690000 | L104: =SUMIF('Hiring plan'!$B$5:$B$32,"Marketing",L39:L66)+0 -> 1690000 | ... BL104: =SUMIF('Hiring plan'!$B$5:$B$32,"Marketing",BL39:BL66)+0 -> 2054205.6
A105: Staff cost: Finance & admin | B105: FCFA | D105: =SUM(E105:BL105) -> 1.2929977e+08 | E105: =SUMIF('Hiring plan'!$B$5:$B$32,"Finance & admin",E39:E66)+0 -> 1950000 | F105: =SUMIF('Hiring plan'!$B$5:$B$32,"Finance & admin",F39:F66)+0 -> 1950000 | G105: =SUMIF('Hiring plan'!$B$5:$B$32,"Finance & admin",G39:G66)+0 -> 1950000 | H105: =SUMIF('Hiring plan'!$B$5:$B$32,"Finance & admin",H39:H66)+0 -> 1950000 | I105: =SUMIF('Hiring plan'!$B$5:$B$32,"Finance & admin",I39:I66)+0 -> 1950000 | J105: =SUMIF('Hiring plan'!$B$5:$B$32,"Finance & admin",J39:J66)+0 -> 1950000 | K105: =SUMIF('Hiring plan'!$B$5:$B$32,"Finance & admin",K39:K66)+0 -> 1950000 | L105: =SUMIF('Hiring plan'!$B$5:$B$32,"Finance & admin",L39:L66)+0 -> 1950000 | ... BL105: =SUMIF('Hiring plan'!$B$5:$B$32,"Finance & admin",BL39:BL66)+0 -> 2370237.2
...

Sheet Staff (€)
A1: Staff (€)
A2: Every amount of the 'Staff' sheet in euros (FCFA ÷ FCFA per euro on Assumptions). Edit the FCFA sheets and Assumptions, not this one.
A3: Month # | D3: Total / end | E3: =Staff!E3 -> 1 | F3: =Staff!F3 -> 2 | G3: =Staff!G3 -> 3 | H3: =Staff!H3 -> 4 | I3: =Staff!I3 -> 5 | J3: =Staff!J3 -> 6 | K3: =Staff!K3 -> 7 | L3: =Staff!L3 -> 8 | ... BL3: =Staff!BL3 -> 60
A4: Month | E4: =Staff!E4 -> 46388 | F4: =Staff!F4 -> 46419 | G4: =Staff!G4 -> 46447 | H4: =Staff!H4 -> 46478 | I4: =Staff!I4 -> 46508 | J4: =Staff!J4 -> 46539 | K4: =Staff!K4 -> 46569 | L4: =Staff!L4 -> 46600 | ... BL4: =Staff!BL4 -> 48183
A5: Year | E5: =Staff!E5 -> 1 | F5: =Staff!F5 -> 1 | G5: =Staff!G5 -> 1 | H5: =Staff!H5 -> 1 | I5: =Staff!I5 -> 1 | J5: =Staff!J5 -> 1 | K5: =Staff!K5 -> 1 | L5: =Staff!L5 -> 1 | ... BL5: =Staff!BL5 -> 5
A8: Headcount by hire line
A10: Employer cost by hire line
A11: =Staff!A39 -> CEO (full salary from year 2) · SN | B11: € | D11: =Staff!D39/FX_EUR -> 269071.93 | E11: =Staff!E39/FX_EUR -> 0 | F11: =Staff!F39/FX_EUR -> 0 | G11: =Staff!G39/FX_EUR -> 0 | H11: =Staff!H39/FX_EUR -> 0 | I11: =Staff!I39/FX_EUR -> 0 | J11: =Staff!J39/FX_EUR -> 0 | K11: =Staff!K39/FX_EUR -> 0 | ... BL11: =Staff!BL39/FX_EUR -> 6022.3388
A12: =Staff!A40 -> CTO (also codes) · SN | B12: € | D12: =Staff!D40/FX_EUR -> 328527.05 | E12: =Staff!E40/FX_EUR -> 4954.5931 | F12: =Staff!F40/FX_EUR -> 4954.5931 | G12: =Staff!G40/FX_EUR -> 4954.5931 | H12: =Staff!H40/FX_EUR -> 4954.5931 | I12: =Staff!I40/FX_EUR -> 4954.5931 | J12: =Staff!J40/FX_EUR -> 4954.5931 | K12: =Staff!K40/FX_EUR -> 4954.5931 | ... BL12: =Staff!BL40/FX_EUR -> 6022.3388
A13: =Staff!A41 -> Financial expert (finance, partners, credit lead) · SN | B13: € | D13: =Staff!D41/FX_EUR -> 197116.23 | E13: =Staff!E41/FX_EUR -> 2972.7558 | F13: =Staff!F41/FX_EUR -> 2972.7558 | G13: =Staff!G41/FX_EUR -> 2972.7558 | H13: =Staff!H41/FX_EUR -> 2972.7558 | I13: =Staff!I41/FX_EUR -> 2972.7558 | J13: =Staff!J41/FX_EUR -> 2972.7558 | K13: =Staff!K41/FX_EUR -> 2972.7558 | ... BL13: =Staff!BL41/FX_EUR -> 3613.4033
A14: =Staff!A42 -> Sales lead (also sells; incl. bonus) · SN | B14: € | D14: =Staff!D42/FX_EUR -> 157692.98 | E14: =Staff!E42/FX_EUR -> 2378.2047 | F14: =Staff!F42/FX_EUR -> 2378.2047 | G14: =Staff!G42/FX_EUR -> 2378.2047 | H14: =Staff!H42/FX_EUR -> 2378.2047 | I14: =Staff!I42/FX_EUR -> 2378.2047 | J14: =Staff!J42/FX_EUR -> 2378.2047 | K14: =Staff!K42/FX_EUR -> 2378.2047 | ... BL14: =Staff!BL42/FX_EUR -> 2890.7226
A15: =Staff!A43 -> Marketing manager (senior) · SN | B15: € | D15: =Staff!D43/FX_EUR -> 112918.78 | E15: =Staff!E43/FX_EUR -> 0 | F15: =Staff!F43/FX_EUR -> 0 | G15: =Staff!G43/FX_EUR -> 0 | H15: =Staff!H43/FX_EUR -> 1783.6535 | I15: =Staff!I43/FX_EUR -> 1783.6535 | J15: =Staff!J43/FX_EUR -> 1783.6535 | K15: =Staff!K43/FX_EUR -> 1783.6535 | ... BL15: =Staff!BL43/FX_EUR -> 2168.042
A16: =Staff!A44 -> Marketing officer (junior) · SN | B16: € | D16: =Staff!D44/FX_EUR -> 49393.389 | E16: =Staff!E44/FX_EUR -> 0 | F16: =Staff!F44/FX_EUR -> 0 | G16: =Staff!G44/FX_EUR -> 0 | H16: =Staff!H44/FX_EUR -> 0 | I16: =Staff!I44/FX_EUR -> 792.73489 | J16: =Staff!J44/FX_EUR -> 792.73489 | K16: =Staff!K44/FX_EUR -> 792.73489 | ... BL16: =Staff!BL44/FX_EUR -> 963.57421
A17: =Staff!A45 -> Country manager, Abidjan · CI | B17: € | D17: =Staff!D45/FX_EUR -> 272227.56 | E17: =Staff!E45/FX_EUR -> 0 | F17: =Staff!F45/FX_EUR -> 0 | G17: =Staff!G45/FX_EUR -> 0 | H17: =Staff!H45/FX_EUR -> 0 | I17: =Staff!I45/FX_EUR -> 0 | J17: =Staff!J45/FX_EUR -> 0 | K17: =Staff!K45/FX_EUR -> 0 | ... BL17: =Staff!BL45/FX_EUR -> 6745.0195
A18: =Staff!A46 -> Compliance officer (AML/CFT) · SN | B18: € | D18: =Staff!D46/FX_EUR -> 127107.83 | E18: =Staff!E46/FX_EUR -> 0 | F18: =Staff!F46/FX_EUR -> 0 | G18: =Staff!G46/FX_EUR -> 0 | H18: =Staff!H46/FX_EUR -> 0 | I18: =Staff!I46/FX_EUR -> 0 | J18: =Staff!J46/FX_EUR -> 0 | K18: =Staff!K46/FX_EUR -> 0 | ... BL18: =Staff!BL46/FX_EUR -> 3613.4033
A19: =Staff!A47 -> (spare line 9) | B19: € | D19: =Staff!D47/FX_EUR -> 0 | E19: =Staff!E47/FX_EUR -> 0 | F19: =Staff!F47/FX_EUR -> 0 | G19: =Staff!G47/FX_EUR -> 0 | H19: =Staff!H47/FX_EUR -> 0 | I19: =Staff!I47/FX_EUR -> 0 | J19: =Staff!J47/FX_EUR -> 0 | K19: =Staff!K47/FX_EUR -> 0 | ... BL19: =Staff!BL47/FX_EUR -> 0
A20: =Staff!A48 -> (spare line 10) | B20: € | D20: =Staff!D48/FX_EUR -> 0 | E20: =Staff!E48/FX_EUR -> 0 | F20: =Staff!F48/FX_EUR -> 0 | G20: =Staff!G48/FX_EUR -> 0 | H20: =Staff!H48/FX_EUR -> 0 | I20: =Staff!I48/FX_EUR -> 0 | J20: =Staff!J48/FX_EUR -> 0 | K20: =Staff!K48/FX_EUR -> 0 | ... BL20: =Staff!BL48/FX_EUR -> 0
A21: =Staff!A49 -> (spare line 11) | B21: € | D21: =Staff!D49/FX_EUR -> 0 | E21: =Staff!E49/FX_EUR -> 0 | F21: =Staff!F49/FX_EUR -> 0 | G21: =Staff!G49/FX_EUR -> 0 | H21: =Staff!H49/FX_EUR -> 0 | I21: =Staff!I49/FX_EUR -> 0 | J21: =Staff!J49/FX_EUR -> 0 | K21: =Staff!K49/FX_EUR -> 0 | ... BL21: =Staff!BL49/FX_EUR -> 0
A22: =Staff!A50 -> (spare line 12) | B22: € | D22: =Staff!D50/FX_EUR -> 0 | E22: =Staff!E50/FX_EUR -> 0 | F22: =Staff!F50/FX_EUR -> 0 | G22: =Staff!G50/FX_EUR -> 0 | H22: =Staff!H50/FX_EUR -> 0 | I22: =Staff!I50/FX_EUR -> 0 | J22: =Staff!J50/FX_EUR -> 0 | K22: =Staff!K50/FX_EUR -> 0 | ... BL22: =Staff!BL50/FX_EUR -> 0
... A38: =Staff!A66 -> (spare line 28) | B38: € | D38: =Staff!D66/FX_EUR -> 0 | E38: =Staff!E66/FX_EUR -> 0 | F38: =Staff!F66/FX_EUR -> 0 | G38: =Staff!G66/FX_EUR -> 0 | H38: =Staff!H66/FX_EUR -> 0 | I38: =Staff!I66/FX_EUR -> 0 | J38: =Staff!J66/FX_EUR -> 0 | K38: =Staff!K66/FX_EUR -> 0 | ... BL38: =Staff!BL66/FX_EUR -> 0
A40: Team that grows with volume
A41: Employer cost: Customer support agents | B41: € | D41: =Staff!D74/FX_EUR -> 382345.14 | E41: =Staff!E74/FX_EUR -> 0 | F41: =Staff!F74/FX_EUR -> 0 | G41: =Staff!G74/FX_EUR -> 0 | H41: =Staff!H74/FX_EUR -> 1109.8288 | I41: =Staff!I74/FX_EUR -> 1109.8288 | J41: =Staff!J74/FX_EUR -> 1109.8288 | K41: =Staff!K74/FX_EUR -> 1109.8288 | ... BL41: =Staff!BL74/FX_EUR -> 19560.557
A42: Employer cost: Developers | B42: € | D42: =Staff!D75/FX_EUR -> 515317.79 | E42: =Staff!E75/FX_EUR -> 4756.4093 | F42: =Staff!F75/FX_EUR -> 4756.4093 | G42: =Staff!G75/FX_EUR -> 4756.4093 | H42: =Staff!H75/FX_EUR -> 4756.4093 | I42: =Staff!I75/FX_EUR -> 4756.4093 | J42: =Staff!J75/FX_EUR -> 4756.4093 | K42: =Staff!K75/FX_EUR -> 4756.4093 | ... BL42: =Staff!BL75/FX_EUR -> 17344.336
A43: Employer cost: Field sales reps, Senegal | B43: € | D43: =Staff!D76/FX_EUR -> 340727.78 | E43: =Staff!E76/FX_EUR -> 0 | F43: =Staff!F76/FX_EUR -> 0 | G43: =Staff!G76/FX_EUR -> 0 | H43: =Staff!H76/FX_EUR -> 1585.4698 | I43: =Staff!I76/FX_EUR -> 1585.4698 | J43: =Staff!J76/FX_EUR -> 1585.4698 | K43: =Staff!K76/FX_EUR -> 1585.4698 | ... BL43: =Staff!BL76/FX_EUR -> 15417.187
A44: Employer cost: Field sales reps, Côte d'Ivoire | B44: € | D44: =Staff!D77/FX_EUR -> 163385.64 | E44: =Staff!E77/FX_EUR -> 0 | F44: =Staff!F77/FX_EUR -> 0 | G44: =Staff!G77/FX_EUR -> 0 | H44: =Staff!H77/FX_EUR -> 0 | I44: =Staff!I77/FX_EUR -> 0 | J44: =Staff!J77/FX_EUR -> 0 | K44: =Staff!K77/FX_EUR -> 0 | ... BL44: =Staff!BL77/FX_EUR -> 8672.1679
A45: Employer cost: Credit analysts and collections | B45: € | D45: =Staff!D78/FX_EUR -> 227290.68 | E45: =Staff!E78/FX_EUR -> 0 | F45: =Staff!F78/FX_EUR -> 0 | G45: =Staff!G78/FX_EUR -> 0 | H45: =Staff!H78/FX_EUR -> 0 | I45: =Staff!I78/FX_EUR -> 0 | J45: =Staff!J78/FX_EUR -> 0 | K45: =Staff!K78/FX_EUR -> 0 | ... BL45: =Staff!BL78/FX_EUR -> 11562.891
A47: Summary
A48: Staff cost: Leadership | B48: € | D48: =Staff!D98/FX_EUR -> 541299.49 | E48: =Staff!E98/FX_EUR -> 0 | F48: =Staff!F98/FX_EUR -> 0 | G48: =Staff!G98/FX_EUR -> 0 | H48: =Staff!H98/FX_EUR -> 0 | I48: =Staff!I98/FX_EUR -> 0 | J48: =Staff!J98/FX_EUR -> 0 | K48: =Staff!K98/FX_EUR -> 0 | ... BL48: =Staff!BL98/FX_EUR -> 12767.358
A49: Staff cost: Engineering & product | B49: € | D49: =Staff!D99/FX_EUR -> 843844.84 | E49: =Staff!E99/FX_EUR -> 9711.0024 | F49: =Staff!F99/FX_EUR -> 9711.0024 | G49: =Staff!G99/FX_EUR -> 9711.0024 | H49: =Staff!H99/FX_EUR -> 9711.0024 | I49: =Staff!I99/FX_EUR -> 9711.0024 | J49: =Staff!J99/FX_EUR -> 9711.0024 | K49: =Staff!K99/FX_EUR -> 9711.0024 | ... BL49: =Staff!BL99/FX_EUR -> 23366.675
A50: Staff cost: Compliance & risk | B50: € | D50: =Staff!D100/FX_EUR -> 127107.83 | E50: =Staff!E100/FX_EUR -> 0 | F50: =Staff!F100/FX_EUR -> 0 | G50: =Staff!G100/FX_EUR -> 0 | H50: =Staff!H100/FX_EUR -> 0 | I50: =Staff!I100/FX_EUR -> 0 | J50: =Staff!J100/FX_EUR -> 0 | K50: =Staff!K100/FX_EUR -> 0 | ... BL50: =Staff!BL100/FX_EUR -> 3613.4033
A51: Staff cost: Credit | B51: € | D51: =Staff!D101/FX_EUR -> 227290.68 | E51: =Staff!E101/FX_EUR -> 0 | F51: =Staff!F101/FX_EUR -> 0 | G51: =Staff!G101/FX_EUR -> 0 | H51: =Staff!H101/FX_EUR -> 0 | I51: =Staff!I101/FX_EUR -> 0 | J51: =Staff!J101/FX_EUR -> 0 | K51: =Staff!K101/FX_EUR -> 0 | ... BL51: =Staff!BL101/FX_EUR -> 11562.891
A52: Staff cost: Operations & support | B52: € | D52: =Staff!D102/FX_EUR -> 382345.14 | E52: =Staff!E102/FX_EUR -> 0 | F52: =Staff!F102/FX_EUR -> 0 | G52: =Staff!G102/FX_EUR -> 0 | H52: =Staff!H102/FX_EUR -> 1109.8288 | I52: =Staff!I102/FX_EUR -> 1109.8288 | J52: =Staff!J102/FX_EUR -> 1109.8288 | K52: =Staff!K102/FX_EUR -> 1109.8288 | ... BL52: =Staff!BL102/FX_EUR -> 19560.557
A53: Staff cost: Sales & partnerships | B53: € | D53: =Staff!D103/FX_EUR -> 661806.4 | E53: =Staff!E103/FX_EUR -> 2378.2047 | F53: =Staff!F103/FX_EUR -> 2378.2047 | G53: =Staff!G103/FX_EUR -> 2378.2047 | H53: =Staff!H103/FX_EUR -> 3963.6744 | I53: =Staff!I103/FX_EUR -> 3963.6744 | J53: =Staff!J103/FX_EUR -> 3963.6744 | K53: =Staff!K103/FX_EUR -> 3963.6744 | ... BL53: =Staff!BL103/FX_EUR -> 26980.078
A54: Staff cost: Marketing | B54: € | D54: =Staff!D104/FX_EUR -> 162312.17 | E54: =Staff!E104/FX_EUR -> 0 | F54: =Staff!F104/FX_EUR -> 0 | G54: =Staff!G104/FX_EUR -> 0 | H54: =Staff!H104/FX_EUR -> 1783.6535 | I54: =Staff!I104/FX_EUR -> 2576.3884 | J54: =Staff!J104/FX_EUR -> 2576.3884 | K54: =Staff!K104/FX_EUR -> 2576.3884 | ... BL54: =Staff!BL104/FX_EUR -> 3131.6162
A55: Staff cost: Finance & admin | B55: € | D55: =Staff!D105/FX_EUR -> 197116.23 | E55: =Staff!E105/FX_EUR -> 2972.7558 | F55: =Staff!F105/FX_EUR -> 2972.7558 | G55: =Staff!G105/FX_EUR -> 2972.7558 | H55: =Staff!H105/FX_EUR -> 2972.7558 | I55: =Staff!I105/FX_EUR -> 2972.7558 | J55: =Staff!J105/FX_EUR -> 2972.7558 | K55: =Staff!K105/FX_EUR -> 2972.7558 | ... BL55: =Staff!BL105/FX_EUR -> 3613.4033
A56: Total staff cost | B56: € | D56: =Staff!D106/FX_EUR -> 3143122.8 | E56: =Staff!E106/FX_EUR -> 15061.963 | F56: =Staff!F106/FX_EUR -> 15061.963 | G56: =Staff!G106/FX_EUR -> 15061.963 | H56: =Staff!H106/FX_EUR -> 19540.915 | I56: =Staff!I106/FX_EUR -> 20333.65 | J56: =Staff!J106/FX_EUR -> 20333.65 | K56: =Staff!K106/FX_EUR -> 20333.65 | ... BL56: =Staff!BL106/FX_EUR -> 104595.98

Sheet Sales & marketing
A1: Sales & marketing
A2: Client acquisition by channel and country, and the non-staff sales and marketing budget.
A3: Month # | D3: Total / end | E3: 1 | F3: =E3+1 -> 2 | G3: =F3+1 -> 3 | H3: =G3+1 -> 4 | I3: =H3+1 -> 5 | J3: =I3+1 -> 6 | K3: =J3+1 -> 7 | L3: =K3+1 -> 8 | M3: =L3+1 -> 9 | ... BL3: =BK3+1 -> 60
A4: Month | E4: =DATE(YEAR(Start_Date),MONTH(Start_Date)+E3-1,1) -> 46388 | F4: =DATE(YEAR(Start_Date),MONTH(Start_Date)+F3-1,1) -> 46419 | G4: =DATE(YEAR(Start_Date),MONTH(Start_Date)+G3-1,1) -> 46447 | H4: =DATE(YEAR(Start_Date),MONTH(Start_Date)+H3-1,1) -> 46478 | I4: =DATE(YEAR(Start_Date),MONTH(Start_Date)+I3-1,1) -> 46508 | J4: =DATE(YEAR(Start_Date),MONTH(Start_Date)+J3-1,1) -> 46539 | K4: =DATE(YEAR(Start_Date),MONTH(Start_Date)+K3-1,1) -> 46569 | L4: =DATE(YEAR(Start_Date),MONTH(Start_Date)+L3-1,1) -> 46600 | ... BL4: =DATE(YEAR(Start_Date),MONTH(Start_Date)+BL3-1,1) -> 48183
A5: Year | E5: =INT((E3-1)/12)+1 -> 1 | F5: =INT((F3-1)/12)+1 -> 1 | G5: =INT((G3-1)/12)+1 -> 1 | H5: =INT((H3-1)/12)+1 -> 1 | I5: =INT((I3-1)/12)+1 -> 1 | J5: =INT((J3-1)/12)+1 -> 1 | K5: =INT((K3-1)/12)+1 -> 1 | L5: =INT((L3-1)/12)+1 -> 1 | ... BL5: =INT((BL3-1)/12)+1 -> 5
A8: Markets open
A9: Senegal open (1 = yes) | B9: flag | E9: =IF(E$3>=Launch_SN,1,0) -> 0 | F9: =IF(F$3>=Launch_SN,1,0) -> 0 | G9: =IF(G$3>=Launch_SN,1,0) -> 0 | H9: =IF(H$3>=Launch_SN,1,0) -> 0 | I9: =IF(I$3>=Launch_SN,1,0) -> 1 | J9: =IF(J$3>=Launch_SN,1,0) -> 1 | K9: =IF(K$3>=Launch_SN,1,0) -> 1 | L9: =IF(L$3>=Launch_SN,1,0) -> 1 | ... BL9: =IF(BL$3>=Launch_SN,1,0) -> 1
A10: Côte d'Ivoire open (1 = yes) | B10: flag | E10: =IF(E$3>=Launch_CI,1,0) -> 0 | F10: =IF(F$3>=Launch_CI,1,0) -> 0 | G10: =IF(G$3>=Launch_CI,1,0) -> 0 | H10: =IF(H$3>=Launch_CI,1,0) -> 0 | I10: =IF(I$3>=Launch_CI,1,0) -> 0 | J10: =IF(J$3>=Launch_CI,1,0) -> 0 | K10: =IF(K$3>=Launch_CI,1,0) -> 0 | L10: =IF(L$3>=Launch_CI,1,0) -> 0 | ... BL10: =IF(BL$3>=Launch_CI,1,0) -> 1
A12: Field sales
A13: Field sales reps, Senegal | B13: people | D13: =BL13 -> 17 | E13: =Staff!E86 -> 1 | F13: =Staff!F86 -> 1 | G13: =Staff!G86 -> 1 | H13: =Staff!H86 -> 3 | I13: =Staff!I86 -> 3 | J13: =Staff!J86 -> 3 | K13: =Staff!K86 -> 3 | L13: =Staff!L86 -> 3 | ... BL13: =Staff!BL86 -> 17
A14: Field sales reps, Côte d'Ivoire | B14: people | D14: =BL14 -> 8 | E14: =Staff!E87 -> 0 | F14: =Staff!F87 -> 0 | G14: =Staff!G87 -> 0 | H14: =Staff!H87 -> 0 | I14: =Staff!I87 -> 0 | J14: =Staff!J87 -> 0 | K14: =Staff!K87 -> 0 | L14: =Staff!L87 -> 0 | ... BL14: =Staff!BL87 -> 8
A15: Productive reps, Senegal (hired before this month) | B15: people | E15: =0 -> 0 | F15: =E13*F9 -> 0 | G15: =F13*G9 -> 0 | H15: =G13*H9 -> 0 | I15: =H13*I9 -> 3 | J15: =I13*J9 -> 3 | K15: =J13*K9 -> 3 | L15: =K13*L9 -> 3 | M15: =L13*M9 -> 3 | ... BL15: =BK13*BL9 -> 17
A16: Productive reps, Côte d'Ivoire | B16: people | E16: =0 -> 0 | F16: =E14*F10 -> 0 | G16: =F14*G10 -> 0 | H16: =G14*H10 -> 0 | I16: =H14*I10 -> 0 | J16: =I14*J10 -> 0 | K16: =J14*K10 -> 0 | L16: =K14*L10 -> 0 | M16: =L14*M10 -> 0 | ... BL16: =BK14*BL10 -> 7
A17: New clients from field sales, Senegal | B17: clients | D17: =SUM(E17:BL17) -> 3288 | E17: =E15*Rep_Productivity -> 0 | F17: =F15*Rep_Productivity -> 0 | G17: =G15*Rep_Productivity -> 0 | H17: =H15*Rep_Productivity -> 0 | I17: =I15*Rep_Productivity -> 24 | J17: =J15*Rep_Productivity -> 24 | K17: =K15*Rep_Productivity -> 24 | L17: =L15*Rep_Productivity -> 24 | ... BL17: =BL15*Rep_Productivity -> 136
A18: New clients from field sales, Côte d'Ivoire | B18: clients | D18: =SUM(E18:BL18) -> 1072.8 | E18: =E16*Rep_Productivity*CI_Productivity -> 0 | F18: =F16*Rep_Productivity*CI_Productivity -> 0 | G18: =G16*Rep_Productivity*CI_Productivity -> 0 | H18: =H16*Rep_Productivity*CI_Productivity -> 0 | I18: =I16*Rep_Productivity*CI_Productivity -> 0 | J18: =J16*Rep_Productivity*CI_Productivity -> 0 | K18: =K16*Rep_Productivity*CI_Productivity -> 0 | L18: =L16*Rep_Productivity*CI_Productivity -> 0 | ... BL18: =BL16*Rep_Productivity*CI_Productivity -> 50.4
A20: Partner channel (accountants, payroll software, chambers of commerce)
A21: New clients from partners, Senegal | B21: clients | D21: =SUM(E21:BL21) -> 2518.0957 | E21: =E9*MIN(Partner_Cap_SN,Partner_Base_SN*(1+Partner_Growth)^MAX(0,E$3-Launch_SN)) -> 0 | F21: =F9*MIN(Partner_Cap_SN,Partner_Base_SN*(1+Partner_Growth)^MAX(0,F$3-Launch_SN)) -> 0 | G21: =G9*MIN(Partner_Cap_SN,Partner_Base_SN*(1+Partner_Growth)^MAX(0,G$3-Launch_SN)) -> 0 | H21: =H9*MIN(Partner_Cap_SN,Partner_Base_SN*(1+Partner_Growth)^MAX(0,H$3-Launch_SN)) -> 0 | I21: =I9*MIN(Partner_Cap_SN,Partner_Base_SN*(1+Partner_Growth)^MAX(0,I$3-Launch_SN)) -> 8 | J21: =J9*MIN(Partner_Cap_SN,Partner_Base_SN*(1+Partner_Growth)^MAX(0,J$3-Launch_SN)) -> 8.48 | K21: =K9*MIN(Partner_Cap_SN,Partner_Base_SN*(1+Partner_Growth)^MAX(0,K$3-Launch_SN)) -> 8.9888 | L21: =L9*MIN(Partner_Cap_SN,Partner_Base_SN*(1+Partner_Growth)^MAX(0,L$3-Launch_SN)) -> 9.528128 | ... BL21: =BL9*MIN(Partner_Cap_SN,Partner_Base_SN*(1+Partner_Growth)^MAX(0,BL$3-Launch_SN)) -> 80
A22: New clients from partners, Côte d'Ivoire | B22: clients | D22: =SUM(E22:BL22) -> 1048.5718 | E22: =E10*MIN(Partner_Cap_CI,Partner_Base_CI*(1+Partner_Growth)^MAX(0,E$3-Launch_CI)) -> 0 | F22: =F10*MIN(Partner_Cap_CI,Partner_Base_CI*(1+Partner_Growth)^MAX(0,F$3-Launch_CI)) -> 0 | G22: =G10*MIN(Partner_Cap_CI,Partner_Base_CI*(1+Partner_Growth)^MAX(0,G$3-Launch_CI)) -> 0 | H22: =H10*MIN(Partner_Cap_CI,Partner_Base_CI*(1+Partner_Growth)^MAX(0,H$3-Launch_CI)) -> 0 | I22: =I10*MIN(Partner_Cap_CI,Partner_Base_CI*(1+Partner_Growth)^MAX(0,I$3-Launch_CI)) -> 0 | J22: =J10*MIN(Partner_Cap_CI,Partner_Base_CI*(1+Partner_Growth)^MAX(0,J$3-Launch_CI)) -> 0 | K22: =K10*MIN(Partner_Cap_CI,Partner_Base_CI*(1+Partner_Growth)^MAX(0,K$3-Launch_CI)) -> 0 | L22: =L10*MIN(Partner_Cap_CI,Partner_Base_CI*(1+Partner_Growth)^MAX(0,L$3-Launch_CI)) -> 0 | ... BL22: =BL10*MIN(Partner_Cap_CI,Partner_Base_CI*(1+Partner_Growth)^MAX(0,BL$3-Launch_CI)) -> 60
A24: Digital marketing
A25: Digital ads budget, Senegal | B25: FCFA | D25: =SUM(E25:BL25) -> 207280000 | E25: =E9*INDEX(Digital_SN,1,E$5) -> 0 | F25: =F9*INDEX(Digital_SN,1,F$5) -> 0 | G25: =G9*INDEX(Digital_SN,1,G$5) -> 0 | H25: =H9*INDEX(Digital_SN,1,H$5) -> 0 | I25: =I9*INDEX(Digital_SN,1,I$5) -> 1310000 | J25: =J9*INDEX(Digital_SN,1,J$5) -> 1310000 | K25: =K9*INDEX(Digital_SN,1,K$5) -> 1310000 | L25: =L9*INDEX(Digital_SN,1,L$5) -> 1310000 | ... BL25: =BL9*INDEX(Digital_SN,1,BL$5) -> 5250000
A26: Digital ads budget, Côte d'Ivoire | B26: FCFA | D26: =SUM(E26:BL26) -> 125940000 | E26: =E10*INDEX(Digital_CI,1,E$5) -> 0 | F26: =F10*INDEX(Digital_CI,1,F$5) -> 0 | G26: =G10*INDEX(Digital_CI,1,G$5) -> 0 | H26: =H10*INDEX(Digital_CI,1,H$5) -> 0 | I26: =I10*INDEX(Digital_CI,1,I$5) -> 0 | J26: =J10*INDEX(Digital_CI,1,J$5) -> 0 | K26: =K10*INDEX(Digital_CI,1,K$5) -> 0 | L26: =L10*INDEX(Digital_CI,1,L$5) -> 0 | ... BL26: =BL10*INDEX(Digital_CI,1,BL$5) -> 3940000
A27: New clients from digital, Senegal | B27: clients | D27: =SUM(E27:BL27) -> 2763.7333 | E27: =E25/CAC_Digital -> 0 | F27: =F25/CAC_Digital -> 0 | G27: =G25/CAC_Digital -> 0 | H27: =H25/CAC_Digital -> 0 | I27: =I25/CAC_Digital -> 17.466667 | J27: =J25/CAC_Digital -> 17.466667 | K27: =K25/CAC_Digital -> 17.466667 | L27: =L25/CAC_Digital -> 17.466667 | ... BL27: =BL25/CAC_Digital -> 70
A28: New clients from digital, Côte d'Ivoire | B28: clients | D28: =SUM(E28:BL28) -> 1679.2 | E28: =E26/CAC_Digital -> 0 | F28: =F26/CAC_Digital -> 0 | G28: =G26/CAC_Digital -> 0 | H28: =H26/CAC_Digital -> 0 | I28: =I26/CAC_Digital -> 0 | J28: =J26/CAC_Digital -> 0 | K28: =K26/CAC_Digital -> 0 | L28: =L26/CAC_Digital -> 0 | ... BL28: =BL26/CAC_Digital -> 52.533333
A30: New clients
A31: New clients, Senegal | B31: clients | D31: =SUM(E31:BL31) -> 8569.8291 | E31: =E17+E21+E27 -> 0 | F31: =F17+F21+F27 -> 0 | G31: =G17+G21+G27 -> 0 | H31: =H17+H21+H27 -> 0 | I31: =I17+I21+I27 -> 49.466667 | J31: =J17+J21+J27 -> 49.946667 | K31: =K17+K21+K27 -> 50.455467 | L31: =L17+L21+L27 -> 50.994795 | ... BL31: =BL17+BL21+BL27 -> 286
A32: New clients, Côte d'Ivoire | B32: clients | D32: =SUM(E32:BL32) -> 3800.5718 | E32: =E18+E22+E28 -> 0 | F32: =F18+F22+F28 -> 0 | G32: =G18+G22+G28 -> 0 | H32: =H18+H22+H28 -> 0 | I32: =I18+I22+I28 -> 0 | J32: =J18+J22+J28 -> 0 | K32: =K18+K22+K28 -> 0 | L32: =L18+L22+L28 -> 0 | ... BL32: =BL18+BL22+BL28 -> 162.93333
A33: New clients, total | B33: clients | D33: =SUM(E33:BL33) -> 12370.401 | E33: =E31+E32 -> 0 | F33: =F31+F32 -> 0 | G33: =G31+G32 -> 0 | H33: =H31+H32 -> 0 | I33: =I31+I32 -> 49.466667 | J33: =J31+J32 -> 49.946667 | K33: =K31+K32 -> 50.455467 | L33: =L31+L32 -> 50.994795 | ... BL33: =BL31+BL32 -> 448.93333
A34: of which Essentiel | B34: clients | D34: =SUM(E34:BL34) -> 7422.2405 | E34: =E33*Mix_Petite -> 0 | F34: =F33*Mix_Petite -> 0 | G34: =G33*Mix_Petite -> 0 | H34: =H33*Mix_Petite -> 0 | I34: =I33*Mix_Petite -> 29.68 | J34: =J33*Mix_Petite -> 29.968 | K34: =K33*Mix_Petite -> 30.27328 | L34: =L33*Mix_Petite -> 30.596877 | ... BL34: =BL33*Mix_Petite -> 269.36
A35: of which Pro | B35: clients | D35: =SUM(E35:BL35) -> 3711.1203 | E35: =E33*Mix_Moyenne -> 0 | F35: =F33*Mix_Moyenne -> 0 | G35: =G33*Mix_Moyenne -> 0 | H35: =H33*Mix_Moyenne -> 0 | I35: =I33*Mix_Moyenne -> 14.84 | J35: =J33*Mix_Moyenne -> 14.984 | K35: =K33*Mix_Moyenne -> 15.13664 | L35: =L33*Mix_Moyenne -> 15.298438 | ... BL35: =BL33*Mix_Moyenne -> 134.68
A36: of which Business | B36: clients | D36: =SUM(E36:BL36) -> 1237.0401 | E36: =E33*Mix_Grande -> 0 | F36: =F33*Mix_Grande -> 0 | G36: =G33*Mix_Grande -> 0 | H36: =H33*Mix_Grande -> 0 | I36: =I33*Mix_Grande -> 4.9466667 | J36: =J33*Mix_Grande -> 4.9946667 | K36: =K33*Mix_Grande -> 5.0455467 | L36: =L33*Mix_Grande -> 5.0994795 | ... BL36: =BL33*Mix_Grande -> 44.893333
A37: New clients from partners (for referral fees) | B37: clients | D37: =SUM(E37:BL37) -> 3566.6675 | E37: =E21+E22 -> 0 | F37: =F21+F22 -> 0 | G37: =G21+G22 -> 0 | H37: =H21+H22 -> 0 | I37: =I21+I22 -> 8 | J37: =J21+J22 -> 8.48 | K37: =K21+K22 -> 8.9888 | L37: =L21+L22 -> 9.528128 | ... BL37: =BL21+BL22 -> 140
A39: Sales and marketing budget (non-staff)
A40: Digital ads | B40: FCFA | D40: =SUM(E40:BL40) -> 333220000 | E40: =E25+E26 -> 0 | F40: =F25+F26 -> 0 | G40: =G25+G26 -> 0 | H40: =H25+H26 -> 0 | I40: =I25+I26 -> 1310000 | J40: =J25+J26 -> 1310000 | K40: =K25+K26 -> 1310000 | L40: =L25+L26 -> 1310000 | ... BL40: =BL25+BL26 -> 9190000
A41: Brand, launch events, PR | B41: FCFA | D41: =SUM(E41:BL41) -> 41330000 | E41: =INDEX(Brand_PR,1,E$5)/12 -> 1366666.7 | F41: =INDEX(Brand_PR,1,F$5)/12 -> 1366666.7 | G41: =INDEX(Brand_PR,1,G$5)/12 -> 1366666.7 | H41: =INDEX(Brand_PR,1,H$5)/12 -> 1366666.7 | I41: =INDEX(Brand_PR,1,I$5)/12 -> 1366666.7 | J41: =INDEX(Brand_PR,1,J$5)/12 -> 1366666.7 | K41: =INDEX(Brand_PR,1,K$5)/12 -> 1366666.7 | L41: =INDEX(Brand_PR,1,L$5)/12 -> 1366666.7 | ... BL41: =INDEX(Brand_PR,1,BL$5)/12 -> 546666.67
A42: Events, sponsorships, sales materials | B42: FCFA | D42: =SUM(E42:BL42) -> 137740000 | E42: =INDEX(Events,1,E$5)/12 -> 820000 | F42: =INDEX(Events,1,F$5)/12 -> 820000 | G42: =INDEX(Events,1,G$5)/12 -> 820000 | H42: =INDEX(Events,1,H$5)/12 -> 820000 | I42: =INDEX(Events,1,I$5)/12 -> 820000 | J42: =INDEX(Events,1,J$5)/12 -> 820000 | K42: =INDEX(Events,1,K$5)/12 -> 820000 | L42: =INDEX(Events,1,L$5)/12 -> 820000 | ... BL42: =INDEX(Events,1,BL$5)/12 -> 3550000
A43: Referral fees to partners | B43: FCFA | D43: =SUM(E43:BL43) -> 89166688 | E43: =E37*Referral_Fee -> 0 | F43: =F37*Referral_Fee -> 0 | G43: =G37*Referral_Fee -> 0 | H43: =H37*Referral_Fee -> 0 | I43: =I37*Referral_Fee -> 200000 | J43: =J37*Referral_Fee -> 212000 | K43: =K37*Referral_Fee -> 224720 | L43: =L37*Referral_Fee -> 238203.2 | ... BL43: =BL37*Referral_Fee -> 3500000
A44: Field sales transport | B44: FCFA | D44: =SUM(E44:BL44) -> 44100000 | E44: =(E13+E14)*Rep_Transport -> 75000 | F44: =(F13+F14)*Rep_Transport -> 75000 | G44: =(G13+G14)*Rep_Transport -> 75000 | H44: =(H13+H14)*Rep_Transport -> 225000 | I44: =(I13+I14)*Rep_Transport -> 225000 | J44: =(J13+J14)*Rep_Transport -> 225000 | K44: =(K13+K14)*Rep_Transport -> 225000 | L44: =(L13+L14)*Rep_Transport -> 225000 | ... BL44: =(BL13+BL14)*Rep_Transport -> 1875000
A45: Total sales and marketing budget (non-staff) | B45: FCFA | D45: =SUM(E45:BL45) -> 6.4555669e+08 | E45: =SUM(E40:E44) -> 2261666.7 | F45: =SUM(F40:F44) -> 2261666.7 | G45: =SUM(G40:G44) -> 2261666.7 | H45: =SUM(H40:H44) -> 2411666.7 | I45: =SUM(I40:I44) -> 3921666.7 | J45: =SUM(J40:J44) -> 3933666.7 | K45: =SUM(K40:K44) -> 3946386.7 | L45: =SUM(L40:L44) -> 3959869.9 | ... BL45: =SUM(BL40:BL44) -> 18661667
A47: Acquisition efficiency
A48: Sales, partnerships and marketing staff cost | B48: FCFA | D48: =SUM(E48:BL48) -> 5.4058634e+08 | E48: =Staff!E103+Staff!E104 -> 1560000 | F48: =Staff!F103+Staff!F104 -> 1560000 | G48: =Staff!G103+Staff!G104 -> 1560000 | H48: =Staff!H103+Staff!H104 -> 3770000 | I48: =Staff!I103+Staff!I104 -> 4290000 | J48: =Staff!J103+Staff!J104 -> 4290000 | K48: =Staff!K103+Staff!K104 -> 4290000 | L48: =Staff!L103+Staff!L104 -> 4290000 | ... BL48: =Staff!BL103+Staff!BL104 -> 19751977
A49: Blended cost to acquire a client (staff + budget) | B49: FCFA | E49: =IFERROR((E45+E48)/E33,0) -> 0 | F49: =IFERROR((F45+F48)/F33,0) -> 0 | G49: =IFERROR((G45+G48)/G33,0) -> 0 | H49: =IFERROR((H45+H48)/H33,0) -> 0 | I49: =IFERROR((I45+I48)/I33,0) -> 166004.04 | J49: =IFERROR((J45+J48)/J33,0) -> 164648.96 | K49: =IFERROR((K45+K48)/K33,0) -> 163240.72 | L49: =IFERROR((L45+L48)/L33,0) -> 161778.67 | ... BL49: =IFERROR((BL45+BL48)/BL33,0) -> 85566.476

Sheet Sales & marketing (€)
A1: Sales & marketing (€)
A2: Every amount of the 'Sales & marketing' sheet in euros (FCFA ÷ FCFA per euro on Assumptions). Edit the FCFA sheets and Assumptions, not this one.
A3: Month # | D3: Total / end | E3: ='Sales & marketing'!E3 -> 1 | F3: ='Sales & marketing'!F3 -> 2 | G3: ='Sales & marketing'!G3 -> 3 | H3: ='Sales & marketing'!H3 -> 4 | I3: ='Sales & marketing'!I3 -> 5 | J3: ='Sales & marketing'!J3 -> 6 | K3: ='Sales & marketing'!K3 -> 7 | L3: ='Sales & marketing'!L3 -> 8 | ... BL3: ='Sales & marketing'!BL3 -> 60
A4: Month | E4: ='Sales & marketing'!E4 -> 46388 | F4: ='Sales & marketing'!F4 -> 46419 | G4: ='Sales & marketing'!G4 -> 46447 | H4: ='Sales & marketing'!H4 -> 46478 | I4: ='Sales & marketing'!I4 -> 46508 | J4: ='Sales & marketing'!J4 -> 46539 | K4: ='Sales & marketing'!K4 -> 46569 | L4: ='Sales & marketing'!L4 -> 46600 | ... BL4: ='Sales & marketing'!BL4 -> 48183
A5: Year | E5: ='Sales & marketing'!E5 -> 1 | F5: ='Sales & marketing'!F5 -> 1 | G5: ='Sales & marketing'!G5 -> 1 | H5: ='Sales & marketing'!H5 -> 1 | I5: ='Sales & marketing'!I5 -> 1 | J5: ='Sales & marketing'!J5 -> 1 | K5: ='Sales & marketing'!K5 -> 1 | L5: ='Sales & marketing'!L5 -> 1 | ... BL5: ='Sales & marketing'!BL5 -> 5
A8: Markets open
A10: Field sales
