Workbook

Sheet Cover
B2: Tabax (working name): business plan model
B3: B2B neobank for SMEs in Senegal, then Côte d'Ivoire. Five years, monthly, every figure driven by formulas.
B5: How to use
B6: 1. Pick a scenario | C6: Assumptions › cell D4: 1 = Prudent, 2 = Base, 3 = Ambitious. Rows with three values switch with it.
B7: 2. Change any input | C7: Inputs are blue on a cream background (Assumptions, Hiring plan, Market). Everything else is a formula: do not type over it.
B8: 3. Change the team | C8: Hiring plan: the fixed roles (founder, CTO, financial expert, sales lead, marketing, country manager, compliance officer). Support, developers, field sales reps and credit analysts grow with clients and the loan book: ratios on Assumptions, section 8.
B9: 4. Check the cash | C9: Dashboard › checks. If cash goes negative, raise more or earlier (Assumptions, section 11).
B11: Tabs
B12: Dashboard | C12: Headline numbers, year-by-year summary and checks.
B13: Assumptions | C13: Every hypothesis with its source: timing, acquisition, pricing, usage per client, cost to serve, credit, team and tools, Maak, fixed costs by year, funding.
B14: Unit costs | C14: What one of each thing costs or earns: one employee by role, one client by plan, one loan, and the price of every fixed item.
B15: Hiring plan | C15: Fixed roles, start months and salaries (employer cost = gross + 30% charges); 'Agency hire' adds the €800 agency fee.
B16: Staff | C16: Headcount and employer cost by month: fixed roles plus the team that grows with volume.
B17: Sales & marketing | C17: New clients by channel (field sales, partners, digital) and country; marketing budget; cost to acquire a client.
B18: Clients & revenue | C18: Active clients by plan, usage (cards, balances, payroll, payouts) and every non-credit revenue line.
B19: Credit | C19: Loan book by product, interest, cost of funds, losses and the share kept by Tabax; cash tied up by credit.
B20: Costs | C20: Variable costs, fixed costs by category and the contingency, month by month.
B21: P&L monthly | C21: Revenue, cost of revenue, gross margin, operating expenses, EBITDA, tax, net income (no depreciation: equipment is expensed).
B22: P&L annual | C22: Years 1–5, cash and funding, operating figures and a euro view.
B23: Cash flow | C23: Monthly cash, cash set aside, funding rounds, runway.
... B27: Regulatory path | C27: What each stage requires from regulators, and where its cost sits in the model.
B29: Colour code
B30: Blue on cream | C30: Input: change freely.
B31: Black | C31: Formula on the same sheet.
B32: Green | C32: Link to another sheet.
B34: Main caveats
B35: Estimates to replace | C35: Partner bank fees, card processor fees and minimums, interchange, the deposit income share, the changes to Maak's platform, the SFD acquisition price and running costs, insurance and the cost of wallet payouts have no public price. Replace them with term sheets and quotes.
B36: Taxes | C36: Amounts exclude VAT and the 17% tax on financial activities (TAF), which apply to fees. Corporate tax is simplified (30%, losses carried forward without limit).
B37: Côte d'Ivoire | C37: Same 30% employer charges as Senegal; the number of formal employers is an estimate.
B38: Credit | C38: No loans before month 18. A partner microfinance institution (SFD) lends at 23% a year, under the 24% SFD usury cap. Tabax buys an SFD around month 24 and lends from it in Senegal; Côte d'Ivoire loans stay with a partner. The loan book is funded by debt lines, not equity.
B39: Licences | C39: Tabax holds no licence of its own until the SFD acquisition: partners hold the accounts, cards and loans. See Regulatory path.
B40: Sources | C40: Business model v2, Cost breakdown in euros, Senegal launch plan and the research notes in this project, plus IPRES/ANSD 2024 and CEPICI 2025 for the market.

Sheet Dashboard
A1: Tabax business plan: dashboard
A2: Key results for the scenario selected on Assumptions. FCFA in columns B–H, euros in column D (headline) and J–N (year by year).
A4: Scenario | B4: =Assumptions!E4 -> Base
A6: Headline numbers
A7: First month with positive EBITDA | B7: =IF(MIN('P&L monthly'!E46:BL46)=999,"not reached",MIN('P&L monthly'!E46:BL46)) -> 41 | C7: month #
A8: which is | B8: =IF(ISNUMBER(B7),DATE(YEAR(Start_Date),MONTH(Start_Date)+B7-1,1),"-") -> 47604
A9: Peak funding need (lowest cumulative cash flow before funding) | B9: =-MIN(0,MIN('Cash flow'!E16:BL16)) -> 2.6598608e+09 | C9: FCFA
A10: in euros | B10: =B9/FX_EUR -> 4054931.6 | C10: €
A11: Equity raised in the plan | B11: =SUM('Cash flow'!E19:BL19) -> 3300000000 | C11: FCFA
A12: in euros | B12: =B11/FX_EUR -> 5030817.6 | C12: €
A13: Lowest closing cash | B13: =MIN('Cash flow'!E24:BL24) -> 3.2416017e+08 | C13: FCFA | D13: =B13/FX_EUR -> 494178.99 | E13: =IF(B13<0,"Cash goes negative: raise more or earlier (Assumptions, section 11)","OK: cash stays positive") -> OK: cash stays positive
A14: in month | B14: =MATCH(B13,'Cash flow'!E24:BL24,0) -> 14 | C14: month #
A15: Cash at the end of year 5 | B15: ='Cash flow'!BL24 -> 1.0956296e+09 | C15: FCFA | D15: =B15/FX_EUR -> 1670276.6
A16: Technology from Maak | B16: =IF(Maak_Option=1,"Lease (option 1)","Equity stake (option 2)") -> Lease (option 1)
A17: Maak's stake in Tabax | B17: =IF(Maak_Option=2,Maak_Equity_Pct,0) -> 0
A18: Year by year
A19: Year | D19: ='P&L annual'!D5 -> 2027 | E19: ='P&L annual'!E5 -> 2028 | F19: ='P&L annual'!F5 -> 2029 | G19: ='P&L annual'!G5 -> 2030 | H19: ='P&L annual'!H5 -> 2031 | J19: ="Y"&1&" (€)" -> Y1 (€) | K19: ="Y"&2&" (€)" -> Y2 (€) | L19: ="Y"&3&" (€)" -> Y3 (€) | M19: ="Y"&4&" (€)" -> Y4 (€) | N19: ="Y"&5&" (€)" -> Y5 (€)
A20: Active clients (end of year) | B20: clients | D20: ='P&L annual'!D50 -> 452.49288 | E20: ='P&L annual'!E50 -> 1644.6901 | F20: ='P&L annual'!F50 -> 3851.8996 | G20: ='P&L annual'!G50 -> 6994.9191 | H20: ='P&L annual'!H50 -> 10979.379
A21: New clients in the year | B21: clients | D21: ='P&L annual'!D53 -> 478.70801 | E21: ='P&L annual'!E53 -> 1372.7331 | F21: ='P&L annual'!F53 -> 2719.2239 | G21: ='P&L annual'!G53 -> 4165.4261 | H21: ='P&L annual'!H53 -> 5687.6227
A22: Headcount (end of year) | B22: people | D22: ='P&L annual'!D54 -> 11 | E22: ='P&L annual'!E54 -> 21 | F22: ='P&L annual'!F54 -> 36 | G22: ='P&L annual'!G54 -> 58 | H22: ='P&L annual'!H54 -> 84
A23: Total revenue | B23: FCFA | D23: ='P&L annual'!D17 -> 70060612 | E23: ='P&L annual'!E17 -> 5.1643063e+08 | F23: ='P&L annual'!F17 -> 1.7403131e+09 | G23: ='P&L annual'!G17 -> 3.6217766e+09 | H23: ='P&L annual'!H17 -> 6.1181572e+09 | J23: =D23/FX_EUR -> 106806.71 | K23: =E23/FX_EUR -> 787293.43 | L23: =F23/FX_EUR -> 2653090.3 | M23: =G23/FX_EUR -> 5521362.9 | N23: =H23/FX_EUR -> 9327070.5
A24: Gross margin | B24: FCFA | D24: ='P&L annual'!D26 -> 10591371 | E24: ='P&L annual'!E26 -> 1.6713033e+08 | F24: ='P&L annual'!F26 -> 6.7288491e+08 | G24: ='P&L annual'!G26 -> 1.5067646e+09 | H24: ='P&L annual'!H26 -> 2.6022451e+09 | J24: =D24/FX_EUR -> 16146.441 | K24: =E24/FX_EUR -> 254788.54 | L24: =F24/FX_EUR -> 1025806.4 | M24: =G24/FX_EUR -> 2297047.8 | N24: =H24/FX_EUR -> 3967097.1
A25: Gross margin % | B25: % | D25: ='P&L annual'!D27 -> 0.1511744 | E25: ='P&L annual'!E27 -> 0.3236259 | F25: ='P&L annual'!F27 -> 0.38664588 | G25: ='P&L annual'!G27 -> 0.41602912 | H25: ='P&L annual'!H27 -> 0.42533152
A26: Total operating expenses | B26: FCFA | D26: ='P&L annual'!D38 -> 4.4346828e+08 | E26: ='P&L annual'!E38 -> 6.8979512e+08 | F26: ='P&L annual'!F38 -> 1.0183646e+09 | G26: ='P&L annual'!G38 -> 1.3398265e+09 | H26: ='P&L annual'!H38 -> 1.7255357e+09 | J26: =D26/FX_EUR -> 676063.03 | K26: =E26/FX_EUR -> 1051585.9 | L26: =F26/FX_EUR -> 1552486.8 | M26: =G26/FX_EUR -> 2042552.4 | N26: =H26/FX_EUR -> 2630562.2
A27: EBITDA | B27: FCFA | D27: ='P&L annual'!D39 -> -4.3287691e+08 | E27: ='P&L annual'!E39 -> -5.2266479e+08 | F27: ='P&L annual'!F39 -> -3.4547966e+08 | G27: ='P&L annual'!G39 -> 1.6693801e+08 | H27: ='P&L annual'!H39 -> 8.7670939e+08 | J27: =D27/FX_EUR -> -659916.59 | K27: =E27/FX_EUR -> -796797.34 | L27: =F27/FX_EUR -> -526680.34 | M27: =G27/FX_EUR -> 254495.36 | N27: =H27/FX_EUR -> 1336534.8
A28: EBITDA margin | B28: % | D28: ='P&L annual'!D40 -> -6.1786058 | E28: ='P&L annual'!E40 -> -1.0120716 | F28: ='P&L annual'!F40 -> -0.1985158 | G28: ='P&L annual'!G40 -> 0.046092852 | H28: ='P&L annual'!H40 -> 0.14329632
A29: Net income | B29: FCFA | D29: ='P&L annual'!D42 -> -4.3287691e+08 | E29: ='P&L annual'!E42 -> -5.2266479e+08 | F29: ='P&L annual'!F42 -> -3.4547966e+08 | G29: ='P&L annual'!G42 -> 1.6693801e+08 | H29: ='P&L annual'!H42 -> 8.7670939e+08 | J29: =D29/FX_EUR -> -659916.59 | K29: =E29/FX_EUR -> -796797.34 | L29: =F29/FX_EUR -> -526680.34 | M29: =G29/FX_EUR -> 254495.36 | N29: =H29/FX_EUR -> 1336534.8
A30: Closing cash | B30: FCFA | D30: ='P&L annual'!D47 -> 4.0712309e+08 | E30: ='P&L annual'!E47 -> 1.5808688e+09 | F30: ='P&L annual'!F47 -> 8.687281e+08 | G30: ='P&L annual'!G47 -> 6.5909492e+08 | H30: ='P&L annual'!H47 -> 1.0956296e+09 | J30: =D30/FX_EUR -> 620655.15 | K30: =E30/FX_EUR -> 2410019 | L30: =F30/FX_EUR -> 1324367.4 | M30: =G30/FX_EUR -> 1004783.7 | N30: =H30/FX_EUR -> 1670276.6
A31: Loan book (end of year) | B31: FCFA | D31: ='P&L annual'!D55 -> 0 | E31: ='P&L annual'!E55 -> 5.3589485e+08 | F31: ='P&L annual'!F55 -> 3.0451853e+09 | G31: ='P&L annual'!G55 -> 5.8353417e+09 | H31: ='P&L annual'!H55 -> 9.163571e+09 | J31: =D31/FX_EUR -> 0 | K31: =E31/FX_EUR -> 816966.44 | L31: =F31/FX_EUR -> 4642355.1 | M31: =G31/FX_EUR -> 8895921.1 | N31: =H31/FX_EUR -> 13969774
A32: Revenue per active client a month (ARPA) | B32: FCFA / month | D32: ='Unit economics'!D13 -> 34257.004 | E32: ='Unit economics'!E13 -> 42293.895 | F32: ='Unit economics'!F13 -> 51837.732 | G32: ='Unit economics'!G13 -> 54865.1 | H32: ='Unit economics'!H13 -> 56076.958 | J32: =D32/FX_EUR -> 52.224466 | K32: =E32/FX_EUR -> 64.476627 | L32: =F32/FX_EUR -> 79.026114 | M32: =G32/FX_EUR -> 83.641305 | N32: =H32/FX_EUR -> 85.488772
A33: Blended CAC | B33: FCFA / client | D33: ='Unit economics'!D20 -> 175920.11 | E33: ='Unit economics'!E20 -> 104908.1 | F33: ='Unit economics'!F20 -> 87505.933 | G33: ='Unit economics'!G20 -> 79715.404 | H33: ='Unit economics'!H20 -> 78319.051 | J33: =D33/FX_EUR -> 268.18848 | K33: =E33/FX_EUR -> 159.93137 | L33: =F33/FX_EUR -> 133.40193 | M33: =G33/FX_EUR -> 121.52535 | N33: =H33/FX_EUR -> 119.39662
A34: CAC payback (months) | B34: months | D34: ='Unit economics'!D21 -> 33.969398 | E34: ='Unit economics'!E21 -> 7.6645751 | F34: ='Unit economics'!F21 -> 4.3659435 | G34: ='Unit economics'!G21 -> 3.4923868 | H34: ='Unit economics'!H21 -> 3.2836389
A36: Checks
A37: New-client mix adds up to 100% | B37: =IF(ABS(Mix_Petite+Mix_Moyenne+Mix_Grande-1)<0.0001,"OK","ERROR") -> OK
A38: Cost of revenue in the P&L equals variable costs | B38: =IF(ABS(SUM('P&L monthly'!E24:BL24)-SUM(Costs!E21:BL21))<1,"OK","ERROR") -> OK
A39: Opex in the P&L equals fixed costs | B39: =IF(ABS(SUM('P&L monthly'!E37:BL37)-SUM(Costs!E91:BL91))<1,"OK","ERROR") -> OK
A40: Annual revenue equals monthly revenue | B40: =IF(ABS('P&L annual'!I17-SUM('P&L monthly'!E17:BL17))<1,"OK","ERROR") -> OK
A41: Closing cash never negative | B41: =IF(MIN('Cash flow'!E24:BL24)>=0,"OK","RAISE MORE") -> OK

Sheet Assumptions
A1: Assumptions and hypotheses
A2: Every blue cell on a cream background is an input. Change it and the whole model updates. Amounts in FCFA unless stated. Column D is the value the model uses.
B4: Scenario (1 = Prudent, 2 = Base, 3 = Ambitious) | D4: 2 | E4: =CHOOSE(Scenario,"Prudent","Base","Ambitious") -> Base | I4: Rows with Prudent / Base / Ambitious values switch with this cell.
B7: 1. General | C7: Unit | D7: Value used | E7: Prudent | F7: Base | G7: Ambitious | H7: € / FCFA equivalent | I7: Source / note
B8: Model start (month 1) | C8: date | D8: 46388 | I8: First month of the plan. Company set-up, licence file and product build start here.
B9: FCFA per euro | C9: FCFA | D9: 655.957 | I9: Fixed parity CFA franc / euro (BCEAO).
B10: FCFA per US dollar | C10: FCFA | D10: 580 | I10: Planning rate, used for vendor prices quoted in USD.
B11: Corporate income tax rate | C11: % | D11: 0.3 | I11: Senegal CIT 30%. Simplification: losses carried forward without limit (Senegal allows 3 years). Minimum tax and the 17% TAF on financial services are not modelled.
B12: Annual pay rise (from year 2) | C12: % / year | D12: 0.05 | I12: Applied to every salary each new year.
B13: Contingency on fixed costs | C13: % | D13: 0.05 | I13: Same 5% as the cost breakdown.
B15: 2. Timing (month numbers, 1 = first month of the model) | C15: Unit | D15: Value used | E15: Prudent | F15: Base | G15: Ambitious | H15: € / FCFA equivalent | I15: Source / note
B16: Commercial launch, Senegal | C16: month # | D16: 5 | I16: After partner bank integration and card programme set-up (business account with IBAN via the partner bank).
B17: Commercial launch, Côte d'Ivoire | C17: month # | D17: 19 | I17: One month after the Abidjan office opens. Partners hold the licences in Côte d'Ivoire too.
B18: Dakar office (Regus) from | C18: month # | D18: 1 | I18: Regus from day one: no lease, deposit or fit-out (decision).
B19: Abidjan office (Regus) and first Côte d'Ivoire hires | C19: month # | D19: 18 | I19: Not before month 18 (decision).
B20: Payment links go live | C20: month # | D20: 18 | I20: 'Bientôt' feature in the app.
B21: B2C launch: employee salary accounts and personal accounts | C21: month # | D21: 29 | I21: Not before 2 years of commercial activity: Senegal launch + 24 months (decision).
B22: Acquisition of a microfinance company (SFD) closes | C22: month # | D22: 24 | I22: Around year 2 (decision). Due diligence and the change-of-control approval run during year 2.
B23: Own SFD lends from | C23: month # | D23: 25 | I23: Before this month the partner SFD lends and Tabax keeps a share of the margin. Côte d'Ivoire loans stay with a partner: SFD licences are national.
B24: Card programme collateral at partner bank | C24: month # | D24: 4
B25: Partner bank set-up fee paid, Senegal | C25: month # | D25: 2
B26: Partner bank set-up fee paid, Côte d'Ivoire | C26: month # | D26: 16
B27: Card processor set-up fee paid | C27: month # | D27: 3
B28: Card processor monthly minimum starts | C28: month # | D28: 5
B29: Cloud hosting starts | C29: month # | D29: 2
B30: Partner SFD integration fee paid | C30: month # | D30: 15 | I30: Partner SFD signed early; integration paid before the first loans.
B31: Côte d'Ivoire subsidiary created | C31: month # | D31: 16 | I31: Before the first Abidjan hires.
B32: First tech audit (then every 12 months) | C32: month # | D32: 4 | I32: Before launch, for the partner bank; repeated yearly.
B34: 3. Client acquisition (sales and marketing) | C34: Unit | D34: Value used | E34: Prudent | F34: Base | G34: Ambitious | H34: € / FCFA equivalent | I34: Source / note
B35: New clients signed per field sales rep per month | C35: clients | D35: =CHOOSE(Scenario,E35,F35,G35) -> 10 | E35: 7 | F35: 10 | G35: 13 | I35: Rep counts come from the hiring plan. A rep sells from the month after joining. Senegal B2B field sales benchmark to validate in the pilot.
B36: Côte d'Ivoire rep productivity vs Senegal | C36: x | D36: 0.9 | I36: Slightly lower at first: new market, brand unknown.
B37: Partner channel, Senegal: clients a month at launch | C37: clients | D37: =CHOOSE(Scenario,E37,F37,G37) -> 10 | E37: 6 | F37: 10 | G37: 14 | I37: Accountants, payroll software, chambers of commerce.
B38: Partner channel, Côte d'Ivoire: clients a month at launch | C38: clients | D38: =CHOOSE(Scenario,E38,F38,G38) -> 6 | E38: 4 | F38: 6 | G38: 9
B39: Partner channel monthly growth | C39: % / month | D39: 0.06
B40: Partner channel cap, Senegal | C40: clients / month | D40: 80
B41: Partner channel cap, Côte d'Ivoire | C41: clients / month | D41: 60
B42: Digital ads cost per signed client | C42: FCFA | D42: =CHOOSE(Scenario,E42,F42,G42) -> 75000 | E42: 100000 | F42: 75000 | G42: 55000 | H42: =D42/FX_EUR -> 114.33676 | I42: Media spend only. Meta leads 600–2,800 FCFA; lead-to-client conversion assumed 2–4%.
B43: Share of new clients on Petite (1–10 staff) | C43: % | D43: 0.6 | I43: From Business model v2. The three shares must add up to 100% (see check on the Dashboard).
B44: Share of new clients on Moyenne (11–50 staff) | C44: % | D44: 0.3
B45: Share of new clients on Grande (51+ staff) | C45: % | D45: 0.1
B46: Monthly churn, Petite | C46: % / month | D46: =CHOOSE(Scenario,E46,F46,G46) -> 0.02 | E46: 0.03 | F46: 0.02 | G46: 0.015 | I46: Small companies leave or close more often.
B47: Monthly churn, Moyenne | C47: % / month | D47: =CHOOSE(Scenario,E47,F47,G47) -> 0.0125 | E47: 0.02 | F47: 0.0125 | G47: 0.01
B48: Monthly churn, Grande | C48: % / month | D48: =CHOOSE(Scenario,E48,F48,G48) -> 0.0075 | E48: 0.015 | F48: 0.0075 | G48: 0.005
B49: Referral fee per partner-channel client | C49: FCFA | D49: 25000 | H49: =D49/FX_EUR -> 38.112254 | I49: Paid to accountants and payroll software partners (cost breakdown).
B50: Field sales transport allowance per rep | C50: FCFA / month | D50: 75000 | H50: =D50/FX_EUR -> 114.33676 | I50: 50–100k FCFA (cost breakdown).
B52: 4. Pricing and fees | C52: Unit | D52: Value used | E52: Prudent | F52: Base | G52: Ambitious | H52: € / FCFA equivalent | I52: Source / note
B53: Subscription, Petite (1–10 staff) | C53: FCFA / month | D53: 9900 | H53: =D53/FX_EUR -> 15.092453 | I53: Business model v2.
B54: Subscription, Moyenne (11–50 staff) | C54: FCFA / month | D54: 29900 | H54: =D54/FX_EUR -> 45.582256 | I54: Business model v2.
B55: Subscription, Grande (51+ staff) | C55: FCFA / month | D55: 79900 | H55: =D55/FX_EUR -> 121.80676 | I55: Business model v2.
B56: Annual price increase | C56: % / year | D56: 0
B57: Free months for every new client | C57: months | D57: 3 | I57: Launch offer: first 3 months free. Use 0 to 6.
B58: Share of clients paying yearly | C58: % | D58: 0.3
B59: Months free on yearly billing | C59: months | D59: 2 | I59: Yearly price = 10 months.
B60: Physical card fee (one-off; first card free) | C60: FCFA | D60: 5000 | H60: =D60/FX_EUR -> 7.6224509 | I60: Business model v2.
B61: Fee on card spending in foreign currencies | C61: % | D61: 0.01 | I61: Business model v2. Card spending in FCFA is free.
B62: Interchange share received on FCFA card spending | C62: % | D62: =CHOOSE(Scenario,E62,F62,G62) -> 0.005 | E62: 0.003 | F62: 0.005 | G62: 0.007 | I62: Placeholder: WAEMU interchange levels are not published. Negotiate with the partner bank.
B63: Share of bank income on client balances | C63: % / year | D63: =CHOOSE(Scenario,E63,F63,G63) -> 0.015 | E63: 0.01 | F63: 0.015 | G63: 0.02 | I63: Negotiated with the partner bank; the largest non-credit lever.
B64: Fee per supplier payout above the allowance | C64: FCFA | D64: 100 | H64: =D64/FX_EUR -> 0.15244902 | I64: Allowance: 50 / 200 / 1,000 payouts a month. Salaries always unlimited.
B65: Payment links: fee on mobile money collections | C65: % | D65: 0.01
B66: Payment links: operator and aggregator cost | C66: % | D66: 0.007 | I66: 0.5–1.5% (cost breakdown).
B67: Payment links: share collected by mobile money | C67: % | D67: 0.7 | I67: The rest by card or transfer, free.
B68: Payment links: share of clients using them (at maturity) | C68: % | D68: 0.25
B69: Payment links: months to reach maturity | C69: months | D69: 12
B71: 5. Usage per client (monthly, by plan) | C71: Unit | D71: Value used | E71: Prudent | F71: Base | G71: Ambitious | H71: € / FCFA equivalent | I71: Source / note
B72: Card spending in FCFA, Petite | C72: FCFA / month | D72: 300000 | H72: =D72/FX_EUR -> 457.34705 | I72: Business model v2 (assumption).
B73: Card spending in FCFA, Moyenne | C73: FCFA / month | D73: 800000 | H73: =D73/FX_EUR -> 1219.5921
B74: Card spending in FCFA, Grande | C74: FCFA / month | D74: 2500000 | H74: =D74/FX_EUR -> 3811.2254
B75: Card spending in foreign currencies, Petite | C75: FCFA / month | D75: 300000 | H75: =D75/FX_EUR -> 457.34705 | I75: Ads, software subscriptions, travel.
B76: Card spending in foreign currencies, Moyenne | C76: FCFA / month | D76: 1200000 | H76: =D76/FX_EUR -> 1829.3882
B77: Card spending in foreign currencies, Grande | C77: FCFA / month | D77: 3500000 | H77: =D77/FX_EUR -> 5335.7156
B78: Average balance, Petite | C78: FCFA | D78: 3000000 | H78: =D78/FX_EUR -> 4573.4705
B79: Average balance, Moyenne | C79: FCFA | D79: 10000000 | H79: =D79/FX_EUR -> 15244.902
B80: Average balance, Grande | C80: FCFA | D80: 40000000 | H80: =D80/FX_EUR -> 60979.607
B81: Employees, Petite | C81: people | D81: 5
B82: Employees, Moyenne | C82: people | D82: 25
B83: Employees, Grande | C83: people | D83: 120
B84: Supplier payouts a month, Petite | C84: payouts | D84: 10
B85: Supplier payouts a month, Moyenne | C85: payouts | D85: 40
B86: Supplier payouts a month, Grande | C86: payouts | D86: 150
B87: Payouts above the allowance, Petite | C87: payouts | D87: 0
B88: Payouts above the allowance, Moyenne | C88: payouts | D88: 5
B89: Payouts above the allowance, Grande | C89: payouts | D89: 40
B90: Physical cards ordered at sign-up, Petite | C90: cards | D90: 1
B91: Physical cards ordered at sign-up, Moyenne | C91: cards | D91: 3
B92: Physical cards ordered at sign-up, Grande | C92: cards | D92: 8
... B95: Active cards (physical + virtual), Grande | C95: cards | D95: 15
B96: Payment link collections, Petite (users) | C96: FCFA / month | D96: 800000 | H96: =D96/FX_EUR -> 1219.5921
B97: Payment link collections, Moyenne (users) | C97: FCFA / month | D97: 3000000 | H97: =D97/FX_EUR -> 4573.4705
B98: Payment link collections, Grande (users) | C98: FCFA / month | D98: 10000000 | H98: =D98/FX_EUR -> 15244.902
B99: Average monthly salary paid through Tabax | C99: FCFA | D99: 200000 | H99: =D99/FX_EUR -> 304.89803 | I99: SME average; the formal-sector average is higher (about 380,000 FCFA).
B100: Share of salaries paid to mobile money wallets | C100: % | D100: 0.6 | I100: Senegal: 20.1% of adults receive wages on a phone vs 12.0% in an account (Global Findex 2025).
B101: Employees who open a Tabax salary account | C101: % | D101: 0.2
B103: 6. Cost to serve (variable costs) | C103: Unit | D103: Value used | E103: Prudent | F103: Base | G103: Ambitious | H103: € / FCFA equivalent | I103: Source / note
B104: Partner bank fee per business account | C104: FCFA / month | D104: 3000 | H104: =D104/FX_EUR -> 4.5734705 | I104: 2,000–5,000 FCFA (estimate; replace with the term sheet).
B105: Company screening tool at onboarding (sanctions, adverse media) | C105: FCFA / company | D105: 1500 | H105: =D105/FX_EUR -> 2.2867353 | I105: Tool fee only (estimate, about €2): our support team reviews the company documents (RCCM, NINEA, statutes), and that time is in their salaries.
B106: ID check tool per person (document, face match, sanctions) | C106: FCFA | D106: 900 | H106: =D106/FX_EUR -> 1.3720412 | I106: Tool fee only: Sumsub-type service, about €1.2–1.6 per check.
B107: People checked per new company | C107: people | D107: 2 | I107: Directors and beneficial owners.
B108: Card processing per active card | C108: FCFA / month | D108: 1000 | H108: =D108/FX_EUR -> 1.5244902 | I108: €0.76–2.29 (estimate; processor quote needed).
B109: Physical card printed and delivered | C109: FCFA | D109: 4500 | H109: =D109/FX_EUR -> 6.8602058 | I109: 3,000–6,000 FCFA.
B110: Visa / Mastercard cross-border fees | C110: % of foreign spending | D110: 0.005 | I110: About 0.5% (assumption).
...

Sheet Unit costs
A1: Unit costs and prices
A2: What one of each thing costs or earns, in FCFA and euros. Every cell links to the inputs on Assumptions and Hiring plan: change them there.
A5: One employee, per month
A6: Employer cost plus what each person adds: Regus desk, phone, Gmail and ClickUp, a Claude seat for the CTO and developers. One-off at hiring: a laptop (a MacBook for the CTO and developers), plus the agency fee for senior roles.
A7: Role | B7: Country | C7: Agency hire | D7: Gross salary | E7: Employer charges | F7: Employer cost | G7: Office (Regus) | H7: Phone and data | I7: Gmail and ClickUp | J7: Claude seat | K7: All-in per month (FCFA) | L7: All-in per month (€) | M7: One-off at hiring (FCFA) | N7: One-off at hiring (€)
A8: ='Hiring plan'!C5 -> CEO (full salary from year 2) | B8: ='Hiring plan'!D5 -> SN | C8: ='Hiring plan'!J5 -> Y | D8: ='Hiring plan'!I5 -> 2500000 | E8: =D8*Employer_Charges -> 750000 | F8: =D8+E8 -> 3250000 | G8: =Regus_EUR*FX_EUR -> 196787.1 | H8: =Phone_Cost -> 5000 | I8: =(Gmail_USD+ClickUp_USD)*FX_USD -> 10440 | J8: =IF('Hiring plan'!B5="Engineering & product",Claude_USD*FX_USD,0) -> 0 | K8: =SUM(F8:J8) -> 3462227.1 | L8: =K8/FX_EUR -> 5278.1312 | M8: =IF('Hiring plan'!B5="Engineering & product",Laptop_Dev_USD*FX_USD,Laptop_EUR*FX_EUR)+IF(C8="Y",Agency_Fee_EUR*FX_EUR,0) -> 852744.1 | N8: =M8/FX_EUR -> 1300
A9: ='Hiring plan'!C6 -> CTO (also codes) | B9: ='Hiring plan'!D6 -> SN | C9: ='Hiring plan'!J6 -> Y | D9: ='Hiring plan'!I6 -> 2500000 | E9: =D9*Employer_Charges -> 750000 | F9: =D9+E9 -> 3250000 | G9: =Regus_EUR*FX_EUR -> 196787.1 | H9: =Phone_Cost -> 5000 | I9: =(Gmail_USD+ClickUp_USD)*FX_USD -> 10440 | J9: =IF('Hiring plan'!B6="Engineering & product",Claude_USD*FX_USD,0) -> 14500 | K9: =SUM(F9:J9) -> 3476727.1 | L9: =K9/FX_EUR -> 5300.2363 | M9: =IF('Hiring plan'!B6="Engineering & product",Laptop_Dev_USD*FX_USD,Laptop_EUR*FX_EUR)+IF(C9="Y",Agency_Fee_EUR*FX_EUR,0) -> 1684765.6 | N9: =M9/FX_EUR -> 2568.4086
A10: ='Hiring plan'!C7 -> Financial expert (finance, partners, credit lead) | B10: ='Hiring plan'!D7 -> SN | C10: ='Hiring plan'!J7 -> Y | D10: ='Hiring plan'!I7 -> 1500000 | E10: =D10*Employer_Charges -> 450000 | F10: =D10+E10 -> 1950000 | G10: =Regus_EUR*FX_EUR -> 196787.1 | H10: =Phone_Cost -> 5000 | I10: =(Gmail_USD+ClickUp_USD)*FX_USD -> 10440 | J10: =IF('Hiring plan'!B7="Engineering & product",Claude_USD*FX_USD,0) -> 0 | K10: =SUM(F10:J10) -> 2162227.1 | L10: =K10/FX_EUR -> 3296.294 | M10: =IF('Hiring plan'!B7="Engineering & product",Laptop_Dev_USD*FX_USD,Laptop_EUR*FX_EUR)+IF(C10="Y",Agency_Fee_EUR*FX_EUR,0) -> 852744.1 | N10: =M10/FX_EUR -> 1300
A11: ='Hiring plan'!C8 -> Sales lead (also sells; incl. bonus) | B11: ='Hiring plan'!D8 -> SN | C11: ='Hiring plan'!J8 -> N | D11: ='Hiring plan'!I8 -> 1200000 | E11: =D11*Employer_Charges -> 360000 | F11: =D11+E11 -> 1560000 | G11: =Regus_EUR*FX_EUR -> 196787.1 | H11: =Phone_Cost -> 5000 | I11: =(Gmail_USD+ClickUp_USD)*FX_USD -> 10440 | J11: =IF('Hiring plan'!B8="Engineering & product",Claude_USD*FX_USD,0) -> 0 | K11: =SUM(F11:J11) -> 1772227.1 | L11: =K11/FX_EUR -> 2701.7428 | M11: =IF('Hiring plan'!B8="Engineering & product",Laptop_Dev_USD*FX_USD,Laptop_EUR*FX_EUR)+IF(C11="Y",Agency_Fee_EUR*FX_EUR,0) -> 327978.5 | N11: =M11/FX_EUR -> 500
A12: ='Hiring plan'!C9 -> Marketing manager (senior) | B12: ='Hiring plan'!D9 -> SN | C12: ='Hiring plan'!J9 -> N | D12: ='Hiring plan'!I9 -> 900000 | E12: =D12*Employer_Charges -> 270000 | F12: =D12+E12 -> 1170000 | G12: =Regus_EUR*FX_EUR -> 196787.1 | H12: =Phone_Cost -> 5000 | I12: =(Gmail_USD+ClickUp_USD)*FX_USD -> 10440 | J12: =IF('Hiring plan'!B9="Engineering & product",Claude_USD*FX_USD,0) -> 0 | K12: =SUM(F12:J12) -> 1382227.1 | L12: =K12/FX_EUR -> 2107.1916 | M12: =IF('Hiring plan'!B9="Engineering & product",Laptop_Dev_USD*FX_USD,Laptop_EUR*FX_EUR)+IF(C12="Y",Agency_Fee_EUR*FX_EUR,0) -> 327978.5 | N12: =M12/FX_EUR -> 500
A13: ='Hiring plan'!C10 -> Marketing officer (junior) | B13: ='Hiring plan'!D10 -> SN | C13: ='Hiring plan'!J10 -> N | D13: ='Hiring plan'!I10 -> 400000 | E13: =D13*Employer_Charges -> 120000 | F13: =D13+E13 -> 520000 | G13: =Regus_EUR*FX_EUR -> 196787.1 | H13: =Phone_Cost -> 5000 | I13: =(Gmail_USD+ClickUp_USD)*FX_USD -> 10440 | J13: =IF('Hiring plan'!B10="Engineering & product",Claude_USD*FX_USD,0) -> 0 | K13: =SUM(F13:J13) -> 732227.1 | L13: =K13/FX_EUR -> 1116.273 | M13: =IF('Hiring plan'!B10="Engineering & product",Laptop_Dev_USD*FX_USD,Laptop_EUR*FX_EUR)+IF(C13="Y",Agency_Fee_EUR*FX_EUR,0) -> 327978.5 | N13: =M13/FX_EUR -> 500
A14: ='Hiring plan'!C11 -> Country manager, Abidjan | B14: ='Hiring plan'!D11 -> CI | C14: ='Hiring plan'!J11 -> Y | D14: ='Hiring plan'!I11 -> 2800000 | E14: =D14*Employer_Charges -> 840000 | F14: =D14+E14 -> 3640000 | G14: =Regus_EUR*FX_EUR -> 196787.1 | H14: =Phone_Cost -> 5000 | I14: =(Gmail_USD+ClickUp_USD)*FX_USD -> 10440 | J14: =IF('Hiring plan'!B11="Engineering & product",Claude_USD*FX_USD,0) -> 0 | K14: =SUM(F14:J14) -> 3852227.1 | L14: =K14/FX_EUR -> 5872.6824 | M14: =IF('Hiring plan'!B11="Engineering & product",Laptop_Dev_USD*FX_USD,Laptop_EUR*FX_EUR)+IF(C14="Y",Agency_Fee_EUR*FX_EUR,0) -> 852744.1 | N14: =M14/FX_EUR -> 1300
A15: ='Hiring plan'!C12 -> Compliance officer (AML/CFT) | B15: ='Hiring plan'!D12 -> SN | C15: ='Hiring plan'!J12 -> Y | D15: ='Hiring plan'!I12 -> 1500000 | E15: =D15*Employer_Charges -> 450000 | F15: =D15+E15 -> 1950000 | G15: =Regus_EUR*FX_EUR -> 196787.1 | H15: =Phone_Cost -> 5000 | I15: =(Gmail_USD+ClickUp_USD)*FX_USD -> 10440 | J15: =IF('Hiring plan'!B12="Engineering & product",Claude_USD*FX_USD,0) -> 0 | K15: =SUM(F15:J15) -> 2162227.1 | L15: =K15/FX_EUR -> 3296.294 | M15: =IF('Hiring plan'!B12="Engineering & product",Laptop_Dev_USD*FX_USD,Laptop_EUR*FX_EUR)+IF(C15="Y",Agency_Fee_EUR*FX_EUR,0) -> 852744.1 | N15: =M15/FX_EUR -> 1300
A16: Customer support agent (grows with volume) | B16: SN | C16: =IF(Agency_Support=1,"Y","N") -> N | D16: =Salary_Support -> 250000 | E16: =D16*Employer_Charges -> 75000 | F16: =D16+E16 -> 325000 | G16: =Regus_EUR*FX_EUR -> 196787.1 | H16: =Phone_Cost -> 5000 | I16: =(Gmail_USD+ClickUp_USD)*FX_USD -> 10440 | J16: =0 -> 0 | K16: =SUM(F16:J16) -> 537227.1 | L16: =K16/FX_EUR -> 818.99743 | M16: =IF(FALSE(),Laptop_Dev_USD*FX_USD,Laptop_EUR*FX_EUR)+IF(C16="Y",Agency_Fee_EUR*FX_EUR,0) -> 327978.5 | N16: =M16/FX_EUR -> 500
A17: Developer (grows with volume) | B17: SN | C17: =IF(Agency_Dev=1,"Y","N") -> Y | D17: =Salary_Dev -> 1200000 | E17: =D17*Employer_Charges -> 360000 | F17: =D17+E17 -> 1560000 | G17: =Regus_EUR*FX_EUR -> 196787.1 | H17: =Phone_Cost -> 5000 | I17: =(Gmail_USD+ClickUp_USD)*FX_USD -> 10440 | J17: =Claude_USD*FX_USD -> 14500 | K17: =SUM(F17:J17) -> 1786727.1 | L17: =K17/FX_EUR -> 2723.8479 | M17: =IF(TRUE(),Laptop_Dev_USD*FX_USD,Laptop_EUR*FX_EUR)+IF(C17="Y",Agency_Fee_EUR*FX_EUR,0) -> 1684765.6 | N17: =M17/FX_EUR -> 2568.4086
A18: Field sales rep, Senegal (grows with volume) | B18: SN | C18: =IF(Agency_Rep=1,"Y","N") -> N | D18: =Salary_Rep_SN -> 400000 | E18: =D18*Employer_Charges -> 120000 | F18: =D18+E18 -> 520000 | G18: =Regus_EUR*FX_EUR -> 196787.1 | H18: =Phone_Cost -> 5000 | I18: =(Gmail_USD+ClickUp_USD)*FX_USD -> 10440 | J18: =0 -> 0 | K18: =SUM(F18:J18) -> 732227.1 | L18: =K18/FX_EUR -> 1116.273 | M18: =IF(FALSE(),Laptop_Dev_USD*FX_USD,Laptop_EUR*FX_EUR)+IF(C18="Y",Agency_Fee_EUR*FX_EUR,0) -> 327978.5 | N18: =M18/FX_EUR -> 500
A19: Field sales rep, Côte d'Ivoire (grows with volume) | B19: CI | C19: =IF(Agency_Rep=1,"Y","N") -> N | D19: =Salary_Rep_CI -> 450000 | E19: =D19*Employer_Charges -> 135000 | F19: =D19+E19 -> 585000 | G19: =Regus_EUR*FX_EUR -> 196787.1 | H19: =Phone_Cost -> 5000 | I19: =(Gmail_USD+ClickUp_USD)*FX_USD -> 10440 | J19: =0 -> 0 | K19: =SUM(F19:J19) -> 797227.1 | L19: =K19/FX_EUR -> 1215.3649 | M19: =IF(FALSE(),Laptop_Dev_USD*FX_USD,Laptop_EUR*FX_EUR)+IF(C19="Y",Agency_Fee_EUR*FX_EUR,0) -> 327978.5 | N19: =M19/FX_EUR -> 500
A20: Credit analyst (grows with volume) | B20: SN | C20: =IF(Agency_Credit=1,"Y","N") -> Y | D20: =Salary_Credit -> 600000 | E20: =D20*Employer_Charges -> 180000 | F20: =D20+E20 -> 780000 | G20: =Regus_EUR*FX_EUR -> 196787.1 | H20: =Phone_Cost -> 5000 | I20: =(Gmail_USD+ClickUp_USD)*FX_USD -> 10440 | J20: =0 -> 0 | K20: =SUM(F20:J20) -> 992227.1 | L20: =K20/FX_EUR -> 1512.6405 | M20: =IF(FALSE(),Laptop_Dev_USD*FX_USD,Laptop_EUR*FX_EUR)+IF(C20="Y",Agency_Fee_EUR*FX_EUR,0) -> 852744.1 | N20: =M20/FX_EUR -> 1300
A21: Company-wide, not per person: 2 shared Claude seats, the website and domain. Field reps also get the transport allowance (Sales & marketing). Pay rises 5% a year from year 2.
A23: One business client, per month, by plan
A24: Steady state: after the free months, payment links at full adoption, no credit. Scenario inputs at their current value.
A25: Line | B25: How it is calculated | D25: Petite | E25: Moyenne | F25: Grande | G25: Petite (€) | H25: Moyenne (€) | I25: Grande (€)
A26: Revenue
A27: Subscription (after the yearly-billing discount) | B27: Plan price × (1 − share paying yearly × free months on yearly billing ÷ 12) | D27: =Price_Petite*(1-Annual_Share*Annual_Free/12) -> 9405 | E27: =Price_Moyenne*(1-Annual_Share*Annual_Free/12) -> 28405 | F27: =Price_Grande*(1-Annual_Share*Annual_Free/12) -> 75905 | G27: =D27/FX_EUR -> 14.33783 | H27: =E27/FX_EUR -> 43.303143 | I27: =F27/FX_EUR -> 115.71643
A28: Fees on foreign-currency card spending | B28: Foreign-currency card spending × FX fee | D28: =Spend_For_Petite*FX_Fee -> 3000 | E28: =Spend_For_Moyenne*FX_Fee -> 12000 | F28: =Spend_For_Grande*FX_Fee -> 35000 | G28: =D28/FX_EUR -> 4.5734705 | H28: =E28/FX_EUR -> 18.293882 | I28: =F28/FX_EUR -> 53.357156
A29: Interchange share | B29: FCFA card spending × interchange share | D29: =Spend_Dom_Petite*Interchange_Share -> 1500 | E29: =Spend_Dom_Moyenne*Interchange_Share -> 4000 | F29: =Spend_Dom_Grande*Interchange_Share -> 12500 | G29: =D29/FX_EUR -> 2.2867353 | H29: =E29/FX_EUR -> 6.0979607 | I29: =F29/FX_EUR -> 19.056127
A30: Share of bank income on balances | B30: Average balance × yearly share ÷ 12 | D30: =Balance_Petite*Deposit_Share/12 -> 3750 | E30: =Balance_Moyenne*Deposit_Share/12 -> 12500 | F30: =Balance_Grande*Deposit_Share/12 -> 50000 | G30: =D30/FX_EUR -> 5.7168381 | H30: =E30/FX_EUR -> 19.056127 | I30: =F30/FX_EUR -> 76.224509
A31: Fees on supplier payouts above the allowance | B31: Payouts above the allowance × fee per payout | D31: =Overage_Petite*Overage_Fee -> 0 | E31: =Overage_Moyenne*Overage_Fee -> 500 | F31: =Overage_Grande*Overage_Fee -> 4000 | G31: =D31/FX_EUR -> 0 | H31: =E31/FX_EUR -> 0.76224509 | I31: =F31/FX_EUR -> 6.0979607
A32: Payment link fees (average client) | B32: Collections × adoption × share by mobile money × fee | D32: =PL_Coll_Petite*PL_Adoption*PL_Momo_Share*PL_Fee -> 1400 | E32: =PL_Coll_Moyenne*PL_Adoption*PL_Momo_Share*PL_Fee -> 5250 | F32: =PL_Coll_Grande*PL_Adoption*PL_Momo_Share*PL_Fee -> 17500 | G32: =D32/FX_EUR -> 2.1342862 | H32: =E32/FX_EUR -> 8.0035734 | I32: =F32/FX_EUR -> 26.678578
A33: Revenue per client | D33: =SUM(D27:D32) -> 19055 | E33: =SUM(E27:E32) -> 62655 | F33: =SUM(F27:F32) -> 194905 | G33: =D33/FX_EUR -> 29.04916 | H33: =E33/FX_EUR -> 95.516932 | I33: =F33/FX_EUR -> 297.13076
A34: Cost to serve
A35: Partner bank fee per business account | B35: Flat fee per account | D35: =Bank_Fee -> 3000 | E35: =Bank_Fee -> 3000 | F35: =Bank_Fee -> 3000 | G35: =D35/FX_EUR -> 4.5734705 | H35: =E35/FX_EUR -> 4.5734705 | I35: =F35/FX_EUR -> 4.5734705
A36: Card processing | B36: Active cards × processing fee per card | D36: =Cards_Act_Petite*Card_Proc_Fee -> 2000 | E36: =Cards_Act_Moyenne*Card_Proc_Fee -> 6000 | F36: =Cards_Act_Grande*Card_Proc_Fee -> 15000 | G36: =D36/FX_EUR -> 3.0489803 | H36: =E36/FX_EUR -> 9.146941 | I36: =F36/FX_EUR -> 22.867353
A37: Visa / Mastercard cross-border fees | B37: Foreign-currency card spending × scheme rate | D37: =Spend_For_Petite*Scheme_Rate -> 1500 | E37: =Spend_For_Moyenne*Scheme_Rate -> 6000 | F37: =Spend_For_Grande*Scheme_Rate -> 17500 | G37: =D37/FX_EUR -> 2.2867353 | H37: =E37/FX_EUR -> 9.146941 | I37: =F37/FX_EUR -> 26.678578
A38: Fraud and chargebacks | B38: All card spending × fraud rate | D38: =(Spend_Dom_Petite+Spend_For_Petite)*Fraud_Rate -> 900 | E38: =(Spend_Dom_Moyenne+Spend_For_Moyenne)*Fraud_Rate -> 3000 | F38: =(Spend_Dom_Grande+Spend_For_Grande)*Fraud_Rate -> 9000 | G38: =D38/FX_EUR -> 1.3720412 | H38: =E38/FX_EUR -> 4.5734705 | I38: =F38/FX_EUR -> 13.720412
A39: Salaries paid to mobile wallets | B39: Employees × average salary × share to wallets × cost rate | D39: =Emp_Petite*Avg_Salary*Wallet_Share*Wallet_Payout_Cost -> 1500 | E39: =Emp_Moyenne*Avg_Salary*Wallet_Share*Wallet_Payout_Cost -> 7500 | F39: =Emp_Grande*Avg_Salary*Wallet_Share*Wallet_Payout_Cost -> 36000 | G39: =D39/FX_EUR -> 2.2867353 | H39: =E39/FX_EUR -> 11.433676 | I39: =F39/FX_EUR -> 54.881646
A40: Salaries paid to bank accounts | B40: Employees × share to banks × cost per transfer | D40: =Emp_Petite*(1-Wallet_Share)*Bank_Payout_Cost -> 200 | E40: =Emp_Moyenne*(1-Wallet_Share)*Bank_Payout_Cost -> 1000 | F40: =Emp_Grande*(1-Wallet_Share)*Bank_Payout_Cost -> 4800 | G40: =D40/FX_EUR -> 0.30489803 | H40: =E40/FX_EUR -> 1.5244902 | I40: =F40/FX_EUR -> 7.3175528
A41: Supplier payouts | B41: Payouts × cost per payout | D41: =Supplier_Petite*Supplier_Payout_Cost -> 1000 | E41: =Supplier_Moyenne*Supplier_Payout_Cost -> 4000 | F41: =Supplier_Grande*Supplier_Payout_Cost -> 15000 | G41: =D41/FX_EUR -> 1.5244902 | H41: =E41/FX_EUR -> 6.0979607 | I41: =F41/FX_EUR -> 22.867353
A42: Payment link collection costs | B42: Collections × adoption × share by mobile money × operator cost | D42: =PL_Coll_Petite*PL_Adoption*PL_Momo_Share*PL_Cost -> 980 | E42: =PL_Coll_Moyenne*PL_Adoption*PL_Momo_Share*PL_Cost -> 3675 | F42: =PL_Coll_Grande*PL_Adoption*PL_Momo_Share*PL_Cost -> 12250 | G42: =D42/FX_EUR -> 1.4940004 | H42: =E42/FX_EUR -> 5.6025014 | I42: =F42/FX_EUR -> 18.675005
A43: SMS, WhatsApp and support tools | B43: Flat per client | D43: =Notif_Cost -> 400 | E43: =Notif_Cost -> 400 | F43: =Notif_Cost -> 400 | G43: =D43/FX_EUR -> 0.60979607 | H43: =E43/FX_EUR -> 0.60979607 | I43: =F43/FX_EUR -> 0.60979607
A44: Cost to serve per client | D44: =SUM(D35:D43) -> 11480 | E44: =SUM(E35:E43) -> 34575 | F44: =SUM(F35:F43) -> 112950 | G44: =D44/FX_EUR -> 17.501147 | H44: =E44/FX_EUR -> 52.709248 | I44: =F44/FX_EUR -> 172.19116
A45: Contribution per client per month | B45: Revenue − cost to serve | D45: =D33-D44 -> 7575 | E45: =E33-E44 -> 28080 | F45: =F33-F44 -> 81955 | G45: =D45/FX_EUR -> 11.548013 | H45: =E45/FX_EUR -> 42.807684 | I45: =F45/FX_EUR -> 124.93959
A46: Contribution margin | D46: =IFERROR(D45/D33,0) -> 0.39753346 | E46: =IFERROR(E45/E33,0) -> 0.44816854 | F46: =IFERROR(F45/F33,0) -> 0.4204869
A47: Once, when the client signs up
A48: Onboarding check tools | B48: Company screening + people checked × ID check (our team's review time is in salaries) | D48: =KYB_Cost+KYC_Cost*KYC_Persons -> 3300 | E48: =KYB_Cost+KYC_Cost*KYC_Persons -> 3300 | F48: =KYB_Cost+KYC_Cost*KYC_Persons -> 3300 | G48: =D48/FX_EUR -> 5.0308176 | H48: =E48/FX_EUR -> 5.0308176 | I48: =F48/FX_EUR -> 5.0308176
A49: Physical cards printed and delivered | B49: Cards ordered at sign-up × cost per card | D49: =Cards_New_Petite*Card_Prod_Cost -> 4500 | E49: =Cards_New_Moyenne*Card_Prod_Cost -> 13500 | F49: =Cards_New_Grande*Card_Prod_Cost -> 36000 | G49: =D49/FX_EUR -> 6.8602058 | H49: =E49/FX_EUR -> 20.580617 | I49: =F49/FX_EUR -> 54.881646
A50: Card fees charged to the client (revenue) | B50: (Cards ordered − 1 free) × card fee | D50: =MAX(0,Cards_New_Petite-1)*Card_Fee -> 0 | E50: =MAX(0,Cards_New_Moyenne-1)*Card_Fee -> 10000 | F50: =MAX(0,Cards_New_Grande-1)*Card_Fee -> 35000 | G50: =D50/FX_EUR -> 0 | H50: =E50/FX_EUR -> 15.244902 | I50: =F50/FX_EUR -> 53.357156
A51: Referral fee (partner-channel clients only) | B51: Fee paid to the accountant or software partner | D51: =Referral_Fee -> 25000 | E51: =Referral_Fee -> 25000 | F51: =Referral_Fee -> 25000 | G51: =D51/FX_EUR -> 38.112254 | H51: =E51/FX_EUR -> 38.112254 | I51: =F51/FX_EUR -> 38.112254
A52: Subscription given away (free months) | B52: Free months × plan price | D52: =Free_Months*Price_Petite -> 29700 | E52: =Free_Months*Price_Moyenne -> 89700 | F52: =Free_Months*Price_Grande -> 239700 | G52: =D52/FX_EUR -> 45.277358 | H52: =E52/FX_EUR -> 136.74677 | I52: =F52/FX_EUR -> 365.42029
A54: One loan: 1,000,000 FCFA lent for a year
A55: Net margin after cost of funds, credit losses and servicing; what Tabax keeps with the partner SFD and with its own SFD; cash Tabax must lock up.
A56: Product | B56: Yield | C56: Cost of funds | D56: Credit losses | E56: Servicing | F56: Net margin | G56: Net margin (FCFA) | H56: Net margin (€) | I56: Tabax keeps, partner phase (FCFA) | J56: Tabax keeps, own SFD (FCFA) | K56: Cash locked, partner phase (FCFA) | L56: Cash locked, own SFD (FCFA)
A57: Factoring | B57: =Yield_Factoring -> 0.23 | C57: =CoF -> 0.09 | D57: =CoR_Factoring*CoR_Mult -> 0.015 | E57: =Servicing -> 0.01 | F57: =B57-C57-D57-E57 -> 0.115 | G57: =F57*1000000 -> 115000 | H57: =G57/FX_EUR -> 175.31637 | I57: =G57*Partner_Share -> 57500 | J57: =G57 -> 115000 | K57: =1000000*First_Loss -> 100000 | L57: =1000000*Capital_Ratio -> 150000
A58: Payroll bridge | B58: =Yield_Bridge -> 0.23 | C58: =CoF -> 0.09 | D58: =CoR_Bridge*CoR_Mult -> 0.02 | E58: =Servicing -> 0.01 | F58: =B58-C58-D58-E58 -> 0.11 | G58: =F58*1000000 -> 110000 | H58: =G58/FX_EUR -> 167.69392 | I58: =G58*Partner_Share -> 55000 | J58: =G58 -> 110000 | K58: =1000000*First_Loss -> 100000 | L58: =1000000*Capital_Ratio -> 150000
A59: Credit line | B59: =Yield_Line -> 0.23 | C59: =CoF -> 0.09 | D59: =CoR_Line*CoR_Mult -> 0.04 | E59: =Servicing -> 0.01 | F59: =B59-C59-D59-E59 -> 0.09 | G59: =F59*1000000 -> 90000 | H59: =G59/FX_EUR -> 137.20412 | I59: =G59*Partner_Share -> 45000 | J59: =G59 -> 90000 | K59: =1000000*First_Loss -> 100000 | L59: =1000000*Capital_Ratio -> 150000
A60: Equipment and term loans | B60: =Yield_Term -> 0.22 | C60: =CoF -> 0.09 | D60: =CoR_Term*CoR_Mult -> 0.03 | E60: =Servicing -> 0.01 | F60: =B60-C60-D60-E60 -> 0.09 | G60: =F60*1000000 -> 90000 | H60: =G60/FX_EUR -> 137.20412 | I60: =G60*Partner_Share -> 45000 | J60: =G60 -> 90000 | K60: =1000000*First_Loss -> 100000 | L60: =1000000*Capital_Ratio -> 150000
A61: Salary advances | B61: =Yield_Advance -> 0.23 | C61: =CoF -> 0.09 | D61: =CoR_Advance*CoR_Mult -> 0.015 | E61: =Servicing -> 0.01 | F61: =B61-C61-D61-E61 -> 0.115 | G61: =F61*1000000 -> 115000 | H61: =G61/FX_EUR -> 175.31637 | I61: =G61*Partner_Share -> 57500 | J61: =G61 -> 115000 | K61: =1000000*First_Loss -> 100000 | L61: =1000000*Capital_Ratio -> 150000
A62: The usury cap is 24% a year all-in (TEG) for microfinance institutions: interest plus every fee charged to the borrower.
A64: Price list and fixed items
A65: List prices clients pay, and the price of each fixed cost at its year-1 level (later years on Assumptions, section 10).
A66: Item | B66: Unit | C66: Price | D66: In FCFA | E66: In €
A67: What clients pay
A68: Subscription, Petite | B68: FCFA / month | C68: =Price_Petite -> 9900 | D68: =C68 -> 9900 | E68: =D68/FX_EUR -> 15.092453
A69: Subscription, Moyenne | B69: FCFA / month | C69: =Price_Moyenne -> 29900 | D69: =C69 -> 29900 | E69: =D69/FX_EUR -> 45.582256
A70: Subscription, Grande | B70: FCFA / month | C70: =Price_Grande -> 79900 | D70: =C70 -> 79900 | E70: =D70/FX_EUR -> 121.80676
A71: Extra physical card | B71: FCFA / card | C71: =Card_Fee -> 5000 | D71: =C71 -> 5000 | E71: =D71/FX_EUR -> 7.6224509
A72: Fee on foreign-currency card spending | B72: % of spending | C72: =FX_Fee -> 0.01
A73: Supplier payout above the allowance | B73: FCFA / payout | C73: =Overage_Fee -> 100 | D73: =C73 -> 100 | E73: =D73/FX_EUR -> 0.15244902
A74: Payment link fee (mobile money) | B74: % of amount | C74: =PL_Fee -> 0.01
A75: Credit (factoring, payroll bridge, credit line, advances) | B75: % / year | C75: =Yield_Line -> 0.23
A76: Technology
A77: Maak platform lease (option 1) | B77: € / year | C77: =IF(Maak_Option=1,Maak_Lease_EUR,0) -> 70000 | D77: =C77*FX_EUR -> 45916990 | E77: =D77/FX_EUR -> 70000
A78: Cloud hosting | B78: USD / month | C78: =INDEX(Cloud_USD,1,1) -> 3000 | D78: =C78*FX_USD -> 1740000 | E78: =D78/FX_EUR -> 2652.6129
A79: Transaction monitoring and sanctions screening | B79: USD / year | C79: =INDEX(Monitoring_USD,1,1) -> 6000 | D79: =C79*FX_USD -> 3480000 | E79: =D79/FX_EUR -> 5305.2258
A80: Freelance QA testing and DevOps on-call | B80: FCFA / year | C80: =INDEX(Freelance,1,1) -> 7900000 | D80: =C80 -> 7900000 | E80: =D80/FX_EUR -> 12043.472
A81: Laptop (non-developers) | B81: € / hire | C81: =Laptop_EUR -> 500 | D81: =C81*FX_EUR -> 327978.5 | E81: =D81/FX_EUR -> 500
A82: MacBook (CTO and developers) | B82: USD / hire | C82: =Laptop_Dev_USD -> 2000 | D82: =C82*FX_USD -> 1160000 | E82: =D82/FX_EUR -> 1768.4086
A83: Phone and data plan | B83: FCFA / person / month | C83: =Phone_Cost -> 5000 | D83: =C83 -> 5000 | E83: =D83/FX_EUR -> 7.6224509
A84: Tech audit | B84: USD / year | C84: =Tech_Audit_USD -> 10000 | D84: =C84*FX_USD -> 5800000 | E84: =D84/FX_EUR -> 8842.043
A85: Website tool | B85: USD / month | C85: =Website_USD -> 25 | D85: =C85*FX_USD -> 14500 | E85: =D85/FX_EUR -> 22.105107
A86: Domain name | B86: USD / year | C86: =Domain_USD -> 20 | D86: =C86*FX_USD -> 11600 | E86: =D86/FX_EUR -> 17.684086
A87: Claude Enterprise seat | B87: USD / seat / month | C87: =Claude_USD -> 25 | D87: =C87*FX_USD -> 14500 | E87: =D87/FX_EUR -> 22.105107
A88: Card processor set-up (once) | B88: USD | C88: =Proc_Setup_USD -> 50000 | D88: =C88*FX_USD -> 29000000 | E88: =D88/FX_EUR -> 44210.215
A89: Card processor monthly minimum | B89: USD / month | C89: =INDEX(Proc_Min_USD,1,1) -> 5000 | D89: =C89*FX_USD -> 2900000 | E89: =D89/FX_EUR -> 4421.0215
A90: Partners
A91: Partner bank set-up and card programme, Senegal (once) | B91: FCFA | C91: =Bank_Setup_SN -> 15000000 | D91: =C91 -> 15000000 | E91: =D91/FX_EUR -> 22867.353
A92: Partner bank platform minimum, Senegal | B92: FCFA / month | C92: =INDEX(Bank_Min_SN,1,1) -> 1500000 | D92: =C92 -> 1500000 | E92: =D92/FX_EUR -> 2286.7353
A93: Partner bank set-up, Côte d'Ivoire (once) | B93: FCFA | C93: =Bank_Setup_CI -> 15000000 | D93: =C93 -> 15000000 | E93: =D93/FX_EUR -> 22867.353
A94: Partner bank platform minimum, Côte d'Ivoire (year 2) | B94: FCFA / month | C94: =INDEX(Bank_Min_CI,1,2) -> 1500000 | D94: =C94 -> 1500000 | E94: =D94/FX_EUR -> 2286.7353
A95: Partner SFD integration (once) | B95: FCFA | C95: =SFD_Setup -> 5000000 | D95: =C95 -> 5000000 | E95: =D95/FX_EUR -> 7622.4509
A96: Partner SFD running fees (year 2) | B96: FCFA / year | C96: =INDEX(SFD_Annual,1,2) -> 3000000 | D96: =C96 -> 3000000 | E96: =D96/FX_EUR -> 4573.4705
A97: Card programme collateral (cash set aside, not a cost) | B97: FCFA | C97: =Card_Collateral -> 60000000 | D97: =C97 -> 60000000 | E97: =D97/FX_EUR -> 91469.41
A98: Legal, audit and insurance
A99: Company set-up, Senegal (once) | B99: FCFA | C99: =Company_Setup_SN -> 2500000 | D99: =C99 -> 2500000 | E99: =D99/FX_EUR -> 3811.2254
A100: Ongoing legal counsel | B100: FCFA / month | C100: =INDEX(Legal_Counsel,1,1) -> 1000000 | D100: =C100 -> 1000000 | E100: =D100/FX_EUR -> 1524.4902
A101: External accountant and tax adviser | B101: FCFA / month | C101: =INDEX(Accountant_Ext,1,1) -> 300000 | D101: =C101 -> 300000 | E101: =D101/FX_EUR -> 457.34705
A102: Statutory auditor | B102: FCFA / year | C102: =INDEX(Auditor,1,1) -> 5000000 | D102: =C102 -> 5000000 | E102: =D102/FX_EUR -> 7622.4509
A103: Data-protection filings | B103: FCFA / year | C103: =INDEX(Data_Protection,1,1) -> 3500000 | D103: =C103 -> 3500000 | E103: =D103/FX_EUR -> 5335.7156
A104: Insurance | B104: USD / year | C104: =INDEX(Insurance_USD,1,1) -> 20000 | D104: =C104*FX_USD -> 11600000 | E104: =D104/FX_EUR -> 17684.086
A105: Sales, marketing and other
...

Sheet Hiring plan
A1: Hiring plan
A2: One line per hire or group of identical hires. Edit headcount, start month, end month (leave blank if they stay) and gross salary. Spare lines at the bottom for new roles.
A4: # | B4: Department | C4: Role | D4: Country | E4: Category | F4: Headcount | G4: Start month | H4: End month | I4: Gross salary (FCFA / month) | J4: Agency hire (Y/N) | K4: Employer cost per person (FCFA / month) | L4: Note | M4: Gross salary (€ / month) | N4: Employer cost per person (€ / month)
A5: 1 | B5: Leadership | C5: CEO (full salary from year 2) | D5: SN | F5: 1 | G5: 13 | I5: 2500000 | J5: Y | K5: =IF(I5="",0,I5*(1+Employer_Charges)) -> 3250000 | L5: Founders and shareholders run the company unpaid in year 1 (decision). | M5: =IF(N(I5)=0,0,I5/FX_EUR) -> 3811.2254 | N5: =IF(N(K5)=0,0,K5/FX_EUR) -> 4954.5931
A6: 2 | B6: Engineering & product | C6: CTO (also codes) | D6: SN | F6: 1 | G6: 1 | I6: 2500000 | J6: Y | K6: =IF(I6="",0,I6*(1+Employer_Charges)) -> 3250000 | L6: Developers are added with volume on the Staff sheet (2 at the start). | M6: =IF(N(I6)=0,0,I6/FX_EUR) -> 3811.2254 | N6: =IF(N(K6)=0,0,K6/FX_EUR) -> 4954.5931
A7: 3 | B7: Finance & admin | C7: Financial expert (finance, partners, credit lead) | D7: SN | F7: 1 | G7: 1 | I7: 1500000 | J7: Y | K7: =IF(I7="",0,I7*(1+Employer_Charges)) -> 1950000 | L7: Starting team. Credit analysts are added with the loan book. | M7: =IF(N(I7)=0,0,I7/FX_EUR) -> 2286.7353 | N7: =IF(N(K7)=0,0,K7/FX_EUR) -> 2972.7558
A8: 4 | B8: Sales & partnerships | C8: Sales lead (also sells; incl. bonus) | D8: SN | E8: Sales rep | F8: 1 | G8: 1 | I8: 1200000 | J8: N | K8: =IF(I8="",0,I8*(1+Employer_Charges)) -> 1560000 | L8: Plus 2 field reps from month 4, then reps grow with clients (Staff sheet). | M8: =IF(N(I8)=0,0,I8/FX_EUR) -> 1829.3882 | N8: =IF(N(K8)=0,0,K8/FX_EUR) -> 2378.2047
A9: 5 | B9: Marketing | C9: Marketing manager (senior) | D9: SN | F9: 1 | G9: 4 | I9: 900000 | J9: N | K9: =IF(I9="",0,I9*(1+Employer_Charges)) -> 1170000 | L9: Prepares the launch; runs digital ads and partnerships. | M9: =IF(N(I9)=0,0,I9/FX_EUR) -> 1372.0412 | N9: =IF(N(K9)=0,0,K9/FX_EUR) -> 1783.6535
A10: 6 | B10: Marketing | C10: Marketing officer (junior) | D10: SN | F10: 1 | G10: 5 | I10: 400000 | J10: N | K10: =IF(I10="",0,I10*(1+Employer_Charges)) -> 520000 | L10: Content, social media, events. | M10: =IF(N(I10)=0,0,I10/FX_EUR) -> 609.79607 | N10: =IF(N(K10)=0,0,K10/FX_EUR) -> 792.73489
A11: 7 | B11: Leadership | C11: Country manager, Abidjan | D11: CI | F11: 1 | G11: =CI_Office_Start -> 18 | I11: 2800000 | J11: Y | K11: =IF(I11="",0,I11*(1+Employer_Charges)) -> 3640000 | L11: Joins when the Abidjan office opens. | M11: =IF(N(I11)=0,0,I11/FX_EUR) -> 4268.5725 | N11: =IF(N(K11)=0,0,K11/FX_EUR) -> 5549.1442
A12: 8 | B12: Compliance & risk | C12: Compliance officer (AML/CFT) | D12: SN | F12: 1 | G12: =SFD_Acq_Month -> 24 | I12: 1500000 | J12: Y | K12: =IF(I12="",0,I12*(1+Employer_Charges)) -> 1950000 | L12: Required once Tabax holds its own licence (SFD). | M12: =IF(N(I12)=0,0,I12/FX_EUR) -> 2286.7353 | N12: =IF(N(K12)=0,0,K12/FX_EUR) -> 2972.7558
A13: 9 | K13: =IF(I13="",0,I13*(1+Employer_Charges)) -> 0 | M13: =IF(N(I13)=0,0,I13/FX_EUR) -> 0 | N13: =IF(N(K13)=0,0,K13/FX_EUR) -> 0
A14: 10 | K14: =IF(I14="",0,I14*(1+Employer_Charges)) -> 0 | M14: =IF(N(I14)=0,0,I14/FX_EUR) -> 0 | N14: =IF(N(K14)=0,0,K14/FX_EUR) -> 0
A15: 11 | K15: =IF(I15="",0,I15*(1+Employer_Charges)) -> 0 | M15: =IF(N(I15)=0,0,I15/FX_EUR) -> 0 | N15: =IF(N(K15)=0,0,K15/FX_EUR) -> 0
A16: 12 | K16: =IF(I16="",0,I16*(1+Employer_Charges)) -> 0 | M16: =IF(N(I16)=0,0,I16/FX_EUR) -> 0 | N16: =IF(N(K16)=0,0,K16/FX_EUR) -> 0
A17: 13 | K17: =IF(I17="",0,I17*(1+Employer_Charges)) -> 0 | M17: =IF(N(I17)=0,0,I17/FX_EUR) -> 0 | N17: =IF(N(K17)=0,0,K17/FX_EUR) -> 0
A18: 14 | K18: =IF(I18="",0,I18*(1+Employer_Charges)) -> 0 | M18: =IF(N(I18)=0,0,I18/FX_EUR) -> 0 | N18: =IF(N(K18)=0,0,K18/FX_EUR) -> 0
A19: 15 | K19: =IF(I19="",0,I19*(1+Employer_Charges)) -> 0 | M19: =IF(N(I19)=0,0,I19/FX_EUR) -> 0 | N19: =IF(N(K19)=0,0,K19/FX_EUR) -> 0
A20: 16 | K20: =IF(I20="",0,I20*(1+Employer_Charges)) -> 0 | M20: =IF(N(I20)=0,0,I20/FX_EUR) -> 0 | N20: =IF(N(K20)=0,0,K20/FX_EUR) -> 0
A21: 17 | K21: =IF(I21="",0,I21*(1+Employer_Charges)) -> 0 | M21: =IF(N(I21)=0,0,I21/FX_EUR) -> 0 | N21: =IF(N(K21)=0,0,K21/FX_EUR) -> 0
A22: 18 | K22: =IF(I22="",0,I22*(1+Employer_Charges)) -> 0 | M22: =IF(N(I22)=0,0,I22/FX_EUR) -> 0 | N22: =IF(N(K22)=0,0,K22/FX_EUR) -> 0
A23: 19 | K23: =IF(I23="",0,I23*(1+Employer_Charges)) -> 0 | M23: =IF(N(I23)=0,0,I23/FX_EUR) -> 0 | N23: =IF(N(K23)=0,0,K23/FX_EUR) -> 0
A24: 20 | K24: =IF(I24="",0,I24*(1+Employer_Charges)) -> 0 | M24: =IF(N(I24)=0,0,I24/FX_EUR) -> 0 | N24: =IF(N(K24)=0,0,K24/FX_EUR) -> 0
... A32: 28 | K32: =IF(I32="",0,I32*(1+Employer_Charges)) -> 0 | M32: =IF(N(I32)=0,0,I32/FX_EUR) -> 0 | N32: =IF(N(K32)=0,0,K32/FX_EUR) -> 0
B34: Employer cost = gross salary × (1 + employer charges), 30% on Assumptions section 8. Customer support, developers, field sales reps and credit analysts grow with volume: see the Staff sheet and the ratios on Assumptions section 8.

Sheet Staff
A1: Staff
A2: Headcount and employer cost by month, from the hiring plan. Pay rises each year by the rate on Assumptions.
A3: Month # | D3: Total / end | E3: 1 | F3: =E3+1 -> 2 | G3: =F3+1 -> 3 | H3: =G3+1 -> 4 | I3: =H3+1 -> 5 | J3: =I3+1 -> 6 | K3: =J3+1 -> 7 | L3: =K3+1 -> 8 | M3: =L3+1 -> 9 | ... BL3: =BK3+1 -> 60
A4: Month | E4: =DATE(YEAR(Start_Date),MONTH(Start_Date)+E3-1,1) -> 46388 | F4: =DATE(YEAR(Start_Date),MONTH(Start_Date)+F3-1,1) -> 46419 | G4: =DATE(YEAR(Start_Date),MONTH(Start_Date)+G3-1,1) -> 46447 | H4: =DATE(YEAR(Start_Date),MONTH(Start_Date)+H3-1,1) -> 46478 | I4: =DATE(YEAR(Start_Date),MONTH(Start_Date)+I3-1,1) -> 46508 | J4: =DATE(YEAR(Start_Date),MONTH(Start_Date)+J3-1,1) -> 46539 | K4: =DATE(YEAR(Start_Date),MONTH(Start_Date)+K3-1,1) -> 46569 | L4: =DATE(YEAR(Start_Date),MONTH(Start_Date)+L3-1,1) -> 46600 | ... BL4: =DATE(YEAR(Start_Date),MONTH(Start_Date)+BL3-1,1) -> 48183
A5: Year | E5: =INT((E3-1)/12)+1 -> 1 | F5: =INT((F3-1)/12)+1 -> 1 | G5: =INT((G3-1)/12)+1 -> 1 | H5: =INT((H3-1)/12)+1 -> 1 | I5: =INT((I3-1)/12)+1 -> 1 | J5: =INT((J3-1)/12)+1 -> 1 | K5: =INT((K3-1)/12)+1 -> 1 | L5: =INT((L3-1)/12)+1 -> 1 | ... BL5: =INT((BL3-1)/12)+1 -> 5
A8: Headcount by hire line
A9: =IF('Hiring plan'!$C$5="","(spare line 1)",'Hiring plan'!$C$5&" · "&'Hiring plan'!$D$5) -> CEO (full salary from year 2) · SN | B9: people | D9: =MAX(E9:BL9) -> 1 | E9: =IF(AND(N('Hiring plan'!$F$5)>0,E$3>='Hiring plan'!$G$5,E$3<=IF('Hiring plan'!$H$5="",999,'Hiring plan'!$H$5)),'Hiring plan'!$F$5,0) -> 0 | F9: =IF(AND(N('Hiring plan'!$F$5)>0,F$3>='Hiring plan'!$G$5,F$3<=IF('Hiring plan'!$H$5="",999,'Hiring plan'!$H$5)),'Hiring plan'!$F$5,0) -> 0 | G9: =IF(AND(N('Hiring plan'!$F$5)>0,G$3>='Hiring plan'!$G$5,G$3<=IF('Hiring plan'!$H$5="",999,'Hiring plan'!$H$5)),'Hiring plan'!$F$5,0) -> 0 | H9: =IF(AND(N('Hiring plan'!$F$5)>0,H$3>='Hiring plan'!$G$5,H$3<=IF('Hiring plan'!$H$5="",999,'Hiring plan'!$H$5)),'Hiring plan'!$F$5,0) -> 0 | I9: =IF(AND(N('Hiring plan'!$F$5)>0,I$3>='Hiring plan'!$G$5,I$3<=IF('Hiring plan'!$H$5="",999,'Hiring plan'!$H$5)),'Hiring plan'!$F$5,0) -> 0 | J9: =IF(AND(N('Hiring plan'!$F$5)>0,J$3>='Hiring plan'!$G$5,J$3<=IF('Hiring plan'!$H$5="",999,'Hiring plan'!$H$5)),'Hiring plan'!$F$5,0) -> 0 | K9: =IF(AND(N('Hiring plan'!$F$5)>0,K$3>='Hiring plan'!$G$5,K$3<=IF('Hiring plan'!$H$5="",999,'Hiring plan'!$H$5)),'Hiring plan'!$F$5,0) -> 0 | L9: =IF(AND(N('Hiring plan'!$F$5)>0,L$3>='Hiring plan'!$G$5,L$3<=IF('Hiring plan'!$H$5="",999,'Hiring plan'!$H$5)),'Hiring plan'!$F$5,0) -> 0 | ... BL9: =IF(AND(N('Hiring plan'!$F$5)>0,BL$3>='Hiring plan'!$G$5,BL$3<=IF('Hiring plan'!$H$5="",999,'Hiring plan'!$H$5)),'Hiring plan'!$F$5,0) -> 1
A10: =IF('Hiring plan'!$C$6="","(spare line 2)",'Hiring plan'!$C$6&" · "&'Hiring plan'!$D$6) -> CTO (also codes) · SN | B10: people | D10: =MAX(E10:BL10) -> 1 | E10: =IF(AND(N('Hiring plan'!$F$6)>0,E$3>='Hiring plan'!$G$6,E$3<=IF('Hiring plan'!$H$6="",999,'Hiring plan'!$H$6)),'Hiring plan'!$F$6,0) -> 1 | F10: =IF(AND(N('Hiring plan'!$F$6)>0,F$3>='Hiring plan'!$G$6,F$3<=IF('Hiring plan'!$H$6="",999,'Hiring plan'!$H$6)),'Hiring plan'!$F$6,0) -> 1 | G10: =IF(AND(N('Hiring plan'!$F$6)>0,G$3>='Hiring plan'!$G$6,G$3<=IF('Hiring plan'!$H$6="",999,'Hiring plan'!$H$6)),'Hiring plan'!$F$6,0) -> 1 | H10: =IF(AND(N('Hiring plan'!$F$6)>0,H$3>='Hiring plan'!$G$6,H$3<=IF('Hiring plan'!$H$6="",999,'Hiring plan'!$H$6)),'Hiring plan'!$F$6,0) -> 1 | I10: =IF(AND(N('Hiring plan'!$F$6)>0,I$3>='Hiring plan'!$G$6,I$3<=IF('Hiring plan'!$H$6="",999,'Hiring plan'!$H$6)),'Hiring plan'!$F$6,0) -> 1 | J10: =IF(AND(N('Hiring plan'!$F$6)>0,J$3>='Hiring plan'!$G$6,J$3<=IF('Hiring plan'!$H$6="",999,'Hiring plan'!$H$6)),'Hiring plan'!$F$6,0) -> 1 | K10: =IF(AND(N('Hiring plan'!$F$6)>0,K$3>='Hiring plan'!$G$6,K$3<=IF('Hiring plan'!$H$6="",999,'Hiring plan'!$H$6)),'Hiring plan'!$F$6,0) -> 1 | L10: =IF(AND(N('Hiring plan'!$F$6)>0,L$3>='Hiring plan'!$G$6,L$3<=IF('Hiring plan'!$H$6="",999,'Hiring plan'!$H$6)),'Hiring plan'!$F$6,0) -> 1 | ... BL10: =IF(AND(N('Hiring plan'!$F$6)>0,BL$3>='Hiring plan'!$G$6,BL$3<=IF('Hiring plan'!$H$6="",999,'Hiring plan'!$H$6)),'Hiring plan'!$F$6,0) -> 1
A11: =IF('Hiring plan'!$C$7="","(spare line 3)",'Hiring plan'!$C$7&" · "&'Hiring plan'!$D$7) -> Financial expert (finance, partners, credit lead) · SN | B11: people | D11: =MAX(E11:BL11) -> 1 | E11: =IF(AND(N('Hiring plan'!$F$7)>0,E$3>='Hiring plan'!$G$7,E$3<=IF('Hiring plan'!$H$7="",999,'Hiring plan'!$H$7)),'Hiring plan'!$F$7,0) -> 1 | F11: =IF(AND(N('Hiring plan'!$F$7)>0,F$3>='Hiring plan'!$G$7,F$3<=IF('Hiring plan'!$H$7="",999,'Hiring plan'!$H$7)),'Hiring plan'!$F$7,0) -> 1 | G11: =IF(AND(N('Hiring plan'!$F$7)>0,G$3>='Hiring plan'!$G$7,G$3<=IF('Hiring plan'!$H$7="",999,'Hiring plan'!$H$7)),'Hiring plan'!$F$7,0) -> 1 | H11: =IF(AND(N('Hiring plan'!$F$7)>0,H$3>='Hiring plan'!$G$7,H$3<=IF('Hiring plan'!$H$7="",999,'Hiring plan'!$H$7)),'Hiring plan'!$F$7,0) -> 1 | I11: =IF(AND(N('Hiring plan'!$F$7)>0,I$3>='Hiring plan'!$G$7,I$3<=IF('Hiring plan'!$H$7="",999,'Hiring plan'!$H$7)),'Hiring plan'!$F$7,0) -> 1 | J11: =IF(AND(N('Hiring plan'!$F$7)>0,J$3>='Hiring plan'!$G$7,J$3<=IF('Hiring plan'!$H$7="",999,'Hiring plan'!$H$7)),'Hiring plan'!$F$7,0) -> 1 | K11: =IF(AND(N('Hiring plan'!$F$7)>0,K$3>='Hiring plan'!$G$7,K$3<=IF('Hiring plan'!$H$7="",999,'Hiring plan'!$H$7)),'Hiring plan'!$F$7,0) -> 1 | L11: =IF(AND(N('Hiring plan'!$F$7)>0,L$3>='Hiring plan'!$G$7,L$3<=IF('Hiring plan'!$H$7="",999,'Hiring plan'!$H$7)),'Hiring plan'!$F$7,0) -> 1 | ... BL11: =IF(AND(N('Hiring plan'!$F$7)>0,BL$3>='Hiring plan'!$G$7,BL$3<=IF('Hiring plan'!$H$7="",999,'Hiring plan'!$H$7)),'Hiring plan'!$F$7,0) -> 1
A12: =IF('Hiring plan'!$C$8="","(spare line 4)",'Hiring plan'!$C$8&" · "&'Hiring plan'!$D$8) -> Sales lead (also sells; incl. bonus) · SN | B12: people | D12: =MAX(E12:BL12) -> 1 | E12: =IF(AND(N('Hiring plan'!$F$8)>0,E$3>='Hiring plan'!$G$8,E$3<=IF('Hiring plan'!$H$8="",999,'Hiring plan'!$H$8)),'Hiring plan'!$F$8,0) -> 1 | F12: =IF(AND(N('Hiring plan'!$F$8)>0,F$3>='Hiring plan'!$G$8,F$3<=IF('Hiring plan'!$H$8="",999,'Hiring plan'!$H$8)),'Hiring plan'!$F$8,0) -> 1 | G12: =IF(AND(N('Hiring plan'!$F$8)>0,G$3>='Hiring plan'!$G$8,G$3<=IF('Hiring plan'!$H$8="",999,'Hiring plan'!$H$8)),'Hiring plan'!$F$8,0) -> 1 | H12: =IF(AND(N('Hiring plan'!$F$8)>0,H$3>='Hiring plan'!$G$8,H$3<=IF('Hiring plan'!$H$8="",999,'Hiring plan'!$H$8)),'Hiring plan'!$F$8,0) -> 1 | I12: =IF(AND(N('Hiring plan'!$F$8)>0,I$3>='Hiring plan'!$G$8,I$3<=IF('Hiring plan'!$H$8="",999,'Hiring plan'!$H$8)),'Hiring plan'!$F$8,0) -> 1 | J12: =IF(AND(N('Hiring plan'!$F$8)>0,J$3>='Hiring plan'!$G$8,J$3<=IF('Hiring plan'!$H$8="",999,'Hiring plan'!$H$8)),'Hiring plan'!$F$8,0) -> 1 | K12: =IF(AND(N('Hiring plan'!$F$8)>0,K$3>='Hiring plan'!$G$8,K$3<=IF('Hiring plan'!$H$8="",999,'Hiring plan'!$H$8)),'Hiring plan'!$F$8,0) -> 1 | L12: =IF(AND(N('Hiring plan'!$F$8)>0,L$3>='Hiring plan'!$G$8,L$3<=IF('Hiring plan'!$H$8="",999,'Hiring plan'!$H$8)),'Hiring plan'!$F$8,0) -> 1 | ... BL12: =IF(AND(N('Hiring plan'!$F$8)>0,BL$3>='Hiring plan'!$G$8,BL$3<=IF('Hiring plan'!$H$8="",999,'Hiring plan'!$H$8)),'Hiring plan'!$F$8,0) -> 1
A13: =IF('Hiring plan'!$C$9="","(spare line 5)",'Hiring plan'!$C$9&" · "&'Hiring plan'!$D$9) -> Marketing manager (senior) · SN | B13: people | D13: =MAX(E13:BL13) -> 1 | E13: =IF(AND(N('Hiring plan'!$F$9)>0,E$3>='Hiring plan'!$G$9,E$3<=IF('Hiring plan'!$H$9="",999,'Hiring plan'!$H$9)),'Hiring plan'!$F$9,0) -> 0 | F13: =IF(AND(N('Hiring plan'!$F$9)>0,F$3>='Hiring plan'!$G$9,F$3<=IF('Hiring plan'!$H$9="",999,'Hiring plan'!$H$9)),'Hiring plan'!$F$9,0) -> 0 | G13: =IF(AND(N('Hiring plan'!$F$9)>0,G$3>='Hiring plan'!$G$9,G$3<=IF('Hiring plan'!$H$9="",999,'Hiring plan'!$H$9)),'Hiring plan'!$F$9,0) -> 0 | H13: =IF(AND(N('Hiring plan'!$F$9)>0,H$3>='Hiring plan'!$G$9,H$3<=IF('Hiring plan'!$H$9="",999,'Hiring plan'!$H$9)),'Hiring plan'!$F$9,0) -> 1 | I13: =IF(AND(N('Hiring plan'!$F$9)>0,I$3>='Hiring plan'!$G$9,I$3<=IF('Hiring plan'!$H$9="",999,'Hiring plan'!$H$9)),'Hiring plan'!$F$9,0) -> 1 | J13: =IF(AND(N('Hiring plan'!$F$9)>0,J$3>='Hiring plan'!$G$9,J$3<=IF('Hiring plan'!$H$9="",999,'Hiring plan'!$H$9)),'Hiring plan'!$F$9,0) -> 1 | K13: =IF(AND(N('Hiring plan'!$F$9)>0,K$3>='Hiring plan'!$G$9,K$3<=IF('Hiring plan'!$H$9="",999,'Hiring plan'!$H$9)),'Hiring plan'!$F$9,0) -> 1 | L13: =IF(AND(N('Hiring plan'!$F$9)>0,L$3>='Hiring plan'!$G$9,L$3<=IF('Hiring plan'!$H$9="",999,'Hiring plan'!$H$9)),'Hiring plan'!$F$9,0) -> 1 | ... BL13: =IF(AND(N('Hiring plan'!$F$9)>0,BL$3>='Hiring plan'!$G$9,BL$3<=IF('Hiring plan'!$H$9="",999,'Hiring plan'!$H$9)),'Hiring plan'!$F$9,0) -> 1
A14: =IF('Hiring plan'!$C$10="","(spare line 6)",'Hiring plan'!$C$10&" · "&'Hiring plan'!$D$10) -> Marketing officer (junior) · SN | B14: people | D14: =MAX(E14:BL14) -> 1 | E14: =IF(AND(N('Hiring plan'!$F$10)>0,E$3>='Hiring plan'!$G$10,E$3<=IF('Hiring plan'!$H$10="",999,'Hiring plan'!$H$10)),'Hiring plan'!$F$10,0) -> 0 | F14: =IF(AND(N('Hiring plan'!$F$10)>0,F$3>='Hiring plan'!$G$10,F$3<=IF('Hiring plan'!$H$10="",999,'Hiring plan'!$H$10)),'Hiring plan'!$F$10,0) -> 0 | G14: =IF(AND(N('Hiring plan'!$F$10)>0,G$3>='Hiring plan'!$G$10,G$3<=IF('Hiring plan'!$H$10="",999,'Hiring plan'!$H$10)),'Hiring plan'!$F$10,0) -> 0 | H14: =IF(AND(N('Hiring plan'!$F$10)>0,H$3>='Hiring plan'!$G$10,H$3<=IF('Hiring plan'!$H$10="",999,'Hiring plan'!$H$10)),'Hiring plan'!$F$10,0) -> 0 | I14: =IF(AND(N('Hiring plan'!$F$10)>0,I$3>='Hiring plan'!$G$10,I$3<=IF('Hiring plan'!$H$10="",999,'Hiring plan'!$H$10)),'Hiring plan'!$F$10,0) -> 1 | J14: =IF(AND(N('Hiring plan'!$F$10)>0,J$3>='Hiring plan'!$G$10,J$3<=IF('Hiring plan'!$H$10="",999,'Hiring plan'!$H$10)),'Hiring plan'!$F$10,0) -> 1 | K14: =IF(AND(N('Hiring plan'!$F$10)>0,K$3>='Hiring plan'!$G$10,K$3<=IF('Hiring plan'!$H$10="",999,'Hiring plan'!$H$10)),'Hiring plan'!$F$10,0) -> 1 | L14: =IF(AND(N('Hiring plan'!$F$10)>0,L$3>='Hiring plan'!$G$10,L$3<=IF('Hiring plan'!$H$10="",999,'Hiring plan'!$H$10)),'Hiring plan'!$F$10,0) -> 1 | ... BL14: =IF(AND(N('Hiring plan'!$F$10)>0,BL$3>='Hiring plan'!$G$10,BL$3<=IF('Hiring plan'!$H$10="",999,'Hiring plan'!$H$10)),'Hiring plan'!$F$10,0) -> 1
A15: =IF('Hiring plan'!$C$11="","(spare line 7)",'Hiring plan'!$C$11&" · "&'Hiring plan'!$D$11) -> Country manager, Abidjan · CI | B15: people | D15: =MAX(E15:BL15) -> 1 | E15: =IF(AND(N('Hiring plan'!$F$11)>0,E$3>='Hiring plan'!$G$11,E$3<=IF('Hiring plan'!$H$11="",999,'Hiring plan'!$H$11)),'Hiring plan'!$F$11,0) -> 0 | F15: =IF(AND(N('Hiring plan'!$F$11)>0,F$3>='Hiring plan'!$G$11,F$3<=IF('Hiring plan'!$H$11="",999,'Hiring plan'!$H$11)),'Hiring plan'!$F$11,0) -> 0 | G15: =IF(AND(N('Hiring plan'!$F$11)>0,G$3>='Hiring plan'!$G$11,G$3<=IF('Hiring plan'!$H$11="",999,'Hiring plan'!$H$11)),'Hiring plan'!$F$11,0) -> 0 | H15: =IF(AND(N('Hiring plan'!$F$11)>0,H$3>='Hiring plan'!$G$11,H$3<=IF('Hiring plan'!$H$11="",999,'Hiring plan'!$H$11)),'Hiring plan'!$F$11,0) -> 0 | I15: =IF(AND(N('Hiring plan'!$F$11)>0,I$3>='Hiring plan'!$G$11,I$3<=IF('Hiring plan'!$H$11="",999,'Hiring plan'!$H$11)),'Hiring plan'!$F$11,0) -> 0 | J15: =IF(AND(N('Hiring plan'!$F$11)>0,J$3>='Hiring plan'!$G$11,J$3<=IF('Hiring plan'!$H$11="",999,'Hiring plan'!$H$11)),'Hiring plan'!$F$11,0) -> 0 | K15: =IF(AND(N('Hiring plan'!$F$11)>0,K$3>='Hiring plan'!$G$11,K$3<=IF('Hiring plan'!$H$11="",999,'Hiring plan'!$H$11)),'Hiring plan'!$F$11,0) -> 0 | L15: =IF(AND(N('Hiring plan'!$F$11)>0,L$3>='Hiring plan'!$G$11,L$3<=IF('Hiring plan'!$H$11="",999,'Hiring plan'!$H$11)),'Hiring plan'!$F$11,0) -> 0 | ... BL15: =IF(AND(N('Hiring plan'!$F$11)>0,BL$3>='Hiring plan'!$G$11,BL$3<=IF('Hiring plan'!$H$11="",999,'Hiring plan'!$H$11)),'Hiring plan'!$F$11,0) -> 1
A16: =IF('Hiring plan'!$C$12="","(spare line 8)",'Hiring plan'!$C$12&" · "&'Hiring plan'!$D$12) -> Compliance officer (AML/CFT) · SN | B16: people | D16: =MAX(E16:BL16) -> 1 | E16: =IF(AND(N('Hiring plan'!$F$12)>0,E$3>='Hiring plan'!$G$12,E$3<=IF('Hiring plan'!$H$12="",999,'Hiring plan'!$H$12)),'Hiring plan'!$F$12,0) -> 0 | F16: =IF(AND(N('Hiring plan'!$F$12)>0,F$3>='Hiring plan'!$G$12,F$3<=IF('Hiring plan'!$H$12="",999,'Hiring plan'!$H$12)),'Hiring plan'!$F$12,0) -> 0 | G16: =IF(AND(N('Hiring plan'!$F$12)>0,G$3>='Hiring plan'!$G$12,G$3<=IF('Hiring plan'!$H$12="",999,'Hiring plan'!$H$12)),'Hiring plan'!$F$12,0) -> 0 | H16: =IF(AND(N('Hiring plan'!$F$12)>0,H$3>='Hiring plan'!$G$12,H$3<=IF('Hiring plan'!$H$12="",999,'Hiring plan'!$H$12)),'Hiring plan'!$F$12,0) -> 0 | I16: =IF(AND(N('Hiring plan'!$F$12)>0,I$3>='Hiring plan'!$G$12,I$3<=IF('Hiring plan'!$H$12="",999,'Hiring plan'!$H$12)),'Hiring plan'!$F$12,0) -> 0 | J16: =IF(AND(N('Hiring plan'!$F$12)>0,J$3>='Hiring plan'!$G$12,J$3<=IF('Hiring plan'!$H$12="",999,'Hiring plan'!$H$12)),'Hiring plan'!$F$12,0) -> 0 | K16: =IF(AND(N('Hiring plan'!$F$12)>0,K$3>='Hiring plan'!$G$12,K$3<=IF('Hiring plan'!$H$12="",999,'Hiring plan'!$H$12)),'Hiring plan'!$F$12,0) -> 0 | L16: =IF(AND(N('Hiring plan'!$F$12)>0,L$3>='Hiring plan'!$G$12,L$3<=IF('Hiring plan'!$H$12="",999,'Hiring plan'!$H$12)),'Hiring plan'!$F$12,0) -> 0 | ... BL16: =IF(AND(N('Hiring plan'!$F$12)>0,BL$3>='Hiring plan'!$G$12,BL$3<=IF('Hiring plan'!$H$12="",999,'Hiring plan'!$H$12)),'Hiring plan'!$F$12,0) -> 1
A17: =IF('Hiring plan'!$C$13="","(spare line 9)",'Hiring plan'!$C$13&" · "&'Hiring plan'!$D$13) -> (spare line 9) | B17: people | D17: =MAX(E17:BL17) -> 0 | E17: =IF(AND(N('Hiring plan'!$F$13)>0,E$3>='Hiring plan'!$G$13,E$3<=IF('Hiring plan'!$H$13="",999,'Hiring plan'!$H$13)),'Hiring plan'!$F$13,0) -> 0 | F17: =IF(AND(N('Hiring plan'!$F$13)>0,F$3>='Hiring plan'!$G$13,F$3<=IF('Hiring plan'!$H$13="",999,'Hiring plan'!$H$13)),'Hiring plan'!$F$13,0) -> 0 | G17: =IF(AND(N('Hiring plan'!$F$13)>0,G$3>='Hiring plan'!$G$13,G$3<=IF('Hiring plan'!$H$13="",999,'Hiring plan'!$H$13)),'Hiring plan'!$F$13,0) -> 0 | H17: =IF(AND(N('Hiring plan'!$F$13)>0,H$3>='Hiring plan'!$G$13,H$3<=IF('Hiring plan'!$H$13="",999,'Hiring plan'!$H$13)),'Hiring plan'!$F$13,0) -> 0 | I17: =IF(AND(N('Hiring plan'!$F$13)>0,I$3>='Hiring plan'!$G$13,I$3<=IF('Hiring plan'!$H$13="",999,'Hiring plan'!$H$13)),'Hiring plan'!$F$13,0) -> 0 | J17: =IF(AND(N('Hiring plan'!$F$13)>0,J$3>='Hiring plan'!$G$13,J$3<=IF('Hiring plan'!$H$13="",999,'Hiring plan'!$H$13)),'Hiring plan'!$F$13,0) -> 0 | K17: =IF(AND(N('Hiring plan'!$F$13)>0,K$3>='Hiring plan'!$G$13,K$3<=IF('Hiring plan'!$H$13="",999,'Hiring plan'!$H$13)),'Hiring plan'!$F$13,0) -> 0 | L17: =IF(AND(N('Hiring plan'!$F$13)>0,L$3>='Hiring plan'!$G$13,L$3<=IF('Hiring plan'!$H$13="",999,'Hiring plan'!$H$13)),'Hiring plan'!$F$13,0) -> 0 | ... BL17: =IF(AND(N('Hiring plan'!$F$13)>0,BL$3>='Hiring plan'!$G$13,BL$3<=IF('Hiring plan'!$H$13="",999,'Hiring plan'!$H$13)),'Hiring plan'!$F$13,0) -> 0
A18: =IF('Hiring plan'!$C$14="","(spare line 10)",'Hiring plan'!$C$14&" · "&'Hiring plan'!$D$14) -> (spare line 10) | B18: people | D18: =MAX(E18:BL18) -> 0 | E18: =IF(AND(N('Hiring plan'!$F$14)>0,E$3>='Hiring plan'!$G$14,E$3<=IF('Hiring plan'!$H$14="",999,'Hiring plan'!$H$14)),'Hiring plan'!$F$14,0) -> 0 | F18: =IF(AND(N('Hiring plan'!$F$14)>0,F$3>='Hiring plan'!$G$14,F$3<=IF('Hiring plan'!$H$14="",999,'Hiring plan'!$H$14)),'Hiring plan'!$F$14,0) -> 0 | G18: =IF(AND(N('Hiring plan'!$F$14)>0,G$3>='Hiring plan'!$G$14,G$3<=IF('Hiring plan'!$H$14="",999,'Hiring plan'!$H$14)),'Hiring plan'!$F$14,0) -> 0 | H18: =IF(AND(N('Hiring plan'!$F$14)>0,H$3>='Hiring plan'!$G$14,H$3<=IF('Hiring plan'!$H$14="",999,'Hiring plan'!$H$14)),'Hiring plan'!$F$14,0) -> 0 | I18: =IF(AND(N('Hiring plan'!$F$14)>0,I$3>='Hiring plan'!$G$14,I$3<=IF('Hiring plan'!$H$14="",999,'Hiring plan'!$H$14)),'Hiring plan'!$F$14,0) -> 0 | J18: =IF(AND(N('Hiring plan'!$F$14)>0,J$3>='Hiring plan'!$G$14,J$3<=IF('Hiring plan'!$H$14="",999,'Hiring plan'!$H$14)),'Hiring plan'!$F$14,0) -> 0 | K18: =IF(AND(N('Hiring plan'!$F$14)>0,K$3>='Hiring plan'!$G$14,K$3<=IF('Hiring plan'!$H$14="",999,'Hiring plan'!$H$14)),'Hiring plan'!$F$14,0) -> 0 | L18: =IF(AND(N('Hiring plan'!$F$14)>0,L$3>='Hiring plan'!$G$14,L$3<=IF('Hiring plan'!$H$14="",999,'Hiring plan'!$H$14)),'Hiring plan'!$F$14,0) -> 0 | ... BL18: =IF(AND(N('Hiring plan'!$F$14)>0,BL$3>='Hiring plan'!$G$14,BL$3<=IF('Hiring plan'!$H$14="",999,'Hiring plan'!$H$14)),'Hiring plan'!$F$14,0) -> 0
A19: =IF('Hiring plan'!$C$15="","(spare line 11)",'Hiring plan'!$C$15&" · "&'Hiring plan'!$D$15) -> (spare line 11) | B19: people | D19: =MAX(E19:BL19) -> 0 | E19: =IF(AND(N('Hiring plan'!$F$15)>0,E$3>='Hiring plan'!$G$15,E$3<=IF('Hiring plan'!$H$15="",999,'Hiring plan'!$H$15)),'Hiring plan'!$F$15,0) -> 0 | F19: =IF(AND(N('Hiring plan'!$F$15)>0,F$3>='Hiring plan'!$G$15,F$3<=IF('Hiring plan'!$H$15="",999,'Hiring plan'!$H$15)),'Hiring plan'!$F$15,0) -> 0 | G19: =IF(AND(N('Hiring plan'!$F$15)>0,G$3>='Hiring plan'!$G$15,G$3<=IF('Hiring plan'!$H$15="",999,'Hiring plan'!$H$15)),'Hiring plan'!$F$15,0) -> 0 | H19: =IF(AND(N('Hiring plan'!$F$15)>0,H$3>='Hiring plan'!$G$15,H$3<=IF('Hiring plan'!$H$15="",999,'Hiring plan'!$H$15)),'Hiring plan'!$F$15,0) -> 0 | I19: =IF(AND(N('Hiring plan'!$F$15)>0,I$3>='Hiring plan'!$G$15,I$3<=IF('Hiring plan'!$H$15="",999,'Hiring plan'!$H$15)),'Hiring plan'!$F$15,0) -> 0 | J19: =IF(AND(N('Hiring plan'!$F$15)>0,J$3>='Hiring plan'!$G$15,J$3<=IF('Hiring plan'!$H$15="",999,'Hiring plan'!$H$15)),'Hiring plan'!$F$15,0) -> 0 | K19: =IF(AND(N('Hiring plan'!$F$15)>0,K$3>='Hiring plan'!$G$15,K$3<=IF('Hiring plan'!$H$15="",999,'Hiring plan'!$H$15)),'Hiring plan'!$F$15,0) -> 0 | L19: =IF(AND(N('Hiring plan'!$F$15)>0,L$3>='Hiring plan'!$G$15,L$3<=IF('Hiring plan'!$H$15="",999,'Hiring plan'!$H$15)),'Hiring plan'!$F$15,0) -> 0 | ... BL19: =IF(AND(N('Hiring plan'!$F$15)>0,BL$3>='Hiring plan'!$G$15,BL$3<=IF('Hiring plan'!$H$15="",999,'Hiring plan'!$H$15)),'Hiring plan'!$F$15,0) -> 0
A20: =IF('Hiring plan'!$C$16="","(spare line 12)",'Hiring plan'!$C$16&" · "&'Hiring plan'!$D$16) -> (spare line 12) | B20: people | D20: =MAX(E20:BL20) -> 0 | E20: =IF(AND(N('Hiring plan'!$F$16)>0,E$3>='Hiring plan'!$G$16,E$3<=IF('Hiring plan'!$H$16="",999,'Hiring plan'!$H$16)),'Hiring plan'!$F$16,0) -> 0 | F20: =IF(AND(N('Hiring plan'!$F$16)>0,F$3>='Hiring plan'!$G$16,F$3<=IF('Hiring plan'!$H$16="",999,'Hiring plan'!$H$16)),'Hiring plan'!$F$16,0) -> 0 | G20: =IF(AND(N('Hiring plan'!$F$16)>0,G$3>='Hiring plan'!$G$16,G$3<=IF('Hiring plan'!$H$16="",999,'Hiring plan'!$H$16)),'Hiring plan'!$F$16,0) -> 0 | H20: =IF(AND(N('Hiring plan'!$F$16)>0,H$3>='Hiring plan'!$G$16,H$3<=IF('Hiring plan'!$H$16="",999,'Hiring plan'!$H$16)),'Hiring plan'!$F$16,0) -> 0 | I20: =IF(AND(N('Hiring plan'!$F$16)>0,I$3>='Hiring plan'!$G$16,I$3<=IF('Hiring plan'!$H$16="",999,'Hiring plan'!$H$16)),'Hiring plan'!$F$16,0) -> 0 | J20: =IF(AND(N('Hiring plan'!$F$16)>0,J$3>='Hiring plan'!$G$16,J$3<=IF('Hiring plan'!$H$16="",999,'Hiring plan'!$H$16)),'Hiring plan'!$F$16,0) -> 0 | K20: =IF(AND(N('Hiring plan'!$F$16)>0,K$3>='Hiring plan'!$G$16,K$3<=IF('Hiring plan'!$H$16="",999,'Hiring plan'!$H$16)),'Hiring plan'!$F$16,0) -> 0 | L20: =IF(AND(N('Hiring plan'!$F$16)>0,L$3>='Hiring plan'!$G$16,L$3<=IF('Hiring plan'!$H$16="",999,'Hiring plan'!$H$16)),'Hiring plan'!$F$16,0) -> 0 | ... BL20: =IF(AND(N('Hiring plan'!$F$16)>0,BL$3>='Hiring plan'!$G$16,BL$3<=IF('Hiring plan'!$H$16="",999,'Hiring plan'!$H$16)),'Hiring plan'!$F$16,0) -> 0
A21: =IF('Hiring plan'!$C$17="","(spare line 13)",'Hiring plan'!$C$17&" · "&'Hiring plan'!$D$17) -> (spare line 13) | B21: people | D21: =MAX(E21:BL21) -> 0 | E21: =IF(AND(N('Hiring plan'!$F$17)>0,E$3>='Hiring plan'!$G$17,E$3<=IF('Hiring plan'!$H$17="",999,'Hiring plan'!$H$17)),'Hiring plan'!$F$17,0) -> 0 | F21: =IF(AND(N('Hiring plan'!$F$17)>0,F$3>='Hiring plan'!$G$17,F$3<=IF('Hiring plan'!$H$17="",999,'Hiring plan'!$H$17)),'Hiring plan'!$F$17,0) -> 0 | G21: =IF(AND(N('Hiring plan'!$F$17)>0,G$3>='Hiring plan'!$G$17,G$3<=IF('Hiring plan'!$H$17="",999,'Hiring plan'!$H$17)),'Hiring plan'!$F$17,0) -> 0 | H21: =IF(AND(N('Hiring plan'!$F$17)>0,H$3>='Hiring plan'!$G$17,H$3<=IF('Hiring plan'!$H$17="",999,'Hiring plan'!$H$17)),'Hiring plan'!$F$17,0) -> 0 | I21: =IF(AND(N('Hiring plan'!$F$17)>0,I$3>='Hiring plan'!$G$17,I$3<=IF('Hiring plan'!$H$17="",999,'Hiring plan'!$H$17)),'Hiring plan'!$F$17,0) -> 0 | J21: =IF(AND(N('Hiring plan'!$F$17)>0,J$3>='Hiring plan'!$G$17,J$3<=IF('Hiring plan'!$H$17="",999,'Hiring plan'!$H$17)),'Hiring plan'!$F$17,0) -> 0 | K21: =IF(AND(N('Hiring plan'!$F$17)>0,K$3>='Hiring plan'!$G$17,K$3<=IF('Hiring plan'!$H$17="",999,'Hiring plan'!$H$17)),'Hiring plan'!$F$17,0) -> 0 | L21: =IF(AND(N('Hiring plan'!$F$17)>0,L$3>='Hiring plan'!$G$17,L$3<=IF('Hiring plan'!$H$17="",999,'Hiring plan'!$H$17)),'Hiring plan'!$F$17,0) -> 0 | ... BL21: =IF(AND(N('Hiring plan'!$F$17)>0,BL$3>='Hiring plan'!$G$17,BL$3<=IF('Hiring plan'!$H$17="",999,'Hiring plan'!$H$17)),'Hiring plan'!$F$17,0) -> 0
A22: =IF('Hiring plan'!$C$18="","(spare line 14)",'Hiring plan'!$C$18&" · "&'Hiring plan'!$D$18) -> (spare line 14) | B22: people | D22: =MAX(E22:BL22) -> 0 | E22: =IF(AND(N('Hiring plan'!$F$18)>0,E$3>='Hiring plan'!$G$18,E$3<=IF('Hiring plan'!$H$18="",999,'Hiring plan'!$H$18)),'Hiring plan'!$F$18,0) -> 0 | F22: =IF(AND(N('Hiring plan'!$F$18)>0,F$3>='Hiring plan'!$G$18,F$3<=IF('Hiring plan'!$H$18="",999,'Hiring plan'!$H$18)),'Hiring plan'!$F$18,0) -> 0 | G22: =IF(AND(N('Hiring plan'!$F$18)>0,G$3>='Hiring plan'!$G$18,G$3<=IF('Hiring plan'!$H$18="",999,'Hiring plan'!$H$18)),'Hiring plan'!$F$18,0) -> 0 | H22: =IF(AND(N('Hiring plan'!$F$18)>0,H$3>='Hiring plan'!$G$18,H$3<=IF('Hiring plan'!$H$18="",999,'Hiring plan'!$H$18)),'Hiring plan'!$F$18,0) -> 0 | I22: =IF(AND(N('Hiring plan'!$F$18)>0,I$3>='Hiring plan'!$G$18,I$3<=IF('Hiring plan'!$H$18="",999,'Hiring plan'!$H$18)),'Hiring plan'!$F$18,0) -> 0 | J22: =IF(AND(N('Hiring plan'!$F$18)>0,J$3>='Hiring plan'!$G$18,J$3<=IF('Hiring plan'!$H$18="",999,'Hiring plan'!$H$18)),'Hiring plan'!$F$18,0) -> 0 | K22: =IF(AND(N('Hiring plan'!$F$18)>0,K$3>='Hiring plan'!$G$18,K$3<=IF('Hiring plan'!$H$18="",999,'Hiring plan'!$H$18)),'Hiring plan'!$F$18,0) -> 0 | L22: =IF(AND(N('Hiring plan'!$F$18)>0,L$3>='Hiring plan'!$G$18,L$3<=IF('Hiring plan'!$H$18="",999,'Hiring plan'!$H$18)),'Hiring plan'!$F$18,0) -> 0 | ... BL22: =IF(AND(N('Hiring plan'!$F$18)>0,BL$3>='Hiring plan'!$G$18,BL$3<=IF('Hiring plan'!$H$18="",999,'Hiring plan'!$H$18)),'Hiring plan'!$F$18,0) -> 0
A23: =IF('Hiring plan'!$C$19="","(spare line 15)",'Hiring plan'!$C$19&" · "&'Hiring plan'!$D$19) -> (spare line 15) | B23: people | D23: =MAX(E23:BL23) -> 0 | E23: =IF(AND(N('Hiring plan'!$F$19)>0,E$3>='Hiring plan'!$G$19,E$3<=IF('Hiring plan'!$H$19="",999,'Hiring plan'!$H$19)),'Hiring plan'!$F$19,0) -> 0 | F23: =IF(AND(N('Hiring plan'!$F$19)>0,F$3>='Hiring plan'!$G$19,F$3<=IF('Hiring plan'!$H$19="",999,'Hiring plan'!$H$19)),'Hiring plan'!$F$19,0) -> 0 | G23: =IF(AND(N('Hiring plan'!$F$19)>0,G$3>='Hiring plan'!$G$19,G$3<=IF('Hiring plan'!$H$19="",999,'Hiring plan'!$H$19)),'Hiring plan'!$F$19,0) -> 0 | H23: =IF(AND(N('Hiring plan'!$F$19)>0,H$3>='Hiring plan'!$G$19,H$3<=IF('Hiring plan'!$H$19="",999,'Hiring plan'!$H$19)),'Hiring plan'!$F$19,0) -> 0 | I23: =IF(AND(N('Hiring plan'!$F$19)>0,I$3>='Hiring plan'!$G$19,I$3<=IF('Hiring plan'!$H$19="",999,'Hiring plan'!$H$19)),'Hiring plan'!$F$19,0) -> 0 | J23: =IF(AND(N('Hiring plan'!$F$19)>0,J$3>='Hiring plan'!$G$19,J$3<=IF('Hiring plan'!$H$19="",999,'Hiring plan'!$H$19)),'Hiring plan'!$F$19,0) -> 0 | K23: =IF(AND(N('Hiring plan'!$F$19)>0,K$3>='Hiring plan'!$G$19,K$3<=IF('Hiring plan'!$H$19="",999,'Hiring plan'!$H$19)),'Hiring plan'!$F$19,0) -> 0 | L23: =IF(AND(N('Hiring plan'!$F$19)>0,L$3>='Hiring plan'!$G$19,L$3<=IF('Hiring plan'!$H$19="",999,'Hiring plan'!$H$19)),'Hiring plan'!$F$19,0) -> 0 | ... BL23: =IF(AND(N('Hiring plan'!$F$19)>0,BL$3>='Hiring plan'!$G$19,BL$3<=IF('Hiring plan'!$H$19="",999,'Hiring plan'!$H$19)),'Hiring plan'!$F$19,0) -> 0
A24: =IF('Hiring plan'!$C$20="","(spare line 16)",'Hiring plan'!$C$20&" · "&'Hiring plan'!$D$20) -> (spare line 16) | B24: people | D24: =MAX(E24:BL24) -> 0 | E24: =IF(AND(N('Hiring plan'!$F$20)>0,E$3>='Hiring plan'!$G$20,E$3<=IF('Hiring plan'!$H$20="",999,'Hiring plan'!$H$20)),'Hiring plan'!$F$20,0) -> 0 | F24: =IF(AND(N('Hiring plan'!$F$20)>0,F$3>='Hiring plan'!$G$20,F$3<=IF('Hiring plan'!$H$20="",999,'Hiring plan'!$H$20)),'Hiring plan'!$F$20,0) -> 0 | G24: =IF(AND(N('Hiring plan'!$F$20)>0,G$3>='Hiring plan'!$G$20,G$3<=IF('Hiring plan'!$H$20="",999,'Hiring plan'!$H$20)),'Hiring plan'!$F$20,0) -> 0 | H24: =IF(AND(N('Hiring plan'!$F$20)>0,H$3>='Hiring plan'!$G$20,H$3<=IF('Hiring plan'!$H$20="",999,'Hiring plan'!$H$20)),'Hiring plan'!$F$20,0) -> 0 | I24: =IF(AND(N('Hiring plan'!$F$20)>0,I$3>='Hiring plan'!$G$20,I$3<=IF('Hiring plan'!$H$20="",999,'Hiring plan'!$H$20)),'Hiring plan'!$F$20,0) -> 0 | J24: =IF(AND(N('Hiring plan'!$F$20)>0,J$3>='Hiring plan'!$G$20,J$3<=IF('Hiring plan'!$H$20="",999,'Hiring plan'!$H$20)),'Hiring plan'!$F$20,0) -> 0 | K24: =IF(AND(N('Hiring plan'!$F$20)>0,K$3>='Hiring plan'!$G$20,K$3<=IF('Hiring plan'!$H$20="",999,'Hiring plan'!$H$20)),'Hiring plan'!$F$20,0) -> 0 | L24: =IF(AND(N('Hiring plan'!$F$20)>0,L$3>='Hiring plan'!$G$20,L$3<=IF('Hiring plan'!$H$20="",999,'Hiring plan'!$H$20)),'Hiring plan'!$F$20,0) -> 0 | ... BL24: =IF(AND(N('Hiring plan'!$F$20)>0,BL$3>='Hiring plan'!$G$20,BL$3<=IF('Hiring plan'!$H$20="",999,'Hiring plan'!$H$20)),'Hiring plan'!$F$20,0) -> 0
A25: =IF('Hiring plan'!$C$21="","(spare line 17)",'Hiring plan'!$C$21&" · "&'Hiring plan'!$D$21) -> (spare line 17) | B25: people | D25: =MAX(E25:BL25) -> 0 | E25: =IF(AND(N('Hiring plan'!$F$21)>0,E$3>='Hiring plan'!$G$21,E$3<=IF('Hiring plan'!$H$21="",999,'Hiring plan'!$H$21)),'Hiring plan'!$F$21,0) -> 0 | F25: =IF(AND(N('Hiring plan'!$F$21)>0,F$3>='Hiring plan'!$G$21,F$3<=IF('Hiring plan'!$H$21="",999,'Hiring plan'!$H$21)),'Hiring plan'!$F$21,0) -> 0 | G25: =IF(AND(N('Hiring plan'!$F$21)>0,G$3>='Hiring plan'!$G$21,G$3<=IF('Hiring plan'!$H$21="",999,'Hiring plan'!$H$21)),'Hiring plan'!$F$21,0) -> 0 | H25: =IF(AND(N('Hiring plan'!$F$21)>0,H$3>='Hiring plan'!$G$21,H$3<=IF('Hiring plan'!$H$21="",999,'Hiring plan'!$H$21)),'Hiring plan'!$F$21,0) -> 0 | I25: =IF(AND(N('Hiring plan'!$F$21)>0,I$3>='Hiring plan'!$G$21,I$3<=IF('Hiring plan'!$H$21="",999,'Hiring plan'!$H$21)),'Hiring plan'!$F$21,0) -> 0 | J25: =IF(AND(N('Hiring plan'!$F$21)>0,J$3>='Hiring plan'!$G$21,J$3<=IF('Hiring plan'!$H$21="",999,'Hiring plan'!$H$21)),'Hiring plan'!$F$21,0) -> 0 | K25: =IF(AND(N('Hiring plan'!$F$21)>0,K$3>='Hiring plan'!$G$21,K$3<=IF('Hiring plan'!$H$21="",999,'Hiring plan'!$H$21)),'Hiring plan'!$F$21,0) -> 0 | L25: =IF(AND(N('Hiring plan'!$F$21)>0,L$3>='Hiring plan'!$G$21,L$3<=IF('Hiring plan'!$H$21="",999,'Hiring plan'!$H$21)),'Hiring plan'!$F$21,0) -> 0 | ... BL25: =IF(AND(N('Hiring plan'!$F$21)>0,BL$3>='Hiring plan'!$G$21,BL$3<=IF('Hiring plan'!$H$21="",999,'Hiring plan'!$H$21)),'Hiring plan'!$F$21,0) -> 0
A26: =IF('Hiring plan'!$C$22="","(spare line 18)",'Hiring plan'!$C$22&" · "&'Hiring plan'!$D$22) -> (spare line 18) | B26: people | D26: =MAX(E26:BL26) -> 0 | E26: =IF(AND(N('Hiring plan'!$F$22)>0,E$3>='Hiring plan'!$G$22,E$3<=IF('Hiring plan'!$H$22="",999,'Hiring plan'!$H$22)),'Hiring plan'!$F$22,0) -> 0 | F26: =IF(AND(N('Hiring plan'!$F$22)>0,F$3>='Hiring plan'!$G$22,F$3<=IF('Hiring plan'!$H$22="",999,'Hiring plan'!$H$22)),'Hiring plan'!$F$22,0) -> 0 | G26: =IF(AND(N('Hiring plan'!$F$22)>0,G$3>='Hiring plan'!$G$22,G$3<=IF('Hiring plan'!$H$22="",999,'Hiring plan'!$H$22)),'Hiring plan'!$F$22,0) -> 0 | H26: =IF(AND(N('Hiring plan'!$F$22)>0,H$3>='Hiring plan'!$G$22,H$3<=IF('Hiring plan'!$H$22="",999,'Hiring plan'!$H$22)),'Hiring plan'!$F$22,0) -> 0 | I26: =IF(AND(N('Hiring plan'!$F$22)>0,I$3>='Hiring plan'!$G$22,I$3<=IF('Hiring plan'!$H$22="",999,'Hiring plan'!$H$22)),'Hiring plan'!$F$22,0) -> 0 | J26: =IF(AND(N('Hiring plan'!$F$22)>0,J$3>='Hiring plan'!$G$22,J$3<=IF('Hiring plan'!$H$22="",999,'Hiring plan'!$H$22)),'Hiring plan'!$F$22,0) -> 0 | K26: =IF(AND(N('Hiring plan'!$F$22)>0,K$3>='Hiring plan'!$G$22,K$3<=IF('Hiring plan'!$H$22="",999,'Hiring plan'!$H$22)),'Hiring plan'!$F$22,0) -> 0 | L26: =IF(AND(N('Hiring plan'!$F$22)>0,L$3>='Hiring plan'!$G$22,L$3<=IF('Hiring plan'!$H$22="",999,'Hiring plan'!$H$22)),'Hiring plan'!$F$22,0) -> 0 | ... BL26: =IF(AND(N('Hiring plan'!$F$22)>0,BL$3>='Hiring plan'!$G$22,BL$3<=IF('Hiring plan'!$H$22="",999,'Hiring plan'!$H$22)),'Hiring plan'!$F$22,0) -> 0
A27: =IF('Hiring plan'!$C$23="","(spare line 19)",'Hiring plan'!$C$23&" · "&'Hiring plan'!$D$23) -> (spare line 19) | B27: people | D27: =MAX(E27:BL27) -> 0 | E27: =IF(AND(N('Hiring plan'!$F$23)>0,E$3>='Hiring plan'!$G$23,E$3<=IF('Hiring plan'!$H$23="",999,'Hiring plan'!$H$23)),'Hiring plan'!$F$23,0) -> 0 | F27: =IF(AND(N('Hiring plan'!$F$23)>0,F$3>='Hiring plan'!$G$23,F$3<=IF('Hiring plan'!$H$23="",999,'Hiring plan'!$H$23)),'Hiring plan'!$F$23,0) -> 0 | G27: =IF(AND(N('Hiring plan'!$F$23)>0,G$3>='Hiring plan'!$G$23,G$3<=IF('Hiring plan'!$H$23="",999,'Hiring plan'!$H$23)),'Hiring plan'!$F$23,0) -> 0 | H27: =IF(AND(N('Hiring plan'!$F$23)>0,H$3>='Hiring plan'!$G$23,H$3<=IF('Hiring plan'!$H$23="",999,'Hiring plan'!$H$23)),'Hiring plan'!$F$23,0) -> 0 | I27: =IF(AND(N('Hiring plan'!$F$23)>0,I$3>='Hiring plan'!$G$23,I$3<=IF('Hiring plan'!$H$23="",999,'Hiring plan'!$H$23)),'Hiring plan'!$F$23,0) -> 0 | J27: =IF(AND(N('Hiring plan'!$F$23)>0,J$3>='Hiring plan'!$G$23,J$3<=IF('Hiring plan'!$H$23="",999,'Hiring plan'!$H$23)),'Hiring plan'!$F$23,0) -> 0 | K27: =IF(AND(N('Hiring plan'!$F$23)>0,K$3>='Hiring plan'!$G$23,K$3<=IF('Hiring plan'!$H$23="",999,'Hiring plan'!$H$23)),'Hiring plan'!$F$23,0) -> 0 | L27: =IF(AND(N('Hiring plan'!$F$23)>0,L$3>='Hiring plan'!$G$23,L$3<=IF('Hiring plan'!$H$23="",999,'Hiring plan'!$H$23)),'Hiring plan'!$F$23,0) -> 0 | ... BL27: =IF(AND(N('Hiring plan'!$F$23)>0,BL$3>='Hiring plan'!$G$23,BL$3<=IF('Hiring plan'!$H$23="",999,'Hiring plan'!$H$23)),'Hiring plan'!$F$23,0) -> 0
A28: =IF('Hiring plan'!$C$24="","(spare line 20)",'Hiring plan'!$C$24&" · "&'Hiring plan'!$D$24) -> (spare line 20) | B28: people | D28: =MAX(E28:BL28) -> 0 | E28: =IF(AND(N('Hiring plan'!$F$24)>0,E$3>='Hiring plan'!$G$24,E$3<=IF('Hiring plan'!$H$24="",999,'Hiring plan'!$H$24)),'Hiring plan'!$F$24,0) -> 0 | F28: =IF(AND(N('Hiring plan'!$F$24)>0,F$3>='Hiring plan'!$G$24,F$3<=IF('Hiring plan'!$H$24="",999,'Hiring plan'!$H$24)),'Hiring plan'!$F$24,0) -> 0 | G28: =IF(AND(N('Hiring plan'!$F$24)>0,G$3>='Hiring plan'!$G$24,G$3<=IF('Hiring plan'!$H$24="",999,'Hiring plan'!$H$24)),'Hiring plan'!$F$24,0) -> 0 | H28: =IF(AND(N('Hiring plan'!$F$24)>0,H$3>='Hiring plan'!$G$24,H$3<=IF('Hiring plan'!$H$24="",999,'Hiring plan'!$H$24)),'Hiring plan'!$F$24,0) -> 0 | I28: =IF(AND(N('Hiring plan'!$F$24)>0,I$3>='Hiring plan'!$G$24,I$3<=IF('Hiring plan'!$H$24="",999,'Hiring plan'!$H$24)),'Hiring plan'!$F$24,0) -> 0 | J28: =IF(AND(N('Hiring plan'!$F$24)>0,J$3>='Hiring plan'!$G$24,J$3<=IF('Hiring plan'!$H$24="",999,'Hiring plan'!$H$24)),'Hiring plan'!$F$24,0) -> 0 | K28: =IF(AND(N('Hiring plan'!$F$24)>0,K$3>='Hiring plan'!$G$24,K$3<=IF('Hiring plan'!$H$24="",999,'Hiring plan'!$H$24)),'Hiring plan'!$F$24,0) -> 0 | L28: =IF(AND(N('Hiring plan'!$F$24)>0,L$3>='Hiring plan'!$G$24,L$3<=IF('Hiring plan'!$H$24="",999,'Hiring plan'!$H$24)),'Hiring plan'!$F$24,0) -> 0 | ... BL28: =IF(AND(N('Hiring plan'!$F$24)>0,BL$3>='Hiring plan'!$G$24,BL$3<=IF('Hiring plan'!$H$24="",999,'Hiring plan'!$H$24)),'Hiring plan'!$F$24,0) -> 0
A29: =IF('Hiring plan'!$C$25="","(spare line 21)",'Hiring plan'!$C$25&" · "&'Hiring plan'!$D$25) -> (spare line 21) | B29: people | D29: =MAX(E29:BL29) -> 0 | E29: =IF(AND(N('Hiring plan'!$F$25)>0,E$3>='Hiring plan'!$G$25,E$3<=IF('Hiring plan'!$H$25="",999,'Hiring plan'!$H$25)),'Hiring plan'!$F$25,0) -> 0 | F29: =IF(AND(N('Hiring plan'!$F$25)>0,F$3>='Hiring plan'!$G$25,F$3<=IF('Hiring plan'!$H$25="",999,'Hiring plan'!$H$25)),'Hiring plan'!$F$25,0) -> 0 | G29: =IF(AND(N('Hiring plan'!$F$25)>0,G$3>='Hiring plan'!$G$25,G$3<=IF('Hiring plan'!$H$25="",999,'Hiring plan'!$H$25)),'Hiring plan'!$F$25,0) -> 0 | H29: =IF(AND(N('Hiring plan'!$F$25)>0,H$3>='Hiring plan'!$G$25,H$3<=IF('Hiring plan'!$H$25="",999,'Hiring plan'!$H$25)),'Hiring plan'!$F$25,0) -> 0 | I29: =IF(AND(N('Hiring plan'!$F$25)>0,I$3>='Hiring plan'!$G$25,I$3<=IF('Hiring plan'!$H$25="",999,'Hiring plan'!$H$25)),'Hiring plan'!$F$25,0) -> 0 | J29: =IF(AND(N('Hiring plan'!$F$25)>0,J$3>='Hiring plan'!$G$25,J$3<=IF('Hiring plan'!$H$25="",999,'Hiring plan'!$H$25)),'Hiring plan'!$F$25,0) -> 0 | K29: =IF(AND(N('Hiring plan'!$F$25)>0,K$3>='Hiring plan'!$G$25,K$3<=IF('Hiring plan'!$H$25="",999,'Hiring plan'!$H$25)),'Hiring plan'!$F$25,0) -> 0 | L29: =IF(AND(N('Hiring plan'!$F$25)>0,L$3>='Hiring plan'!$G$25,L$3<=IF('Hiring plan'!$H$25="",999,'Hiring plan'!$H$25)),'Hiring plan'!$F$25,0) -> 0 | ... BL29: =IF(AND(N('Hiring plan'!$F$25)>0,BL$3>='Hiring plan'!$G$25,BL$3<=IF('Hiring plan'!$H$25="",999,'Hiring plan'!$H$25)),'Hiring plan'!$F$25,0) -> 0
A30: =IF('Hiring plan'!$C$26="","(spare line 22)",'Hiring plan'!$C$26&" · "&'Hiring plan'!$D$26) -> (spare line 22) | B30: people | D30: =MAX(E30:BL30) -> 0 | E30: =IF(AND(N('Hiring plan'!$F$26)>0,E$3>='Hiring plan'!$G$26,E$3<=IF('Hiring plan'!$H$26="",999,'Hiring plan'!$H$26)),'Hiring plan'!$F$26,0) -> 0 | F30: =IF(AND(N('Hiring plan'!$F$26)>0,F$3>='Hiring plan'!$G$26,F$3<=IF('Hiring plan'!$H$26="",999,'Hiring plan'!$H$26)),'Hiring plan'!$F$26,0) -> 0 | G30: =IF(AND(N('Hiring plan'!$F$26)>0,G$3>='Hiring plan'!$G$26,G$3<=IF('Hiring plan'!$H$26="",999,'Hiring plan'!$H$26)),'Hiring plan'!$F$26,0) -> 0 | H30: =IF(AND(N('Hiring plan'!$F$26)>0,H$3>='Hiring plan'!$G$26,H$3<=IF('Hiring plan'!$H$26="",999,'Hiring plan'!$H$26)),'Hiring plan'!$F$26,0) -> 0 | I30: =IF(AND(N('Hiring plan'!$F$26)>0,I$3>='Hiring plan'!$G$26,I$3<=IF('Hiring plan'!$H$26="",999,'Hiring plan'!$H$26)),'Hiring plan'!$F$26,0) -> 0 | J30: =IF(AND(N('Hiring plan'!$F$26)>0,J$3>='Hiring plan'!$G$26,J$3<=IF('Hiring plan'!$H$26="",999,'Hiring plan'!$H$26)),'Hiring plan'!$F$26,0) -> 0 | K30: =IF(AND(N('Hiring plan'!$F$26)>0,K$3>='Hiring plan'!$G$26,K$3<=IF('Hiring plan'!$H$26="",999,'Hiring plan'!$H$26)),'Hiring plan'!$F$26,0) -> 0 | L30: =IF(AND(N('Hiring plan'!$F$26)>0,L$3>='Hiring plan'!$G$26,L$3<=IF('Hiring plan'!$H$26="",999,'Hiring plan'!$H$26)),'Hiring plan'!$F$26,0) -> 0 | ... BL30: =IF(AND(N('Hiring plan'!$F$26)>0,BL$3>='Hiring plan'!$G$26,BL$3<=IF('Hiring plan'!$H$26="",999,'Hiring plan'!$H$26)),'Hiring plan'!$F$26,0) -> 0
A31: =IF('Hiring plan'!$C$27="","(spare line 23)",'Hiring plan'!$C$27&" · "&'Hiring plan'!$D$27) -> (spare line 23) | B31: people | D31: =MAX(E31:BL31) -> 0 | E31: =IF(AND(N('Hiring plan'!$F$27)>0,E$3>='Hiring plan'!$G$27,E$3<=IF('Hiring plan'!$H$27="",999,'Hiring plan'!$H$27)),'Hiring plan'!$F$27,0) -> 0 | F31: =IF(AND(N('Hiring plan'!$F$27)>0,F$3>='Hiring plan'!$G$27,F$3<=IF('Hiring plan'!$H$27="",999,'Hiring plan'!$H$27)),'Hiring plan'!$F$27,0) -> 0 | G31: =IF(AND(N('Hiring plan'!$F$27)>0,G$3>='Hiring plan'!$G$27,G$3<=IF('Hiring plan'!$H$27="",999,'Hiring plan'!$H$27)),'Hiring plan'!$F$27,0) -> 0 | H31: =IF(AND(N('Hiring plan'!$F$27)>0,H$3>='Hiring plan'!$G$27,H$3<=IF('Hiring plan'!$H$27="",999,'Hiring plan'!$H$27)),'Hiring plan'!$F$27,0) -> 0 | I31: =IF(AND(N('Hiring plan'!$F$27)>0,I$3>='Hiring plan'!$G$27,I$3<=IF('Hiring plan'!$H$27="",999,'Hiring plan'!$H$27)),'Hiring plan'!$F$27,0) -> 0 | J31: =IF(AND(N('Hiring plan'!$F$27)>0,J$3>='Hiring plan'!$G$27,J$3<=IF('Hiring plan'!$H$27="",999,'Hiring plan'!$H$27)),'Hiring plan'!$F$27,0) -> 0 | K31: =IF(AND(N('Hiring plan'!$F$27)>0,K$3>='Hiring plan'!$G$27,K$3<=IF('Hiring plan'!$H$27="",999,'Hiring plan'!$H$27)),'Hiring plan'!$F$27,0) -> 0 | L31: =IF(AND(N('Hiring plan'!$F$27)>0,L$3>='Hiring plan'!$G$27,L$3<=IF('Hiring plan'!$H$27="",999,'Hiring plan'!$H$27)),'Hiring plan'!$F$27,0) -> 0 | ... BL31: =IF(AND(N('Hiring plan'!$F$27)>0,BL$3>='Hiring plan'!$G$27,BL$3<=IF('Hiring plan'!$H$27="",999,'Hiring plan'!$H$27)),'Hiring plan'!$F$27,0) -> 0
A32: =IF('Hiring plan'!$C$28="","(spare line 24)",'Hiring plan'!$C$28&" · "&'Hiring plan'!$D$28) -> (spare line 24) | B32: people | D32: =MAX(E32:BL32) -> 0 | E32: =IF(AND(N('Hiring plan'!$F$28)>0,E$3>='Hiring plan'!$G$28,E$3<=IF('Hiring plan'!$H$28="",999,'Hiring plan'!$H$28)),'Hiring plan'!$F$28,0) -> 0 | F32: =IF(AND(N('Hiring plan'!$F$28)>0,F$3>='Hiring plan'!$G$28,F$3<=IF('Hiring plan'!$H$28="",999,'Hiring plan'!$H$28)),'Hiring plan'!$F$28,0) -> 0 | G32: =IF(AND(N('Hiring plan'!$F$28)>0,G$3>='Hiring plan'!$G$28,G$3<=IF('Hiring plan'!$H$28="",999,'Hiring plan'!$H$28)),'Hiring plan'!$F$28,0) -> 0 | H32: =IF(AND(N('Hiring plan'!$F$28)>0,H$3>='Hiring plan'!$G$28,H$3<=IF('Hiring plan'!$H$28="",999,'Hiring plan'!$H$28)),'Hiring plan'!$F$28,0) -> 0 | I32: =IF(AND(N('Hiring plan'!$F$28)>0,I$3>='Hiring plan'!$G$28,I$3<=IF('Hiring plan'!$H$28="",999,'Hiring plan'!$H$28)),'Hiring plan'!$F$28,0) -> 0 | J32: =IF(AND(N('Hiring plan'!$F$28)>0,J$3>='Hiring plan'!$G$28,J$3<=IF('Hiring plan'!$H$28="",999,'Hiring plan'!$H$28)),'Hiring plan'!$F$28,0) -> 0 | K32: =IF(AND(N('Hiring plan'!$F$28)>0,K$3>='Hiring plan'!$G$28,K$3<=IF('Hiring plan'!$H$28="",999,'Hiring plan'!$H$28)),'Hiring plan'!$F$28,0) -> 0 | L32: =IF(AND(N('Hiring plan'!$F$28)>0,L$3>='Hiring plan'!$G$28,L$3<=IF('Hiring plan'!$H$28="",999,'Hiring plan'!$H$28)),'Hiring plan'!$F$28,0) -> 0 | ... BL32: =IF(AND(N('Hiring plan'!$F$28)>0,BL$3>='Hiring plan'!$G$28,BL$3<=IF('Hiring plan'!$H$28="",999,'Hiring plan'!$H$28)),'Hiring plan'!$F$28,0) -> 0
A33: =IF('Hiring plan'!$C$29="","(spare line 25)",'Hiring plan'!$C$29&" · "&'Hiring plan'!$D$29) -> (spare line 25) | B33: people | D33: =MAX(E33:BL33) -> 0 | E33: =IF(AND(N('Hiring plan'!$F$29)>0,E$3>='Hiring plan'!$G$29,E$3<=IF('Hiring plan'!$H$29="",999,'Hiring plan'!$H$29)),'Hiring plan'!$F$29,0) -> 0 | F33: =IF(AND(N('Hiring plan'!$F$29)>0,F$3>='Hiring plan'!$G$29,F$3<=IF('Hiring plan'!$H$29="",999,'Hiring plan'!$H$29)),'Hiring plan'!$F$29,0) -> 0 | G33: =IF(AND(N('Hiring plan'!$F$29)>0,G$3>='Hiring plan'!$G$29,G$3<=IF('Hiring plan'!$H$29="",999,'Hiring plan'!$H$29)),'Hiring plan'!$F$29,0) -> 0 | H33: =IF(AND(N('Hiring plan'!$F$29)>0,H$3>='Hiring plan'!$G$29,H$3<=IF('Hiring plan'!$H$29="",999,'Hiring plan'!$H$29)),'Hiring plan'!$F$29,0) -> 0 | I33: =IF(AND(N('Hiring plan'!$F$29)>0,I$3>='Hiring plan'!$G$29,I$3<=IF('Hiring plan'!$H$29="",999,'Hiring plan'!$H$29)),'Hiring plan'!$F$29,0) -> 0 | J33: =IF(AND(N('Hiring plan'!$F$29)>0,J$3>='Hiring plan'!$G$29,J$3<=IF('Hiring plan'!$H$29="",999,'Hiring plan'!$H$29)),'Hiring plan'!$F$29,0) -> 0 | K33: =IF(AND(N('Hiring plan'!$F$29)>0,K$3>='Hiring plan'!$G$29,K$3<=IF('Hiring plan'!$H$29="",999,'Hiring plan'!$H$29)),'Hiring plan'!$F$29,0) -> 0 | L33: =IF(AND(N('Hiring plan'!$F$29)>0,L$3>='Hiring plan'!$G$29,L$3<=IF('Hiring plan'!$H$29="",999,'Hiring plan'!$H$29)),'Hiring plan'!$F$29,0) -> 0 | ... BL33: =IF(AND(N('Hiring plan'!$F$29)>0,BL$3>='Hiring plan'!$G$29,BL$3<=IF('Hiring plan'!$H$29="",999,'Hiring plan'!$H$29)),'Hiring plan'!$F$29,0) -> 0
A34: =IF('Hiring plan'!$C$30="","(spare line 26)",'Hiring plan'!$C$30&" · "&'Hiring plan'!$D$30) -> (spare line 26) | B34: people | D34: =MAX(E34:BL34) -> 0 | E34: =IF(AND(N('Hiring plan'!$F$30)>0,E$3>='Hiring plan'!$G$30,E$3<=IF('Hiring plan'!$H$30="",999,'Hiring plan'!$H$30)),'Hiring plan'!$F$30,0) -> 0 | F34: =IF(AND(N('Hiring plan'!$F$30)>0,F$3>='Hiring plan'!$G$30,F$3<=IF('Hiring plan'!$H$30="",999,'Hiring plan'!$H$30)),'Hiring plan'!$F$30,0) -> 0 | G34: =IF(AND(N('Hiring plan'!$F$30)>0,G$3>='Hiring plan'!$G$30,G$3<=IF('Hiring plan'!$H$30="",999,'Hiring plan'!$H$30)),'Hiring plan'!$F$30,0) -> 0 | H34: =IF(AND(N('Hiring plan'!$F$30)>0,H$3>='Hiring plan'!$G$30,H$3<=IF('Hiring plan'!$H$30="",999,'Hiring plan'!$H$30)),'Hiring plan'!$F$30,0) -> 0 | I34: =IF(AND(N('Hiring plan'!$F$30)>0,I$3>='Hiring plan'!$G$30,I$3<=IF('Hiring plan'!$H$30="",999,'Hiring plan'!$H$30)),'Hiring plan'!$F$30,0) -> 0 | J34: =IF(AND(N('Hiring plan'!$F$30)>0,J$3>='Hiring plan'!$G$30,J$3<=IF('Hiring plan'!$H$30="",999,'Hiring plan'!$H$30)),'Hiring plan'!$F$30,0) -> 0 | K34: =IF(AND(N('Hiring plan'!$F$30)>0,K$3>='Hiring plan'!$G$30,K$3<=IF('Hiring plan'!$H$30="",999,'Hiring plan'!$H$30)),'Hiring plan'!$F$30,0) -> 0 | L34: =IF(AND(N('Hiring plan'!$F$30)>0,L$3>='Hiring plan'!$G$30,L$3<=IF('Hiring plan'!$H$30="",999,'Hiring plan'!$H$30)),'Hiring plan'!$F$30,0) -> 0 | ... BL34: =IF(AND(N('Hiring plan'!$F$30)>0,BL$3>='Hiring plan'!$G$30,BL$3<=IF('Hiring plan'!$H$30="",999,'Hiring plan'!$H$30)),'Hiring plan'!$F$30,0) -> 0
A35: =IF('Hiring plan'!$C$31="","(spare line 27)",'Hiring plan'!$C$31&" · "&'Hiring plan'!$D$31) -> (spare line 27) | B35: people | D35: =MAX(E35:BL35) -> 0 | E35: =IF(AND(N('Hiring plan'!$F$31)>0,E$3>='Hiring plan'!$G$31,E$3<=IF('Hiring plan'!$H$31="",999,'Hiring plan'!$H$31)),'Hiring plan'!$F$31,0) -> 0 | F35: =IF(AND(N('Hiring plan'!$F$31)>0,F$3>='Hiring plan'!$G$31,F$3<=IF('Hiring plan'!$H$31="",999,'Hiring plan'!$H$31)),'Hiring plan'!$F$31,0) -> 0 | G35: =IF(AND(N('Hiring plan'!$F$31)>0,G$3>='Hiring plan'!$G$31,G$3<=IF('Hiring plan'!$H$31="",999,'Hiring plan'!$H$31)),'Hiring plan'!$F$31,0) -> 0 | H35: =IF(AND(N('Hiring plan'!$F$31)>0,H$3>='Hiring plan'!$G$31,H$3<=IF('Hiring plan'!$H$31="",999,'Hiring plan'!$H$31)),'Hiring plan'!$F$31,0) -> 0 | I35: =IF(AND(N('Hiring plan'!$F$31)>0,I$3>='Hiring plan'!$G$31,I$3<=IF('Hiring plan'!$H$31="",999,'Hiring plan'!$H$31)),'Hiring plan'!$F$31,0) -> 0 | J35: =IF(AND(N('Hiring plan'!$F$31)>0,J$3>='Hiring plan'!$G$31,J$3<=IF('Hiring plan'!$H$31="",999,'Hiring plan'!$H$31)),'Hiring plan'!$F$31,0) -> 0 | K35: =IF(AND(N('Hiring plan'!$F$31)>0,K$3>='Hiring plan'!$G$31,K$3<=IF('Hiring plan'!$H$31="",999,'Hiring plan'!$H$31)),'Hiring plan'!$F$31,0) -> 0 | L35: =IF(AND(N('Hiring plan'!$F$31)>0,L$3>='Hiring plan'!$G$31,L$3<=IF('Hiring plan'!$H$31="",999,'Hiring plan'!$H$31)),'Hiring plan'!$F$31,0) -> 0 | ... BL35: =IF(AND(N('Hiring plan'!$F$31)>0,BL$3>='Hiring plan'!$G$31,BL$3<=IF('Hiring plan'!$H$31="",999,'Hiring plan'!$H$31)),'Hiring plan'!$F$31,0) -> 0
A36: =IF('Hiring plan'!$C$32="","(spare line 28)",'Hiring plan'!$C$32&" · "&'Hiring plan'!$D$32) -> (spare line 28) | B36: people | D36: =MAX(E36:BL36) -> 0 | E36: =IF(AND(N('Hiring plan'!$F$32)>0,E$3>='Hiring plan'!$G$32,E$3<=IF('Hiring plan'!$H$32="",999,'Hiring plan'!$H$32)),'Hiring plan'!$F$32,0) -> 0 | F36: =IF(AND(N('Hiring plan'!$F$32)>0,F$3>='Hiring plan'!$G$32,F$3<=IF('Hiring plan'!$H$32="",999,'Hiring plan'!$H$32)),'Hiring plan'!$F$32,0) -> 0 | G36: =IF(AND(N('Hiring plan'!$F$32)>0,G$3>='Hiring plan'!$G$32,G$3<=IF('Hiring plan'!$H$32="",999,'Hiring plan'!$H$32)),'Hiring plan'!$F$32,0) -> 0 | H36: =IF(AND(N('Hiring plan'!$F$32)>0,H$3>='Hiring plan'!$G$32,H$3<=IF('Hiring plan'!$H$32="",999,'Hiring plan'!$H$32)),'Hiring plan'!$F$32,0) -> 0 | I36: =IF(AND(N('Hiring plan'!$F$32)>0,I$3>='Hiring plan'!$G$32,I$3<=IF('Hiring plan'!$H$32="",999,'Hiring plan'!$H$32)),'Hiring plan'!$F$32,0) -> 0 | J36: =IF(AND(N('Hiring plan'!$F$32)>0,J$3>='Hiring plan'!$G$32,J$3<=IF('Hiring plan'!$H$32="",999,'Hiring plan'!$H$32)),'Hiring plan'!$F$32,0) -> 0 | K36: =IF(AND(N('Hiring plan'!$F$32)>0,K$3>='Hiring plan'!$G$32,K$3<=IF('Hiring plan'!$H$32="",999,'Hiring plan'!$H$32)),'Hiring plan'!$F$32,0) -> 0 | L36: =IF(AND(N('Hiring plan'!$F$32)>0,L$3>='Hiring plan'!$G$32,L$3<=IF('Hiring plan'!$H$32="",999,'Hiring plan'!$H$32)),'Hiring plan'!$F$32,0) -> 0 | ... BL36: =IF(AND(N('Hiring plan'!$F$32)>0,BL$3>='Hiring plan'!$G$32,BL$3<=IF('Hiring plan'!$H$32="",999,'Hiring plan'!$H$32)),'Hiring plan'!$F$32,0) -> 0
A38: Employer cost by hire line
A39: =A9 -> CEO (full salary from year 2) · SN | B39: FCFA | D39: =SUM(E39:BL39) -> 1.7649962e+08 | E39: =E9*'Hiring plan'!$K$5*(1+Salary_Raise)^(E$5-1) -> 0 | F39: =F9*'Hiring plan'!$K$5*(1+Salary_Raise)^(F$5-1) -> 0 | G39: =G9*'Hiring plan'!$K$5*(1+Salary_Raise)^(G$5-1) -> 0 | H39: =H9*'Hiring plan'!$K$5*(1+Salary_Raise)^(H$5-1) -> 0 | I39: =I9*'Hiring plan'!$K$5*(1+Salary_Raise)^(I$5-1) -> 0 | J39: =J9*'Hiring plan'!$K$5*(1+Salary_Raise)^(J$5-1) -> 0 | K39: =K9*'Hiring plan'!$K$5*(1+Salary_Raise)^(K$5-1) -> 0 | L39: =L9*'Hiring plan'!$K$5*(1+Salary_Raise)^(L$5-1) -> 0 | ... BL39: =BL9*'Hiring plan'!$K$5*(1+Salary_Raise)^(BL$5-1) -> 3950395.3
A40: =A10 -> CTO (also codes) · SN | B40: FCFA | D40: =SUM(E40:BL40) -> 2.1549962e+08 | E40: =E10*'Hiring plan'!$K$6*(1+Salary_Raise)^(E$5-1) -> 3250000 | F40: =F10*'Hiring plan'!$K$6*(1+Salary_Raise)^(F$5-1) -> 3250000 | G40: =G10*'Hiring plan'!$K$6*(1+Salary_Raise)^(G$5-1) -> 3250000 | H40: =H10*'Hiring plan'!$K$6*(1+Salary_Raise)^(H$5-1) -> 3250000 | I40: =I10*'Hiring plan'!$K$6*(1+Salary_Raise)^(I$5-1) -> 3250000 | J40: =J10*'Hiring plan'!$K$6*(1+Salary_Raise)^(J$5-1) -> 3250000 | K40: =K10*'Hiring plan'!$K$6*(1+Salary_Raise)^(K$5-1) -> 3250000 | L40: =L10*'Hiring plan'!$K$6*(1+Salary_Raise)^(L$5-1) -> 3250000 | ... BL40: =BL10*'Hiring plan'!$K$6*(1+Salary_Raise)^(BL$5-1) -> 3950395.3
A41: =A11 -> Financial expert (finance, partners, credit lead) · SN | B41: FCFA | D41: =SUM(E41:BL41) -> 1.2929977e+08 | E41: =E11*'Hiring plan'!$K$7*(1+Salary_Raise)^(E$5-1) -> 1950000 | F41: =F11*'Hiring plan'!$K$7*(1+Salary_Raise)^(F$5-1) -> 1950000 | G41: =G11*'Hiring plan'!$K$7*(1+Salary_Raise)^(G$5-1) -> 1950000 | H41: =H11*'Hiring plan'!$K$7*(1+Salary_Raise)^(H$5-1) -> 1950000 | I41: =I11*'Hiring plan'!$K$7*(1+Salary_Raise)^(I$5-1) -> 1950000 | J41: =J11*'Hiring plan'!$K$7*(1+Salary_Raise)^(J$5-1) -> 1950000 | K41: =K11*'Hiring plan'!$K$7*(1+Salary_Raise)^(K$5-1) -> 1950000 | L41: =L11*'Hiring plan'!$K$7*(1+Salary_Raise)^(L$5-1) -> 1950000 | ... BL41: =BL11*'Hiring plan'!$K$7*(1+Salary_Raise)^(BL$5-1) -> 2370237.2
A42: =A12 -> Sales lead (also sells; incl. bonus) · SN | B42: FCFA | D42: =SUM(E42:BL42) -> 103439817 | E42: =E12*'Hiring plan'!$K$8*(1+Salary_Raise)^(E$5-1) -> 1560000 | F42: =F12*'Hiring plan'!$K$8*(1+Salary_Raise)^(F$5-1) -> 1560000 | G42: =G12*'Hiring plan'!$K$8*(1+Salary_Raise)^(G$5-1) -> 1560000 | H42: =H12*'Hiring plan'!$K$8*(1+Salary_Raise)^(H$5-1) -> 1560000 | I42: =I12*'Hiring plan'!$K$8*(1+Salary_Raise)^(I$5-1) -> 1560000 | J42: =J12*'Hiring plan'!$K$8*(1+Salary_Raise)^(J$5-1) -> 1560000 | K42: =K12*'Hiring plan'!$K$8*(1+Salary_Raise)^(K$5-1) -> 1560000 | L42: =L12*'Hiring plan'!$K$8*(1+Salary_Raise)^(L$5-1) -> 1560000 | ... BL42: =BL12*'Hiring plan'!$K$8*(1+Salary_Raise)^(BL$5-1) -> 1896189.8
A43: =A13 -> Marketing manager (senior) · SN | B43: FCFA | D43: =SUM(E43:BL43) -> 74069863 | E43: =E13*'Hiring plan'!$K$9*(1+Salary_Raise)^(E$5-1) -> 0 | F43: =F13*'Hiring plan'!$K$9*(1+Salary_Raise)^(F$5-1) -> 0 | G43: =G13*'Hiring plan'!$K$9*(1+Salary_Raise)^(G$5-1) -> 0 | H43: =H13*'Hiring plan'!$K$9*(1+Salary_Raise)^(H$5-1) -> 1170000 | I43: =I13*'Hiring plan'!$K$9*(1+Salary_Raise)^(I$5-1) -> 1170000 | J43: =J13*'Hiring plan'!$K$9*(1+Salary_Raise)^(J$5-1) -> 1170000 | K43: =K13*'Hiring plan'!$K$9*(1+Salary_Raise)^(K$5-1) -> 1170000 | L43: =L13*'Hiring plan'!$K$9*(1+Salary_Raise)^(L$5-1) -> 1170000 | ... BL43: =BL13*'Hiring plan'!$K$9*(1+Salary_Raise)^(BL$5-1) -> 1422142.3
A44: =A14 -> Marketing officer (junior) · SN | B44: FCFA | D44: =SUM(E44:BL44) -> 32399939 | E44: =E14*'Hiring plan'!$K$10*(1+Salary_Raise)^(E$5-1) -> 0 | F44: =F14*'Hiring plan'!$K$10*(1+Salary_Raise)^(F$5-1) -> 0 | G44: =G14*'Hiring plan'!$K$10*(1+Salary_Raise)^(G$5-1) -> 0 | H44: =H14*'Hiring plan'!$K$10*(1+Salary_Raise)^(H$5-1) -> 0 | I44: =I14*'Hiring plan'!$K$10*(1+Salary_Raise)^(I$5-1) -> 520000 | J44: =J14*'Hiring plan'!$K$10*(1+Salary_Raise)^(J$5-1) -> 520000 | K44: =K14*'Hiring plan'!$K$10*(1+Salary_Raise)^(K$5-1) -> 520000 | L44: =L14*'Hiring plan'!$K$10*(1+Salary_Raise)^(L$5-1) -> 520000 | ... BL44: =BL14*'Hiring plan'!$K$10*(1+Salary_Raise)^(BL$5-1) -> 632063.25
A45: =A15 -> Country manager, Abidjan · CI | B45: FCFA | D45: =SUM(E45:BL45) -> 178569573 | E45: =E15*'Hiring plan'!$K$11*(1+Salary_Raise)^(E$5-1) -> 0 | F45: =F15*'Hiring plan'!$K$11*(1+Salary_Raise)^(F$5-1) -> 0 | G45: =G15*'Hiring plan'!$K$11*(1+Salary_Raise)^(G$5-1) -> 0 | H45: =H15*'Hiring plan'!$K$11*(1+Salary_Raise)^(H$5-1) -> 0 | I45: =I15*'Hiring plan'!$K$11*(1+Salary_Raise)^(I$5-1) -> 0 | J45: =J15*'Hiring plan'!$K$11*(1+Salary_Raise)^(J$5-1) -> 0 | K45: =K15*'Hiring plan'!$K$11*(1+Salary_Raise)^(K$5-1) -> 0 | L45: =L15*'Hiring plan'!$K$11*(1+Salary_Raise)^(L$5-1) -> 0 | ... BL45: =BL15*'Hiring plan'!$K$11*(1+Salary_Raise)^(BL$5-1) -> 4424442.8
A46: =A16 -> Compliance officer (AML/CFT) · SN | B46: FCFA | D46: =SUM(E46:BL46) -> 83377271 | E46: =E16*'Hiring plan'!$K$12*(1+Salary_Raise)^(E$5-1) -> 0 | F46: =F16*'Hiring plan'!$K$12*(1+Salary_Raise)^(F$5-1) -> 0 | G46: =G16*'Hiring plan'!$K$12*(1+Salary_Raise)^(G$5-1) -> 0 | H46: =H16*'Hiring plan'!$K$12*(1+Salary_Raise)^(H$5-1) -> 0 | I46: =I16*'Hiring plan'!$K$12*(1+Salary_Raise)^(I$5-1) -> 0 | J46: =J16*'Hiring plan'!$K$12*(1+Salary_Raise)^(J$5-1) -> 0 | K46: =K16*'Hiring plan'!$K$12*(1+Salary_Raise)^(K$5-1) -> 0 | L46: =L16*'Hiring plan'!$K$12*(1+Salary_Raise)^(L$5-1) -> 0 | ... BL46: =BL16*'Hiring plan'!$K$12*(1+Salary_Raise)^(BL$5-1) -> 2370237.2
A47: =A17 -> (spare line 9) | B47: FCFA | D47: =SUM(E47:BL47) -> 0 | E47: =E17*'Hiring plan'!$K$13*(1+Salary_Raise)^(E$5-1) -> 0 | F47: =F17*'Hiring plan'!$K$13*(1+Salary_Raise)^(F$5-1) -> 0 | G47: =G17*'Hiring plan'!$K$13*(1+Salary_Raise)^(G$5-1) -> 0 | H47: =H17*'Hiring plan'!$K$13*(1+Salary_Raise)^(H$5-1) -> 0 | I47: =I17*'Hiring plan'!$K$13*(1+Salary_Raise)^(I$5-1) -> 0 | J47: =J17*'Hiring plan'!$K$13*(1+Salary_Raise)^(J$5-1) -> 0 | K47: =K17*'Hiring plan'!$K$13*(1+Salary_Raise)^(K$5-1) -> 0 | L47: =L17*'Hiring plan'!$K$13*(1+Salary_Raise)^(L$5-1) -> 0 | ... BL47: =BL17*'Hiring plan'!$K$13*(1+Salary_Raise)^(BL$5-1) -> 0
A48: =A18 -> (spare line 10) | B48: FCFA | D48: =SUM(E48:BL48) -> 0 | E48: =E18*'Hiring plan'!$K$14*(1+Salary_Raise)^(E$5-1) -> 0 | F48: =F18*'Hiring plan'!$K$14*(1+Salary_Raise)^(F$5-1) -> 0 | G48: =G18*'Hiring plan'!$K$14*(1+Salary_Raise)^(G$5-1) -> 0 | H48: =H18*'Hiring plan'!$K$14*(1+Salary_Raise)^(H$5-1) -> 0 | I48: =I18*'Hiring plan'!$K$14*(1+Salary_Raise)^(I$5-1) -> 0 | J48: =J18*'Hiring plan'!$K$14*(1+Salary_Raise)^(J$5-1) -> 0 | K48: =K18*'Hiring plan'!$K$14*(1+Salary_Raise)^(K$5-1) -> 0 | L48: =L18*'Hiring plan'!$K$14*(1+Salary_Raise)^(L$5-1) -> 0 | ... BL48: =BL18*'Hiring plan'!$K$14*(1+Salary_Raise)^(BL$5-1) -> 0
A49: =A19 -> (spare line 11) | B49: FCFA | D49: =SUM(E49:BL49) -> 0 | E49: =E19*'Hiring plan'!$K$15*(1+Salary_Raise)^(E$5-1) -> 0 | F49: =F19*'Hiring plan'!$K$15*(1+Salary_Raise)^(F$5-1) -> 0 | G49: =G19*'Hiring plan'!$K$15*(1+Salary_Raise)^(G$5-1) -> 0 | H49: =H19*'Hiring plan'!$K$15*(1+Salary_Raise)^(H$5-1) -> 0 | I49: =I19*'Hiring plan'!$K$15*(1+Salary_Raise)^(I$5-1) -> 0 | J49: =J19*'Hiring plan'!$K$15*(1+Salary_Raise)^(J$5-1) -> 0 | K49: =K19*'Hiring plan'!$K$15*(1+Salary_Raise)^(K$5-1) -> 0 | L49: =L19*'Hiring plan'!$K$15*(1+Salary_Raise)^(L$5-1) -> 0 | ... BL49: =BL19*'Hiring plan'!$K$15*(1+Salary_Raise)^(BL$5-1) -> 0
A50: =A20 -> (spare line 12) | B50: FCFA | D50: =SUM(E50:BL50) -> 0 | E50: =E20*'Hiring plan'!$K$16*(1+Salary_Raise)^(E$5-1) -> 0 | F50: =F20*'Hiring plan'!$K$16*(1+Salary_Raise)^(F$5-1) -> 0 | G50: =G20*'Hiring plan'!$K$16*(1+Salary_Raise)^(G$5-1) -> 0 | H50: =H20*'Hiring plan'!$K$16*(1+Salary_Raise)^(H$5-1) -> 0 | I50: =I20*'Hiring plan'!$K$16*(1+Salary_Raise)^(I$5-1) -> 0 | J50: =J20*'Hiring plan'!$K$16*(1+Salary_Raise)^(J$5-1) -> 0 | K50: =K20*'Hiring plan'!$K$16*(1+Salary_Raise)^(K$5-1) -> 0 | L50: =L20*'Hiring plan'!$K$16*(1+Salary_Raise)^(L$5-1) -> 0 | ... BL50: =BL20*'Hiring plan'!$K$16*(1+Salary_Raise)^(BL$5-1) -> 0
A51: =A21 -> (spare line 13) | B51: FCFA | D51: =SUM(E51:BL51) -> 0 | E51: =E21*'Hiring plan'!$K$17*(1+Salary_Raise)^(E$5-1) -> 0 | F51: =F21*'Hiring plan'!$K$17*(1+Salary_Raise)^(F$5-1) -> 0 | G51: =G21*'Hiring plan'!$K$17*(1+Salary_Raise)^(G$5-1) -> 0 | H51: =H21*'Hiring plan'!$K$17*(1+Salary_Raise)^(H$5-1) -> 0 | I51: =I21*'Hiring plan'!$K$17*(1+Salary_Raise)^(I$5-1) -> 0 | J51: =J21*'Hiring plan'!$K$17*(1+Salary_Raise)^(J$5-1) -> 0 | K51: =K21*'Hiring plan'!$K$17*(1+Salary_Raise)^(K$5-1) -> 0 | L51: =L21*'Hiring plan'!$K$17*(1+Salary_Raise)^(L$5-1) -> 0 | ... BL51: =BL21*'Hiring plan'!$K$17*(1+Salary_Raise)^(BL$5-1) -> 0
A52: =A22 -> (spare line 14) | B52: FCFA | D52: =SUM(E52:BL52) -> 0 | E52: =E22*'Hiring plan'!$K$18*(1+Salary_Raise)^(E$5-1) -> 0 | F52: =F22*'Hiring plan'!$K$18*(1+Salary_Raise)^(F$5-1) -> 0 | G52: =G22*'Hiring plan'!$K$18*(1+Salary_Raise)^(G$5-1) -> 0 | H52: =H22*'Hiring plan'!$K$18*(1+Salary_Raise)^(H$5-1) -> 0 | I52: =I22*'Hiring plan'!$K$18*(1+Salary_Raise)^(I$5-1) -> 0 | J52: =J22*'Hiring plan'!$K$18*(1+Salary_Raise)^(J$5-1) -> 0 | K52: =K22*'Hiring plan'!$K$18*(1+Salary_Raise)^(K$5-1) -> 0 | L52: =L22*'Hiring plan'!$K$18*(1+Salary_Raise)^(L$5-1) -> 0 | ... BL52: =BL22*'Hiring plan'!$K$18*(1+Salary_Raise)^(BL$5-1) -> 0
A53: =A23 -> (spare line 15) | B53: FCFA | D53: =SUM(E53:BL53) -> 0 | E53: =E23*'Hiring plan'!$K$19*(1+Salary_Raise)^(E$5-1) -> 0 | F53: =F23*'Hiring plan'!$K$19*(1+Salary_Raise)^(F$5-1) -> 0 | G53: =G23*'Hiring plan'!$K$19*(1+Salary_Raise)^(G$5-1) -> 0 | H53: =H23*'Hiring plan'!$K$19*(1+Salary_Raise)^(H$5-1) -> 0 | I53: =I23*'Hiring plan'!$K$19*(1+Salary_Raise)^(I$5-1) -> 0 | J53: =J23*'Hiring plan'!$K$19*(1+Salary_Raise)^(J$5-1) -> 0 | K53: =K23*'Hiring plan'!$K$19*(1+Salary_Raise)^(K$5-1) -> 0 | L53: =L23*'Hiring plan'!$K$19*(1+Salary_Raise)^(L$5-1) -> 0 | ... BL53: =BL23*'Hiring plan'!$K$19*(1+Salary_Raise)^(BL$5-1) -> 0
A54: =A24 -> (spare line 16) | B54: FCFA | D54: =SUM(E54:BL54) -> 0 | E54: =E24*'Hiring plan'!$K$20*(1+Salary_Raise)^(E$5-1) -> 0 | F54: =F24*'Hiring plan'!$K$20*(1+Salary_Raise)^(F$5-1) -> 0 | G54: =G24*'Hiring plan'!$K$20*(1+Salary_Raise)^(G$5-1) -> 0 | H54: =H24*'Hiring plan'!$K$20*(1+Salary_Raise)^(H$5-1) -> 0 | I54: =I24*'Hiring plan'!$K$20*(1+Salary_Raise)^(I$5-1) -> 0 | J54: =J24*'Hiring plan'!$K$20*(1+Salary_Raise)^(J$5-1) -> 0 | K54: =K24*'Hiring plan'!$K$20*(1+Salary_Raise)^(K$5-1) -> 0 | L54: =L24*'Hiring plan'!$K$20*(1+Salary_Raise)^(L$5-1) -> 0 | ... BL54: =BL24*'Hiring plan'!$K$20*(1+Salary_Raise)^(BL$5-1) -> 0
A55: =A25 -> (spare line 17) | B55: FCFA | D55: =SUM(E55:BL55) -> 0 | E55: =E25*'Hiring plan'!$K$21*(1+Salary_Raise)^(E$5-1) -> 0 | F55: =F25*'Hiring plan'!$K$21*(1+Salary_Raise)^(F$5-1) -> 0 | G55: =G25*'Hiring plan'!$K$21*(1+Salary_Raise)^(G$5-1) -> 0 | H55: =H25*'Hiring plan'!$K$21*(1+Salary_Raise)^(H$5-1) -> 0 | I55: =I25*'Hiring plan'!$K$21*(1+Salary_Raise)^(I$5-1) -> 0 | J55: =J25*'Hiring plan'!$K$21*(1+Salary_Raise)^(J$5-1) -> 0 | K55: =K25*'Hiring plan'!$K$21*(1+Salary_Raise)^(K$5-1) -> 0 | L55: =L25*'Hiring plan'!$K$21*(1+Salary_Raise)^(L$5-1) -> 0 | ... BL55: =BL25*'Hiring plan'!$K$21*(1+Salary_Raise)^(BL$5-1) -> 0
A56: =A26 -> (spare line 18) | B56: FCFA | D56: =SUM(E56:BL56) -> 0 | E56: =E26*'Hiring plan'!$K$22*(1+Salary_Raise)^(E$5-1) -> 0 | F56: =F26*'Hiring plan'!$K$22*(1+Salary_Raise)^(F$5-1) -> 0 | G56: =G26*'Hiring plan'!$K$22*(1+Salary_Raise)^(G$5-1) -> 0 | H56: =H26*'Hiring plan'!$K$22*(1+Salary_Raise)^(H$5-1) -> 0 | I56: =I26*'Hiring plan'!$K$22*(1+Salary_Raise)^(I$5-1) -> 0 | J56: =J26*'Hiring plan'!$K$22*(1+Salary_Raise)^(J$5-1) -> 0 | K56: =K26*'Hiring plan'!$K$22*(1+Salary_Raise)^(K$5-1) -> 0 | L56: =L26*'Hiring plan'!$K$22*(1+Salary_Raise)^(L$5-1) -> 0 | ... BL56: =BL26*'Hiring plan'!$K$22*(1+Salary_Raise)^(BL$5-1) -> 0
A57: =A27 -> (spare line 19) | B57: FCFA | D57: =SUM(E57:BL57) -> 0 | E57: =E27*'Hiring plan'!$K$23*(1+Salary_Raise)^(E$5-1) -> 0 | F57: =F27*'Hiring plan'!$K$23*(1+Salary_Raise)^(F$5-1) -> 0 | G57: =G27*'Hiring plan'!$K$23*(1+Salary_Raise)^(G$5-1) -> 0 | H57: =H27*'Hiring plan'!$K$23*(1+Salary_Raise)^(H$5-1) -> 0 | I57: =I27*'Hiring plan'!$K$23*(1+Salary_Raise)^(I$5-1) -> 0 | J57: =J27*'Hiring plan'!$K$23*(1+Salary_Raise)^(J$5-1) -> 0 | K57: =K27*'Hiring plan'!$K$23*(1+Salary_Raise)^(K$5-1) -> 0 | L57: =L27*'Hiring plan'!$K$23*(1+Salary_Raise)^(L$5-1) -> 0 | ... BL57: =BL27*'Hiring plan'!$K$23*(1+Salary_Raise)^(BL$5-1) -> 0
A58: =A28 -> (spare line 20) | B58: FCFA | D58: =SUM(E58:BL58) -> 0 | E58: =E28*'Hiring plan'!$K$24*(1+Salary_Raise)^(E$5-1) -> 0 | F58: =F28*'Hiring plan'!$K$24*(1+Salary_Raise)^(F$5-1) -> 0 | G58: =G28*'Hiring plan'!$K$24*(1+Salary_Raise)^(G$5-1) -> 0 | H58: =H28*'Hiring plan'!$K$24*(1+Salary_Raise)^(H$5-1) -> 0 | I58: =I28*'Hiring plan'!$K$24*(1+Salary_Raise)^(I$5-1) -> 0 | J58: =J28*'Hiring plan'!$K$24*(1+Salary_Raise)^(J$5-1) -> 0 | K58: =K28*'Hiring plan'!$K$24*(1+Salary_Raise)^(K$5-1) -> 0 | L58: =L28*'Hiring plan'!$K$24*(1+Salary_Raise)^(L$5-1) -> 0 | ... BL58: =BL28*'Hiring plan'!$K$24*(1+Salary_Raise)^(BL$5-1) -> 0
A59: =A29 -> (spare line 21) | B59: FCFA | D59: =SUM(E59:BL59) -> 0 | E59: =E29*'Hiring plan'!$K$25*(1+Salary_Raise)^(E$5-1) -> 0 | F59: =F29*'Hiring plan'!$K$25*(1+Salary_Raise)^(F$5-1) -> 0 | G59: =G29*'Hiring plan'!$K$25*(1+Salary_Raise)^(G$5-1) -> 0 | H59: =H29*'Hiring plan'!$K$25*(1+Salary_Raise)^(H$5-1) -> 0 | I59: =I29*'Hiring plan'!$K$25*(1+Salary_Raise)^(I$5-1) -> 0 | J59: =J29*'Hiring plan'!$K$25*(1+Salary_Raise)^(J$5-1) -> 0 | K59: =K29*'Hiring plan'!$K$25*(1+Salary_Raise)^(K$5-1) -> 0 | L59: =L29*'Hiring plan'!$K$25*(1+Salary_Raise)^(L$5-1) -> 0 | ... BL59: =BL29*'Hiring plan'!$K$25*(1+Salary_Raise)^(BL$5-1) -> 0
A60: =A30 -> (spare line 22) | B60: FCFA | D60: =SUM(E60:BL60) -> 0 | E60: =E30*'Hiring plan'!$K$26*(1+Salary_Raise)^(E$5-1) -> 0 | F60: =F30*'Hiring plan'!$K$26*(1+Salary_Raise)^(F$5-1) -> 0 | G60: =G30*'Hiring plan'!$K$26*(1+Salary_Raise)^(G$5-1) -> 0 | H60: =H30*'Hiring plan'!$K$26*(1+Salary_Raise)^(H$5-1) -> 0 | I60: =I30*'Hiring plan'!$K$26*(1+Salary_Raise)^(I$5-1) -> 0 | J60: =J30*'Hiring plan'!$K$26*(1+Salary_Raise)^(J$5-1) -> 0 | K60: =K30*'Hiring plan'!$K$26*(1+Salary_Raise)^(K$5-1) -> 0 | L60: =L30*'Hiring plan'!$K$26*(1+Salary_Raise)^(L$5-1) -> 0 | ... BL60: =BL30*'Hiring plan'!$K$26*(1+Salary_Raise)^(BL$5-1) -> 0
A61: =A31 -> (spare line 23) | B61: FCFA | D61: =SUM(E61:BL61) -> 0 | E61: =E31*'Hiring plan'!$K$27*(1+Salary_Raise)^(E$5-1) -> 0 | F61: =F31*'Hiring plan'!$K$27*(1+Salary_Raise)^(F$5-1) -> 0 | G61: =G31*'Hiring plan'!$K$27*(1+Salary_Raise)^(G$5-1) -> 0 | H61: =H31*'Hiring plan'!$K$27*(1+Salary_Raise)^(H$5-1) -> 0 | I61: =I31*'Hiring plan'!$K$27*(1+Salary_Raise)^(I$5-1) -> 0 | J61: =J31*'Hiring plan'!$K$27*(1+Salary_Raise)^(J$5-1) -> 0 | K61: =K31*'Hiring plan'!$K$27*(1+Salary_Raise)^(K$5-1) -> 0 | L61: =L31*'Hiring plan'!$K$27*(1+Salary_Raise)^(L$5-1) -> 0 | ... BL61: =BL31*'Hiring plan'!$K$27*(1+Salary_Raise)^(BL$5-1) -> 0
A62: =A32 -> (spare line 24) | B62: FCFA | D62: =SUM(E62:BL62) -> 0 | E62: =E32*'Hiring plan'!$K$28*(1+Salary_Raise)^(E$5-1) -> 0 | F62: =F32*'Hiring plan'!$K$28*(1+Salary_Raise)^(F$5-1) -> 0 | G62: =G32*'Hiring plan'!$K$28*(1+Salary_Raise)^(G$5-1) -> 0 | H62: =H32*'Hiring plan'!$K$28*(1+Salary_Raise)^(H$5-1) -> 0 | I62: =I32*'Hiring plan'!$K$28*(1+Salary_Raise)^(I$5-1) -> 0 | J62: =J32*'Hiring plan'!$K$28*(1+Salary_Raise)^(J$5-1) -> 0 | K62: =K32*'Hiring plan'!$K$28*(1+Salary_Raise)^(K$5-1) -> 0 | L62: =L32*'Hiring plan'!$K$28*(1+Salary_Raise)^(L$5-1) -> 0 | ... BL62: =BL32*'Hiring plan'!$K$28*(1+Salary_Raise)^(BL$5-1) -> 0
A63: =A33 -> (spare line 25) | B63: FCFA | D63: =SUM(E63:BL63) -> 0 | E63: =E33*'Hiring plan'!$K$29*(1+Salary_Raise)^(E$5-1) -> 0 | F63: =F33*'Hiring plan'!$K$29*(1+Salary_Raise)^(F$5-1) -> 0 | G63: =G33*'Hiring plan'!$K$29*(1+Salary_Raise)^(G$5-1) -> 0 | H63: =H33*'Hiring plan'!$K$29*(1+Salary_Raise)^(H$5-1) -> 0 | I63: =I33*'Hiring plan'!$K$29*(1+Salary_Raise)^(I$5-1) -> 0 | J63: =J33*'Hiring plan'!$K$29*(1+Salary_Raise)^(J$5-1) -> 0 | K63: =K33*'Hiring plan'!$K$29*(1+Salary_Raise)^(K$5-1) -> 0 | L63: =L33*'Hiring plan'!$K$29*(1+Salary_Raise)^(L$5-1) -> 0 | ... BL63: =BL33*'Hiring plan'!$K$29*(1+Salary_Raise)^(BL$5-1) -> 0
A64: =A34 -> (spare line 26) | B64: FCFA | D64: =SUM(E64:BL64) -> 0 | E64: =E34*'Hiring plan'!$K$30*(1+Salary_Raise)^(E$5-1) -> 0 | F64: =F34*'Hiring plan'!$K$30*(1+Salary_Raise)^(F$5-1) -> 0 | G64: =G34*'Hiring plan'!$K$30*(1+Salary_Raise)^(G$5-1) -> 0 | H64: =H34*'Hiring plan'!$K$30*(1+Salary_Raise)^(H$5-1) -> 0 | I64: =I34*'Hiring plan'!$K$30*(1+Salary_Raise)^(I$5-1) -> 0 | J64: =J34*'Hiring plan'!$K$30*(1+Salary_Raise)^(J$5-1) -> 0 | K64: =K34*'Hiring plan'!$K$30*(1+Salary_Raise)^(K$5-1) -> 0 | L64: =L34*'Hiring plan'!$K$30*(1+Salary_Raise)^(L$5-1) -> 0 | ... BL64: =BL34*'Hiring plan'!$K$30*(1+Salary_Raise)^(BL$5-1) -> 0
A65: =A35 -> (spare line 27) | B65: FCFA | D65: =SUM(E65:BL65) -> 0 | E65: =E35*'Hiring plan'!$K$31*(1+Salary_Raise)^(E$5-1) -> 0 | F65: =F35*'Hiring plan'!$K$31*(1+Salary_Raise)^(F$5-1) -> 0 | G65: =G35*'Hiring plan'!$K$31*(1+Salary_Raise)^(G$5-1) -> 0 | H65: =H35*'Hiring plan'!$K$31*(1+Salary_Raise)^(H$5-1) -> 0 | I65: =I35*'Hiring plan'!$K$31*(1+Salary_Raise)^(I$5-1) -> 0 | J65: =J35*'Hiring plan'!$K$31*(1+Salary_Raise)^(J$5-1) -> 0 | K65: =K35*'Hiring plan'!$K$31*(1+Salary_Raise)^(K$5-1) -> 0 | L65: =L35*'Hiring plan'!$K$31*(1+Salary_Raise)^(L$5-1) -> 0 | ... BL65: =BL35*'Hiring plan'!$K$31*(1+Salary_Raise)^(BL$5-1) -> 0
A66: =A36 -> (spare line 28) | B66: FCFA | D66: =SUM(E66:BL66) -> 0 | E66: =E36*'Hiring plan'!$K$32*(1+Salary_Raise)^(E$5-1) -> 0 | F66: =F36*'Hiring plan'!$K$32*(1+Salary_Raise)^(F$5-1) -> 0 | G66: =G36*'Hiring plan'!$K$32*(1+Salary_Raise)^(G$5-1) -> 0 | H66: =H36*'Hiring plan'!$K$32*(1+Salary_Raise)^(H$5-1) -> 0 | I66: =I36*'Hiring plan'!$K$32*(1+Salary_Raise)^(I$5-1) -> 0 | J66: =J36*'Hiring plan'!$K$32*(1+Salary_Raise)^(J$5-1) -> 0 | K66: =K36*'Hiring plan'!$K$32*(1+Salary_Raise)^(K$5-1) -> 0 | L66: =L36*'Hiring plan'!$K$32*(1+Salary_Raise)^(L$5-1) -> 0 | ... BL66: =BL36*'Hiring plan'!$K$32*(1+Salary_Raise)^(BL$5-1) -> 0
A68: Team that grows with volume
A69: Customer support agents · SN | B69: people | D69: =MAX(E69:BL69) -> 33 | E69: =IF(E$3>=Support_Start,MAX(Support_Min,ROUNDUP('Clients & revenue'!E17/Clients_per_Support+'Clients & revenue'!E32/EmpAcc_per_Support,0)),0) -> 0 | F69: =IF(F$3>=Support_Start,MAX(Support_Min,ROUNDUP('Clients & revenue'!F17/Clients_per_Support+'Clients & revenue'!F32/EmpAcc_per_Support,0)),0) -> 0 | G69: =IF(G$3>=Support_Start,MAX(Support_Min,ROUNDUP('Clients & revenue'!G17/Clients_per_Support+'Clients & revenue'!G32/EmpAcc_per_Support,0)),0) -> 0 | H69: =IF(H$3>=Support_Start,MAX(Support_Min,ROUNDUP('Clients & revenue'!H17/Clients_per_Support+'Clients & revenue'!H32/EmpAcc_per_Support,0)),0) -> 2 | I69: =IF(I$3>=Support_Start,MAX(Support_Min,ROUNDUP('Clients & revenue'!I17/Clients_per_Support+'Clients & revenue'!I32/EmpAcc_per_Support,0)),0) -> 2 | J69: =IF(J$3>=Support_Start,MAX(Support_Min,ROUNDUP('Clients & revenue'!J17/Clients_per_Support+'Clients & revenue'!J32/EmpAcc_per_Support,0)),0) -> 2 | K69: =IF(K$3>=Support_Start,MAX(Support_Min,ROUNDUP('Clients & revenue'!K17/Clients_per_Support+'Clients & revenue'!K32/EmpAcc_per_Support,0)),0) -> 2 | L69: =IF(L$3>=Support_Start,MAX(Support_Min,ROUNDUP('Clients & revenue'!L17/Clients_per_Support+'Clients & revenue'!L32/EmpAcc_per_Support,0)),0) -> 2 | ... BL69: =IF(BL$3>=Support_Start,MAX(Support_Min,ROUNDUP('Clients & revenue'!BL17/Clients_per_Support+'Clients & revenue'!BL32/EmpAcc_per_Support,0)),0) -> 33
A70: Developers · SN | B70: people | D70: =MAX(E70:BL70) -> 7 | E70: =Devs_Min+ROUNDDOWN('Clients & revenue'!E17/Clients_per_Dev,0) -> 2 | F70: =Devs_Min+ROUNDDOWN('Clients & revenue'!F17/Clients_per_Dev,0) -> 2 | G70: =Devs_Min+ROUNDDOWN('Clients & revenue'!G17/Clients_per_Dev,0) -> 2 | H70: =Devs_Min+ROUNDDOWN('Clients & revenue'!H17/Clients_per_Dev,0) -> 2 | I70: =Devs_Min+ROUNDDOWN('Clients & revenue'!I17/Clients_per_Dev,0) -> 2 | J70: =Devs_Min+ROUNDDOWN('Clients & revenue'!J17/Clients_per_Dev,0) -> 2 | K70: =Devs_Min+ROUNDDOWN('Clients & revenue'!K17/Clients_per_Dev,0) -> 2 | L70: =Devs_Min+ROUNDDOWN('Clients & revenue'!L17/Clients_per_Dev,0) -> 2 | ... BL70: =Devs_Min+ROUNDDOWN('Clients & revenue'!BL17/Clients_per_Dev,0) -> 7
A71: Field sales reps, Senegal · SN | B71: people | D71: =MAX(E71:BL71) -> 19 | E71: =IF(E$3>=Reps_Start,MAX(Reps_Min_SN,ROUNDUP(0/Clients_per_Rep,0)),0) -> 0 | F71: =IF(F$3>=Reps_Start,MAX(Reps_Min_SN,ROUNDUP('Clients & revenue'!E19/Clients_per_Rep,0)),0) -> 0 | G71: =IF(G$3>=Reps_Start,MAX(Reps_Min_SN,ROUNDUP('Clients & revenue'!F19/Clients_per_Rep,0)),0) -> 0 | H71: =IF(H$3>=Reps_Start,MAX(Reps_Min_SN,ROUNDUP('Clients & revenue'!G19/Clients_per_Rep,0)),0) -> 2 | I71: =IF(I$3>=Reps_Start,MAX(Reps_Min_SN,ROUNDUP('Clients & revenue'!H19/Clients_per_Rep,0)),0) -> 2 | J71: =IF(J$3>=Reps_Start,MAX(Reps_Min_SN,ROUNDUP('Clients & revenue'!I19/Clients_per_Rep,0)),0) -> 2 | K71: =IF(K$3>=Reps_Start,MAX(Reps_Min_SN,ROUNDUP('Clients & revenue'!J19/Clients_per_Rep,0)),0) -> 2 | L71: =IF(L$3>=Reps_Start,MAX(Reps_Min_SN,ROUNDUP('Clients & revenue'!K19/Clients_per_Rep,0)),0) -> 2 | M71: =IF(M$3>=Reps_Start,MAX(Reps_Min_SN,ROUNDUP('Clients & revenue'!L19/Clients_per_Rep,0)),0) -> 2 | ... BL71: =IF(BL$3>=Reps_Start,MAX(Reps_Min_SN,ROUNDUP('Clients & revenue'!BK19/Clients_per_Rep,0)),0) -> 19
A72: Field sales reps, Côte d'Ivoire · CI | B72: people | D72: =MAX(E72:BL72) -> 8 | E72: =IF(E$3>=CI_Office_Start,MAX(Reps_Min_CI,ROUNDUP(0/Clients_per_Rep,0)),0) -> 0 | F72: =IF(F$3>=CI_Office_Start,MAX(Reps_Min_CI,ROUNDUP('Clients & revenue'!E20/Clients_per_Rep,0)),0) -> 0 | G72: =IF(G$3>=CI_Office_Start,MAX(Reps_Min_CI,ROUNDUP('Clients & revenue'!F20/Clients_per_Rep,0)),0) -> 0 | H72: =IF(H$3>=CI_Office_Start,MAX(Reps_Min_CI,ROUNDUP('Clients & revenue'!G20/Clients_per_Rep,0)),0) -> 0 | I72: =IF(I$3>=CI_Office_Start,MAX(Reps_Min_CI,ROUNDUP('Clients & revenue'!H20/Clients_per_Rep,0)),0) -> 0 | J72: =IF(J$3>=CI_Office_Start,MAX(Reps_Min_CI,ROUNDUP('Clients & revenue'!I20/Clients_per_Rep,0)),0) -> 0 | K72: =IF(K$3>=CI_Office_Start,MAX(Reps_Min_CI,ROUNDUP('Clients & revenue'!J20/Clients_per_Rep,0)),0) -> 0 | L72: =IF(L$3>=CI_Office_Start,MAX(Reps_Min_CI,ROUNDUP('Clients & revenue'!K20/Clients_per_Rep,0)),0) -> 0 | M72: =IF(M$3>=CI_Office_Start,MAX(Reps_Min_CI,ROUNDUP('Clients & revenue'!L20/Clients_per_Rep,0)),0) -> 0 | ... BL72: =IF(BL$3>=CI_Office_Start,MAX(Reps_Min_CI,ROUNDUP('Clients & revenue'!BK20/Clients_per_Rep,0)),0) -> 8
A73: Credit analysts and collections · SN | B73: people | D73: =MAX(E73:BL73) -> 9 | E73: =IF(E$3>=MIN(Start_Factoring,Start_Bridge,Start_Line,Start_Term)-Credit_Lead_Months,MAX(1,ROUNDUP(0/Book_per_Credit,0)),0) -> 0 | F73: =IF(F$3>=MIN(Start_Factoring,Start_Bridge,Start_Line,Start_Term)-Credit_Lead_Months,MAX(1,ROUNDUP(Credit!E25/Book_per_Credit,0)),0) -> 0 | G73: =IF(G$3>=MIN(Start_Factoring,Start_Bridge,Start_Line,Start_Term)-Credit_Lead_Months,MAX(1,ROUNDUP(Credit!F25/Book_per_Credit,0)),0) -> 0 | H73: =IF(H$3>=MIN(Start_Factoring,Start_Bridge,Start_Line,Start_Term)-Credit_Lead_Months,MAX(1,ROUNDUP(Credit!G25/Book_per_Credit,0)),0) -> 0 | I73: =IF(I$3>=MIN(Start_Factoring,Start_Bridge,Start_Line,Start_Term)-Credit_Lead_Months,MAX(1,ROUNDUP(Credit!H25/Book_per_Credit,0)),0) -> 0 | J73: =IF(J$3>=MIN(Start_Factoring,Start_Bridge,Start_Line,Start_Term)-Credit_Lead_Months,MAX(1,ROUNDUP(Credit!I25/Book_per_Credit,0)),0) -> 0 | K73: =IF(K$3>=MIN(Start_Factoring,Start_Bridge,Start_Line,Start_Term)-Credit_Lead_Months,MAX(1,ROUNDUP(Credit!J25/Book_per_Credit,0)),0) -> 0 | L73: =IF(L$3>=MIN(Start_Factoring,Start_Bridge,Start_Line,Start_Term)-Credit_Lead_Months,MAX(1,ROUNDUP(Credit!K25/Book_per_Credit,0)),0) -> 0 | M73: =IF(M$3>=MIN(Start_Factoring,Start_Bridge,Start_Line,Start_Term)-Credit_Lead_Months,MAX(1,ROUNDUP(Credit!L25/Book_per_Credit,0)),0) -> 0 | ... BL73: =IF(BL$3>=MIN(Start_Factoring,Start_Bridge,Start_Line,Start_Term)-Credit_Lead_Months,MAX(1,ROUNDUP(Credit!BK25/Book_per_Credit,0)),0) -> 9
A74: Employer cost: Customer support agents | B74: FCFA | D74: =SUM(E74:BL74) -> 2.5788744e+08 | E74: =E69*Salary_Support*(1+Employer_Charges)*(1+Salary_Raise)^(E$5-1) -> 0 | F74: =F69*Salary_Support*(1+Employer_Charges)*(1+Salary_Raise)^(F$5-1) -> 0 | G74: =G69*Salary_Support*(1+Employer_Charges)*(1+Salary_Raise)^(G$5-1) -> 0 | H74: =H69*Salary_Support*(1+Employer_Charges)*(1+Salary_Raise)^(H$5-1) -> 650000 | I74: =I69*Salary_Support*(1+Employer_Charges)*(1+Salary_Raise)^(I$5-1) -> 650000 | J74: =J69*Salary_Support*(1+Employer_Charges)*(1+Salary_Raise)^(J$5-1) -> 650000 | K74: =K69*Salary_Support*(1+Employer_Charges)*(1+Salary_Raise)^(K$5-1) -> 650000 | L74: =L69*Salary_Support*(1+Employer_Charges)*(1+Salary_Raise)^(L$5-1) -> 650000 | ... BL74: =BL69*Salary_Support*(1+Employer_Charges)*(1+Salary_Raise)^(BL$5-1) -> 13036305
A75: Employer cost: Developers | B75: FCFA | D75: =SUM(E75:BL75) -> 365660802 | E75: =E70*Salary_Dev*(1+Employer_Charges)*(1+Salary_Raise)^(E$5-1) -> 3120000 | F75: =F70*Salary_Dev*(1+Employer_Charges)*(1+Salary_Raise)^(F$5-1) -> 3120000 | G75: =G70*Salary_Dev*(1+Employer_Charges)*(1+Salary_Raise)^(G$5-1) -> 3120000 | H75: =H70*Salary_Dev*(1+Employer_Charges)*(1+Salary_Raise)^(H$5-1) -> 3120000 | I75: =I70*Salary_Dev*(1+Employer_Charges)*(1+Salary_Raise)^(I$5-1) -> 3120000 | J75: =J70*Salary_Dev*(1+Employer_Charges)*(1+Salary_Raise)^(J$5-1) -> 3120000 | K75: =K70*Salary_Dev*(1+Employer_Charges)*(1+Salary_Raise)^(K$5-1) -> 3120000 | L75: =L70*Salary_Dev*(1+Employer_Charges)*(1+Salary_Raise)^(L$5-1) -> 3120000 | ... BL75: =BL70*Salary_Dev*(1+Employer_Charges)*(1+Salary_Raise)^(BL$5-1) -> 13273328
A76: Employer cost: Field sales reps, Senegal | B76: FCFA | D76: =SUM(E76:BL76) -> 2.61819e+08 | E76: =E71*Salary_Rep_SN*(1+Employer_Charges)*(1+Salary_Raise)^(E$5-1) -> 0 | F76: =F71*Salary_Rep_SN*(1+Employer_Charges)*(1+Salary_Raise)^(F$5-1) -> 0 | G76: =G71*Salary_Rep_SN*(1+Employer_Charges)*(1+Salary_Raise)^(G$5-1) -> 0 | H76: =H71*Salary_Rep_SN*(1+Employer_Charges)*(1+Salary_Raise)^(H$5-1) -> 1040000 | I76: =I71*Salary_Rep_SN*(1+Employer_Charges)*(1+Salary_Raise)^(I$5-1) -> 1040000 | J76: =J71*Salary_Rep_SN*(1+Employer_Charges)*(1+Salary_Raise)^(J$5-1) -> 1040000 | K76: =K71*Salary_Rep_SN*(1+Employer_Charges)*(1+Salary_Raise)^(K$5-1) -> 1040000 | L76: =L71*Salary_Rep_SN*(1+Employer_Charges)*(1+Salary_Raise)^(L$5-1) -> 1040000 | ... BL76: =BL71*Salary_Rep_SN*(1+Employer_Charges)*(1+Salary_Raise)^(BL$5-1) -> 12009202
A77: Employer cost: Field sales reps, Côte d'Ivoire | B77: FCFA | D77: =SUM(E77:BL77) -> 1.1408312e+08 | E77: =E72*Salary_Rep_CI*(1+Employer_Charges)*(1+Salary_Raise)^(E$5-1) -> 0 | F77: =F72*Salary_Rep_CI*(1+Employer_Charges)*(1+Salary_Raise)^(F$5-1) -> 0 | G77: =G72*Salary_Rep_CI*(1+Employer_Charges)*(1+Salary_Raise)^(G$5-1) -> 0 | H77: =H72*Salary_Rep_CI*(1+Employer_Charges)*(1+Salary_Raise)^(H$5-1) -> 0 | I77: =I72*Salary_Rep_CI*(1+Employer_Charges)*(1+Salary_Raise)^(I$5-1) -> 0 | J77: =J72*Salary_Rep_CI*(1+Employer_Charges)*(1+Salary_Raise)^(J$5-1) -> 0 | K77: =K72*Salary_Rep_CI*(1+Employer_Charges)*(1+Salary_Raise)^(K$5-1) -> 0 | L77: =L72*Salary_Rep_CI*(1+Employer_Charges)*(1+Salary_Raise)^(L$5-1) -> 0 | ... BL77: =BL72*Salary_Rep_CI*(1+Employer_Charges)*(1+Salary_Raise)^(BL$5-1) -> 5688569.2
A78: Employer cost: Credit analysts and collections | B78: FCFA | D78: =SUM(E78:BL78) -> 1.7031648e+08 | E78: =E73*Salary_Credit*(1+Employer_Charges)*(1+Salary_Raise)^(E$5-1) -> 0 | F78: =F73*Salary_Credit*(1+Employer_Charges)*(1+Salary_Raise)^(F$5-1) -> 0 | G78: =G73*Salary_Credit*(1+Employer_Charges)*(1+Salary_Raise)^(G$5-1) -> 0 | H78: =H73*Salary_Credit*(1+Employer_Charges)*(1+Salary_Raise)^(H$5-1) -> 0 | I78: =I73*Salary_Credit*(1+Employer_Charges)*(1+Salary_Raise)^(I$5-1) -> 0 | J78: =J73*Salary_Credit*(1+Employer_Charges)*(1+Salary_Raise)^(J$5-1) -> 0 | K78: =K73*Salary_Credit*(1+Employer_Charges)*(1+Salary_Raise)^(K$5-1) -> 0 | L78: =L73*Salary_Credit*(1+Employer_Charges)*(1+Salary_Raise)^(L$5-1) -> 0 | ... BL78: =BL73*Salary_Credit*(1+Employer_Charges)*(1+Salary_Raise)^(BL$5-1) -> 8532853.9
A79: New hires in these roles | B79: people | D79: =SUM(E79:BL79) -> 76 | E79: =E69+E70+E71+E72+E73 -> 2 | F79: =MAX(0,F69-E69)+MAX(0,F70-E70)+MAX(0,F71-E71)+MAX(0,F72-E72)+MAX(0,F73-E73) -> 0 | G79: =MAX(0,G69-F69)+MAX(0,G70-F70)+MAX(0,G71-F71)+MAX(0,G72-F72)+MAX(0,G73-F73) -> 0 | H79: =MAX(0,H69-G69)+MAX(0,H70-G70)+MAX(0,H71-G71)+MAX(0,H72-G72)+MAX(0,H73-G73) -> 4 | I79: =MAX(0,I69-H69)+MAX(0,I70-H70)+MAX(0,I71-H71)+MAX(0,I72-H72)+MAX(0,I73-H73) -> 0 | J79: =MAX(0,J69-I69)+MAX(0,J70-I70)+MAX(0,J71-I71)+MAX(0,J72-I72)+MAX(0,J73-I73) -> 0 | K79: =MAX(0,K69-J69)+MAX(0,K70-J70)+MAX(0,K71-J71)+MAX(0,K72-J72)+MAX(0,K73-J73) -> 0 | L79: =MAX(0,L69-K69)+MAX(0,L70-K70)+MAX(0,L71-K71)+MAX(0,L72-K72)+MAX(0,L73-K73) -> 0 | M79: =MAX(0,M69-L69)+MAX(0,M70-L70)+MAX(0,M71-L71)+MAX(0,M72-L72)+MAX(0,M73-L73) -> 0 | ... BL79: =MAX(0,BL69-BK69)+MAX(0,BL70-BK70)+MAX(0,BL71-BK71)+MAX(0,BL72-BK72)+MAX(0,BL73-BK73) -> 1
A81: Summary
A82: Total headcount | B82: people | D82: =BL82 -> 84 | E82: =SUM(E9:E36)+E69+E70+E71+E72+E73 -> 5 | F82: =SUM(F9:F36)+F69+F70+F71+F72+F73 -> 5 | G82: =SUM(G9:G36)+G69+G70+G71+G72+G73 -> 5 | H82: =SUM(H9:H36)+H69+H70+H71+H72+H73 -> 10 | I82: =SUM(I9:I36)+I69+I70+I71+I72+I73 -> 11 | J82: =SUM(J9:J36)+J69+J70+J71+J72+J73 -> 11 | K82: =SUM(K9:K36)+K69+K70+K71+K72+K73 -> 11 | L82: =SUM(L9:L36)+L69+L70+L71+L72+L73 -> 11 | ... BL82: =SUM(BL9:BL36)+BL69+BL70+BL71+BL72+BL73 -> 84
A83: Headcount, Senegal | B83: people | D83: =BL83 -> 75 | E83: =SUMIF('Hiring plan'!$D$5:$D$32,"SN",E9:E36)+E69+E70+E71+E73 -> 5 | F83: =SUMIF('Hiring plan'!$D$5:$D$32,"SN",F9:F36)+F69+F70+F71+F73 -> 5 | G83: =SUMIF('Hiring plan'!$D$5:$D$32,"SN",G9:G36)+G69+G70+G71+G73 -> 5 | H83: =SUMIF('Hiring plan'!$D$5:$D$32,"SN",H9:H36)+H69+H70+H71+H73 -> 10 | I83: =SUMIF('Hiring plan'!$D$5:$D$32,"SN",I9:I36)+I69+I70+I71+I73 -> 11 | J83: =SUMIF('Hiring plan'!$D$5:$D$32,"SN",J9:J36)+J69+J70+J71+J73 -> 11 | K83: =SUMIF('Hiring plan'!$D$5:$D$32,"SN",K9:K36)+K69+K70+K71+K73 -> 11 | L83: =SUMIF('Hiring plan'!$D$5:$D$32,"SN",L9:L36)+L69+L70+L71+L73 -> 11 | ... BL83: =SUMIF('Hiring plan'!$D$5:$D$32,"SN",BL9:BL36)+BL69+BL70+BL71+BL73 -> 75
A84: Headcount, Côte d'Ivoire | B84: people | D84: =BL84 -> 9 | E84: =SUMIF('Hiring plan'!$D$5:$D$32,"CI",E9:E36)+E72 -> 0 | F84: =SUMIF('Hiring plan'!$D$5:$D$32,"CI",F9:F36)+F72 -> 0 | G84: =SUMIF('Hiring plan'!$D$5:$D$32,"CI",G9:G36)+G72 -> 0 | H84: =SUMIF('Hiring plan'!$D$5:$D$32,"CI",H9:H36)+H72 -> 0 | I84: =SUMIF('Hiring plan'!$D$5:$D$32,"CI",I9:I36)+I72 -> 0 | J84: =SUMIF('Hiring plan'!$D$5:$D$32,"CI",J9:J36)+J72 -> 0 | K84: =SUMIF('Hiring plan'!$D$5:$D$32,"CI",K9:K36)+K72 -> 0 | L84: =SUMIF('Hiring plan'!$D$5:$D$32,"CI",L9:L36)+L72 -> 0 | ... BL84: =SUMIF('Hiring plan'!$D$5:$D$32,"CI",BL9:BL36)+BL72 -> 9
A85: Engineering headcount (CTO and developers) | B85: people | D85: =BL85 -> 8 | E85: =SUMIF('Hiring plan'!$B$5:$B$32,"Engineering & product",E9:E36)+E70 -> 3 | F85: =SUMIF('Hiring plan'!$B$5:$B$32,"Engineering & product",F9:F36)+F70 -> 3 | G85: =SUMIF('Hiring plan'!$B$5:$B$32,"Engineering & product",G9:G36)+G70 -> 3 | H85: =SUMIF('Hiring plan'!$B$5:$B$32,"Engineering & product",H9:H36)+H70 -> 3 | I85: =SUMIF('Hiring plan'!$B$5:$B$32,"Engineering & product",I9:I36)+I70 -> 3 | J85: =SUMIF('Hiring plan'!$B$5:$B$32,"Engineering & product",J9:J36)+J70 -> 3 | K85: =SUMIF('Hiring plan'!$B$5:$B$32,"Engineering & product",K9:K36)+K70 -> 3 | L85: =SUMIF('Hiring plan'!$B$5:$B$32,"Engineering & product",L9:L36)+L70 -> 3 | ... BL85: =SUMIF('Hiring plan'!$B$5:$B$32,"Engineering & product",BL9:BL36)+BL70 -> 8
A86: Field sales reps, Senegal | B86: people | D86: =BL86 -> 20 | E86: =SUMIFS(E9:E36,'Hiring plan'!$E$5:$E$32,"Sales rep",'Hiring plan'!$D$5:$D$32,"SN")+E71 -> 1 | F86: =SUMIFS(F9:F36,'Hiring plan'!$E$5:$E$32,"Sales rep",'Hiring plan'!$D$5:$D$32,"SN")+F71 -> 1 | G86: =SUMIFS(G9:G36,'Hiring plan'!$E$5:$E$32,"Sales rep",'Hiring plan'!$D$5:$D$32,"SN")+G71 -> 1 | H86: =SUMIFS(H9:H36,'Hiring plan'!$E$5:$E$32,"Sales rep",'Hiring plan'!$D$5:$D$32,"SN")+H71 -> 3 | I86: =SUMIFS(I9:I36,'Hiring plan'!$E$5:$E$32,"Sales rep",'Hiring plan'!$D$5:$D$32,"SN")+I71 -> 3 | J86: =SUMIFS(J9:J36,'Hiring plan'!$E$5:$E$32,"Sales rep",'Hiring plan'!$D$5:$D$32,"SN")+J71 -> 3 | K86: =SUMIFS(K9:K36,'Hiring plan'!$E$5:$E$32,"Sales rep",'Hiring plan'!$D$5:$D$32,"SN")+K71 -> 3 | L86: =SUMIFS(L9:L36,'Hiring plan'!$E$5:$E$32,"Sales rep",'Hiring plan'!$D$5:$D$32,"SN")+L71 -> 3 | ... BL86: =SUMIFS(BL9:BL36,'Hiring plan'!$E$5:$E$32,"Sales rep",'Hiring plan'!$D$5:$D$32,"SN")+BL71 -> 20
A87: Field sales reps, Côte d'Ivoire | B87: people | D87: =BL87 -> 8 | E87: =SUMIFS(E9:E36,'Hiring plan'!$E$5:$E$32,"Sales rep",'Hiring plan'!$D$5:$D$32,"CI")+E72 -> 0 | F87: =SUMIFS(F9:F36,'Hiring plan'!$E$5:$E$32,"Sales rep",'Hiring plan'!$D$5:$D$32,"CI")+F72 -> 0 | G87: =SUMIFS(G9:G36,'Hiring plan'!$E$5:$E$32,"Sales rep",'Hiring plan'!$D$5:$D$32,"CI")+G72 -> 0 | H87: =SUMIFS(H9:H36,'Hiring plan'!$E$5:$E$32,"Sales rep",'Hiring plan'!$D$5:$D$32,"CI")+H72 -> 0 | I87: =SUMIFS(I9:I36,'Hiring plan'!$E$5:$E$32,"Sales rep",'Hiring plan'!$D$5:$D$32,"CI")+I72 -> 0 | J87: =SUMIFS(J9:J36,'Hiring plan'!$E$5:$E$32,"Sales rep",'Hiring plan'!$D$5:$D$32,"CI")+J72 -> 0 | K87: =SUMIFS(K9:K36,'Hiring plan'!$E$5:$E$32,"Sales rep",'Hiring plan'!$D$5:$D$32,"CI")+K72 -> 0 | L87: =SUMIFS(L9:L36,'Hiring plan'!$E$5:$E$32,"Sales rep",'Hiring plan'!$D$5:$D$32,"CI")+L72 -> 0 | ... BL87: =SUMIFS(BL9:BL36,'Hiring plan'!$E$5:$E$32,"Sales rep",'Hiring plan'!$D$5:$D$32,"CI")+BL72 -> 8
A88: New hires this month | B88: people | D88: =SUM(E88:BL88) -> 84 | E88: =SUMPRODUCT(--('Hiring plan'!$G$5:$G$32=E$3),'Hiring plan'!$F$5:$F$32)+E79 -> 5 | F88: =SUMPRODUCT(--('Hiring plan'!$G$5:$G$32=F$3),'Hiring plan'!$F$5:$F$32)+F79 -> 0 | G88: =SUMPRODUCT(--('Hiring plan'!$G$5:$G$32=G$3),'Hiring plan'!$F$5:$F$32)+G79 -> 0 | H88: =SUMPRODUCT(--('Hiring plan'!$G$5:$G$32=H$3),'Hiring plan'!$F$5:$F$32)+H79 -> 5 | I88: =SUMPRODUCT(--('Hiring plan'!$G$5:$G$32=I$3),'Hiring plan'!$F$5:$F$32)+I79 -> 1 | J88: =SUMPRODUCT(--('Hiring plan'!$G$5:$G$32=J$3),'Hiring plan'!$F$5:$F$32)+J79 -> 0 | K88: =SUMPRODUCT(--('Hiring plan'!$G$5:$G$32=K$3),'Hiring plan'!$F$5:$F$32)+K79 -> 0 | L88: =SUMPRODUCT(--('Hiring plan'!$G$5:$G$32=L$3),'Hiring plan'!$F$5:$F$32)+L79 -> 0 | ... BL88: =SUMPRODUCT(--('Hiring plan'!$G$5:$G$32=BL$3),'Hiring plan'!$F$5:$F$32)+BL79 -> 1
A89: of which CTO and developers (MacBooks) | B89: people | D89: =SUM(E89:BL89) -> 8 | E89: =SUMPRODUCT(--('Hiring plan'!$G$5:$G$32=E$3),--('Hiring plan'!$B$5:$B$32="Engineering & product"),'Hiring plan'!$F$5:$F$32)+E70 -> 3 | F89: =SUMPRODUCT(--('Hiring plan'!$G$5:$G$32=F$3),--('Hiring plan'!$B$5:$B$32="Engineering & product"),'Hiring plan'!$F$5:$F$32)+MAX(0,F70-E70) -> 0 | G89: =SUMPRODUCT(--('Hiring plan'!$G$5:$G$32=G$3),--('Hiring plan'!$B$5:$B$32="Engineering & product"),'Hiring plan'!$F$5:$F$32)+MAX(0,G70-F70) -> 0 | H89: =SUMPRODUCT(--('Hiring plan'!$G$5:$G$32=H$3),--('Hiring plan'!$B$5:$B$32="Engineering & product"),'Hiring plan'!$F$5:$F$32)+MAX(0,H70-G70) -> 0 | I89: =SUMPRODUCT(--('Hiring plan'!$G$5:$G$32=I$3),--('Hiring plan'!$B$5:$B$32="Engineering & product"),'Hiring plan'!$F$5:$F$32)+MAX(0,I70-H70) -> 0 | J89: =SUMPRODUCT(--('Hiring plan'!$G$5:$G$32=J$3),--('Hiring plan'!$B$5:$B$32="Engineering & product"),'Hiring plan'!$F$5:$F$32)+MAX(0,J70-I70) -> 0 | K89: =SUMPRODUCT(--('Hiring plan'!$G$5:$G$32=K$3),--('Hiring plan'!$B$5:$B$32="Engineering & product"),'Hiring plan'!$F$5:$F$32)+MAX(0,K70-J70) -> 0 | L89: =SUMPRODUCT(--('Hiring plan'!$G$5:$G$32=L$3),--('Hiring plan'!$B$5:$B$32="Engineering & product"),'Hiring plan'!$F$5:$F$32)+MAX(0,L70-K70) -> 0 | M89: =SUMPRODUCT(--('Hiring plan'!$G$5:$G$32=M$3),--('Hiring plan'!$B$5:$B$32="Engineering & product"),'Hiring plan'!$F$5:$F$32)+MAX(0,M70-L70) -> 0 | ... BL89: =SUMPRODUCT(--('Hiring plan'!$G$5:$G$32=BL$3),--('Hiring plan'!$B$5:$B$32="Engineering & product"),'Hiring plan'!$F$5:$F$32)+MAX(0,BL70-BK70) -> 0
A90: Staff cost: Leadership | B90: FCFA | D90: =SUM(E90:BL90) -> 3.5506919e+08 | E90: =SUMIF('Hiring plan'!$B$5:$B$32,"Leadership",E39:E66)+0 -> 0 | F90: =SUMIF('Hiring plan'!$B$5:$B$32,"Leadership",F39:F66)+0 -> 0 | G90: =SUMIF('Hiring plan'!$B$5:$B$32,"Leadership",G39:G66)+0 -> 0 | H90: =SUMIF('Hiring plan'!$B$5:$B$32,"Leadership",H39:H66)+0 -> 0 | I90: =SUMIF('Hiring plan'!$B$5:$B$32,"Leadership",I39:I66)+0 -> 0 | J90: =SUMIF('Hiring plan'!$B$5:$B$32,"Leadership",J39:J66)+0 -> 0 | K90: =SUMIF('Hiring plan'!$B$5:$B$32,"Leadership",K39:K66)+0 -> 0 | L90: =SUMIF('Hiring plan'!$B$5:$B$32,"Leadership",L39:L66)+0 -> 0 | ... BL90: =SUMIF('Hiring plan'!$B$5:$B$32,"Leadership",BL39:BL66)+0 -> 8374838.1
A91: Staff cost: Engineering & product | B91: FCFA | D91: =SUM(E91:BL91) -> 5.8116042e+08 | E91: =SUMIF('Hiring plan'!$B$5:$B$32,"Engineering & product",E39:E66)+E75 -> 6370000 | F91: =SUMIF('Hiring plan'!$B$5:$B$32,"Engineering & product",F39:F66)+F75 -> 6370000 | G91: =SUMIF('Hiring plan'!$B$5:$B$32,"Engineering & product",G39:G66)+G75 -> 6370000 | H91: =SUMIF('Hiring plan'!$B$5:$B$32,"Engineering & product",H39:H66)+H75 -> 6370000 | I91: =SUMIF('Hiring plan'!$B$5:$B$32,"Engineering & product",I39:I66)+I75 -> 6370000 | J91: =SUMIF('Hiring plan'!$B$5:$B$32,"Engineering & product",J39:J66)+J75 -> 6370000 | K91: =SUMIF('Hiring plan'!$B$5:$B$32,"Engineering & product",K39:K66)+K75 -> 6370000 | L91: =SUMIF('Hiring plan'!$B$5:$B$32,"Engineering & product",L39:L66)+L75 -> 6370000 | ... BL91: =SUMIF('Hiring plan'!$B$5:$B$32,"Engineering & product",BL39:BL66)+BL75 -> 17223724
A92: Staff cost: Compliance & risk | B92: FCFA | D92: =SUM(E92:BL92) -> 83377271 | E92: =SUMIF('Hiring plan'!$B$5:$B$32,"Compliance & risk",E39:E66)+0 -> 0 | F92: =SUMIF('Hiring plan'!$B$5:$B$32,"Compliance & risk",F39:F66)+0 -> 0 | G92: =SUMIF('Hiring plan'!$B$5:$B$32,"Compliance & risk",G39:G66)+0 -> 0 | H92: =SUMIF('Hiring plan'!$B$5:$B$32,"Compliance & risk",H39:H66)+0 -> 0 | I92: =SUMIF('Hiring plan'!$B$5:$B$32,"Compliance & risk",I39:I66)+0 -> 0 | J92: =SUMIF('Hiring plan'!$B$5:$B$32,"Compliance & risk",J39:J66)+0 -> 0 | K92: =SUMIF('Hiring plan'!$B$5:$B$32,"Compliance & risk",K39:K66)+0 -> 0 | L92: =SUMIF('Hiring plan'!$B$5:$B$32,"Compliance & risk",L39:L66)+0 -> 0 | ... BL92: =SUMIF('Hiring plan'!$B$5:$B$32,"Compliance & risk",BL39:BL66)+0 -> 2370237.2
A93: Staff cost: Credit | B93: FCFA | D93: =SUM(E93:BL93) -> 1.7031648e+08 | E93: =SUMIF('Hiring plan'!$B$5:$B$32,"Credit",E39:E66)+E78 -> 0 | F93: =SUMIF('Hiring plan'!$B$5:$B$32,"Credit",F39:F66)+F78 -> 0 | G93: =SUMIF('Hiring plan'!$B$5:$B$32,"Credit",G39:G66)+G78 -> 0 | H93: =SUMIF('Hiring plan'!$B$5:$B$32,"Credit",H39:H66)+H78 -> 0 | I93: =SUMIF('Hiring plan'!$B$5:$B$32,"Credit",I39:I66)+I78 -> 0 | J93: =SUMIF('Hiring plan'!$B$5:$B$32,"Credit",J39:J66)+J78 -> 0 | K93: =SUMIF('Hiring plan'!$B$5:$B$32,"Credit",K39:K66)+K78 -> 0 | L93: =SUMIF('Hiring plan'!$B$5:$B$32,"Credit",L39:L66)+L78 -> 0 | ... BL93: =SUMIF('Hiring plan'!$B$5:$B$32,"Credit",BL39:BL66)+BL78 -> 8532853.9
A94: Staff cost: Operations & support | B94: FCFA | D94: =SUM(E94:BL94) -> 2.5788744e+08 | E94: =SUMIF('Hiring plan'!$B$5:$B$32,"Operations & support",E39:E66)+E74 -> 0 | F94: =SUMIF('Hiring plan'!$B$5:$B$32,"Operations & support",F39:F66)+F74 -> 0 | G94: =SUMIF('Hiring plan'!$B$5:$B$32,"Operations & support",G39:G66)+G74 -> 0 | H94: =SUMIF('Hiring plan'!$B$5:$B$32,"Operations & support",H39:H66)+H74 -> 650000 | I94: =SUMIF('Hiring plan'!$B$5:$B$32,"Operations & support",I39:I66)+I74 -> 650000 | J94: =SUMIF('Hiring plan'!$B$5:$B$32,"Operations & support",J39:J66)+J74 -> 650000 | K94: =SUMIF('Hiring plan'!$B$5:$B$32,"Operations & support",K39:K66)+K74 -> 650000 | L94: =SUMIF('Hiring plan'!$B$5:$B$32,"Operations & support",L39:L66)+L74 -> 650000 | ... BL94: =SUMIF('Hiring plan'!$B$5:$B$32,"Operations & support",BL39:BL66)+BL74 -> 13036305
A95: Staff cost: Sales & partnerships | B95: FCFA | D95: =SUM(E95:BL95) -> 4.7934194e+08 | E95: =SUMIF('Hiring plan'!$B$5:$B$32,"Sales & partnerships",E39:E66)+E76+E77 -> 1560000 | F95: =SUMIF('Hiring plan'!$B$5:$B$32,"Sales & partnerships",F39:F66)+F76+F77 -> 1560000 | G95: =SUMIF('Hiring plan'!$B$5:$B$32,"Sales & partnerships",G39:G66)+G76+G77 -> 1560000 | H95: =SUMIF('Hiring plan'!$B$5:$B$32,"Sales & partnerships",H39:H66)+H76+H77 -> 2600000 | I95: =SUMIF('Hiring plan'!$B$5:$B$32,"Sales & partnerships",I39:I66)+I76+I77 -> 2600000 | J95: =SUMIF('Hiring plan'!$B$5:$B$32,"Sales & partnerships",J39:J66)+J76+J77 -> 2600000 | K95: =SUMIF('Hiring plan'!$B$5:$B$32,"Sales & partnerships",K39:K66)+K76+K77 -> 2600000 | L95: =SUMIF('Hiring plan'!$B$5:$B$32,"Sales & partnerships",L39:L66)+L76+L77 -> 2600000 | ... BL95: =SUMIF('Hiring plan'!$B$5:$B$32,"Sales & partnerships",BL39:BL66)+BL76+BL77 -> 19593961
A96: Staff cost: Marketing | B96: FCFA | D96: =SUM(E96:BL96) -> 1.064698e+08 | E96: =SUMIF('Hiring plan'!$B$5:$B$32,"Marketing",E39:E66)+0 -> 0 | F96: =SUMIF('Hiring plan'!$B$5:$B$32,"Marketing",F39:F66)+0 -> 0 | G96: =SUMIF('Hiring plan'!$B$5:$B$32,"Marketing",G39:G66)+0 -> 0 | H96: =SUMIF('Hiring plan'!$B$5:$B$32,"Marketing",H39:H66)+0 -> 1170000 | I96: =SUMIF('Hiring plan'!$B$5:$B$32,"Marketing",I39:I66)+0 -> 1690000 | J96: =SUMIF('Hiring plan'!$B$5:$B$32,"Marketing",J39:J66)+0 -> 1690000 | K96: =SUMIF('Hiring plan'!$B$5:$B$32,"Marketing",K39:K66)+0 -> 1690000 | L96: =SUMIF('Hiring plan'!$B$5:$B$32,"Marketing",L39:L66)+0 -> 1690000 | ... BL96: =SUMIF('Hiring plan'!$B$5:$B$32,"Marketing",BL39:BL66)+0 -> 2054205.6
A97: Staff cost: Finance & admin | B97: FCFA | D97: =SUM(E97:BL97) -> 1.2929977e+08 | E97: =SUMIF('Hiring plan'!$B$5:$B$32,"Finance & admin",E39:E66)+0 -> 1950000 | F97: =SUMIF('Hiring plan'!$B$5:$B$32,"Finance & admin",F39:F66)+0 -> 1950000 | G97: =SUMIF('Hiring plan'!$B$5:$B$32,"Finance & admin",G39:G66)+0 -> 1950000 | H97: =SUMIF('Hiring plan'!$B$5:$B$32,"Finance & admin",H39:H66)+0 -> 1950000 | I97: =SUMIF('Hiring plan'!$B$5:$B$32,"Finance & admin",I39:I66)+0 -> 1950000 | J97: =SUMIF('Hiring plan'!$B$5:$B$32,"Finance & admin",J39:J66)+0 -> 1950000 | K97: =SUMIF('Hiring plan'!$B$5:$B$32,"Finance & admin",K39:K66)+0 -> 1950000 | L97: =SUMIF('Hiring plan'!$B$5:$B$32,"Finance & admin",L39:L66)+0 -> 1950000 | ... BL97: =SUMIF('Hiring plan'!$B$5:$B$32,"Finance & admin",BL39:BL66)+0 -> 2370237.2
A98: Total staff cost | B98: FCFA | D98: =SUM(E98:BL98) -> 2.1629223e+09 | E98: =SUM(E39:E66)+E74+E75+E76+E77+E78 -> 9880000 | F98: =SUM(F39:F66)+F74+F75+F76+F77+F78 -> 9880000 | G98: =SUM(G39:G66)+G74+G75+G76+G77+G78 -> 9880000 | H98: =SUM(H39:H66)+H74+H75+H76+H77+H78 -> 12740000 | I98: =SUM(I39:I66)+I74+I75+I76+I77+I78 -> 13260000 | J98: =SUM(J39:J66)+J74+J75+J76+J77+J78 -> 13260000 | K98: =SUM(K39:K66)+K74+K75+K76+K77+K78 -> 13260000 | L98: =SUM(L39:L66)+L74+L75+L76+L77+L78 -> 13260000 | ... BL98: =SUM(BL39:BL66)+BL74+BL75+BL76+BL77+BL78 -> 73556361

Sheet Staff (€)
A1: Staff (€)
A2: Every amount of the 'Staff' sheet in euros (FCFA ÷ FCFA per euro on Assumptions). Edit the FCFA sheets and Assumptions, not this one.
A3: Month # | D3: Total / end | E3: =Staff!E3 -> 1 | F3: =Staff!F3 -> 2 | G3: =Staff!G3 -> 3 | H3: =Staff!H3 -> 4 | I3: =Staff!I3 -> 5 | J3: =Staff!J3 -> 6 | K3: =Staff!K3 -> 7 | L3: =Staff!L3 -> 8 | ... BL3: =Staff!BL3 -> 60
A4: Month | E4: =Staff!E4 -> 46388 | F4: =Staff!F4 -> 46419 | G4: =Staff!G4 -> 46447 | H4: =Staff!H4 -> 46478 | I4: =Staff!I4 -> 46508 | J4: =Staff!J4 -> 46539 | K4: =Staff!K4 -> 46569 | L4: =Staff!L4 -> 46600 | ... BL4: =Staff!BL4 -> 48183
A5: Year | E5: =Staff!E5 -> 1 | F5: =Staff!F5 -> 1 | G5: =Staff!G5 -> 1 | H5: =Staff!H5 -> 1 | I5: =Staff!I5 -> 1 | J5: =Staff!J5 -> 1 | K5: =Staff!K5 -> 1 | L5: =Staff!L5 -> 1 | ... BL5: =Staff!BL5 -> 5
A8: Headcount by hire line
A10: Employer cost by hire line
A11: =Staff!A39 -> CEO (full salary from year 2) · SN | B11: € | D11: =Staff!D39/FX_EUR -> 269071.93 | E11: =Staff!E39/FX_EUR -> 0 | F11: =Staff!F39/FX_EUR -> 0 | G11: =Staff!G39/FX_EUR -> 0 | H11: =Staff!H39/FX_EUR -> 0 | I11: =Staff!I39/FX_EUR -> 0 | J11: =Staff!J39/FX_EUR -> 0 | K11: =Staff!K39/FX_EUR -> 0 | ... BL11: =Staff!BL39/FX_EUR -> 6022.3388
A12: =Staff!A40 -> CTO (also codes) · SN | B12: € | D12: =Staff!D40/FX_EUR -> 328527.05 | E12: =Staff!E40/FX_EUR -> 4954.5931 | F12: =Staff!F40/FX_EUR -> 4954.5931 | G12: =Staff!G40/FX_EUR -> 4954.5931 | H12: =Staff!H40/FX_EUR -> 4954.5931 | I12: =Staff!I40/FX_EUR -> 4954.5931 | J12: =Staff!J40/FX_EUR -> 4954.5931 | K12: =Staff!K40/FX_EUR -> 4954.5931 | ... BL12: =Staff!BL40/FX_EUR -> 6022.3388
A13: =Staff!A41 -> Financial expert (finance, partners, credit lead) · SN | B13: € | D13: =Staff!D41/FX_EUR -> 197116.23 | E13: =Staff!E41/FX_EUR -> 2972.7558 | F13: =Staff!F41/FX_EUR -> 2972.7558 | G13: =Staff!G41/FX_EUR -> 2972.7558 | H13: =Staff!H41/FX_EUR -> 2972.7558 | I13: =Staff!I41/FX_EUR -> 2972.7558 | J13: =Staff!J41/FX_EUR -> 2972.7558 | K13: =Staff!K41/FX_EUR -> 2972.7558 | ... BL13: =Staff!BL41/FX_EUR -> 3613.4033
A14: =Staff!A42 -> Sales lead (also sells; incl. bonus) · SN | B14: € | D14: =Staff!D42/FX_EUR -> 157692.98 | E14: =Staff!E42/FX_EUR -> 2378.2047 | F14: =Staff!F42/FX_EUR -> 2378.2047 | G14: =Staff!G42/FX_EUR -> 2378.2047 | H14: =Staff!H42/FX_EUR -> 2378.2047 | I14: =Staff!I42/FX_EUR -> 2378.2047 | J14: =Staff!J42/FX_EUR -> 2378.2047 | K14: =Staff!K42/FX_EUR -> 2378.2047 | ... BL14: =Staff!BL42/FX_EUR -> 2890.7226
A15: =Staff!A43 -> Marketing manager (senior) · SN | B15: € | D15: =Staff!D43/FX_EUR -> 112918.78 | E15: =Staff!E43/FX_EUR -> 0 | F15: =Staff!F43/FX_EUR -> 0 | G15: =Staff!G43/FX_EUR -> 0 | H15: =Staff!H43/FX_EUR -> 1783.6535 | I15: =Staff!I43/FX_EUR -> 1783.6535 | J15: =Staff!J43/FX_EUR -> 1783.6535 | K15: =Staff!K43/FX_EUR -> 1783.6535 | ... BL15: =Staff!BL43/FX_EUR -> 2168.042
A16: =Staff!A44 -> Marketing officer (junior) · SN | B16: € | D16: =Staff!D44/FX_EUR -> 49393.389 | E16: =Staff!E44/FX_EUR -> 0 | F16: =Staff!F44/FX_EUR -> 0 | G16: =Staff!G44/FX_EUR -> 0 | H16: =Staff!H44/FX_EUR -> 0 | I16: =Staff!I44/FX_EUR -> 792.73489 | J16: =Staff!J44/FX_EUR -> 792.73489 | K16: =Staff!K44/FX_EUR -> 792.73489 | ... BL16: =Staff!BL44/FX_EUR -> 963.57421
A17: =Staff!A45 -> Country manager, Abidjan · CI | B17: € | D17: =Staff!D45/FX_EUR -> 272227.56 | E17: =Staff!E45/FX_EUR -> 0 | F17: =Staff!F45/FX_EUR -> 0 | G17: =Staff!G45/FX_EUR -> 0 | H17: =Staff!H45/FX_EUR -> 0 | I17: =Staff!I45/FX_EUR -> 0 | J17: =Staff!J45/FX_EUR -> 0 | K17: =Staff!K45/FX_EUR -> 0 | ... BL17: =Staff!BL45/FX_EUR -> 6745.0195
A18: =Staff!A46 -> Compliance officer (AML/CFT) · SN | B18: € | D18: =Staff!D46/FX_EUR -> 127107.83 | E18: =Staff!E46/FX_EUR -> 0 | F18: =Staff!F46/FX_EUR -> 0 | G18: =Staff!G46/FX_EUR -> 0 | H18: =Staff!H46/FX_EUR -> 0 | I18: =Staff!I46/FX_EUR -> 0 | J18: =Staff!J46/FX_EUR -> 0 | K18: =Staff!K46/FX_EUR -> 0 | ... BL18: =Staff!BL46/FX_EUR -> 3613.4033
A19: =Staff!A47 -> (spare line 9) | B19: € | D19: =Staff!D47/FX_EUR -> 0 | E19: =Staff!E47/FX_EUR -> 0 | F19: =Staff!F47/FX_EUR -> 0 | G19: =Staff!G47/FX_EUR -> 0 | H19: =Staff!H47/FX_EUR -> 0 | I19: =Staff!I47/FX_EUR -> 0 | J19: =Staff!J47/FX_EUR -> 0 | K19: =Staff!K47/FX_EUR -> 0 | ... BL19: =Staff!BL47/FX_EUR -> 0
A20: =Staff!A48 -> (spare line 10) | B20: € | D20: =Staff!D48/FX_EUR -> 0 | E20: =Staff!E48/FX_EUR -> 0 | F20: =Staff!F48/FX_EUR -> 0 | G20: =Staff!G48/FX_EUR -> 0 | H20: =Staff!H48/FX_EUR -> 0 | I20: =Staff!I48/FX_EUR -> 0 | J20: =Staff!J48/FX_EUR -> 0 | K20: =Staff!K48/FX_EUR -> 0 | ... BL20: =Staff!BL48/FX_EUR -> 0
A21: =Staff!A49 -> (spare line 11) | B21: € | D21: =Staff!D49/FX_EUR -> 0 | E21: =Staff!E49/FX_EUR -> 0 | F21: =Staff!F49/FX_EUR -> 0 | G21: =Staff!G49/FX_EUR -> 0 | H21: =Staff!H49/FX_EUR -> 0 | I21: =Staff!I49/FX_EUR -> 0 | J21: =Staff!J49/FX_EUR -> 0 | K21: =Staff!K49/FX_EUR -> 0 | ... BL21: =Staff!BL49/FX_EUR -> 0
A22: =Staff!A50 -> (spare line 12) | B22: € | D22: =Staff!D50/FX_EUR -> 0 | E22: =Staff!E50/FX_EUR -> 0 | F22: =Staff!F50/FX_EUR -> 0 | G22: =Staff!G50/FX_EUR -> 0 | H22: =Staff!H50/FX_EUR -> 0 | I22: =Staff!I50/FX_EUR -> 0 | J22: =Staff!J50/FX_EUR -> 0 | K22: =Staff!K50/FX_EUR -> 0 | ... BL22: =Staff!BL50/FX_EUR -> 0
... A38: =Staff!A66 -> (spare line 28) | B38: € | D38: =Staff!D66/FX_EUR -> 0 | E38: =Staff!E66/FX_EUR -> 0 | F38: =Staff!F66/FX_EUR -> 0 | G38: =Staff!G66/FX_EUR -> 0 | H38: =Staff!H66/FX_EUR -> 0 | I38: =Staff!I66/FX_EUR -> 0 | J38: =Staff!J66/FX_EUR -> 0 | K38: =Staff!K66/FX_EUR -> 0 | ... BL38: =Staff!BL66/FX_EUR -> 0
A40: Team that grows with volume
A41: Employer cost: Customer support agents | B41: € | D41: =Staff!D74/FX_EUR -> 393146.87 | E41: =Staff!E74/FX_EUR -> 0 | F41: =Staff!F74/FX_EUR -> 0 | G41: =Staff!G74/FX_EUR -> 0 | H41: =Staff!H74/FX_EUR -> 990.91861 | I41: =Staff!I74/FX_EUR -> 990.91861 | J41: =Staff!J74/FX_EUR -> 990.91861 | K41: =Staff!K74/FX_EUR -> 990.91861 | ... BL41: =Staff!BL74/FX_EUR -> 19873.718
A42: Employer cost: Developers | B42: € | D42: =Staff!D75/FX_EUR -> 557446.3 | E42: =Staff!E75/FX_EUR -> 4756.4093 | F42: =Staff!F75/FX_EUR -> 4756.4093 | G42: =Staff!G75/FX_EUR -> 4756.4093 | H42: =Staff!H75/FX_EUR -> 4756.4093 | I42: =Staff!I75/FX_EUR -> 4756.4093 | J42: =Staff!J75/FX_EUR -> 4756.4093 | K42: =Staff!K75/FX_EUR -> 4756.4093 | ... BL42: =Staff!BL75/FX_EUR -> 20235.058
A43: Employer cost: Field sales reps, Senegal | B43: € | D43: =Staff!D76/FX_EUR -> 399140.5 | E43: =Staff!E76/FX_EUR -> 0 | F43: =Staff!F76/FX_EUR -> 0 | G43: =Staff!G76/FX_EUR -> 0 | H43: =Staff!H76/FX_EUR -> 1585.4698 | I43: =Staff!I76/FX_EUR -> 1585.4698 | J43: =Staff!J76/FX_EUR -> 1585.4698 | K43: =Staff!K76/FX_EUR -> 1585.4698 | ... BL43: =Staff!BL76/FX_EUR -> 18307.91
A44: Employer cost: Field sales reps, Côte d'Ivoire | B44: € | D44: =Staff!D77/FX_EUR -> 173918.59 | E44: =Staff!E77/FX_EUR -> 0 | F44: =Staff!F77/FX_EUR -> 0 | G44: =Staff!G77/FX_EUR -> 0 | H44: =Staff!H77/FX_EUR -> 0 | I44: =Staff!I77/FX_EUR -> 0 | J44: =Staff!J77/FX_EUR -> 0 | K44: =Staff!K77/FX_EUR -> 0 | ... BL44: =Staff!BL77/FX_EUR -> 8672.1679
A45: Employer cost: Credit analysts and collections | B45: € | D45: =Staff!D78/FX_EUR -> 259645.79 | E45: =Staff!E78/FX_EUR -> 0 | F45: =Staff!F78/FX_EUR -> 0 | G45: =Staff!G78/FX_EUR -> 0 | H45: =Staff!H78/FX_EUR -> 0 | I45: =Staff!I78/FX_EUR -> 0 | J45: =Staff!J78/FX_EUR -> 0 | K45: =Staff!K78/FX_EUR -> 0 | ... BL45: =Staff!BL78/FX_EUR -> 13008.252
A47: Summary
A48: Staff cost: Leadership | B48: € | D48: =Staff!D90/FX_EUR -> 541299.49 | E48: =Staff!E90/FX_EUR -> 0 | F48: =Staff!F90/FX_EUR -> 0 | G48: =Staff!G90/FX_EUR -> 0 | H48: =Staff!H90/FX_EUR -> 0 | I48: =Staff!I90/FX_EUR -> 0 | J48: =Staff!J90/FX_EUR -> 0 | K48: =Staff!K90/FX_EUR -> 0 | ... BL48: =Staff!BL90/FX_EUR -> 12767.358
A49: Staff cost: Engineering & product | B49: € | D49: =Staff!D91/FX_EUR -> 885973.35 | E49: =Staff!E91/FX_EUR -> 9711.0024 | F49: =Staff!F91/FX_EUR -> 9711.0024 | G49: =Staff!G91/FX_EUR -> 9711.0024 | H49: =Staff!H91/FX_EUR -> 9711.0024 | I49: =Staff!I91/FX_EUR -> 9711.0024 | J49: =Staff!J91/FX_EUR -> 9711.0024 | K49: =Staff!K91/FX_EUR -> 9711.0024 | ... BL49: =Staff!BL91/FX_EUR -> 26257.397
A50: Staff cost: Compliance & risk | B50: € | D50: =Staff!D92/FX_EUR -> 127107.83 | E50: =Staff!E92/FX_EUR -> 0 | F50: =Staff!F92/FX_EUR -> 0 | G50: =Staff!G92/FX_EUR -> 0 | H50: =Staff!H92/FX_EUR -> 0 | I50: =Staff!I92/FX_EUR -> 0 | J50: =Staff!J92/FX_EUR -> 0 | K50: =Staff!K92/FX_EUR -> 0 | ... BL50: =Staff!BL92/FX_EUR -> 3613.4033
A51: Staff cost: Credit | B51: € | D51: =Staff!D93/FX_EUR -> 259645.79 | E51: =Staff!E93/FX_EUR -> 0 | F51: =Staff!F93/FX_EUR -> 0 | G51: =Staff!G93/FX_EUR -> 0 | H51: =Staff!H93/FX_EUR -> 0 | I51: =Staff!I93/FX_EUR -> 0 | J51: =Staff!J93/FX_EUR -> 0 | K51: =Staff!K93/FX_EUR -> 0 | ... BL51: =Staff!BL93/FX_EUR -> 13008.252
A52: Staff cost: Operations & support | B52: € | D52: =Staff!D94/FX_EUR -> 393146.87 | E52: =Staff!E94/FX_EUR -> 0 | F52: =Staff!F94/FX_EUR -> 0 | G52: =Staff!G94/FX_EUR -> 0 | H52: =Staff!H94/FX_EUR -> 990.91861 | I52: =Staff!I94/FX_EUR -> 990.91861 | J52: =Staff!J94/FX_EUR -> 990.91861 | K52: =Staff!K94/FX_EUR -> 990.91861 | ... BL52: =Staff!BL94/FX_EUR -> 19873.718
A53: Staff cost: Sales & partnerships | B53: € | D53: =Staff!D95/FX_EUR -> 730752.07 | E53: =Staff!E95/FX_EUR -> 2378.2047 | F53: =Staff!F95/FX_EUR -> 2378.2047 | G53: =Staff!G95/FX_EUR -> 2378.2047 | H53: =Staff!H95/FX_EUR -> 3963.6744 | I53: =Staff!I95/FX_EUR -> 3963.6744 | J53: =Staff!J95/FX_EUR -> 3963.6744 | K53: =Staff!K95/FX_EUR -> 3963.6744 | ... BL53: =Staff!BL95/FX_EUR -> 29870.801
A54: Staff cost: Marketing | B54: € | D54: =Staff!D96/FX_EUR -> 162312.17 | E54: =Staff!E96/FX_EUR -> 0 | F54: =Staff!F96/FX_EUR -> 0 | G54: =Staff!G96/FX_EUR -> 0 | H54: =Staff!H96/FX_EUR -> 1783.6535 | I54: =Staff!I96/FX_EUR -> 2576.3884 | J54: =Staff!J96/FX_EUR -> 2576.3884 | K54: =Staff!K96/FX_EUR -> 2576.3884 | ... BL54: =Staff!BL96/FX_EUR -> 3131.6162
A55: Staff cost: Finance & admin | B55: € | D55: =Staff!D97/FX_EUR -> 197116.23 | E55: =Staff!E97/FX_EUR -> 2972.7558 | F55: =Staff!F97/FX_EUR -> 2972.7558 | G55: =Staff!G97/FX_EUR -> 2972.7558 | H55: =Staff!H97/FX_EUR -> 2972.7558 | I55: =Staff!I97/FX_EUR -> 2972.7558 | J55: =Staff!J97/FX_EUR -> 2972.7558 | K55: =Staff!K97/FX_EUR -> 2972.7558 | ... BL55: =Staff!BL97/FX_EUR -> 3613.4033
A56: Total staff cost | B56: € | D56: =Staff!D98/FX_EUR -> 3297353.8 | E56: =Staff!E98/FX_EUR -> 15061.963 | F56: =Staff!F98/FX_EUR -> 15061.963 | G56: =Staff!G98/FX_EUR -> 15061.963 | H56: =Staff!H98/FX_EUR -> 19422.005 | I56: =Staff!I98/FX_EUR -> 20214.74 | J56: =Staff!J98/FX_EUR -> 20214.74 | K56: =Staff!K98/FX_EUR -> 20214.74 | ... BL56: =Staff!BL98/FX_EUR -> 112135.95

Sheet Sales & marketing
A1: Sales & marketing
A2: Client acquisition by channel and country, and the non-staff sales and marketing budget.
A3: Month # | D3: Total / end | E3: 1 | F3: =E3+1 -> 2 | G3: =F3+1 -> 3 | H3: =G3+1 -> 4 | I3: =H3+1 -> 5 | J3: =I3+1 -> 6 | K3: =J3+1 -> 7 | L3: =K3+1 -> 8 | M3: =L3+1 -> 9 | ... BL3: =BK3+1 -> 60
A4: Month | E4: =DATE(YEAR(Start_Date),MONTH(Start_Date)+E3-1,1) -> 46388 | F4: =DATE(YEAR(Start_Date),MONTH(Start_Date)+F3-1,1) -> 46419 | G4: =DATE(YEAR(Start_Date),MONTH(Start_Date)+G3-1,1) -> 46447 | H4: =DATE(YEAR(Start_Date),MONTH(Start_Date)+H3-1,1) -> 46478 | I4: =DATE(YEAR(Start_Date),MONTH(Start_Date)+I3-1,1) -> 46508 | J4: =DATE(YEAR(Start_Date),MONTH(Start_Date)+J3-1,1) -> 46539 | K4: =DATE(YEAR(Start_Date),MONTH(Start_Date)+K3-1,1) -> 46569 | L4: =DATE(YEAR(Start_Date),MONTH(Start_Date)+L3-1,1) -> 46600 | ... BL4: =DATE(YEAR(Start_Date),MONTH(Start_Date)+BL3-1,1) -> 48183
A5: Year | E5: =INT((E3-1)/12)+1 -> 1 | F5: =INT((F3-1)/12)+1 -> 1 | G5: =INT((G3-1)/12)+1 -> 1 | H5: =INT((H3-1)/12)+1 -> 1 | I5: =INT((I3-1)/12)+1 -> 1 | J5: =INT((J3-1)/12)+1 -> 1 | K5: =INT((K3-1)/12)+1 -> 1 | L5: =INT((L3-1)/12)+1 -> 1 | ... BL5: =INT((BL3-1)/12)+1 -> 5
A8: Markets open
A9: Senegal open (1 = yes) | B9: flag | E9: =IF(E$3>=Launch_SN,1,0) -> 0 | F9: =IF(F$3>=Launch_SN,1,0) -> 0 | G9: =IF(G$3>=Launch_SN,1,0) -> 0 | H9: =IF(H$3>=Launch_SN,1,0) -> 0 | I9: =IF(I$3>=Launch_SN,1,0) -> 1 | J9: =IF(J$3>=Launch_SN,1,0) -> 1 | K9: =IF(K$3>=Launch_SN,1,0) -> 1 | L9: =IF(L$3>=Launch_SN,1,0) -> 1 | ... BL9: =IF(BL$3>=Launch_SN,1,0) -> 1
A10: Côte d'Ivoire open (1 = yes) | B10: flag | E10: =IF(E$3>=Launch_CI,1,0) -> 0 | F10: =IF(F$3>=Launch_CI,1,0) -> 0 | G10: =IF(G$3>=Launch_CI,1,0) -> 0 | H10: =IF(H$3>=Launch_CI,1,0) -> 0 | I10: =IF(I$3>=Launch_CI,1,0) -> 0 | J10: =IF(J$3>=Launch_CI,1,0) -> 0 | K10: =IF(K$3>=Launch_CI,1,0) -> 0 | L10: =IF(L$3>=Launch_CI,1,0) -> 0 | ... BL10: =IF(BL$3>=Launch_CI,1,0) -> 1
A12: Field sales
A13: Field sales reps, Senegal | B13: people | D13: =BL13 -> 20 | E13: =Staff!E86 -> 1 | F13: =Staff!F86 -> 1 | G13: =Staff!G86 -> 1 | H13: =Staff!H86 -> 3 | I13: =Staff!I86 -> 3 | J13: =Staff!J86 -> 3 | K13: =Staff!K86 -> 3 | L13: =Staff!L86 -> 3 | ... BL13: =Staff!BL86 -> 20
A14: Field sales reps, Côte d'Ivoire | B14: people | D14: =BL14 -> 8 | E14: =Staff!E87 -> 0 | F14: =Staff!F87 -> 0 | G14: =Staff!G87 -> 0 | H14: =Staff!H87 -> 0 | I14: =Staff!I87 -> 0 | J14: =Staff!J87 -> 0 | K14: =Staff!K87 -> 0 | L14: =Staff!L87 -> 0 | ... BL14: =Staff!BL87 -> 8
A15: Productive reps, Senegal (hired before this month) | B15: people | E15: =0 -> 0 | F15: =E13*F9 -> 0 | G15: =F13*G9 -> 0 | H15: =G13*H9 -> 0 | I15: =H13*I9 -> 3 | J15: =I13*J9 -> 3 | K15: =J13*K9 -> 3 | L15: =K13*L9 -> 3 | M15: =L13*M9 -> 3 | ... BL15: =BK13*BL9 -> 20
A16: Productive reps, Côte d'Ivoire | B16: people | E16: =0 -> 0 | F16: =E14*F10 -> 0 | G16: =F14*G10 -> 0 | H16: =G14*H10 -> 0 | I16: =H14*I10 -> 0 | J16: =I14*J10 -> 0 | K16: =J14*K10 -> 0 | L16: =K14*L10 -> 0 | M16: =L14*M10 -> 0 | ... BL16: =BK14*BL10 -> 8
A17: New clients from field sales, Senegal | B17: clients | D17: =SUM(E17:BL17) -> 4710 | E17: =E15*Rep_Productivity -> 0 | F17: =F15*Rep_Productivity -> 0 | G17: =G15*Rep_Productivity -> 0 | H17: =H15*Rep_Productivity -> 0 | I17: =I15*Rep_Productivity -> 30 | J17: =J15*Rep_Productivity -> 30 | K17: =K15*Rep_Productivity -> 30 | L17: =L15*Rep_Productivity -> 30 | ... BL17: =BL15*Rep_Productivity -> 200
A18: New clients from field sales, Côte d'Ivoire | B18: clients | D18: =SUM(E18:BL18) -> 1431 | E18: =E16*Rep_Productivity*CI_Productivity -> 0 | F18: =F16*Rep_Productivity*CI_Productivity -> 0 | G18: =G16*Rep_Productivity*CI_Productivity -> 0 | H18: =H16*Rep_Productivity*CI_Productivity -> 0 | I18: =I16*Rep_Productivity*CI_Productivity -> 0 | J18: =J16*Rep_Productivity*CI_Productivity -> 0 | K18: =K16*Rep_Productivity*CI_Productivity -> 0 | L18: =L16*Rep_Productivity*CI_Productivity -> 0 | ... BL18: =BL16*Rep_Productivity*CI_Productivity -> 72
A20: Partner channel (accountants, payroll software, chambers of commerce)
A21: New clients from partners, Senegal | B21: clients | D21: =SUM(E21:BL21) -> 2791.2087 | E21: =E9*MIN(Partner_Cap_SN,Partner_Base_SN*(1+Partner_Growth)^MAX(0,E$3-Launch_SN)) -> 0 | F21: =F9*MIN(Partner_Cap_SN,Partner_Base_SN*(1+Partner_Growth)^MAX(0,F$3-Launch_SN)) -> 0 | G21: =G9*MIN(Partner_Cap_SN,Partner_Base_SN*(1+Partner_Growth)^MAX(0,G$3-Launch_SN)) -> 0 | H21: =H9*MIN(Partner_Cap_SN,Partner_Base_SN*(1+Partner_Growth)^MAX(0,H$3-Launch_SN)) -> 0 | I21: =I9*MIN(Partner_Cap_SN,Partner_Base_SN*(1+Partner_Growth)^MAX(0,I$3-Launch_SN)) -> 10 | J21: =J9*MIN(Partner_Cap_SN,Partner_Base_SN*(1+Partner_Growth)^MAX(0,J$3-Launch_SN)) -> 10.6 | K21: =K9*MIN(Partner_Cap_SN,Partner_Base_SN*(1+Partner_Growth)^MAX(0,K$3-Launch_SN)) -> 11.236 | L21: =L9*MIN(Partner_Cap_SN,Partner_Base_SN*(1+Partner_Growth)^MAX(0,L$3-Launch_SN)) -> 11.91016 | ... BL21: =BL9*MIN(Partner_Cap_SN,Partner_Base_SN*(1+Partner_Growth)^MAX(0,BL$3-Launch_SN)) -> 80
A22: New clients from partners, Côte d'Ivoire | B22: clients | D22: =SUM(E22:BL22) -> 1048.5718 | E22: =E10*MIN(Partner_Cap_CI,Partner_Base_CI*(1+Partner_Growth)^MAX(0,E$3-Launch_CI)) -> 0 | F22: =F10*MIN(Partner_Cap_CI,Partner_Base_CI*(1+Partner_Growth)^MAX(0,F$3-Launch_CI)) -> 0 | G22: =G10*MIN(Partner_Cap_CI,Partner_Base_CI*(1+Partner_Growth)^MAX(0,G$3-Launch_CI)) -> 0 | H22: =H10*MIN(Partner_Cap_CI,Partner_Base_CI*(1+Partner_Growth)^MAX(0,H$3-Launch_CI)) -> 0 | I22: =I10*MIN(Partner_Cap_CI,Partner_Base_CI*(1+Partner_Growth)^MAX(0,I$3-Launch_CI)) -> 0 | J22: =J10*MIN(Partner_Cap_CI,Partner_Base_CI*(1+Partner_Growth)^MAX(0,J$3-Launch_CI)) -> 0 | K22: =K10*MIN(Partner_Cap_CI,Partner_Base_CI*(1+Partner_Growth)^MAX(0,K$3-Launch_CI)) -> 0 | L22: =L10*MIN(Partner_Cap_CI,Partner_Base_CI*(1+Partner_Growth)^MAX(0,L$3-Launch_CI)) -> 0 | ... BL22: =BL10*MIN(Partner_Cap_CI,Partner_Base_CI*(1+Partner_Growth)^MAX(0,BL$3-Launch_CI)) -> 60
A24: Digital marketing
A25: Digital ads budget, Senegal | B25: FCFA | D25: =SUM(E25:BL25) -> 207280000 | E25: =E9*INDEX(Digital_SN,1,E$5) -> 0 | F25: =F9*INDEX(Digital_SN,1,F$5) -> 0 | G25: =G9*INDEX(Digital_SN,1,G$5) -> 0 | H25: =H9*INDEX(Digital_SN,1,H$5) -> 0 | I25: =I9*INDEX(Digital_SN,1,I$5) -> 1310000 | J25: =J9*INDEX(Digital_SN,1,J$5) -> 1310000 | K25: =K9*INDEX(Digital_SN,1,K$5) -> 1310000 | L25: =L9*INDEX(Digital_SN,1,L$5) -> 1310000 | ... BL25: =BL9*INDEX(Digital_SN,1,BL$5) -> 5250000
A26: Digital ads budget, Côte d'Ivoire | B26: FCFA | D26: =SUM(E26:BL26) -> 125940000 | E26: =E10*INDEX(Digital_CI,1,E$5) -> 0 | F26: =F10*INDEX(Digital_CI,1,F$5) -> 0 | G26: =G10*INDEX(Digital_CI,1,G$5) -> 0 | H26: =H10*INDEX(Digital_CI,1,H$5) -> 0 | I26: =I10*INDEX(Digital_CI,1,I$5) -> 0 | J26: =J10*INDEX(Digital_CI,1,J$5) -> 0 | K26: =K10*INDEX(Digital_CI,1,K$5) -> 0 | L26: =L10*INDEX(Digital_CI,1,L$5) -> 0 | ... BL26: =BL10*INDEX(Digital_CI,1,BL$5) -> 3940000
A27: New clients from digital, Senegal | B27: clients | D27: =SUM(E27:BL27) -> 2763.7333 | E27: =E25/CAC_Digital -> 0 | F27: =F25/CAC_Digital -> 0 | G27: =G25/CAC_Digital -> 0 | H27: =H25/CAC_Digital -> 0 | I27: =I25/CAC_Digital -> 17.466667 | J27: =J25/CAC_Digital -> 17.466667 | K27: =K25/CAC_Digital -> 17.466667 | L27: =L25/CAC_Digital -> 17.466667 | ... BL27: =BL25/CAC_Digital -> 70
A28: New clients from digital, Côte d'Ivoire | B28: clients | D28: =SUM(E28:BL28) -> 1679.2 | E28: =E26/CAC_Digital -> 0 | F28: =F26/CAC_Digital -> 0 | G28: =G26/CAC_Digital -> 0 | H28: =H26/CAC_Digital -> 0 | I28: =I26/CAC_Digital -> 0 | J28: =J26/CAC_Digital -> 0 | K28: =K26/CAC_Digital -> 0 | L28: =L26/CAC_Digital -> 0 | ... BL28: =BL26/CAC_Digital -> 52.533333
A30: New clients
A31: New clients, Senegal | B31: clients | D31: =SUM(E31:BL31) -> 10264.942 | E31: =E17+E21+E27 -> 0 | F31: =F17+F21+F27 -> 0 | G31: =G17+G21+G27 -> 0 | H31: =H17+H21+H27 -> 0 | I31: =I17+I21+I27 -> 57.466667 | J31: =J17+J21+J27 -> 58.066667 | K31: =K17+K21+K27 -> 58.702667 | L31: =L17+L21+L27 -> 59.376827 | ... BL31: =BL17+BL21+BL27 -> 350
A32: New clients, Côte d'Ivoire | B32: clients | D32: =SUM(E32:BL32) -> 4158.7718 | E32: =E18+E22+E28 -> 0 | F32: =F18+F22+F28 -> 0 | G32: =G18+G22+G28 -> 0 | H32: =H18+H22+H28 -> 0 | I32: =I18+I22+I28 -> 0 | J32: =J18+J22+J28 -> 0 | K32: =K18+K22+K28 -> 0 | L32: =L18+L22+L28 -> 0 | ... BL32: =BL18+BL22+BL28 -> 184.53333
A33: New clients, total | B33: clients | D33: =SUM(E33:BL33) -> 14423.714 | E33: =E31+E32 -> 0 | F33: =F31+F32 -> 0 | G33: =G31+G32 -> 0 | H33: =H31+H32 -> 0 | I33: =I31+I32 -> 57.466667 | J33: =J31+J32 -> 58.066667 | K33: =K31+K32 -> 58.702667 | L33: =L31+L32 -> 59.376827 | ... BL33: =BL31+BL32 -> 534.53333
A34: of which Petite | B34: clients | D34: =SUM(E34:BL34) -> 8654.2283 | E34: =E33*Mix_Petite -> 0 | F34: =F33*Mix_Petite -> 0 | G34: =G33*Mix_Petite -> 0 | H34: =H33*Mix_Petite -> 0 | I34: =I33*Mix_Petite -> 34.48 | J34: =J33*Mix_Petite -> 34.84 | K34: =K33*Mix_Petite -> 35.2216 | L34: =L33*Mix_Petite -> 35.626096 | ... BL34: =BL33*Mix_Petite -> 320.72
A35: of which Moyenne | B35: clients | D35: =SUM(E35:BL35) -> 4327.1141 | E35: =E33*Mix_Moyenne -> 0 | F35: =F33*Mix_Moyenne -> 0 | G35: =G33*Mix_Moyenne -> 0 | H35: =H33*Mix_Moyenne -> 0 | I35: =I33*Mix_Moyenne -> 17.24 | J35: =J33*Mix_Moyenne -> 17.42 | K35: =K33*Mix_Moyenne -> 17.6108 | L35: =L33*Mix_Moyenne -> 17.813048 | ... BL35: =BL33*Mix_Moyenne -> 160.36
A36: of which Grande | B36: clients | D36: =SUM(E36:BL36) -> 1442.3714 | E36: =E33*Mix_Grande -> 0 | F36: =F33*Mix_Grande -> 0 | G36: =G33*Mix_Grande -> 0 | H36: =H33*Mix_Grande -> 0 | I36: =I33*Mix_Grande -> 5.7466667 | J36: =J33*Mix_Grande -> 5.8066667 | K36: =K33*Mix_Grande -> 5.8702667 | L36: =L33*Mix_Grande -> 5.9376827 | ... BL36: =BL33*Mix_Grande -> 53.453333
A37: New clients from partners (for referral fees) | B37: clients | D37: =SUM(E37:BL37) -> 3839.7805 | E37: =E21+E22 -> 0 | F37: =F21+F22 -> 0 | G37: =G21+G22 -> 0 | H37: =H21+H22 -> 0 | I37: =I21+I22 -> 10 | J37: =J21+J22 -> 10.6 | K37: =K21+K22 -> 11.236 | L37: =L21+L22 -> 11.91016 | ... BL37: =BL21+BL22 -> 140
A39: Sales and marketing budget (non-staff)
A40: Digital ads | B40: FCFA | D40: =SUM(E40:BL40) -> 333220000 | E40: =E25+E26 -> 0 | F40: =F25+F26 -> 0 | G40: =G25+G26 -> 0 | H40: =H25+H26 -> 0 | I40: =I25+I26 -> 1310000 | J40: =J25+J26 -> 1310000 | K40: =K25+K26 -> 1310000 | L40: =L25+L26 -> 1310000 | ... BL40: =BL25+BL26 -> 9190000
A41: Brand, launch events, PR | B41: FCFA | D41: =SUM(E41:BL41) -> 41330000 | E41: =INDEX(Brand_PR,1,E$5)/12 -> 1366666.7 | F41: =INDEX(Brand_PR,1,F$5)/12 -> 1366666.7 | G41: =INDEX(Brand_PR,1,G$5)/12 -> 1366666.7 | H41: =INDEX(Brand_PR,1,H$5)/12 -> 1366666.7 | I41: =INDEX(Brand_PR,1,I$5)/12 -> 1366666.7 | J41: =INDEX(Brand_PR,1,J$5)/12 -> 1366666.7 | K41: =INDEX(Brand_PR,1,K$5)/12 -> 1366666.7 | L41: =INDEX(Brand_PR,1,L$5)/12 -> 1366666.7 | ... BL41: =INDEX(Brand_PR,1,BL$5)/12 -> 546666.67
A42: Events, sponsorships, sales materials | B42: FCFA | D42: =SUM(E42:BL42) -> 137740000 | E42: =INDEX(Events,1,E$5)/12 -> 820000 | F42: =INDEX(Events,1,F$5)/12 -> 820000 | G42: =INDEX(Events,1,G$5)/12 -> 820000 | H42: =INDEX(Events,1,H$5)/12 -> 820000 | I42: =INDEX(Events,1,I$5)/12 -> 820000 | J42: =INDEX(Events,1,J$5)/12 -> 820000 | K42: =INDEX(Events,1,K$5)/12 -> 820000 | L42: =INDEX(Events,1,L$5)/12 -> 820000 | ... BL42: =INDEX(Events,1,BL$5)/12 -> 3550000
A43: Referral fees to partners | B43: FCFA | D43: =SUM(E43:BL43) -> 95994512 | E43: =E37*Referral_Fee -> 0 | F43: =F37*Referral_Fee -> 0 | G43: =G37*Referral_Fee -> 0 | H43: =H37*Referral_Fee -> 0 | I43: =I37*Referral_Fee -> 250000 | J43: =J37*Referral_Fee -> 265000 | K43: =K37*Referral_Fee -> 280900 | L43: =L37*Referral_Fee -> 297754 | ... BL43: =BL37*Referral_Fee -> 3500000
A44: Field sales transport | B44: FCFA | D44: =SUM(E44:BL44) -> 49575000 | E44: =(E13+E14)*Rep_Transport -> 75000 | F44: =(F13+F14)*Rep_Transport -> 75000 | G44: =(G13+G14)*Rep_Transport -> 75000 | H44: =(H13+H14)*Rep_Transport -> 225000 | I44: =(I13+I14)*Rep_Transport -> 225000 | J44: =(J13+J14)*Rep_Transport -> 225000 | K44: =(K13+K14)*Rep_Transport -> 225000 | L44: =(L13+L14)*Rep_Transport -> 225000 | ... BL44: =(BL13+BL14)*Rep_Transport -> 2100000
A45: Total sales and marketing budget (non-staff) | B45: FCFA | D45: =SUM(E45:BL45) -> 6.5785951e+08 | E45: =SUM(E40:E44) -> 2261666.7 | F45: =SUM(F40:F44) -> 2261666.7 | G45: =SUM(G40:G44) -> 2261666.7 | H45: =SUM(H40:H44) -> 2411666.7 | I45: =SUM(I40:I44) -> 3971666.7 | J45: =SUM(J40:J44) -> 3986666.7 | K45: =SUM(K40:K44) -> 4002566.7 | L45: =SUM(L40:L44) -> 4019420.7 | ... BL45: =SUM(BL40:BL44) -> 18886667
A47: Acquisition efficiency
A48: Sales, partnerships and marketing staff cost | B48: FCFA | D48: =SUM(E48:BL48) -> 5.8581174e+08 | E48: =Staff!E95+Staff!E96 -> 1560000 | F48: =Staff!F95+Staff!F96 -> 1560000 | G48: =Staff!G95+Staff!G96 -> 1560000 | H48: =Staff!H95+Staff!H96 -> 3770000 | I48: =Staff!I95+Staff!I96 -> 4290000 | J48: =Staff!J95+Staff!J96 -> 4290000 | K48: =Staff!K95+Staff!K96 -> 4290000 | L48: =Staff!L95+Staff!L96 -> 4290000 | ... BL48: =Staff!BL95+Staff!BL96 -> 21648166
A49: Blended cost to acquire a client (staff + budget) | B49: FCFA | E49: =IFERROR((E45+E48)/E33,0) -> 0 | F49: =IFERROR((F45+F48)/F33,0) -> 0 | G49: =IFERROR((G45+G48)/G33,0) -> 0 | H49: =IFERROR((H45+H48)/H33,0) -> 0 | I49: =IFERROR((I45+I48)/I33,0) -> 143764.5 | J49: =IFERROR((J45+J48)/J33,0) -> 142537.31 | K49: =IFERROR((K45+K48)/K33,0) -> 141263.88 | L49: =IFERROR((L45+L48)/L33,0) -> 139943.83 | ... BL49: =IFERROR((BL45+BL48)/BL33,0) -> 75832.189

Sheet Sales & marketing (€)
A1: Sales & marketing (€)
A2: Every amount of the 'Sales & marketing' sheet in euros (FCFA ÷ FCFA per euro on Assumptions). Edit the FCFA sheets and Assumptions, not this one.
A3: Month # | D3: Total / end | E3: ='Sales & marketing'!E3 -> 1 | F3: ='Sales & marketing'!F3 -> 2 | G3: ='Sales & marketing'!G3 -> 3 | H3: ='Sales & marketing'!H3 -> 4 | I3: ='Sales & marketing'!I3 -> 5 | J3: ='Sales & marketing'!J3 -> 6 | K3: ='Sales & marketing'!K3 -> 7 | L3: ='Sales & marketing'!L3 -> 8 | ... BL3: ='Sales & marketing'!BL3 -> 60
A4: Month | E4: ='Sales & marketing'!E4 -> 46388 | F4: ='Sales & marketing'!F4 -> 46419 | G4: ='Sales & marketing'!G4 -> 46447 | H4: ='Sales & marketing'!H4 -> 46478 | I4: ='Sales & marketing'!I4 -> 46508 | J4: ='Sales & marketing'!J4 -> 46539 | K4: ='Sales & marketing'!K4 -> 46569 | L4: ='Sales & marketing'!L4 -> 46600 | ... BL4: ='Sales & marketing'!BL4 -> 48183
A5: Year | E5: ='Sales & marketing'!E5 -> 1 | F5: ='Sales & marketing'!F5 -> 1 | G5: ='Sales & marketing'!G5 -> 1 | H5: ='Sales & marketing'!H5 -> 1 | I5: ='Sales & marketing'!I5 -> 1 | J5: ='Sales & marketing'!J5 -> 1 | K5: ='Sales & marketing'!K5 -> 1 | L5: ='Sales & marketing'!L5 -> 1 | ... BL5: ='Sales & marketing'!BL5 -> 5
A8: Markets open
A10: Field sales
A12: Partner channel (accountants, payroll software, chambers of commerce)
A14: Digital marketing
A15: Digital ads budget, Senegal | B15: € | D15: ='Sales & marketing'!D25/FX_EUR -> 315996.32 | E15: ='Sales & marketing'!E25/FX_EUR -> 0 | F15: ='Sales & marketing'!F25/FX_EUR -> 0 | G15: ='Sales & marketing'!G25/FX_EUR -> 0 | H15: ='Sales & marketing'!H25/FX_EUR -> 0 | I15: ='Sales & marketing'!I25/FX_EUR -> 1997.0821 | J15: ='Sales & marketing'!J25/FX_EUR -> 1997.0821 | K15: ='Sales & marketing'!K25/FX_EUR -> 1997.0821 | ... BL15: ='Sales & marketing'!BL25/FX_EUR -> 8003.5734
A16: Digital ads budget, Côte d'Ivoire | B16: € | D16: ='Sales & marketing'!D26/FX_EUR -> 191994.29 | E16: ='Sales & marketing'!E26/FX_EUR -> 0 | F16: ='Sales & marketing'!F26/FX_EUR -> 0 | G16: ='Sales & marketing'!G26/FX_EUR -> 0 | H16: ='Sales & marketing'!H26/FX_EUR -> 0 | I16: ='Sales & marketing'!I26/FX_EUR -> 0 | J16: ='Sales & marketing'!J26/FX_EUR -> 0 | K16: ='Sales & marketing'!K26/FX_EUR -> 0 | ... BL16: ='Sales & marketing'!BL26/FX_EUR -> 6006.4913
A18: New clients
A20: Sales and marketing budget (non-staff)
A21: Digital ads | B21: € | D21: ='Sales & marketing'!D40/FX_EUR -> 507990.62 | E21: ='Sales & marketing'!E40/FX_EUR -> 0 | F21: ='Sales & marketing'!F40/FX_EUR -> 0 | G21: ='Sales & marketing'!G40/FX_EUR -> 0 | H21: ='Sales & marketing'!H40/FX_EUR -> 0 | I21: ='Sales & marketing'!I40/FX_EUR -> 1997.0821 | J21: ='Sales & marketing'!J40/FX_EUR -> 1997.0821 | K21: ='Sales & marketing'!K40/FX_EUR -> 1997.0821 | ... BL21: ='Sales & marketing'!BL40/FX_EUR -> 14010.065
A22: Brand, launch events, PR | B22: € | D22: ='Sales & marketing'!D41/FX_EUR -> 63007.179 | E22: ='Sales & marketing'!E41/FX_EUR -> 2083.4699 | F22: ='Sales & marketing'!F41/FX_EUR -> 2083.4699 | G22: ='Sales & marketing'!G41/FX_EUR -> 2083.4699 | H22: ='Sales & marketing'!H41/FX_EUR -> 2083.4699 | I22: ='Sales & marketing'!I41/FX_EUR -> 2083.4699 | J22: ='Sales & marketing'!J41/FX_EUR -> 2083.4699 | K22: ='Sales & marketing'!K41/FX_EUR -> 2083.4699 | ... BL22: ='Sales & marketing'!BL41/FX_EUR -> 833.38796
A23: Events, sponsorships, sales materials | B23: € | D23: ='Sales & marketing'!D42/FX_EUR -> 209983.28 | E23: ='Sales & marketing'!E42/FX_EUR -> 1250.0819 | F23: ='Sales & marketing'!F42/FX_EUR -> 1250.0819 | G23: ='Sales & marketing'!G42/FX_EUR -> 1250.0819 | H23: ='Sales & marketing'!H42/FX_EUR -> 1250.0819 | I23: ='Sales & marketing'!I42/FX_EUR -> 1250.0819 | J23: ='Sales & marketing'!J42/FX_EUR -> 1250.0819 | K23: ='Sales & marketing'!K42/FX_EUR -> 1250.0819 | ... BL23: ='Sales & marketing'!BL42/FX_EUR -> 5411.9401
A24: Referral fees to partners | B24: € | D24: ='Sales & marketing'!D43/FX_EUR -> 146342.69 | E24: ='Sales & marketing'!E43/FX_EUR -> 0 | F24: ='Sales & marketing'!F43/FX_EUR -> 0 | G24: ='Sales & marketing'!G43/FX_EUR -> 0 | H24: ='Sales & marketing'!H43/FX_EUR -> 0 | I24: ='Sales & marketing'!I43/FX_EUR -> 381.12254 | J24: ='Sales & marketing'!J43/FX_EUR -> 403.9899 | K24: ='Sales & marketing'!K43/FX_EUR -> 428.22929 | ... BL24: ='Sales & marketing'!BL43/FX_EUR -> 5335.7156
A25: Field sales transport | B25: € | D25: ='Sales & marketing'!D44/FX_EUR -> 75576.6 | E25: ='Sales & marketing'!E44/FX_EUR -> 114.33676 | F25: ='Sales & marketing'!F44/FX_EUR -> 114.33676 | G25: ='Sales & marketing'!G44/FX_EUR -> 114.33676 | H25: ='Sales & marketing'!H44/FX_EUR -> 343.01029 | I25: ='Sales & marketing'!I44/FX_EUR -> 343.01029 | J25: ='Sales & marketing'!J44/FX_EUR -> 343.01029 | K25: ='Sales & marketing'!K44/FX_EUR -> 343.01029 | ... BL25: ='Sales & marketing'!BL44/FX_EUR -> 3201.4294
A26: Total sales and marketing budget (non-staff) | B26: € | D26: ='Sales & marketing'!D45/FX_EUR -> 1002900.4 | E26: ='Sales & marketing'!E45/FX_EUR -> 3447.8886 | F26: ='Sales & marketing'!F45/FX_EUR -> 3447.8886 | G26: ='Sales & marketing'!G45/FX_EUR -> 3447.8886 | H26: ='Sales & marketing'!H45/FX_EUR -> 3676.5621 | I26: ='Sales & marketing'!I45/FX_EUR -> 6054.7668 | J26: ='Sales & marketing'!J45/FX_EUR -> 6077.6342 | K26: ='Sales & marketing'!K45/FX_EUR -> 6101.8735 | ... BL26: ='Sales & marketing'!BL45/FX_EUR -> 28792.538
A28: Acquisition efficiency
A29: Sales, partnerships and marketing staff cost | B29: € | D29: ='Sales & marketing'!D48/FX_EUR -> 893064.24 | E29: ='Sales & marketing'!E48/FX_EUR -> 2378.2047 | F29: ='Sales & marketing'!F48/FX_EUR -> 2378.2047 | G29: ='Sales & marketing'!G48/FX_EUR -> 2378.2047 | H29: ='Sales & marketing'!H48/FX_EUR -> 5747.3279 | I29: ='Sales & marketing'!I48/FX_EUR -> 6540.0628 | J29: ='Sales & marketing'!J48/FX_EUR -> 6540.0628 | K29: ='Sales & marketing'!K48/FX_EUR -> 6540.0628 | ... BL29: ='Sales & marketing'!BL48/FX_EUR -> 33002.417
A30: Blended cost to acquire a client (staff + budget) | B30: € | E30: ='Sales & marketing'!E49/FX_EUR -> 0 | F30: ='Sales & marketing'!F49/FX_EUR -> 0 | G30: ='Sales & marketing'!G49/FX_EUR -> 0 | H30: ='Sales & marketing'!H49/FX_EUR -> 0 | I30: ='Sales & marketing'!I49/FX_EUR -> 219.16757 | J30: ='Sales & marketing'!J49/FX_EUR -> 217.29673 | K30: ='Sales & marketing'!K49/FX_EUR -> 215.3554 | L30: ='Sales & marketing'!L49/FX_EUR -> 213.343 | ... BL30: ='Sales & marketing'!BL49/FX_EUR -> 115.60543

Sheet Clients & revenue
A1: Clients & revenue
A2: Active clients by plan, usage and every revenue line except credit (see Credit).
A3: Month # | D3: Total / end | E3: 1 | F3: =E3+1 -> 2 | G3: =F3+1 -> 3 | H3: =G3+1 -> 4 | I3: =H3+1 -> 5 | J3: =I3+1 -> 6 | K3: =J3+1 -> 7 | L3: =K3+1 -> 8 | M3: =L3+1 -> 9 | ... BL3: =BK3+1 -> 60
A4: Month | E4: =DATE(YEAR(Start_Date),MONTH(Start_Date)+E3-1,1) -> 46388 | F4: =DATE(YEAR(Start_Date),MONTH(Start_Date)+F3-1,1) -> 46419 | G4: =DATE(YEAR(Start_Date),MONTH(Start_Date)+G3-1,1) -> 46447 | H4: =DATE(YEAR(Start_Date),MONTH(Start_Date)+H3-1,1) -> 46478 | I4: =DATE(YEAR(Start_Date),MONTH(Start_Date)+I3-1,1) -> 46508 | J4: =DATE(YEAR(Start_Date),MONTH(Start_Date)+J3-1,1) -> 46539 | K4: =DATE(YEAR(Start_Date),MONTH(Start_Date)+K3-1,1) -> 46569 | L4: =DATE(YEAR(Start_Date),MONTH(Start_Date)+L3-1,1) -> 46600 | ... BL4: =DATE(YEAR(Start_Date),MONTH(Start_Date)+BL3-1,1) -> 48183
A5: Year | E5: =INT((E3-1)/12)+1 -> 1 | F5: =INT((F3-1)/12)+1 -> 1 | G5: =INT((G3-1)/12)+1 -> 1 | H5: =INT((H3-1)/12)+1 -> 1 | I5: =INT((I3-1)/12)+1 -> 1 | J5: =INT((J3-1)/12)+1 -> 1 | K5: =INT((K3-1)/12)+1 -> 1 | L5: =INT((L3-1)/12)+1 -> 1 | ... BL5: =INT((BL3-1)/12)+1 -> 5
A8: New clients by plan
A9: New clients, Petite | B9: clients | D9: =SUM(E9:BL9) -> 8654.2283 | E9: ='Sales & marketing'!E34 -> 0 | F9: ='Sales & marketing'!F34 -> 0 | G9: ='Sales & marketing'!G34 -> 0 | H9: ='Sales & marketing'!H34 -> 0 | I9: ='Sales & marketing'!I34 -> 34.48 | J9: ='Sales & marketing'!J34 -> 34.84 | K9: ='Sales & marketing'!K34 -> 35.2216 | L9: ='Sales & marketing'!L34 -> 35.626096 | ... BL9: ='Sales & marketing'!BL34 -> 320.72
A10: New clients, Moyenne | B10: clients | D10: =SUM(E10:BL10) -> 4327.1141 | E10: ='Sales & marketing'!E35 -> 0 | F10: ='Sales & marketing'!F35 -> 0 | G10: ='Sales & marketing'!G35 -> 0 | H10: ='Sales & marketing'!H35 -> 0 | I10: ='Sales & marketing'!I35 -> 17.24 | J10: ='Sales & marketing'!J35 -> 17.42 | K10: ='Sales & marketing'!K35 -> 17.6108 | L10: ='Sales & marketing'!L35 -> 17.813048 | ... BL10: ='Sales & marketing'!BL35 -> 160.36
A11: New clients, Grande | B11: clients | D11: =SUM(E11:BL11) -> 1442.3714 | E11: ='Sales & marketing'!E36 -> 0 | F11: ='Sales & marketing'!F36 -> 0 | G11: ='Sales & marketing'!G36 -> 0 | H11: ='Sales & marketing'!H36 -> 0 | I11: ='Sales & marketing'!I36 -> 5.7466667 | J11: ='Sales & marketing'!J36 -> 5.8066667 | K11: ='Sales & marketing'!K36 -> 5.8702667 | L11: ='Sales & marketing'!L36 -> 5.9376827 | ... BL11: ='Sales & marketing'!BL36 -> 53.453333
A13: Active clients (end of month)
A14: Active clients, Petite | B14: clients | D14: =BL14 -> 6219.5875 | E14: =E9 -> 0 | F14: =E14*(1-Churn_Petite)+F9 -> 0 | G14: =F14*(1-Churn_Petite)+G9 -> 0 | H14: =G14*(1-Churn_Petite)+H9 -> 0 | I14: =H14*(1-Churn_Petite)+I9 -> 34.48 | J14: =I14*(1-Churn_Petite)+J9 -> 68.6304 | K14: =J14*(1-Churn_Petite)+K9 -> 102.47939 | L14: =K14*(1-Churn_Petite)+L9 -> 136.0559 | M14: =L14*(1-Churn_Petite)+M9 -> 169.38964 | ... BL14: =BK14*(1-Churn_Petite)+BL9 -> 6219.5875
A15: Active clients, Moyenne | B15: clients | D15: =BL15 -> 3494.7264 | E15: =E10 -> 0 | F15: =E15*(1-Churn_Moyenne)+F10 -> 0 | G15: =F15*(1-Churn_Moyenne)+G10 -> 0 | H15: =G15*(1-Churn_Moyenne)+H10 -> 0 | I15: =H15*(1-Churn_Moyenne)+I10 -> 17.24 | J15: =I15*(1-Churn_Moyenne)+J10 -> 34.4445 | K15: =J15*(1-Churn_Moyenne)+K10 -> 51.624744 | L15: =K15*(1-Churn_Moyenne)+L10 -> 68.792482 | M15: =L15*(1-Churn_Moyenne)+M10 -> 85.960007 | ... BL15: =BK15*(1-Churn_Moyenne)+BL10 -> 3494.7264
A16: Active clients, Grande | B16: clients | D16: =BL16 -> 1265.0652 | E16: =E11 -> 0 | F16: =E16*(1-Churn_Grande)+F11 -> 0 | G16: =F16*(1-Churn_Grande)+G11 -> 0 | H16: =G16*(1-Churn_Grande)+H11 -> 0 | I16: =H16*(1-Churn_Grande)+I11 -> 5.7466667 | J16: =I16*(1-Churn_Grande)+J11 -> 11.510233 | K16: =J16*(1-Churn_Grande)+K11 -> 17.294173 | L16: =K16*(1-Churn_Grande)+L11 -> 23.10215 | M16: =L16*(1-Churn_Grande)+M11 -> 28.938027 | ... BL16: =BK16*(1-Churn_Grande)+BL11 -> 1265.0652
A17: Active clients, total | B17: clients | D17: =BL17 -> 10979.379 | E17: =E14+E15+E16 -> 0 | F17: =F14+F15+F16 -> 0 | G17: =G14+G15+G16 -> 0 | H17: =H14+H15+H16 -> 0 | I17: =I14+I15+I16 -> 57.466667 | J17: =J14+J15+J16 -> 114.58513 | K17: =K14+K15+K16 -> 171.39831 | L17: =L14+L15+L16 -> 227.95053 | ... BL17: =BL14+BL15+BL16 -> 10979.379
A18: Blended monthly churn (by sales mix) | B18: % | E18: =Mix_Petite*Churn_Petite+Mix_Moyenne*Churn_Moyenne+Mix_Grande*Churn_Grande -> 0.0165 | F18: =Mix_Petite*Churn_Petite+Mix_Moyenne*Churn_Moyenne+Mix_Grande*Churn_Grande -> 0.0165 | G18: =Mix_Petite*Churn_Petite+Mix_Moyenne*Churn_Moyenne+Mix_Grande*Churn_Grande -> 0.0165 | H18: =Mix_Petite*Churn_Petite+Mix_Moyenne*Churn_Moyenne+Mix_Grande*Churn_Grande -> 0.0165 | I18: =Mix_Petite*Churn_Petite+Mix_Moyenne*Churn_Moyenne+Mix_Grande*Churn_Grande -> 0.0165 | J18: =Mix_Petite*Churn_Petite+Mix_Moyenne*Churn_Moyenne+Mix_Grande*Churn_Grande -> 0.0165 | K18: =Mix_Petite*Churn_Petite+Mix_Moyenne*Churn_Moyenne+Mix_Grande*Churn_Grande -> 0.0165 | L18: =Mix_Petite*Churn_Petite+Mix_Moyenne*Churn_Moyenne+Mix_Grande*Churn_Grande -> 0.0165 | ... BL18: =Mix_Petite*Churn_Petite+Mix_Moyenne*Churn_Moyenne+Mix_Grande*Churn_Grande -> 0.0165
A19: Active clients, Senegal (approx.) | B19: clients | D19: =BL19 -> 7652.4581 | E19: ='Sales & marketing'!E31 -> 0 | F19: =E19*(1-F18)+'Sales & marketing'!F31 -> 0 | G19: =F19*(1-G18)+'Sales & marketing'!G31 -> 0 | H19: =G19*(1-H18)+'Sales & marketing'!H31 -> 0 | I19: =H19*(1-I18)+'Sales & marketing'!I31 -> 57.466667 | J19: =I19*(1-J18)+'Sales & marketing'!J31 -> 114.58513 | K19: =J19*(1-K18)+'Sales & marketing'!K31 -> 171.39715 | L19: =K19*(1-L18)+'Sales & marketing'!L31 -> 227.94592 | M19: =L19*(1-M18)+'Sales & marketing'!M31 -> 284.27625 | ... BL19: =BK19*(1-BL18)+'Sales & marketing'!BL31 -> 7652.4581
A20: Active clients, Côte d'Ivoire (approx.) | B20: clients | D20: =BL20 -> 3282.5456 | E20: ='Sales & marketing'!E32 -> 0 | F20: =E20*(1-F18)+'Sales & marketing'!F32 -> 0 | G20: =F20*(1-G18)+'Sales & marketing'!G32 -> 0 | H20: =G20*(1-H18)+'Sales & marketing'!H32 -> 0 | I20: =H20*(1-I18)+'Sales & marketing'!I32 -> 0 | J20: =I20*(1-J18)+'Sales & marketing'!J32 -> 0 | K20: =J20*(1-K18)+'Sales & marketing'!K32 -> 0 | L20: =K20*(1-L18)+'Sales & marketing'!L32 -> 0 | M20: =L20*(1-M18)+'Sales & marketing'!M32 -> 0 | ... BL20: =BK20*(1-BL18)+'Sales & marketing'!BL32 -> 3282.5456
A22: Clients in their free months, and paying clients
A23: In free months, Petite | B23: clients | E23: =IF(Free_Months<=0,0,SUM(OFFSET(E9,0,1-MIN(Free_Months,E$3),1,MIN(Free_Months,E$3)))) -> 0 | F23: =IF(Free_Months<=0,0,SUM(OFFSET(F9,0,1-MIN(Free_Months,F$3),1,MIN(Free_Months,F$3)))) -> 0 | G23: =IF(Free_Months<=0,0,SUM(OFFSET(G9,0,1-MIN(Free_Months,G$3),1,MIN(Free_Months,G$3)))) -> 0 | H23: =IF(Free_Months<=0,0,SUM(OFFSET(H9,0,1-MIN(Free_Months,H$3),1,MIN(Free_Months,H$3)))) -> 0 | I23: =IF(Free_Months<=0,0,SUM(OFFSET(I9,0,1-MIN(Free_Months,I$3),1,MIN(Free_Months,I$3)))) -> 34.48 | J23: =IF(Free_Months<=0,0,SUM(OFFSET(J9,0,1-MIN(Free_Months,J$3),1,MIN(Free_Months,J$3)))) -> 69.32 | K23: =IF(Free_Months<=0,0,SUM(OFFSET(K9,0,1-MIN(Free_Months,K$3),1,MIN(Free_Months,K$3)))) -> 104.5416 | L23: =IF(Free_Months<=0,0,SUM(OFFSET(L9,0,1-MIN(Free_Months,L$3),1,MIN(Free_Months,L$3)))) -> 105.6877 | ... BL23: =IF(Free_Months<=0,0,SUM(OFFSET(BL9,0,1-MIN(Free_Months,BL$3),1,MIN(Free_Months,BL$3)))) -> 937.69263
A24: In free months, Moyenne | B24: clients | E24: =IF(Free_Months<=0,0,SUM(OFFSET(E10,0,1-MIN(Free_Months,E$3),1,MIN(Free_Months,E$3)))) -> 0 | F24: =IF(Free_Months<=0,0,SUM(OFFSET(F10,0,1-MIN(Free_Months,F$3),1,MIN(Free_Months,F$3)))) -> 0 | G24: =IF(Free_Months<=0,0,SUM(OFFSET(G10,0,1-MIN(Free_Months,G$3),1,MIN(Free_Months,G$3)))) -> 0 | H24: =IF(Free_Months<=0,0,SUM(OFFSET(H10,0,1-MIN(Free_Months,H$3),1,MIN(Free_Months,H$3)))) -> 0 | I24: =IF(Free_Months<=0,0,SUM(OFFSET(I10,0,1-MIN(Free_Months,I$3),1,MIN(Free_Months,I$3)))) -> 17.24 | J24: =IF(Free_Months<=0,0,SUM(OFFSET(J10,0,1-MIN(Free_Months,J$3),1,MIN(Free_Months,J$3)))) -> 34.66 | K24: =IF(Free_Months<=0,0,SUM(OFFSET(K10,0,1-MIN(Free_Months,K$3),1,MIN(Free_Months,K$3)))) -> 52.2708 | L24: =IF(Free_Months<=0,0,SUM(OFFSET(L10,0,1-MIN(Free_Months,L$3),1,MIN(Free_Months,L$3)))) -> 52.843848 | ... BL24: =IF(Free_Months<=0,0,SUM(OFFSET(BL10,0,1-MIN(Free_Months,BL$3),1,MIN(Free_Months,BL$3)))) -> 468.84631
A25: In free months, Grande | B25: clients | E25: =IF(Free_Months<=0,0,SUM(OFFSET(E11,0,1-MIN(Free_Months,E$3),1,MIN(Free_Months,E$3)))) -> 0 | F25: =IF(Free_Months<=0,0,SUM(OFFSET(F11,0,1-MIN(Free_Months,F$3),1,MIN(Free_Months,F$3)))) -> 0 | G25: =IF(Free_Months<=0,0,SUM(OFFSET(G11,0,1-MIN(Free_Months,G$3),1,MIN(Free_Months,G$3)))) -> 0 | H25: =IF(Free_Months<=0,0,SUM(OFFSET(H11,0,1-MIN(Free_Months,H$3),1,MIN(Free_Months,H$3)))) -> 0 | I25: =IF(Free_Months<=0,0,SUM(OFFSET(I11,0,1-MIN(Free_Months,I$3),1,MIN(Free_Months,I$3)))) -> 5.7466667 | J25: =IF(Free_Months<=0,0,SUM(OFFSET(J11,0,1-MIN(Free_Months,J$3),1,MIN(Free_Months,J$3)))) -> 11.553333 | K25: =IF(Free_Months<=0,0,SUM(OFFSET(K11,0,1-MIN(Free_Months,K$3),1,MIN(Free_Months,K$3)))) -> 17.4236 | L25: =IF(Free_Months<=0,0,SUM(OFFSET(L11,0,1-MIN(Free_Months,L$3),1,MIN(Free_Months,L$3)))) -> 17.614616 | ... BL25: =IF(Free_Months<=0,0,SUM(OFFSET(BL11,0,1-MIN(Free_Months,BL$3),1,MIN(Free_Months,BL$3)))) -> 156.2821
A26: Paying clients, Petite | B26: clients | D26: =BL26 -> 5281.8949 | E26: =MAX(0,E14-E23) -> 0 | F26: =MAX(0,F14-F23) -> 0 | G26: =MAX(0,G14-G23) -> 0 | H26: =MAX(0,H14-H23) -> 0 | I26: =MAX(0,I14-I23) -> 0 | J26: =MAX(0,J14-J23) -> 0 | K26: =MAX(0,K14-K23) -> 0 | L26: =MAX(0,L14-L23) -> 30.368204 | ... BL26: =MAX(0,BL14-BL23) -> 5281.8949
A27: Paying clients, Moyenne | B27: clients | D27: =BL27 -> 3025.88 | E27: =MAX(0,E15-E24) -> 0 | F27: =MAX(0,F15-F24) -> 0 | G27: =MAX(0,G15-G24) -> 0 | H27: =MAX(0,H15-H24) -> 0 | I27: =MAX(0,I15-I24) -> 0 | J27: =MAX(0,J15-J24) -> 0 | K27: =MAX(0,K15-K24) -> 0 | L27: =MAX(0,L15-L24) -> 15.948634 | ... BL27: =MAX(0,BL15-BL24) -> 3025.88
A28: Paying clients, Grande | B28: clients | D28: =BL28 -> 1108.7831 | E28: =MAX(0,E16-E25) -> 0 | F28: =MAX(0,F16-F25) -> 0 | G28: =MAX(0,G16-G25) -> 0 | H28: =MAX(0,H16-H25) -> 0 | I28: =MAX(0,I16-I25) -> 0 | J28: =MAX(0,J16-J25) -> 0 | K28: =MAX(0,K16-K25) -> 0 | L28: =MAX(0,L16-L25) -> 5.4875336 | ... BL28: =MAX(0,BL16-BL25) -> 1108.7831
A30: Usage
A31: Employees of active clients | B31: people | D31: =BL31 -> 270273.92 | E31: =E14*Emp_Petite+E15*Emp_Moyenne+E16*Emp_Grande -> 0 | F31: =F14*Emp_Petite+F15*Emp_Moyenne+F16*Emp_Grande -> 0 | G31: =G14*Emp_Petite+G15*Emp_Moyenne+G16*Emp_Grande -> 0 | H31: =H14*Emp_Petite+H15*Emp_Moyenne+H16*Emp_Grande -> 0 | I31: =I14*Emp_Petite+I15*Emp_Moyenne+I16*Emp_Grande -> 1293 | J31: =J14*Emp_Petite+J15*Emp_Moyenne+J16*Emp_Grande -> 2585.4925 | K31: =K14*Emp_Petite+K15*Emp_Moyenne+K16*Emp_Grande -> 3878.3163 | L31: =L14*Emp_Petite+L15*Emp_Moyenne+L16*Emp_Grande -> 5172.3495 | ... BL31: =BL14*Emp_Petite+BL15*Emp_Moyenne+BL16*Emp_Grande -> 270273.92
A32: Employee salary accounts | B32: accounts | D32: =BL32 -> 54054.785 | E32: =IF(E$3>=EmpAcc_Start,E31*EmpAcc_Adoption,0) -> 0 | F32: =IF(F$3>=EmpAcc_Start,F31*EmpAcc_Adoption,0) -> 0 | G32: =IF(G$3>=EmpAcc_Start,G31*EmpAcc_Adoption,0) -> 0 | H32: =IF(H$3>=EmpAcc_Start,H31*EmpAcc_Adoption,0) -> 0 | I32: =IF(I$3>=EmpAcc_Start,I31*EmpAcc_Adoption,0) -> 0 | J32: =IF(J$3>=EmpAcc_Start,J31*EmpAcc_Adoption,0) -> 0 | K32: =IF(K$3>=EmpAcc_Start,K31*EmpAcc_Adoption,0) -> 0 | L32: =IF(L$3>=EmpAcc_Start,L31*EmpAcc_Adoption,0) -> 0 | ... BL32: =IF(BL$3>=EmpAcc_Start,BL31*EmpAcc_Adoption,0) -> 54054.785
A33: Physical cards issued | B33: cards | D33: =SUM(E33:BL33) -> 33174.542 | E33: =E9*Cards_New_Petite+E10*Cards_New_Moyenne+E11*Cards_New_Grande -> 0 | F33: =F9*Cards_New_Petite+F10*Cards_New_Moyenne+F11*Cards_New_Grande -> 0 | G33: =G9*Cards_New_Petite+G10*Cards_New_Moyenne+G11*Cards_New_Grande -> 0 | H33: =H9*Cards_New_Petite+H10*Cards_New_Moyenne+H11*Cards_New_Grande -> 0 | I33: =I9*Cards_New_Petite+I10*Cards_New_Moyenne+I11*Cards_New_Grande -> 132.17333 | J33: =J9*Cards_New_Petite+J10*Cards_New_Moyenne+J11*Cards_New_Grande -> 133.55333 | K33: =K9*Cards_New_Petite+K10*Cards_New_Moyenne+K11*Cards_New_Grande -> 135.01613 | L33: =L9*Cards_New_Petite+L10*Cards_New_Moyenne+L11*Cards_New_Grande -> 136.5667 | ... BL33: =BL9*Cards_New_Petite+BL10*Cards_New_Moyenne+BL11*Cards_New_Grande -> 1229.4267
A34: Physical cards charged (first one free) | B34: cards | D34: =SUM(E34:BL34) -> 18750.828 | E34: =E9*MAX(0,Cards_New_Petite-1)+E10*MAX(0,Cards_New_Moyenne-1)+E11*MAX(0,Cards_New_Grande-1) -> 0 | F34: =F9*MAX(0,Cards_New_Petite-1)+F10*MAX(0,Cards_New_Moyenne-1)+F11*MAX(0,Cards_New_Grande-1) -> 0 | G34: =G9*MAX(0,Cards_New_Petite-1)+G10*MAX(0,Cards_New_Moyenne-1)+G11*MAX(0,Cards_New_Grande-1) -> 0 | H34: =H9*MAX(0,Cards_New_Petite-1)+H10*MAX(0,Cards_New_Moyenne-1)+H11*MAX(0,Cards_New_Grande-1) -> 0 | I34: =I9*MAX(0,Cards_New_Petite-1)+I10*MAX(0,Cards_New_Moyenne-1)+I11*MAX(0,Cards_New_Grande-1) -> 74.706667 | J34: =J9*MAX(0,Cards_New_Petite-1)+J10*MAX(0,Cards_New_Moyenne-1)+J11*MAX(0,Cards_New_Grande-1) -> 75.486667 | K34: =K9*MAX(0,Cards_New_Petite-1)+K10*MAX(0,Cards_New_Moyenne-1)+K11*MAX(0,Cards_New_Grande-1) -> 76.313467 | L34: =L9*MAX(0,Cards_New_Petite-1)+L10*MAX(0,Cards_New_Moyenne-1)+L11*MAX(0,Cards_New_Grande-1) -> 77.189875 | ... BL34: =BL9*MAX(0,Cards_New_Petite-1)+BL10*MAX(0,Cards_New_Moyenne-1)+BL11*MAX(0,Cards_New_Grande-1) -> 694.89333
A35: Active cards | B35: cards | D35: =BL35 -> 52383.511 | E35: =E14*Cards_Act_Petite+E15*Cards_Act_Moyenne+E16*Cards_Act_Grande -> 0 | F35: =F14*Cards_Act_Petite+F15*Cards_Act_Moyenne+F16*Cards_Act_Grande -> 0 | G35: =G14*Cards_Act_Petite+G15*Cards_Act_Moyenne+G16*Cards_Act_Grande -> 0 | H35: =H14*Cards_Act_Petite+H15*Cards_Act_Moyenne+H16*Cards_Act_Grande -> 0 | I35: =I14*Cards_Act_Petite+I15*Cards_Act_Moyenne+I16*Cards_Act_Grande -> 258.6 | J35: =J14*Cards_Act_Petite+J15*Cards_Act_Moyenne+J16*Cards_Act_Grande -> 516.5813 | K35: =K14*Cards_Act_Petite+K15*Cards_Act_Moyenne+K16*Cards_Act_Grande -> 774.11985 | L35: =L14*Cards_Act_Petite+L15*Cards_Act_Moyenne+L16*Cards_Act_Grande -> 1031.3989 | ... BL35: =BL14*Cards_Act_Petite+BL15*Cards_Act_Moyenne+BL16*Cards_Act_Grande -> 52383.511
A36: Card spending in FCFA | B36: FCFA | D36: =SUM(E36:BL36) -> 1.567188e+11 | E36: =E14*Spend_Dom_Petite+E15*Spend_Dom_Moyenne+E16*Spend_Dom_Grande -> 0 | F36: =F14*Spend_Dom_Petite+F15*Spend_Dom_Moyenne+F16*Spend_Dom_Grande -> 0 | G36: =G14*Spend_Dom_Petite+G15*Spend_Dom_Moyenne+G16*Spend_Dom_Grande -> 0 | H36: =H14*Spend_Dom_Petite+H15*Spend_Dom_Moyenne+H16*Spend_Dom_Grande -> 0 | I36: =I14*Spend_Dom_Petite+I15*Spend_Dom_Moyenne+I16*Spend_Dom_Grande -> 38502667 | J36: =J14*Spend_Dom_Petite+J15*Spend_Dom_Moyenne+J16*Spend_Dom_Grande -> 76920303 | K36: =K14*Spend_Dom_Petite+K15*Spend_Dom_Moyenne+K16*Spend_Dom_Grande -> 1.1527905e+08 | L36: =L14*Spend_Dom_Petite+L15*Spend_Dom_Moyenne+L16*Spend_Dom_Grande -> 1.5360613e+08 | ... BL36: =BL14*Spend_Dom_Petite+BL15*Spend_Dom_Moyenne+BL16*Spend_Dom_Grande -> 7.8243204e+09
A37: Card spending in foreign currencies | B37: FCFA | D37: =SUM(E37:BL37) -> 2.0965899e+11 | E37: =E14*Spend_For_Petite+E15*Spend_For_Moyenne+E16*Spend_For_Grande -> 0 | F37: =F14*Spend_For_Petite+F15*Spend_For_Moyenne+F16*Spend_For_Grande -> 0 | G37: =G14*Spend_For_Petite+G15*Spend_For_Moyenne+G16*Spend_For_Grande -> 0 | H37: =H14*Spend_For_Petite+H15*Spend_For_Moyenne+H16*Spend_For_Grande -> 0 | I37: =I14*Spend_For_Petite+I15*Spend_For_Moyenne+I16*Spend_For_Grande -> 51145333 | J37: =J14*Spend_For_Petite+J15*Spend_For_Moyenne+J16*Spend_For_Grande -> 1.0220834e+08 | K37: =K14*Spend_For_Petite+K15*Spend_For_Moyenne+K16*Spend_For_Grande -> 1.5322312e+08 | L37: =L14*Spend_For_Petite+L15*Spend_For_Moyenne+L16*Spend_For_Grande -> 2.0422527e+08 | ... BL37: =BL14*Spend_For_Petite+BL15*Spend_For_Moyenne+BL16*Spend_For_Grande -> 1.0487276e+10
A38: Client balances (average) | B38: FCFA | D38: =BL38 -> 1.0420863e+11 | E38: =E14*Balance_Petite+E15*Balance_Moyenne+E16*Balance_Grande -> 0 | F38: =F14*Balance_Petite+F15*Balance_Moyenne+F16*Balance_Grande -> 0 | G38: =G14*Balance_Petite+G15*Balance_Moyenne+G16*Balance_Grande -> 0 | H38: =H14*Balance_Petite+H15*Balance_Moyenne+H16*Balance_Grande -> 0 | I38: =I14*Balance_Petite+I15*Balance_Moyenne+I16*Balance_Grande -> 5.0570667e+08 | J38: =J14*Balance_Petite+J15*Balance_Moyenne+J16*Balance_Grande -> 1.0107455e+09 | K38: =K14*Balance_Petite+K15*Balance_Moyenne+K16*Balance_Grande -> 1.5154525e+09 | L38: =L14*Balance_Petite+L15*Balance_Moyenne+L16*Balance_Grande -> 2.0201785e+09 | ... BL38: =BL14*Balance_Petite+BL15*Balance_Moyenne+BL16*Balance_Grande -> 1.0420863e+11
A39: Salaries paid through Tabax | B39: FCFA | D39: =SUM(E39:BL39) -> 1.0761216e+12 | E39: =E31*Avg_Salary -> 0 | F39: =F31*Avg_Salary -> 0 | G39: =G31*Avg_Salary -> 0 | H39: =H31*Avg_Salary -> 0 | I39: =I31*Avg_Salary -> 258600000 | J39: =J31*Avg_Salary -> 517098500 | K39: =K31*Avg_Salary -> 7.7566327e+08 | L39: =L31*Avg_Salary -> 1.0344699e+09 | ... BL39: =BL31*Avg_Salary -> 5.4054785e+10
A40: Supplier payouts | B40: payouts | D40: =SUM(E40:BL40) -> 7818829.1 | E40: =E14*Supplier_Petite+E15*Supplier_Moyenne+E16*Supplier_Grande -> 0 | F40: =F14*Supplier_Petite+F15*Supplier_Moyenne+F16*Supplier_Grande -> 0 | G40: =G14*Supplier_Petite+G15*Supplier_Moyenne+G16*Supplier_Grande -> 0 | H40: =H14*Supplier_Petite+H15*Supplier_Moyenne+H16*Supplier_Grande -> 0 | I40: =I14*Supplier_Petite+I15*Supplier_Moyenne+I16*Supplier_Grande -> 1896.4 | J40: =J14*Supplier_Petite+J15*Supplier_Moyenne+J16*Supplier_Grande -> 3790.619 | K40: =K14*Supplier_Petite+K15*Supplier_Moyenne+K16*Supplier_Grande -> 5683.9097 | L40: =L14*Supplier_Petite+L15*Supplier_Moyenne+L16*Supplier_Grande -> 7577.5807 | ... BL40: =BL14*Supplier_Petite+BL15*Supplier_Moyenne+BL16*Supplier_Grande -> 391744.71
A41: Supplier payouts above the allowance | B41: payouts | D41: =SUM(E41:BL41) -> 1346664.2 | E41: =E14*Overage_Petite+E15*Overage_Moyenne+E16*Overage_Grande -> 0 | F41: =F14*Overage_Petite+F15*Overage_Moyenne+F16*Overage_Grande -> 0 | G41: =G14*Overage_Petite+G15*Overage_Moyenne+G16*Overage_Grande -> 0 | H41: =H14*Overage_Petite+H15*Overage_Moyenne+H16*Overage_Grande -> 0 | I41: =I14*Overage_Petite+I15*Overage_Moyenne+I16*Overage_Grande -> 316.06667 | J41: =J14*Overage_Petite+J15*Overage_Moyenne+J16*Overage_Grande -> 632.63183 | K41: =K14*Overage_Petite+K15*Overage_Moyenne+K16*Overage_Grande -> 949.89065 | L41: =L14*Overage_Petite+L15*Overage_Moyenne+L16*Overage_Grande -> 1268.0484 | ... BL41: =BL14*Overage_Petite+BL15*Overage_Moyenne+BL16*Overage_Grande -> 68076.241
A42: Payment links: share of clients using them | B42: % | E42: =IF(E$3>=PayLinks_Start,MIN(1,(E$3-PayLinks_Start+1)/PL_Ramp)*PL_Adoption,0) -> 0 | F42: =IF(F$3>=PayLinks_Start,MIN(1,(F$3-PayLinks_Start+1)/PL_Ramp)*PL_Adoption,0) -> 0 | G42: =IF(G$3>=PayLinks_Start,MIN(1,(G$3-PayLinks_Start+1)/PL_Ramp)*PL_Adoption,0) -> 0 | H42: =IF(H$3>=PayLinks_Start,MIN(1,(H$3-PayLinks_Start+1)/PL_Ramp)*PL_Adoption,0) -> 0 | I42: =IF(I$3>=PayLinks_Start,MIN(1,(I$3-PayLinks_Start+1)/PL_Ramp)*PL_Adoption,0) -> 0 | J42: =IF(J$3>=PayLinks_Start,MIN(1,(J$3-PayLinks_Start+1)/PL_Ramp)*PL_Adoption,0) -> 0 | K42: =IF(K$3>=PayLinks_Start,MIN(1,(K$3-PayLinks_Start+1)/PL_Ramp)*PL_Adoption,0) -> 0 | L42: =IF(L$3>=PayLinks_Start,MIN(1,(L$3-PayLinks_Start+1)/PL_Ramp)*PL_Adoption,0) -> 0 | ... BL42: =IF(BL$3>=PayLinks_Start,MIN(1,(BL$3-PayLinks_Start+1)/PL_Ramp)*PL_Adoption,0) -> 0.25
A43: Payment links: amounts collected | B43: FCFA | D43: =SUM(E43:BL43) -> 1.32695e+11 | E43: =(E14*PL_Coll_Petite+E15*PL_Coll_Moyenne+E16*PL_Coll_Grande)*E42 -> 0 | F43: =(F14*PL_Coll_Petite+F15*PL_Coll_Moyenne+F16*PL_Coll_Grande)*F42 -> 0 | G43: =(G14*PL_Coll_Petite+G15*PL_Coll_Moyenne+G16*PL_Coll_Grande)*G42 -> 0 | H43: =(H14*PL_Coll_Petite+H15*PL_Coll_Moyenne+H16*PL_Coll_Grande)*H42 -> 0 | I43: =(I14*PL_Coll_Petite+I15*PL_Coll_Moyenne+I16*PL_Coll_Grande)*I42 -> 0 | J43: =(J14*PL_Coll_Petite+J15*PL_Coll_Moyenne+J16*PL_Coll_Grande)*J42 -> 0 | K43: =(K14*PL_Coll_Petite+K15*PL_Coll_Moyenne+K16*PL_Coll_Grande)*K42 -> 0 | L43: =(L14*PL_Coll_Petite+L15*PL_Coll_Moyenne+L16*PL_Coll_Grande)*L42 -> 0 | ... BL43: =(BL14*PL_Coll_Petite+BL15*PL_Coll_Moyenne+BL16*PL_Coll_Grande)*BL42 -> 7.0276253e+09
A45: Revenue (excluding credit)
A46: Price factor (yearly increase × yearly-billing discount) | B46: x | E46: =(1+Price_Increase)^(E$5-1)*(1-Annual_Share*Annual_Free/12) -> 0.95 | F46: =(1+Price_Increase)^(F$5-1)*(1-Annual_Share*Annual_Free/12) -> 0.95 | G46: =(1+Price_Increase)^(G$5-1)*(1-Annual_Share*Annual_Free/12) -> 0.95 | H46: =(1+Price_Increase)^(H$5-1)*(1-Annual_Share*Annual_Free/12) -> 0.95 | I46: =(1+Price_Increase)^(I$5-1)*(1-Annual_Share*Annual_Free/12) -> 0.95 | J46: =(1+Price_Increase)^(J$5-1)*(1-Annual_Share*Annual_Free/12) -> 0.95 | K46: =(1+Price_Increase)^(K$5-1)*(1-Annual_Share*Annual_Free/12) -> 0.95 | L46: =(1+Price_Increase)^(L$5-1)*(1-Annual_Share*Annual_Free/12) -> 0.95 | ... BL46: =(1+Price_Increase)^(BL$5-1)*(1-Annual_Share*Annual_Free/12) -> 0.95
A47: Subscriptions, Petite | B47: FCFA | D47: =SUM(E47:BL47) -> 9.6822457e+08 | E47: =E26*Price_Petite*E46 -> 0 | F47: =F26*Price_Petite*F46 -> 0 | G47: =G26*Price_Petite*G46 -> 0 | H47: =H26*Price_Petite*H46 -> 0 | I47: =I26*Price_Petite*I46 -> 0 | J47: =J26*Price_Petite*J46 -> 0 | K47: =K26*Price_Petite*K46 -> 0 | L47: =L26*Price_Petite*L46 -> 285612.96 | ... BL47: =BL26*Price_Petite*BL46 -> 49676221
A48: Subscriptions, Moyenne | B48: FCFA | D48: =SUM(E48:BL48) -> 1.635655e+09 | E48: =E27*Price_Moyenne*E46 -> 0 | F48: =F27*Price_Moyenne*F46 -> 0 | G48: =G27*Price_Moyenne*G46 -> 0 | H48: =H27*Price_Moyenne*H46 -> 0 | I48: =I27*Price_Moyenne*I46 -> 0 | J48: =J27*Price_Moyenne*J46 -> 0 | K48: =K27*Price_Moyenne*K46 -> 0 | L48: =L27*Price_Moyenne*L46 -> 453020.96 | ... BL48: =BL27*Price_Moyenne*BL46 -> 85950122
A49: Subscriptions, Grande | B49: FCFA | D49: =SUM(E49:BL49) -> 1.574141e+09 | E49: =E28*Price_Grande*E46 -> 0 | F49: =F28*Price_Grande*F46 -> 0 | G49: =G28*Price_Grande*G46 -> 0 | H49: =H28*Price_Grande*H46 -> 0 | I49: =I28*Price_Grande*I46 -> 0 | J49: =J28*Price_Grande*J46 -> 0 | K49: =K28*Price_Grande*K46 -> 0 | L49: =L28*Price_Grande*L46 -> 416531.24 | ... BL49: =BL28*Price_Grande*BL46 -> 84162183
A50: Subscriptions | B50: FCFA | D50: =SUM(E50:BL50) -> 4.1780206e+09 | E50: =E47+E48+E49 -> 0 | F50: =F47+F48+F49 -> 0 | G50: =G47+G48+G49 -> 0 | H50: =H47+H48+H49 -> 0 | I50: =I47+I48+I49 -> 0 | J50: =J47+J48+J49 -> 0 | K50: =K47+K48+K49 -> 0 | L50: =L47+L48+L49 -> 1155165.2 | ... BL50: =BL47+BL48+BL49 -> 2.1978853e+08
A51: Fees on foreign-currency card spending | B51: FCFA | D51: =SUM(E51:BL51) -> 2.0965899e+09 | E51: =E37*FX_Fee -> 0 | F51: =F37*FX_Fee -> 0 | G51: =G37*FX_Fee -> 0 | H51: =H37*FX_Fee -> 0 | I51: =I37*FX_Fee -> 511453.33 | J51: =J37*FX_Fee -> 1022083.4 | K51: =K37*FX_Fee -> 1532231.2 | L51: =L37*FX_Fee -> 2042252.7 | ... BL51: =BL37*FX_Fee -> 1.0487276e+08
A52: Interchange share on FCFA card spending | B52: FCFA | D52: =SUM(E52:BL52) -> 7.8359401e+08 | E52: =E36*Interchange_Share -> 0 | F52: =F36*Interchange_Share -> 0 | G52: =G36*Interchange_Share -> 0 | H52: =H36*Interchange_Share -> 0 | I52: =I36*Interchange_Share -> 192513.33 | J52: =J36*Interchange_Share -> 384601.52 | K52: =K36*Interchange_Share -> 576395.23 | L52: =L36*Interchange_Share -> 768030.65 | ... BL52: =BL36*Interchange_Share -> 39121602
A53: Share of bank income on client balances | B53: FCFA | D53: =SUM(E53:BL53) -> 2.6011848e+09 | E53: =E38*Deposit_Share/12 -> 0 | F53: =F38*Deposit_Share/12 -> 0 | G53: =G38*Deposit_Share/12 -> 0 | H53: =H38*Deposit_Share/12 -> 0 | I53: =I38*Deposit_Share/12 -> 632133.33 | J53: =J38*Deposit_Share/12 -> 1263431.9 | K53: =K38*Deposit_Share/12 -> 1894315.7 | L53: =L38*Deposit_Share/12 -> 2525223.1 | ... BL53: =BL38*Deposit_Share/12 -> 1.3026079e+08
A54: Physical card fees | B54: FCFA | D54: =SUM(E54:BL54) -> 93754140 | E54: =E34*Card_Fee -> 0 | F54: =F34*Card_Fee -> 0 | G54: =G34*Card_Fee -> 0 | H54: =H34*Card_Fee -> 0 | I54: =I34*Card_Fee -> 373533.33 | J54: =J34*Card_Fee -> 377433.33 | K54: =K34*Card_Fee -> 381567.33 | L54: =L34*Card_Fee -> 385949.37 | ... BL54: =BL34*Card_Fee -> 3474466.7
A55: Supplier payouts above the allowance | B55: FCFA | D55: =SUM(E55:BL55) -> 1.3466642e+08 | E55: =E41*Overage_Fee -> 0 | F55: =F41*Overage_Fee -> 0 | G55: =G41*Overage_Fee -> 0 | H55: =H41*Overage_Fee -> 0 | I55: =I41*Overage_Fee -> 31606.667 | J55: =J41*Overage_Fee -> 63263.183 | K55: =K41*Overage_Fee -> 94989.065 | L55: =L41*Overage_Fee -> 126804.84 | ... BL55: =BL41*Overage_Fee -> 6807624.1
A56: Payment link fees | B56: FCFA | D56: =SUM(E56:BL56) -> 9.2886503e+08 | E56: =E43*PL_Momo_Share*PL_Fee -> 0 | F56: =F43*PL_Momo_Share*PL_Fee -> 0 | G56: =G43*PL_Momo_Share*PL_Fee -> 0 | H56: =H43*PL_Momo_Share*PL_Fee -> 0 | I56: =I43*PL_Momo_Share*PL_Fee -> 0 | J56: =J43*PL_Momo_Share*PL_Fee -> 0 | K56: =K43*PL_Momo_Share*PL_Fee -> 0 | L56: =L43*PL_Momo_Share*PL_Fee -> 0 | ... BL56: =BL43*PL_Momo_Share*PL_Fee -> 49193377
A57: Revenue excluding credit | B57: FCFA | D57: =SUM(E57:BL57) -> 1.0816675e+10 | E57: =E50+SUM(E51:E56) -> 0 | F57: =F50+SUM(F51:F56) -> 0 | G57: =G50+SUM(G51:G56) -> 0 | H57: =H50+SUM(H51:H56) -> 0 | I57: =I50+SUM(I51:I56) -> 1741240 | J57: =J50+SUM(J51:J56) -> 3110813.3 | K57: =K50+SUM(K51:K56) -> 4479498.5 | L57: =L50+SUM(L51:L56) -> 7003425.9 | ... BL57: =BL50+SUM(BL51:BL56) -> 5.5351915e+08

Sheet Clients & revenue (€)
A1: Clients & revenue (€)
A2: Every amount of the 'Clients & revenue' sheet in euros (FCFA ÷ FCFA per euro on Assumptions). Edit the FCFA sheets and Assumptions, not this one.
A3: Month # | D3: Total / end | E3: ='Clients & revenue'!E3 -> 1 | F3: ='Clients & revenue'!F3 -> 2 | G3: ='Clients & revenue'!G3 -> 3 | H3: ='Clients & revenue'!H3 -> 4 | I3: ='Clients & revenue'!I3 -> 5 | J3: ='Clients & revenue'!J3 -> 6 | K3: ='Clients & revenue'!K3 -> 7 | L3: ='Clients & revenue'!L3 -> 8 | ... BL3: ='Clients & revenue'!BL3 -> 60
A4: Month | E4: ='Clients & revenue'!E4 -> 46388 | F4: ='Clients & revenue'!F4 -> 46419 | G4: ='Clients & revenue'!G4 -> 46447 | H4: ='Clients & revenue'!H4 -> 46478 | I4: ='Clients & revenue'!I4 -> 46508 | J4: ='Clients & revenue'!J4 -> 46539 | K4: ='Clients & revenue'!K4 -> 46569 | L4: ='Clients & revenue'!L4 -> 46600 | ... BL4: ='Clients & revenue'!BL4 -> 48183
A5: Year | E5: ='Clients & revenue'!E5 -> 1 | F5: ='Clients & revenue'!F5 -> 1 | G5: ='Clients & revenue'!G5 -> 1 | H5: ='Clients & revenue'!H5 -> 1 | I5: ='Clients & revenue'!I5 -> 1 | J5: ='Clients & revenue'!J5 -> 1 | K5: ='Clients & revenue'!K5 -> 1 | L5: ='Clients & revenue'!L5 -> 1 | ... BL5: ='Clients & revenue'!BL5 -> 5
A8: New clients by plan
A10: Active clients (end of month)
A12: Clients in their free months, and paying clients
A14: Usage
A15: Card spending in FCFA | B15: € | D15: ='Clients & revenue'!D36/FX_EUR -> 2.3891627e+08 | E15: ='Clients & revenue'!E36/FX_EUR -> 0 | F15: ='Clients & revenue'!F36/FX_EUR -> 0 | G15: ='Clients & revenue'!G36/FX_EUR -> 0 | H15: ='Clients & revenue'!H36/FX_EUR -> 0 | I15: ='Clients & revenue'!I36/FX_EUR -> 58696.937 | J15: ='Clients & revenue'!J36/FX_EUR -> 117264.25 | K15: ='Clients & revenue'!K36/FX_EUR -> 175741.77 | ... BL15: ='Clients & revenue'!BL36/FX_EUR -> 11928100
A16: Card spending in foreign currencies | B16: € | D16: ='Clients & revenue'!D37/FX_EUR -> 3.1962307e+08 | E16: ='Clients & revenue'!E37/FX_EUR -> 0 | F16: ='Clients & revenue'!F37/FX_EUR -> 0 | G16: ='Clients & revenue'!G37/FX_EUR -> 0 | H16: ='Clients & revenue'!H37/FX_EUR -> 0 | I16: ='Clients & revenue'!I37/FX_EUR -> 77970.558 | J16: ='Clients & revenue'!J37/FX_EUR -> 155815.6 | K16: ='Clients & revenue'!K37/FX_EUR -> 233587.14 | ... BL16: ='Clients & revenue'!BL37/FX_EUR -> 15987749
A17: Client balances (average) | B17: € | D17: ='Clients & revenue'!D38/FX_EUR -> 1.5886504e+08 | E17: ='Clients & revenue'!E38/FX_EUR -> 0 | F17: ='Clients & revenue'!F38/FX_EUR -> 0 | G17: ='Clients & revenue'!G38/FX_EUR -> 0 | H17: ='Clients & revenue'!H38/FX_EUR -> 0 | I17: ='Clients & revenue'!I38/FX_EUR -> 770944.84 | J17: ='Clients & revenue'!J38/FX_EUR -> 1540871.6 | K17: ='Clients & revenue'!K38/FX_EUR -> 2310292.5 | ... BL17: ='Clients & revenue'!BL38/FX_EUR -> 1.5886504e+08
A18: Salaries paid through Tabax | B18: € | D18: ='Clients & revenue'!D39/FX_EUR -> 1.6405369e+09 | E18: ='Clients & revenue'!E39/FX_EUR -> 0 | F18: ='Clients & revenue'!F39/FX_EUR -> 0 | G18: ='Clients & revenue'!G39/FX_EUR -> 0 | H18: ='Clients & revenue'!H39/FX_EUR -> 0 | I18: ='Clients & revenue'!I39/FX_EUR -> 394233.16 | J18: ='Clients & revenue'!J39/FX_EUR -> 788311.58 | K18: ='Clients & revenue'!K39/FX_EUR -> 1182491 | ... BL18: ='Clients & revenue'!BL39/FX_EUR -> 82405988
A19: Payment links: amounts collected | B19: € | D19: ='Clients & revenue'!D43/FX_EUR -> 2.0229223e+08 | E19: ='Clients & revenue'!E43/FX_EUR -> 0 | F19: ='Clients & revenue'!F43/FX_EUR -> 0 | G19: ='Clients & revenue'!G43/FX_EUR -> 0 | H19: ='Clients & revenue'!H43/FX_EUR -> 0 | I19: ='Clients & revenue'!I43/FX_EUR -> 0 | J19: ='Clients & revenue'!J43/FX_EUR -> 0 | K19: ='Clients & revenue'!K43/FX_EUR -> 0 | ... BL19: ='Clients & revenue'!BL43/FX_EUR -> 10713546
A21: Revenue (excluding credit)
